Workbook
Name lst_Shift: Lists!$A$6:INDEX(Lists!$A:$A,5+COUNTA(Lists!$A$6:$A$1048576))
Name lst_Material: Lists!$C$6:INDEX(Lists!$C:$C,5+COUNTA(Lists!$C$6:$C$1048576))
Name lst_Area: Lists!$E$6:INDEX(Lists!$E:$E,5+COUNTA(Lists!$E$6:$E$1048576))
Name lst_Equipment_Class: Lists!$G$6:INDEX(Lists!$G:$G,5+COUNTA(Lists!$G$6:$G$1048576))
Name lst_Gold_Movement_Type: Lists!$I$6:INDEX(Lists!$I:$I,5+COUNTA(Lists!$I$6:$I$1048576))
Name lst_Yes_No: Lists!$K$6:INDEX(Lists!$K:$K,5+COUNTA(Lists!$K$6:$K$1048576))
Name lst_Source_Type: Lists!$M$6:INDEX(Lists!$M:$M,5+COUNTA(Lists!$M$6:$M$1048576))
Name lst_Destination_Type: Lists!$O$6:INDEX(Lists!$O:$O,5+COUNTA(Lists!$O$6:$O$1048576))
Name lst_Source: Lists!$R$6:INDEX(Lists!$R:$R,5+COUNTA(Lists!$R$6:$R$1048576))
Name lst_Destination: Lists!$U$6:INDEX(Lists!$U:$U,5+COUNTA(Lists!$U$6:$U$1048576))
Name cfg_Site: Config!$B$5
Name cfg_Company: Config!$B$6
Name cfg_ReportTitle: Config!$B$7
Name cfg_PriorLTIDate: Config!$B$8
Name cfg_TroyOz: Config!$B$9
Name cfg_HoursPerDay: Config!$B$10
Name cfg_RateBasisHours: Config!$B$11
Name cfg_Year: Config!$B$14
Name cfg_YearStart: Config!$B$15
Name cfg_YearEnd: Config!$B$16
Name cfg_LastDataDate: Config!$B$17
Name cfg_FeedCheck: Config!$B$18
Name cfg_YearCheck: Config!$B$19
Name cd_Date: Calc_Daily!$A$2:$A$366
Name cd_Month: Calc_Daily!$B$2:$B$366
Name cd_Day: Calc_Daily!$C$2:$C$366
Name cd_Days_In_Month: Calc_Daily!$D$2:$D$366
Name cd_Month_Start: Calc_Daily!$E$2:$E$366
Name cd_Ore_Mined_t: Calc_Daily!$F$2:$F$366
Name cd_Ore_Mined_t_MTD: Calc_Daily!$G$2:$G$366
Name cd_Ore_Mined_t_YTD: Calc_Daily!$H$2:$H$366
Name cd_Ore_Mined_oz: Calc_Daily!$I$2:$I$366
Name cd_Ore_Mined_oz_MTD: Calc_Daily!$J$2:$J$366
Name cd_Ore_Mined_oz_YTD: Calc_Daily!$K$2:$K$366
Name cd_Ore_Graded_t: Calc_Daily!$L$2:$L$366
Name cd_Ore_Graded_t_MTD: Calc_Daily!$M$2:$M$366
Name cd_Ore_Graded_t_YTD: Calc_Daily!$N$2:$N$366
Name cd_Ore_Grade_gpt: Calc_Daily!$O$2:$O$366
Name cd_Ore_Grade_gpt_MTD: Calc_Daily!$P$2:$P$366
Name cd_Ore_Grade_gpt_YTD: Calc_Daily!$Q$2:$Q$366
Name cd_Ore_Ungraded_t: Calc_Daily!$R$2:$R$366
Name cd_Ore_Ungraded_t_MTD: Calc_Daily!$S$2:$S$366
Name cd_Ore_Ungraded_t_YTD: Calc_Daily!$T$2:$T$366
Name cd_Waste_t: Calc_Daily!$U$2:$U$366
Name cd_Waste_t_MTD: Calc_Daily!$V$2:$V$366
Name cd_Waste_t_YTD: Calc_Daily!$W$2:$W$366
Name cd_TMM_t: Calc_Daily!$X$2:$X$366
Name cd_TMM_t_MTD: Calc_Daily!$Y$2:$Y$366
Name cd_TMM_t_YTD: Calc_Daily!$Z$2:$Z$366
Name cd_Strip_Ratio: Calc_Daily!$AA$2:$AA$366
Name cd_Strip_Ratio_MTD: Calc_Daily!$AB$2:$AB$366
Name cd_Strip_Ratio_YTD: Calc_Daily!$AC$2:$AC$366
Name cd_Rehandle_t: Calc_Daily!$AD$2:$AD$366
Name cd_Rehandle_t_MTD: Calc_Daily!$AE$2:$AE$366
Name cd_Rehandle_t_YTD: Calc_Daily!$AF$2:$AF$366
Name cd_Moved_Total_t: Calc_Daily!$AG$2:$AG$366
Name cd_Moved_Total_t_MTD: Calc_Daily!$AH$2:$AH$366
Name cd_Moved_Total_t_YTD: Calc_Daily!$AI$2:$AI$366
Name cd_Unclassified_t: Calc_Daily!$AJ$2:$AJ$366
Name cd_Unclassified_t_MTD: Calc_Daily!$AK$2:$AK$366

Sheet README
B2: Mako Gold Mine Production System, 2026
B3: Petowal Mining Company S.A.. Version 0.3.0. Generated workbook: do not restructure by hand; change the schema and regenerate.
B5: How the workbook works
B6: 1. Inputs are the green tabs: Plant, Mining_Movements, Mining_Daily, Fleet, Safety, Gold, Budget, Commentary. Each is an Excel table. Type in the blue-headed columns only; grey-headed columns are formulas that fill automatically.
B7: 2. Calc_Daily rebuilds every KPI per day from the tables (day, month to date, year to date, budget). Daily_Report, Monthly_Summary and Dashboard read only from Calc_Daily.
B8: 3. There are no links to other workbooks and no macros. Copying the file anywhere keeps it working.
B9: 4. Lists holds every drop-down. Add a new pit, stockpile or equipment class there; do not type free text into list columns.
B10: 5. Config holds the site constants (troy ounce, hours per day, injury rate basis), the stockpile opening balances (exactly one stockpile has Plant_Feed = Y) and the monthly safety history used for rolling 12-month rates. The reporting year is fixed when the workbook is generated; to roll to a new year run build_workbook.py --year, do not type over it.
B11: 6. If the report opens blank behind a yellow Protected View bar (a file received by e-mail or download), click Enable Editing; the workbook then calculates.
B13: Daily routine
B14: Plant: enter the row for the day (dates are pre-filled). Mining: add one movement row per source, material and destination; add the Mining_Daily row and one Fleet row per equipment class. HSE: enter the Safety row. Everyone: one Commentary row per topic. Then open Daily_Report, check the date in C5 and the 'Rows for this date' line in B7, and print or export to PDF.
B15: One person edits the file at a time: open, enter, save, close. If Excel opens it Read-Only someone else has it: wait, do not Save As a copy. Suggested order: Mining 06:30, Plant 06:45, HSE 07:00, Commentary 07:15. Simultaneous entry needs the file on SharePoint or OneDrive.
... B26: Schema and generator: mps_schema.json and build_workbook.py in the MPS tools folder. Report issues to the Director, Operations and Projects.

Sheet Daily_Report
B2: =cfg_ReportTitle
B3: =cfg_Company&" | "&cfg_Site
L4: row
B5: Report date | C5: =MAX(cfg_YearStart,MIN(TODAY()-1,cfg_YearEnd,IF(N(cfg_LastDataDate)>0,cfg_LastDataDate,cfg_YearEnd))) | F5: =IF(ISNUMBER(rpt_Row),cfg_YearCheck,"Report date is outside the reporting year: enter a date between 1 January and 31 December "&cfg_Year) | L5: =IFERROR(MATCH($C$5,cd_Date,0),NA())
B6: =IF(ISNUMBER(rpt_Row),"Data to "&IF(N(cfg_LastDataDate)>0,DAY(cfg_LastDataDate)&" "&CHOOSE(MONTH(cfg_LastDataDate),"Jan","Feb","Mar","Apr","May","Jun","Jul","Aug","Sep","Oct","Nov","Dec")&" "&YEAR(cfg_LastDataDate),"(no plant data yet)")&" | Week "&_xlfn.ISOWEEKNUM($C$5)&" | Day "&DAY($C$5)&" of "&DAY(EOMONTH($C$5,0)),"Report date is outside the reporting year")
B7: ="Rows for this date: Plant "&COUNTIFS(tblPlant[Date],rpt_Date,tblPlant[Milled_t],"<>")&", Movements "&COUNTIFS(tblMovement[Date],rpt_Date)&", Fleet "&COUNTIFS(tblFleet[Date],rpt_Date)&", Mining daily "&COUNTIFS(tblMiningDaily[Date],rpt_Date,tblMiningDaily[Diesel_L],"<>")&", Safety "&COUNTIFS(tblSafety[Date],rpt_Date,tblSafety[Hours_Employees],"<>")&", Comments "&COUNTIFS(tblCommentary[Date],rpt_Date)&" | Movement rows with unknown source or destination: "&(COUNTIF(tblMovement[Source_Type],"?")+COUNTIF(tblMovement[Dest_Type],"?"))&" | Movement rows dated outside the year: "&(COUNTIFS(tblMovement[Date],"<"&cfg_YearStart)+COUNTIFS(tblMovement[Date],">"&cfg_YearEnd))
B8: SAFETY | C8: Unit | D8: Day | E8: MTD | F8: MTD budget | G8: Var % | H8: YTD | I8: YTD budget | J8: Var %
B9: Hours worked | C9: h | D9: =IFERROR(INDEX(cd_Hours_Worked,rpt_Row),"") | E9: =IFERROR(INDEX(cd_Hours_Worked_MTD,rpt_Row),"") | F9: =IFERROR(INDEX(cd_Bud_Hours_Worked_MTD,rpt_Row),"") | G9: =IF(AND(ISNUMBER(F9),ISNUMBER(E9),F9<>0),E9/F9-1,"") | H9: =IFERROR(INDEX(cd_Hours_Worked_YTD,rpt_Row),"") | I9: =IFERROR(INDEX(cd_Bud_Hours_Worked_YTD,rpt_Row),"") | J9: =IF(AND(ISNUMBER(I9),ISNUMBER(H9),I9<>0),H9/I9-1,"")
B10: Recordable injuries | D10: =IFERROR(INDEX(cd_Recordables,rpt_Row),"") | E10: =IFERROR(INDEX(cd_Recordables_MTD,rpt_Row),"") | H10: =IFERROR(INDEX(cd_Recordables_YTD,rpt_Row),"")
B11: Lost time injuries | D11: =IFERROR(INDEX(cd_LTI,rpt_Row),"") | E11: =IFERROR(INDEX(cd_LTI_MTD,rpt_Row),"") | H11: =IFERROR(INDEX(cd_LTI_YTD,rpt_Row),"")
B12: Restricted work injuries | D12: =IFERROR(INDEX(cd_RWI,rpt_Row),"") | E12: =IFERROR(INDEX(cd_RWI_MTD,rpt_Row),"") | H12: =IFERROR(INDEX(cd_RWI_YTD,rpt_Row),"")
B13: Medical treatment injuries | D13: =IFERROR(INDEX(cd_MTI,rpt_Row),"") | E13: =IFERROR(INDEX(cd_MTI_MTD,rpt_Row),"") | H13: =IFERROR(INDEX(cd_MTI_YTD,rpt_Row),"")
B14: First aid injuries | D14: =IFERROR(INDEX(cd_FAI,rpt_Row),"") | E14: =IFERROR(INDEX(cd_FAI_MTD,rpt_Row),"") | H14: =IFERROR(INDEX(cd_FAI_YTD,rpt_Row),"")
B15: Near misses | D15: =IFERROR(INDEX(cd_Near_Miss,rpt_Row),"") | E15: =IFERROR(INDEX(cd_Near_Miss_MTD,rpt_Row),"") | H15: =IFERROR(INDEX(cd_Near_Miss_YTD,rpt_Row),"")
B16: Hazard reports | D16: =IFERROR(INDEX(cd_Hazard_Reports,rpt_Row),"") | E16: =IFERROR(INDEX(cd_Hazard_Reports_MTD,rpt_Row),"") | H16: =IFERROR(INDEX(cd_Hazard_Reports_YTD,rpt_Row),"")
B17: High potential incidents | D17: =IFERROR(INDEX(cd_HPI,rpt_Row),"") | E17: =IFERROR(INDEX(cd_HPI_MTD,rpt_Row),"") | H17: =IFERROR(INDEX(cd_HPI_YTD,rpt_Row),"")
B18: Environmental incidents | D18: =IFERROR(INDEX(cd_Env_Incidents,rpt_Row),"") | E18: =IFERROR(INDEX(cd_Env_Incidents_MTD,rpt_Row),"") | H18: =IFERROR(INDEX(cd_Env_Incidents_YTD,rpt_Row),"")
B19: Community incidents | D19: =IFERROR(INDEX(cd_Community_Incidents,rpt_Row),"") | E19: =IFERROR(INDEX(cd_Community_Incidents_MTD,rpt_Row),"") | H19: =IFERROR(INDEX(cd_Community_Incidents_YTD,rpt_Row),"")
B20: Vehicle incidents | D20: =IFERROR(INDEX(cd_Vehicle_Incidents,rpt_Row),"") | E20: =IFERROR(INDEX(cd_Vehicle_Incidents_MTD,rpt_Row),"") | H20: =IFERROR(INDEX(cd_Vehicle_Incidents_YTD,rpt_Row),"")
B21: TRIFR, rolling 12 months + MTD | C21: ="per "&TEXT(cfg_RateBasisHours,"#,##0")&" h" | D21: =IFERROR(INDEX(cd_TRIFR_12m,rpt_Row),"")
B22: LTIFR, rolling 12 months + MTD | C22: ="per "&TEXT(cfg_RateBasisHours,"#,##0")&" h" | D22: =IFERROR(INDEX(cd_LTIFR_12m,rpt_Row),"")
B23: Days since last LTI | D23: =IFERROR(INDEX(cd_Days_Since_LTI,rpt_Row),"")
B25: MINING | C25: Unit | D25: Day | E25: MTD | F25: MTD budget | G25: Var % | H25: YTD | I25: YTD budget | J25: Var %
B26: Ore mined (ex-pit) | C26: t | D26: =IFERROR(INDEX(cd_Ore_Mined_t,rpt_Row),"") | E26: =IFERROR(INDEX(cd_Ore_Mined_t_MTD,rpt_Row),"") | F26: =IFERROR(INDEX(cd_Bud_Ore_Mined_t_MTD,rpt_Row),"") | G26: =IF(AND(ISNUMBER(F26),ISNUMBER(E26),F26<>0),E26/F26-1,"") | H26: =IFERROR(INDEX(cd_Ore_Mined_t_YTD,rpt_Row),"") | I26: =IFERROR(INDEX(cd_Bud_Ore_Mined_t_YTD,rpt_Row),"") | J26: =IF(AND(ISNUMBER(I26),ISNUMBER(H26),I26<>0),H26/I26-1,"")
B27: Ore grade mined | C27: g/t | D27: =IFERROR(INDEX(cd_Ore_Grade_gpt,rpt_Row),"") | E27: =IFERROR(INDEX(cd_Ore_Grade_gpt_MTD,rpt_Row),"") | F27: =IFERROR(INDEX(cd_Bud_Ore_Grade_gpt_MTD,rpt_Row),"") | G27: =IF(AND(ISNUMBER(F27),ISNUMBER(E27),F27<>0),E27/F27-1,"") | H27: =IFERROR(INDEX(cd_Ore_Grade_gpt_YTD,rpt_Row),"") | I27: =IFERROR(INDEX(cd_Bud_Ore_Grade_gpt_YTD,rpt_Row),"") | J27: =IF(AND(ISNUMBER(I27),ISNUMBER(H27),I27<>0),H27/I27-1,"")
B28: Contained gold mined | C28: oz | D28: =IFERROR(INDEX(cd_Ore_Mined_oz,rpt_Row),"") | E28: =IFERROR(INDEX(cd_Ore_Mined_oz_MTD,rpt_Row),"") | F28: =IFERROR(INDEX(cd_Bud_Ore_Mined_oz_MTD,rpt_Row),"") | G28: =IF(AND(ISNUMBER(F28),ISNUMBER(E28),F28<>0),E28/F28-1,"") | H28: =IFERROR(INDEX(cd_Ore_Mined_oz_YTD,rpt_Row),"") | I28: =IFERROR(INDEX(cd_Bud_Ore_Mined_oz_YTD,rpt_Row),"") | J28: =IF(AND(ISNUMBER(I28),ISNUMBER(H28),I28<>0),H28/I28-1,"")
B29: Ore mined without a grade (check) | C29: t | D29: =IFERROR(INDEX(cd_Ore_Ungraded_t,rpt_Row),"") | E29: =IFERROR(INDEX(cd_Ore_Ungraded_t_MTD,rpt_Row),"") | H29: =IFERROR(INDEX(cd_Ore_Ungraded_t_YTD,rpt_Row),"")
B30: Waste mined | C30: t | D30: =IFERROR(INDEX(cd_Waste_t,rpt_Row),"") | E30: =IFERROR(INDEX(cd_Waste_t_MTD,rpt_Row),"") | F30: =IFERROR(INDEX(cd_Bud_Waste_t_MTD,rpt_Row),"") | G30: =IF(AND(ISNUMBER(F30),ISNUMBER(E30),F30<>0),E30/F30-1,"") | H30: =IFERROR(INDEX(cd_Waste_t_YTD,rpt_Row),"") | I30: =IFERROR(INDEX(cd_Bud_Waste_t_YTD,rpt_Row),"") | J30: =IF(AND(ISNUMBER(I30),ISNUMBER(H30),I30<>0),H30/I30-1,"")
B31: Total material moved | C31: t | D31: =IFERROR(INDEX(cd_TMM_t,rpt_Row),"") | E31: =IFERROR(INDEX(cd_TMM_t_MTD,rpt_Row),"") | F31: =IFERROR(INDEX(cd_Bud_TMM_t_MTD,rpt_Row),"") | G31: =IF(AND(ISNUMBER(F31),ISNUMBER(E31),F31<>0),E31/F31-1,"") | H31: =IFERROR(INDEX(cd_TMM_t_YTD,rpt_Row),"") | I31: =IFERROR(INDEX(cd_Bud_TMM_t_YTD,rpt_Row),"") | J31: =IF(AND(ISNUMBER(I31),ISNUMBER(H31),I31<>0),H31/I31-1,"")
B32: Strip ratio (waste : ore) | D32: =IFERROR(INDEX(cd_Strip_Ratio,rpt_Row),"") | E32: =IFERROR(INDEX(cd_Strip_Ratio_MTD,rpt_Row),"") | F32: =IFERROR(INDEX(cd_Bud_Strip_Ratio_MTD,rpt_Row),"") | G32: =IF(AND(ISNUMBER(F32),ISNUMBER(E32),F32<>0),E32/F32-1,"") | H32: =IFERROR(INDEX(cd_Strip_Ratio_YTD,rpt_Row),"") | I32: =IFERROR(INDEX(cd_Bud_Strip_Ratio_YTD,rpt_Row),"") | J32: =IF(AND(ISNUMBER(I32),ISNUMBER(H32),I32<>0),H32/I32-1,"")
B33: Rehandle from stockpiles | C33: t | D33: =IFERROR(INDEX(cd_Rehandle_t,rpt_Row),"") | E33: =IFERROR(INDEX(cd_Rehandle_t_MTD,rpt_Row),"") | H33: =IFERROR(INDEX(cd_Rehandle_t_YTD,rpt_Row),"")
B34: Movements with unknown source type (check) | C34: t | D34: =IFERROR(INDEX(cd_Unclassified_t,rpt_Row),"") | E34: =IFERROR(INDEX(cd_Unclassified_t_MTD,rpt_Row),"") | H34: =IFERROR(INDEX(cd_Unclassified_t_YTD,rpt_Row),"")
B35: Drilled | C35: m | D35: =IFERROR(INDEX(cd_Drill_m,rpt_Row),"") | E35: =IFERROR(INDEX(cd_Drill_m_MTD,rpt_Row),"") | F35: =IFERROR(INDEX(cd_Bud_Drill_m_MTD,rpt_Row),"") | G35: =IF(AND(ISNUMBER(F35),ISNUMBER(E35),F35<>0),E35/F35-1,"") | H35: =IFERROR(INDEX(cd_Drill_m_YTD,rpt_Row),"") | I35: =IFERROR(INDEX(cd_Bud_Drill_m_YTD,rpt_Row),"") | J35: =IF(AND(ISNUMBER(I35),ISNUMBER(H35),I35<>0),H35/I35-1,"")
B36: Grade control drilled | C36: m | D36: =IFERROR(INDEX(cd_GC_Drill_m,rpt_Row),"") | E36: =IFERROR(INDEX(cd_GC_Drill_m_MTD,rpt_Row),"") | H36: =IFERROR(INDEX(cd_GC_Drill_m_YTD,rpt_Row),"")
B37: Blasted | C37: t | D37: =IFERROR(INDEX(cd_Blast_t,rpt_Row),"") | E37: =IFERROR(INDEX(cd_Blast_t_MTD,rpt_Row),"") | H37: =IFERROR(INDEX(cd_Blast_t_YTD,rpt_Row),"")
B38: Powder factor | C38: kg/t | D38: =IFERROR(INDEX(cd_Powder_Factor_kgpt,rpt_Row),"") | E38: =IFERROR(INDEX(cd_Powder_Factor_kgpt_MTD,rpt_Row),"") | H38: =IFERROR(INDEX(cd_Powder_Factor_kgpt_YTD,rpt_Row),"")
B39: Mining diesel | C39: L | D39: =IFERROR(INDEX(cd_Diesel_Mining_L,rpt_Row),"") | E39: =IFERROR(INDEX(cd_Diesel_Mining_L_MTD,rpt_Row),"") | F39: =IFERROR(INDEX(cd_Bud_Diesel_Mining_L_MTD,rpt_Row),"") | G39: =IF(AND(ISNUMBER(F39),ISNUMBER(E39),F39<>0),E39/F39-1,"") | H39: =IFERROR(INDEX(cd_Diesel_Mining_L_YTD,rpt_Row),"") | I39: =IFERROR(INDEX(cd_Bud_Diesel_Mining_L_YTD,rpt_Row),"") | J39: =IF(AND(ISNUMBER(I39),ISNUMBER(H39),I39<>0),H39/I39-1,"")
B40: Excavator availability | C40: % | D40: =IFERROR(INDEX(cd_Exc_Availability_pct,rpt_Row),"") | E40: =IFERROR(INDEX(cd_Exc_Availability_pct_MTD,rpt_Row),"") | H40: =IFERROR(INDEX(cd_Exc_Availability_pct_YTD,rpt_Row),"")
B41: Excavator utilisation | C41: % | D41: =IFERROR(INDEX(cd_Exc_Utilisation_pct,rpt_Row),"") | E41: =IFERROR(INDEX(cd_Exc_Utilisation_pct_MTD,rpt_Row),"") | H41: =IFERROR(INDEX(cd_Exc_Utilisation_pct_YTD,rpt_Row),"")
B42: Excavator productivity (TMM + rehandle) | C42: t/h | D42: =IFERROR(INDEX(cd_Exc_Productivity_tph,rpt_Row),"") | E42: =IFERROR(INDEX(cd_Exc_Productivity_tph_MTD,rpt_Row),"") | H42: =IFERROR(INDEX(cd_Exc_Productivity_tph_YTD,rpt_Row),"")
B43: Truck availability | C43: % | D43: =IFERROR(INDEX(cd_Trk_Availability_pct,rpt_Row),"") | E43: =IFERROR(INDEX(cd_Trk_Availability_pct_MTD,rpt_Row),"") | H43: =IFERROR(INDEX(cd_Trk_Availability_pct_YTD,rpt_Row),"")
B44: Truck utilisation | C44: % | D44: =IFERROR(INDEX(cd_Trk_Utilisation_pct,rpt_Row),"") | E44: =IFERROR(INDEX(cd_Trk_Utilisation_pct_MTD,rpt_Row),"") | H44: =IFERROR(INDEX(cd_Trk_Utilisation_pct_YTD,rpt_Row),"")
B45: Truck productivity (TMM + rehandle) | C45: t/h | D45: =IFERROR(INDEX(cd_Trk_Productivity_tph,rpt_Row),"") | E45: =IFERROR(INDEX(cd_Trk_Productivity_tph_MTD,rpt_Row),"") | H45: =IFERROR(INDEX(cd_Trk_Productivity_tph_YTD,rpt_Row),"")
B47: PROCESSING | C47: Unit | D47: Day | E47: MTD | F47: MTD budget | G47: Var % | H47: YTD | I47: YTD budget | J47: Var %
B48: Crushed | C48: t | D48: =IFERROR(INDEX(cd_Crushed_t,rpt_Row),"") | E48: =IFERROR(INDEX(cd_Crushed_t_MTD,rpt_Row),"") | H48: =IFERROR(INDEX(cd_Crushed_t_YTD,rpt_Row),"")
B49: Milled | C49: t | D49: =IFERROR(INDEX(cd_Milled_t,rpt_Row),"") | E49: =IFERROR(INDEX(cd_Milled_t_MTD,rpt_Row),"") | F49: =IFERROR(INDEX(cd_Bud_Milled_t_MTD,rpt_Row),"") | G49: =IF(AND(ISNUMBER(F49),ISNUMBER(E49),F49<>0),E49/F49-1,"") | H49: =IFERROR(INDEX(cd_Milled_t_YTD,rpt_Row),"") | I49: =IFERROR(INDEX(cd_Bud_Milled_t_YTD,rpt_Row),"") | J49: =IF(AND(ISNUMBER(I49),ISNUMBER(H49),I49<>0),H49/I49-1,"")
B50: Head grade | C50: g/t | D50: =IFERROR(INDEX(cd_Head_Grade_gpt,rpt_Row),"") | E50: =IFERROR(INDEX(cd_Head_Grade_gpt_MTD,rpt_Row),"") | F50: =IFERROR(INDEX(cd_Bud_Head_Grade_gpt_MTD,rpt_Row),"") | G50: =IF(AND(ISNUMBER(F50),ISNUMBER(E50),F50<>0),E50/F50-1,"") | H50: =IFERROR(INDEX(cd_Head_Grade_gpt_YTD,rpt_Row),"") | I50: =IFERROR(INDEX(cd_Bud_Head_Grade_gpt_YTD,rpt_Row),"") | J50: =IF(AND(ISNUMBER(I50),ISNUMBER(H50),I50<>0),H50/I50-1,"")
B51: Contained gold in feed | C51: oz | D51: =IFERROR(INDEX(cd_Feed_oz,rpt_Row),"") | E51: =IFERROR(INDEX(cd_Feed_oz_MTD,rpt_Row),"") | F51: =IFERROR(INDEX(cd_Bud_Feed_oz_MTD,rpt_Row),"") | G51: =IF(AND(ISNUMBER(F51),ISNUMBER(E51),F51<>0),E51/F51-1,"") | H51: =IFERROR(INDEX(cd_Feed_oz_YTD,rpt_Row),"") | I51: =IFERROR(INDEX(cd_Bud_Feed_oz_YTD,rpt_Row),"") | J51: =IF(AND(ISNUMBER(I51),ISNUMBER(H51),I51<>0),H51/I51-1,"")
B52: Recovery | C52: % | D52: =IFERROR(INDEX(cd_Recovery_pct,rpt_Row),"") | E52: =IFERROR(INDEX(cd_Recovery_pct_MTD,rpt_Row),"") | F52: =IFERROR(INDEX(cd_Bud_Recovery_pct_MTD,rpt_Row),"") | G52: =IF(AND(ISNUMBER(F52),ISNUMBER(E52),F52<>0),E52/F52-1,"") | H52: =IFERROR(INDEX(cd_Recovery_pct_YTD,rpt_Row),"") | I52: =IFERROR(INDEX(cd_Bud_Recovery_pct_YTD,rpt_Row),"") | J52: =IF(AND(ISNUMBER(I52),ISNUMBER(H52),I52<>0),H52/I52-1,"")
B53: Gold recovered | C53: oz | D53: =IFERROR(INDEX(cd_Recovered_oz,rpt_Row),"") | E53: =IFERROR(INDEX(cd_Recovered_oz_MTD,rpt_Row),"") | F53: =IFERROR(INDEX(cd_Bud_Recovered_oz_MTD,rpt_Row),"") | G53: =IF(AND(ISNUMBER(F53),ISNUMBER(E53),F53<>0),E53/F53-1,"") | H53: =IFERROR(INDEX(cd_Recovered_oz_YTD,rpt_Row),"") | I53: =IFERROR(INDEX(cd_Bud_Recovered_oz_YTD,rpt_Row),"") | J53: =IF(AND(ISNUMBER(I53),ISNUMBER(H53),I53<>0),H53/I53-1,"")
B54: Gravity gold | C54: oz | D54: =IFERROR(INDEX(cd_Gravity_Gold_oz,rpt_Row),"") | E54: =IFERROR(INDEX(cd_Gravity_Gold_oz_MTD,rpt_Row),"") | H54: =IFERROR(INDEX(cd_Gravity_Gold_oz_YTD,rpt_Row),"")
B55: Gravity share of gold recovered | C55: % | D55: =IFERROR(INDEX(cd_Gravity_Share_pct,rpt_Row),"") | E55: =IFERROR(INDEX(cd_Gravity_Share_pct_MTD,rpt_Row),"") | H55: =IFERROR(INDEX(cd_Gravity_Share_pct_YTD,rpt_Row),"")
B56: Gold poured | C56: oz | D56: =IFERROR(INDEX(cd_Gold_Poured_oz,rpt_Row),"") | E56: =IFERROR(INDEX(cd_Gold_Poured_oz_MTD,rpt_Row),"") | F56: =IFERROR(INDEX(cd_Bud_Gold_Poured_oz_MTD,rpt_Row),"") | G56: =IF(AND(ISNUMBER(F56),ISNUMBER(E56),F56<>0),E56/F56-1,"") | H56: =IFERROR(INDEX(cd_Gold_Poured_oz_YTD,rpt_Row),"") | I56: =IFERROR(INDEX(cd_Bud_Gold_Poured_oz_YTD,rpt_Row),"") | J56: =IF(AND(ISNUMBER(I56),ISNUMBER(H56),I56<>0),H56/I56-1,"")
B57: Mill throughput | C57: t/h | D57: =IFERROR(INDEX(cd_Throughput_tph,rpt_Row),"") | E57: =IFERROR(INDEX(cd_Throughput_tph_MTD,rpt_Row),"") | H57: =IFERROR(INDEX(cd_Throughput_tph_YTD,rpt_Row),"")
B58: Mill run hours | C58: h | D58: =IFERROR(INDEX(cd_Mill_Run_h,rpt_Row),"") | E58: =IFERROR(INDEX(cd_Mill_Run_h_MTD,rpt_Row),"") | H58: =IFERROR(INDEX(cd_Mill_Run_h_YTD,rpt_Row),"")
B59: Mill availability | C59: % | D59: =IFERROR(INDEX(cd_Mill_Availability_pct,rpt_Row),"") | E59: =IFERROR(INDEX(cd_Mill_Availability_pct_MTD,rpt_Row),"") | H59: =IFERROR(INDEX(cd_Mill_Availability_pct_YTD,rpt_Row),"")
B60: Mill utilisation | C60: % | D60: =IFERROR(INDEX(cd_Mill_Utilisation_pct,rpt_Row),"") | E60: =IFERROR(INDEX(cd_Mill_Utilisation_pct_MTD,rpt_Row),"") | H60: =IFERROR(INDEX(cd_Mill_Utilisation_pct_YTD,rpt_Row),"")
B61: Cyanide consumption | C61: kg/t | D61: =IFERROR(INDEX(cd_Cyanide_kgpt,rpt_Row),"") | E61: =IFERROR(INDEX(cd_Cyanide_kgpt_MTD,rpt_Row),"") | H61: =IFERROR(INDEX(cd_Cyanide_kgpt_YTD,rpt_Row),"")
B62: Lime consumption | C62: kg/t | D62: =IFERROR(INDEX(cd_Lime_kgpt,rpt_Row),"") | E62: =IFERROR(INDEX(cd_Lime_kgpt_MTD,rpt_Row),"") | H62: =IFERROR(INDEX(cd_Lime_kgpt_YTD,rpt_Row),"")
B63: Power consumption | C63: kWh/t | D63: =IFERROR(INDEX(cd_Power_kWhpt,rpt_Row),"") | E63: =IFERROR(INDEX(cd_Power_kWhpt_MTD,rpt_Row),"") | H63: =IFERROR(INDEX(cd_Power_kWhpt_YTD,rpt_Row),"")
B64: Gold in circuit (end of day) | C64: oz | D64: =IFERROR(INDEX(cd_GIC_oz,rpt_Row),"")
B66: GOLD | C66: Unit | D66: Day | E66: MTD | F66: MTD budget | G66: Var % | H66: YTD | I66: YTD budget | J66: Var %
B67: Gold shipped | C67: oz | D67: =IFERROR(INDEX(cd_Gold_Shipped_oz,rpt_Row),"") | E67: =IFERROR(INDEX(cd_Gold_Shipped_oz_MTD,rpt_Row),"") | H67: =IFERROR(INDEX(cd_Gold_Shipped_oz_YTD,rpt_Row),"")
B68: Gold sold | C68: oz | D68: =IFERROR(INDEX(cd_Gold_Sold_oz,rpt_Row),"") | E68: =IFERROR(INDEX(cd_Gold_Sold_oz_MTD,rpt_Row),"") | H68: =IFERROR(INDEX(cd_Gold_Sold_oz_YTD,rpt_Row),"")
B69: Dore shipped | C69: kg | D69: =IFERROR(INDEX(cd_Dore_Shipped_kg,rpt_Row),"") | E69: =IFERROR(INDEX(cd_Dore_Shipped_kg_MTD,rpt_Row),"") | H69: =IFERROR(INDEX(cd_Dore_Shipped_kg_YTD,rpt_Row),"")
B70: =IF(cfg_FeedCheck="OK","",cfg_FeedCheck&" (Config): the plant feed deduction below is wrong until this is fixed")
B71: STOCKPILES (to report date) | D71: Opening t | E71: Opening g/t | F71: In t | G71: Out t | H71: Plant feed t | I71: Balance t | J71: Balance g/t
B72: =IF(OR(NOT(ISNUMBER(rpt_Row)),INDEX(tblStockpiles[Stockpile],1)=""),"",INDEX(tblStockpiles[Stockpile],1)) | D72: =IF(OR(NOT(ISNUMBER(rpt_Row)),INDEX(tblStockpiles[Stockpile],1)=""),"",INDEX(tblStockpiles[Opening_t],1)) | E72: =IF(OR(NOT(ISNUMBER(rpt_Row)),INDEX(tblStockpiles[Stockpile],1)=""),"",INDEX(tblStockpiles[Opening_gpt],1)) | F72: =IF(OR(NOT(ISNUMBER(rpt_Row)),INDEX(tblStockpiles[Stockpile],1)=""),"",SUMIFS(tblMovement[Tonnes_t],tblMovement[Destination],INDEX(tblStockpiles[Stockpile],1),tblMovement[Date],">="&MAX(cfg_YearStart,N(INDEX(tblStockpiles[Survey_Date],1))),tblMovement[Date],"<="&rpt_Date)) | G72: =IF(OR(NOT(ISNUMBER(rpt_Row)),INDEX(tblStockpiles[Stockpile],1)=""),"",SUMIFS(tblMovement[Tonnes_t],tblMovement[Source],INDEX(tblStockpiles[Stockpile],1),tblMovement[Date],">="&MAX(cfg_YearStart,N(INDEX(tblStockpiles[Survey_Date],1))),tblMovement[Date],"<="&rpt_Date)) | H72: =IF(OR(NOT(ISNUMBER(rpt_Row)),INDEX(tblStockpiles[Stockpile],1)=""),"",IF(INDEX(tblStockpiles[Plant_Feed],1)="Y",SUMIFS(tblPlant[Milled_t],tblPlant[Date],">="&MAX(cfg_YearStart,N(INDEX(tblStockpiles[Survey_Date],1))),tblPlant[Date],"<="&rpt_Date)-SUMIFS(tblMovement[Tonnes_t],tblMovement[Dest_Type],"Plant",tblMovement[Date],">="&MAX(cfg_YearStart,N(INDEX(tblStockpiles[Survey_Date],1))),tblMovement[Date],"<="&rpt_Date),0)) | I72: =IF($B72="","",D72+F72-G72-H72) | J72: =IFERROR(IF(AND($B72<>"",I72>0),(D72*E72/cfg_TroyOz+SUMIFS(tblMovement[Contained_oz],tblMovement[Destination],INDEX(tblStockpiles[Stockpile],1),tblMovement[Date],">="&MAX(cfg_YearStart,N(INDEX(tblStockpiles[Survey_Date],1))),tblMovement[Date],"<="&rpt_Date)-SUMIFS(tblMovement[Contained_oz],tblMovement[Source],INDEX(tblStockpiles[Stockpile],1),tblMovement[Date],">="&MAX(cfg_YearStart,N(INDEX(tblStockpiles[Survey_Date],1))),tblMovement[Date],"<="&rpt_Date)-IF(INDEX(tblStockpiles[Plant_Feed],1)="Y",SUMIFS(tblPlant[Feed_oz],tblPlant[Date],">="&MAX(cfg_YearStart,N(INDEX(tblStockpiles[Survey_Date],1))),tblPlant[Date],"<="&rpt_Date)-SUMIFS(tblMovement[Contained_oz],tblMovement[Dest_Type],"Plant",tblMovement[Date],">="&MAX(cfg_YearStart,N(INDEX(tblStockpiles[Survey_Date],1))),tblMovement[Date],"<="&rpt_Date),0))*cfg_TroyOz/I72,""),"")
B73: =IF(OR(NOT(ISNUMBER(rpt_Row)),INDEX(tblStockpiles[Stockpile],2)=""),"",INDEX(tblStockpiles[Stockpile],2)) | D73: =IF(OR(NOT(ISNUMBER(rpt_Row)),INDEX(tblStockpiles[Stockpile],2)=""),"",INDEX(tblStockpiles[Opening_t],2)) | E73: =IF(OR(NOT(ISNUMBER(rpt_Row)),INDEX(tblStockpiles[Stockpile],2)=""),"",INDEX(tblStockpiles[Opening_gpt],2)) | F73: =IF(OR(NOT(ISNUMBER(rpt_Row)),INDEX(tblStockpiles[Stockpile],2)=""),"",SUMIFS(tblMovement[Tonnes_t],tblMovement[Destination],INDEX(tblStockpiles[Stockpile],2),tblMovement[Date],">="&MAX(cfg_YearStart,N(INDEX(tblStockpiles[Survey_Date],2))),tblMovement[Date],"<="&rpt_Date)) | G73: =IF(OR(NOT(ISNUMBER(rpt_Row)),INDEX(tblStockpiles[Stockpile],2)=""),"",SUMIFS(tblMovement[Tonnes_t],tblMovement[Source],INDEX(tblStockpiles[Stockpile],2),tblMovement[Date],">="&MAX(cfg_YearStart,N(INDEX(tblStockpiles[Survey_Date],2))),tblMovement[Date],"<="&rpt_Date)) | H73: =IF(OR(NOT(ISNUMBER(rpt_Row)),INDEX(tblStockpiles[Stockpile],2)=""),"",IF(INDEX(tblStockpiles[Plant_Feed],2)="Y",SUMIFS(tblPlant[Milled_t],tblPlant[Date],">="&MAX(cfg_YearStart,N(INDEX(tblStockpiles[Survey_Date],2))),tblPlant[Date],"<="&rpt_Date)-SUMIFS(tblMovement[Tonnes_t],tblMovement[Dest_Type],"Plant",tblMovement[Date],">="&MAX(cfg_YearStart,N(INDEX(tblStockpiles[Survey_Date],2))),tblMovement[Date],"<="&rpt_Date),0)) | I73: =IF($B73="","",D73+F73-G73-H73) | J73: =IFERROR(IF(AND($B73<>"",I73>0),(D73*E73/cfg_TroyOz+SUMIFS(tblMovement[Contained_oz],tblMovement[Destination],INDEX(tblStockpiles[Stockpile],2),tblMovement[Date],">="&MAX(cfg_YearStart,N(INDEX(tblStockpiles[Survey_Date],2))),tblMovement[Date],"<="&rpt_Date)-SUMIFS(tblMovement[Contained_oz],tblMovement[Source],INDEX(tblStockpiles[Stockpile],2),tblMovement[Date],">="&MAX(cfg_YearStart,N(INDEX(tblStockpiles[Survey_Date],2))),tblMovement[Date],"<="&rpt_Date)-IF(INDEX(tblStockpiles[Plant_Feed],2)="Y",SUMIFS(tblPlant[Feed_oz],tblPlant[Date],">="&MAX(cfg_YearStart,N(INDEX(tblStockpiles[Survey_Date],2))),tblPlant[Date],"<="&rpt_Date)-SUMIFS(tblMovement[Contained_oz],tblMovement[Dest_Type],"Plant",tblMovement[Date],">="&MAX(cfg_YearStart,N(INDEX(tblStockpiles[Survey_Date],2))),tblMovement[Date],"<="&rpt_Date),0))*cfg_TroyOz/I73,""),"")
B74: =IF(OR(NOT(ISNUMBER(rpt_Row)),INDEX(tblStockpiles[Stockpile],3)=""),"",INDEX(tblStockpiles[Stockpile],3)) | D74: =IF(OR(NOT(ISNUMBER(rpt_Row)),INDEX(tblStockpiles[Stockpile],3)=""),"",INDEX(tblStockpiles[Opening_t],3)) | E74: =IF(OR(NOT(ISNUMBER(rpt_Row)),INDEX(tblStockpiles[Stockpile],3)=""),"",INDEX(tblStockpiles[Opening_gpt],3)) | F74: =IF(OR(NOT(ISNUMBER(rpt_Row)),INDEX(tblStockpiles[Stockpile],3)=""),"",SUMIFS(tblMovement[Tonnes_t],tblMovement[Destination],INDEX(tblStockpiles[Stockpile],3),tblMovement[Date],">="&MAX(cfg_YearStart,N(INDEX(tblStockpiles[Survey_Date],3))),tblMovement[Date],"<="&rpt_Date)) | G74: =IF(OR(NOT(ISNUMBER(rpt_Row)),INDEX(tblStockpiles[Stockpile],3)=""),"",SUMIFS(tblMovement[Tonnes_t],tblMovement[Source],INDEX(tblStockpiles[Stockpile],3),tblMovement[Date],">="&MAX(cfg_YearStart,N(INDEX(tblStockpiles[Survey_Date],3))),tblMovement[Date],"<="&rpt_Date)) | H74: =IF(OR(NOT(ISNUMBER(rpt_Row)),INDEX(tblStockpiles[Stockpile],3)=""),"",IF(INDEX(tblStockpiles[Plant_Feed],3)="Y",SUMIFS(tblPlant[Milled_t],tblPlant[Date],">="&MAX(cfg_YearStart,N(INDEX(tblStockpiles[Survey_Date],3))),tblPlant[Date],"<="&rpt_Date)-SUMIFS(tblMovement[Tonnes_t],tblMovement[Dest_Type],"Plant",tblMovement[Date],">="&MAX(cfg_YearStart,N(INDEX(tblStockpiles[Survey_Date],3))),tblMovement[Date],"<="&rpt_Date),0)) | I74: =IF($B74="","",D74+F74-G74-H74) | J74: =IFERROR(IF(AND($B74<>"",I74>0),(D74*E74/cfg_TroyOz+SUMIFS(tblMovement[Contained_oz],tblMovement[Destination],INDEX(tblStockpiles[Stockpile],3),tblMovement[Date],">="&MAX(cfg_YearStart,N(INDEX(tblStockpiles[Survey_Date],3))),tblMovement[Date],"<="&rpt_Date)-SUMIFS(tblMovement[Contained_oz],tblMovement[Source],INDEX(tblStockpiles[Stockpile],3),tblMovement[Date],">="&MAX(cfg_YearStart,N(INDEX(tblStockpiles[Survey_Date],3))),tblMovement[Date],"<="&rpt_Date)-IF(INDEX(tblStockpiles[Plant_Feed],3)="Y",SUMIFS(tblPlant[Feed_oz],tblPlant[Date],">="&MAX(cfg_YearStart,N(INDEX(tblStockpiles[Survey_Date],3))),tblPlant[Date],"<="&rpt_Date)-SUMIFS(tblMovement[Contained_oz],tblMovement[Dest_Type],"Plant",tblMovement[Date],">="&MAX(cfg_YearStart,N(INDEX(tblStockpiles[Survey_Date],3))),tblMovement[Date],"<="&rpt_Date),0))*cfg_TroyOz/I74,""),"")
B75: =IF(OR(NOT(ISNUMBER(rpt_Row)),INDEX(tblStockpiles[Stockpile],4)=""),"",INDEX(tblStockpiles[Stockpile],4)) | D75: =IF(OR(NOT(ISNUMBER(rpt_Row)),INDEX(tblStockpiles[Stockpile],4)=""),"",INDEX(tblStockpiles[Opening_t],4)) | E75: =IF(OR(NOT(ISNUMBER(rpt_Row)),INDEX(tblStockpiles[Stockpile],4)=""),"",INDEX(tblStockpiles[Opening_gpt],4)) | F75: =IF(OR(NOT(ISNUMBER(rpt_Row)),INDEX(tblStockpiles[Stockpile],4)=""),"",SUMIFS(tblMovement[Tonnes_t],tblMovement[Destination],INDEX(tblStockpiles[Stockpile],4),tblMovement[Date],">="&MAX(cfg_YearStart,N(INDEX(tblStockpiles[Survey_Date],4))),tblMovement[Date],"<="&rpt_Date)) | G75: =IF(OR(NOT(ISNUMBER(rpt_Row)),INDEX(tblStockpiles[Stockpile],4)=""),"",SUMIFS(tblMovement[Tonnes_t],tblMovement[Source],INDEX(tblStockpiles[Stockpile],4),tblMovement[Date],">="&MAX(cfg_YearStart,N(INDEX(tblStockpiles[Survey_Date],4))),tblMovement[Date],"<="&rpt_Date)) | H75: =IF(OR(NOT(ISNUMBER(rpt_Row)),INDEX(tblStockpiles[Stockpile],4)=""),"",IF(INDEX(tblStockpiles[Plant_Feed],4)="Y",SUMIFS(tblPlant[Milled_t],tblPlant[Date],">="&MAX(cfg_YearStart,N(INDEX(tblStockpiles[Survey_Date],4))),tblPlant[Date],"<="&rpt_Date)-SUMIFS(tblMovement[Tonnes_t],tblMovement[Dest_Type],"Plant",tblMovement[Date],">="&MAX(cfg_YearStart,N(INDEX(tblStockpiles[Survey_Date],4))),tblMovement[Date],"<="&rpt_Date),0)) | I75: =IF($B75="","",D75+F75-G75-H75) | J75: =IFERROR(IF(AND($B75<>"",I75>0),(D75*E75/cfg_TroyOz+SUMIFS(tblMovement[Contained_oz],tblMovement[Destination],INDEX(tblStockpiles[Stockpile],4),tblMovement[Date],">="&MAX(cfg_YearStart,N(INDEX(tblStockpiles[Survey_Date],4))),tblMovement[Date],"<="&rpt_Date)-SUMIFS(tblMovement[Contained_oz],tblMovement[Source],INDEX(tblStockpiles[Stockpile],4),tblMovement[Date],">="&MAX(cfg_YearStart,N(INDEX(tblStockpiles[Survey_Date],4))),tblMovement[Date],"<="&rpt_Date)-IF(INDEX(tblStockpiles[Plant_Feed],4)="Y",SUMIFS(tblPlant[Feed_oz],tblPlant[Date],">="&MAX(cfg_YearStart,N(INDEX(tblStockpiles[Survey_Date],4))),tblPlant[Date],"<="&rpt_Date)-SUMIFS(tblMovement[Contained_oz],tblMovement[Dest_Type],"Plant",tblMovement[Date],">="&MAX(cfg_YearStart,N(INDEX(tblStockpiles[Survey_Date],4))),tblMovement[Date],"<="&rpt_Date),0))*cfg_TroyOz/I75,""),"")
B76: =IF(OR(NOT(ISNUMBER(rpt_Row)),INDEX(tblStockpiles[Stockpile],5)=""),"",INDEX(tblStockpiles[Stockpile],5)) | D76: =IF(OR(NOT(ISNUMBER(rpt_Row)),INDEX(tblStockpiles[Stockpile],5)=""),"",INDEX(tblStockpiles[Opening_t],5)) | E76: =IF(OR(NOT(ISNUMBER(rpt_Row)),INDEX(tblStockpiles[Stockpile],5)=""),"",INDEX(tblStockpiles[Opening_gpt],5)) | F76: =IF(OR(NOT(ISNUMBER(rpt_Row)),INDEX(tblStockpiles[Stockpile],5)=""),"",SUMIFS(tblMovement[Tonnes_t],tblMovement[Destination],INDEX(tblStockpiles[Stockpile],5),tblMovement[Date],">="&MAX(cfg_YearStart,N(INDEX(tblStockpiles[Survey_Date],5))),tblMovement[Date],"<="&rpt_Date)) | G76: =IF(OR(NOT(ISNUMBER(rpt_Row)),INDEX(tblStockpiles[Stockpile],5)=""),"",SUMIFS(tblMovement[Tonnes_t],tblMovement[Source],INDEX(tblStockpiles[Stockpile],5),tblMovement[Date],">="&MAX(cfg_YearStart,N(INDEX(tblStockpiles[Survey_Date],5))),tblMovement[Date],"<="&rpt_Date)) | H76: =IF(OR(NOT(ISNUMBER(rpt_Row)),INDEX(tblStockpiles[Stockpile],5)=""),"",IF(INDEX(tblStockpiles[Plant_Feed],5)="Y",SUMIFS(tblPlant[Milled_t],tblPlant[Date],">="&MAX(cfg_YearStart,N(INDEX(tblStockpiles[Survey_Date],5))),tblPlant[Date],"<="&rpt_Date)-SUMIFS(tblMovement[Tonnes_t],tblMovement[Dest_Type],"Plant",tblMovement[Date],">="&MAX(cfg_YearStart,N(INDEX(tblStockpiles[Survey_Date],5))),tblMovement[Date],"<="&rpt_Date),0)) | I76: =IF($B76="","",D76+F76-G76-H76) | J76: =IFERROR(IF(AND($B76<>"",I76>0),(D76*E76/cfg_TroyOz+SUMIFS(tblMovement[Contained_oz],tblMovement[Destination],INDEX(tblStockpiles[Stockpile],5),tblMovement[Date],">="&MAX(cfg_YearStart,N(INDEX(tblStockpiles[Survey_Date],5))),tblMovement[Date],"<="&rpt_Date)-SUMIFS(tblMovement[Contained_oz],tblMovement[Source],INDEX(tblStockpiles[Stockpile],5),tblMovement[Date],">="&MAX(cfg_YearStart,N(INDEX(tblStockpiles[Survey_Date],5))),tblMovement[Date],"<="&rpt_Date)-IF(INDEX(tblStockpiles[Plant_Feed],5)="Y",SUMIFS(tblPlant[Feed_oz],tblPlant[Date],">="&MAX(cfg_YearStart,N(INDEX(tblStockpiles[Survey_Date],5))),tblPlant[Date],"<="&rpt_Date)-SUMIFS(tblMovement[Contained_oz],tblMovement[Dest_Type],"Plant",tblMovement[Date],">="&MAX(cfg_YearStart,N(INDEX(tblStockpiles[Survey_Date],5))),tblMovement[Date],"<="&rpt_Date),0))*cfg_TroyOz/I76,""),"")
B77: =IF(OR(NOT(ISNUMBER(rpt_Row)),INDEX(tblStockpiles[Stockpile],6)=""),"",INDEX(tblStockpiles[Stockpile],6)) | D77: =IF(OR(NOT(ISNUMBER(rpt_Row)),INDEX(tblStockpiles[Stockpile],6)=""),"",INDEX(tblStockpiles[Opening_t],6)) | E77: =IF(OR(NOT(ISNUMBER(rpt_Row)),INDEX(tblStockpiles[Stockpile],6)=""),"",INDEX(tblStockpiles[Opening_gpt],6)) | F77: =IF(OR(NOT(ISNUMBER(rpt_Row)),INDEX(tblStockpiles[Stockpile],6)=""),"",SUMIFS(tblMovement[Tonnes_t],tblMovement[Destination],INDEX(tblStockpiles[Stockpile],6),tblMovement[Date],">="&MAX(cfg_YearStart,N(INDEX(tblStockpiles[Survey_Date],6))),tblMovement[Date],"<="&rpt_Date)) | G77: =IF(OR(NOT(ISNUMBER(rpt_Row)),INDEX(tblStockpiles[Stockpile],6)=""),"",SUMIFS(tblMovement[Tonnes_t],tblMovement[Source],INDEX(tblStockpiles[Stockpile],6),tblMovement[Date],">="&MAX(cfg_YearStart,N(INDEX(tblStockpiles[Survey_Date],6))),tblMovement[Date],"<="&rpt_Date)) | H77: =IF(OR(NOT(ISNUMBER(rpt_Row)),INDEX(tblStockpiles[Stockpile],6)=""),"",IF(INDEX(tblStockpiles[Plant_Feed],6)="Y",SUMIFS(tblPlant[Milled_t],tblPlant[Date],">="&MAX(cfg_YearStart,N(INDEX(tblStockpiles[Survey_Date],6))),tblPlant[Date],"<="&rpt_Date)-SUMIFS(tblMovement[Tonnes_t],tblMovement[Dest_Type],"Plant",tblMovement[Date],">="&MAX(cfg_YearStart,N(INDEX(tblStockpiles[Survey_Date],6))),tblMovement[Date],"<="&rpt_Date),0)) | I77: =IF($B77="","",D77+F77-G77-H77) | J77: =IFERROR(IF(AND($B77<>"",I77>0),(D77*E77/cfg_TroyOz+SUMIFS(tblMovement[Contained_oz],tblMovement[Destination],INDEX(tblStockpiles[Stockpile],6),tblMovement[Date],">="&MAX(cfg_YearStart,N(INDEX(tblStockpiles[Survey_Date],6))),tblMovement[Date],"<="&rpt_Date)-SUMIFS(tblMovement[Contained_oz],tblMovement[Source],INDEX(tblStockpiles[Stockpile],6),tblMovement[Date],">="&MAX(cfg_YearStart,N(INDEX(tblStockpiles[Survey_Date],6))),tblMovement[Date],"<="&rpt_Date)-IF(INDEX(tblStockpiles[Plant_Feed],6)="Y",SUMIFS(tblPlant[Feed_oz],tblPlant[Date],">="&MAX(cfg_YearStart,N(INDEX(tblStockpiles[Survey_Date],6))),tblPlant[Date],"<="&rpt_Date)-SUMIFS(tblMovement[Contained_oz],tblMovement[Dest_Type],"Plant",tblMovement[Date],">="&MAX(cfg_YearStart,N(INDEX(tblStockpiles[Survey_Date],6))),tblMovement[Date],"<="&rpt_Date),0))*cfg_TroyOz/I77,""),"")
B78: =IF(OR(NOT(ISNUMBER(rpt_Row)),INDEX(tblStockpiles[Stockpile],7)=""),"",INDEX(tblStockpiles[Stockpile],7)) | D78: =IF(OR(NOT(ISNUMBER(rpt_Row)),INDEX(tblStockpiles[Stockpile],7)=""),"",INDEX(tblStockpiles[Opening_t],7)) | E78: =IF(OR(NOT(ISNUMBER(rpt_Row)),INDEX(tblStockpiles[Stockpile],7)=""),"",INDEX(tblStockpiles[Opening_gpt],7)) | F78: =IF(OR(NOT(ISNUMBER(rpt_Row)),INDEX(tblStockpiles[Stockpile],7)=""),"",SUMIFS(tblMovement[Tonnes_t],tblMovement[Destination],INDEX(tblStockpiles[Stockpile],7),tblMovement[Date],">="&MAX(cfg_YearStart,N(INDEX(tblStockpiles[Survey_Date],7))),tblMovement[Date],"<="&rpt_Date)) | G78: =IF(OR(NOT(ISNUMBER(rpt_Row)),INDEX(tblStockpiles[Stockpile],7)=""),"",SUMIFS(tblMovement[Tonnes_t],tblMovement[Source],INDEX(tblStockpiles[Stockpile],7),tblMovement[Date],">="&MAX(cfg_YearStart,N(INDEX(tblStockpiles[Survey_Date],7))),tblMovement[Date],"<="&rpt_Date)) | H78: =IF(OR(NOT(ISNUMBER(rpt_Row)),INDEX(tblStockpiles[Stockpile],7)=""),"",IF(INDEX(tblStockpiles[Plant_Feed],7)="Y",SUMIFS(tblPlant[Milled_t],tblPlant[Date],">="&MAX(cfg_YearStart,N(INDEX(tblStockpiles[Survey_Date],7))),tblPlant[Date],"<="&rpt_Date)-SUMIFS(tblMovement[Tonnes_t],tblMovement[Dest_Type],"Plant",tblMovement[Date],">="&MAX(cfg_YearStart,N(INDEX(tblStockpiles[Survey_Date],7))),tblMovement[Date],"<="&rpt_Date),0)) | I78: =IF($B78="","",D78+F78-G78-H78) | J78: =IFERROR(IF(AND($B78<>"",I78>0),(D78*E78/cfg_TroyOz+SUMIFS(tblMovement[Contained_oz],tblMovement[Destination],INDEX(tblStockpiles[Stockpile],7),tblMovement[Date],">="&MAX(cfg_YearStart,N(INDEX(tblStockpiles[Survey_Date],7))),tblMovement[Date],"<="&rpt_Date)-SUMIFS(tblMovement[Contained_oz],tblMovement[Source],INDEX(tblStockpiles[Stockpile],7),tblMovement[Date],">="&MAX(cfg_YearStart,N(INDEX(tblStockpiles[Survey_Date],7))),tblMovement[Date],"<="&rpt_Date)-IF(INDEX(tblStockpiles[Plant_Feed],7)="Y",SUMIFS(tblPlant[Feed_oz],tblPlant[Date],">="&MAX(cfg_YearStart,N(INDEX(tblStockpiles[Survey_Date],7))),tblPlant[Date],"<="&rpt_Date)-SUMIFS(tblMovement[Contained_oz],tblMovement[Dest_Type],"Plant",tblMovement[Date],">="&MAX(cfg_YearStart,N(INDEX(tblStockpiles[Survey_Date],7))),tblMovement[Date],"<="&rpt_Date),0))*cfg_TroyOz/I78,""),"")
B79: =IF(OR(NOT(ISNUMBER(rpt_Row)),INDEX(tblStockpiles[Stockpile],8)=""),"",INDEX(tblStockpiles[Stockpile],8)) | D79: =IF(OR(NOT(ISNUMBER(rpt_Row)),INDEX(tblStockpiles[Stockpile],8)=""),"",INDEX(tblStockpiles[Opening_t],8)) | E79: =IF(OR(NOT(ISNUMBER(rpt_Row)),INDEX(tblStockpiles[Stockpile],8)=""),"",INDEX(tblStockpiles[Opening_gpt],8)) | F79: =IF(OR(NOT(ISNUMBER(rpt_Row)),INDEX(tblStockpiles[Stockpile],8)=""),"",SUMIFS(tblMovement[Tonnes_t],tblMovement[Destination],INDEX(tblStockpiles[Stockpile],8),tblMovement[Date],">="&MAX(cfg_YearStart,N(INDEX(tblStockpiles[Survey_Date],8))),tblMovement[Date],"<="&rpt_Date)) | G79: =IF(OR(NOT(ISNUMBER(rpt_Row)),INDEX(tblStockpiles[Stockpile],8)=""),"",SUMIFS(tblMovement[Tonnes_t],tblMovement[Source],INDEX(tblStockpiles[Stockpile],8),tblMovement[Date],">="&MAX(cfg_YearStart,N(INDEX(tblStockpiles[Survey_Date],8))),tblMovement[Date],"<="&rpt_Date)) | H79: =IF(OR(NOT(ISNUMBER(rpt_Row)),INDEX(tblStockpiles[Stockpile],8)=""),"",IF(INDEX(tblStockpiles[Plant_Feed],8)="Y",SUMIFS(tblPlant[Milled_t],tblPlant[Date],">="&MAX(cfg_YearStart,N(INDEX(tblStockpiles[Survey_Date],8))),tblPlant[Date],"<="&rpt_Date)-SUMIFS(tblMovement[Tonnes_t],tblMovement[Dest_Type],"Plant",tblMovement[Date],">="&MAX(cfg_YearStart,N(INDEX(tblStockpiles[Survey_Date],8))),tblMovement[Date],"<="&rpt_Date),0)) | I79: =IF($B79="","",D79+F79-G79-H79) | J79: =IFERROR(IF(AND($B79<>"",I79>0),(D79*E79/cfg_TroyOz+SUMIFS(tblMovement[Contained_oz],tblMovement[Destination],INDEX(tblStockpiles[Stockpile],8),tblMovement[Date],">="&MAX(cfg_YearStart,N(INDEX(tblStockpiles[Survey_Date],8))),tblMovement[Date],"<="&rpt_Date)-SUMIFS(tblMovement[Contained_oz],tblMovement[Source],INDEX(tblStockpiles[Stockpile],8),tblMovement[Date],">="&MAX(cfg_YearStart,N(INDEX(tblStockpiles[Survey_Date],8))),tblMovement[Date],"<="&rpt_Date)-IF(INDEX(tblStockpiles[Plant_Feed],8)="Y",SUMIFS(tblPlant[Feed_oz],tblPlant[Date],">="&MAX(cfg_YearStart,N(INDEX(tblStockpiles[Survey_Date],8))),tblPlant[Date],"<="&rpt_Date)-SUMIFS(tblMovement[Contained_oz],tblMovement[Dest_Type],"Plant",tblMovement[Date],">="&MAX(cfg_YearStart,N(INDEX(tblStockpiles[Survey_Date],8))),tblMovement[Date],"<="&rpt_Date),0))*cfg_TroyOz/I79,""),"")
B80: =IF(OR(NOT(ISNUMBER(rpt_Row)),INDEX(tblStockpiles[Stockpile],9)=""),"",INDEX(tblStockpiles[Stockpile],9)) | D80: =IF(OR(NOT(ISNUMBER(rpt_Row)),INDEX(tblStockpiles[Stockpile],9)=""),"",INDEX(tblStockpiles[Opening_t],9)) | E80: =IF(OR(NOT(ISNUMBER(rpt_Row)),INDEX(tblStockpiles[Stockpile],9)=""),"",INDEX(tblStockpiles[Opening_gpt],9)) | F80: =IF(OR(NOT(ISNUMBER(rpt_Row)),INDEX(tblStockpiles[Stockpile],9)=""),"",SUMIFS(tblMovement[Tonnes_t],tblMovement[Destination],INDEX(tblStockpiles[Stockpile],9),tblMovement[Date],">="&MAX(cfg_YearStart,N(INDEX(tblStockpiles[Survey_Date],9))),tblMovement[Date],"<="&rpt_Date)) | G80: =IF(OR(NOT(ISNUMBER(rpt_Row)),INDEX(tblStockpiles[Stockpile],9)=""),"",SUMIFS(tblMovement[Tonnes_t],tblMovement[Source],INDEX(tblStockpiles[Stockpile],9),tblMovement[Date],">="&MAX(cfg_YearStart,N(INDEX(tblStockpiles[Survey_Date],9))),tblMovement[Date],"<="&rpt_Date)) | H80: =IF(OR(NOT(ISNUMBER(rpt_Row)),INDEX(tblStockpiles[Stockpile],9)=""),"",IF(INDEX(tblStockpiles[Plant_Feed],9)="Y",SUMIFS(tblPlant[Milled_t],tblPlant[Date],">="&MAX(cfg_YearStart,N(INDEX(tblStockpiles[Survey_Date],9))),tblPlant[Date],"<="&rpt_Date)-SUMIFS(tblMovement[Tonnes_t],tblMovement[Dest_Type],"Plant",tblMovement[Date],">="&MAX(cfg_YearStart,N(INDEX(tblStockpiles[Survey_Date],9))),tblMovement[Date],"<="&rpt_Date),0)) | I80: =IF($B80="","",D80+F80-G80-H80) | J80: =IFERROR(IF(AND($B80<>"",I80>0),(D80*E80/cfg_TroyOz+SUMIFS(tblMovement[Contained_oz],tblMovement[Destination],INDEX(tblStockpiles[Stockpile],9),tblMovement[Date],">="&MAX(cfg_YearStart,N(INDEX(tblStockpiles[Survey_Date],9))),tblMovement[Date],"<="&rpt_Date)-SUMIFS(tblMovement[Contained_oz],tblMovement[Source],INDEX(tblStockpiles[Stockpile],9),tblMovement[Date],">="&MAX(cfg_YearStart,N(INDEX(tblStockpiles[Survey_Date],9))),tblMovement[Date],"<="&rpt_Date)-IF(INDEX(tblStockpiles[Plant_Feed],9)="Y",SUMIFS(tblPlant[Feed_oz],tblPlant[Date],">="&MAX(cfg_YearStart,N(INDEX(tblStockpiles[Survey_Date],9))),tblPlant[Date],"<="&rpt_Date)-SUMIFS(tblMovement[Contained_oz],tblMovement[Dest_Type],"Plant",tblMovement[Date],">="&MAX(cfg_YearStart,N(INDEX(tblStockpiles[Survey_Date],9))),tblMovement[Date],"<="&rpt_Date),0))*cfg_TroyOz/I80,""),"")
B81: =IF(OR(NOT(ISNUMBER(rpt_Row)),INDEX(tblStockpiles[Stockpile],10)=""),"",INDEX(tblStockpiles[Stockpile],10)) | D81: =IF(OR(NOT(ISNUMBER(rpt_Row)),INDEX(tblStockpiles[Stockpile],10)=""),"",INDEX(tblStockpiles[Opening_t],10)) | E81: =IF(OR(NOT(ISNUMBER(rpt_Row)),INDEX(tblStockpiles[Stockpile],10)=""),"",INDEX(tblStockpiles[Opening_gpt],10)) | F81: =IF(OR(NOT(ISNUMBER(rpt_Row)),INDEX(tblStockpiles[Stockpile],10)=""),"",SUMIFS(tblMovement[Tonnes_t],tblMovement[Destination],INDEX(tblStockpiles[Stockpile],10),tblMovement[Date],">="&MAX(cfg_YearStart,N(INDEX(tblStockpiles[Survey_Date],10))),tblMovement[Date],"<="&rpt_Date)) | G81: =IF(OR(NOT(ISNUMBER(rpt_Row)),INDEX(tblStockpiles[Stockpile],10)=""),"",SUMIFS(tblMovement[Tonnes_t],tblMovement[Source],INDEX(tblStockpiles[Stockpile],10),tblMovement[Date],">="&MAX(cfg_YearStart,N(INDEX(tblStockpiles[Survey_Date],10))),tblMovement[Date],"<="&rpt_Date)) | H81: =IF(OR(NOT(ISNUMBER(rpt_Row)),INDEX(tblStockpiles[Stockpile],10)=""),"",IF(INDEX(tblStockpiles[Plant_Feed],10)="Y",SUMIFS(tblPlant[Milled_t],tblPlant[Date],">="&MAX(cfg_YearStart,N(INDEX(tblStockpiles[Survey_Date],10))),tblPlant[Date],"<="&rpt_Date)-SUMIFS(tblMovement[Tonnes_t],tblMovement[Dest_Type],"Plant",tblMovement[Date],">="&MAX(cfg_YearStart,N(INDEX(tblStockpiles[Survey_Date],10))),tblMovement[Date],"<="&rpt_Date),0)) | I81: =IF($B81="","",D81+F81-G81-H81) | J81: =IFERROR(IF(AND($B81<>"",I81>0),(D81*E81/cfg_TroyOz+SUMIFS(tblMovement[Contained_oz],tblMovement[Destination],INDEX(tblStockpiles[Stockpile],10),tblMovement[Date],">="&MAX(cfg_YearStart,N(INDEX(tblStockpiles[Survey_Date],10))),tblMovement[Date],"<="&rpt_Date)-SUMIFS(tblMovement[Contained_oz],tblMovement[Source],INDEX(tblStockpiles[Stockpile],10),tblMovement[Date],">="&MAX(cfg_YearStart,N(INDEX(tblStockpiles[Survey_Date],10))),tblMovement[Date],"<="&rpt_Date)-IF(INDEX(tblStockpiles[Plant_Feed],10)="Y",SUMIFS(tblPlant[Feed_oz],tblPlant[Date],">="&MAX(cfg_YearStart,N(INDEX(tblStockpiles[Survey_Date],10))),tblPlant[Date],"<="&rpt_Date)-SUMIFS(tblMovement[Contained_oz],tblMovement[Dest_Type],"Plant",tblMovement[Date],">="&MAX(cfg_YearStart,N(INDEX(tblStockpiles[Survey_Date],10))),tblMovement[Date],"<="&rpt_Date),0))*cfg_TroyOz/I81,""),"")
B83: COMMENTARY | C83: Area
B84: =IFERROR(INDEX(tblCommentary[Area],MATCH(rpt_Date&"|"&1,tblCommentary[Key_Day],0)),"") | C84: =IFERROR(INDEX(tblCommentary[Comment],MATCH(rpt_Date&"|"&1,tblCommentary[Key_Day],0)),"")
B85: =IFERROR(INDEX(tblCommentary[Area],MATCH(rpt_Date&"|"&2,tblCommentary[Key_Day],0)),"") | C85: =IFERROR(INDEX(tblCommentary[Comment],MATCH(rpt_Date&"|"&2,tblCommentary[Key_Day],0)),"")
B86: =IFERROR(INDEX(tblCommentary[Area],MATCH(rpt_Date&"|"&3,tblCommentary[Key_Day],0)),"") | C86: =IFERROR(INDEX(tblCommentary[Comment],MATCH(rpt_Date&"|"&3,tblCommentary[Key_Day],0)),"")
B87: =IFERROR(INDEX(tblCommentary[Area],MATCH(rpt_Date&"|"&4,tblCommentary[Key_Day],0)),"") | C87: =IFERROR(INDEX(tblCommentary[Comment],MATCH(rpt_Date&"|"&4,tblCommentary[Key_Day],0)),"")
B88: =IFERROR(INDEX(tblCommentary[Area],MATCH(rpt_Date&"|"&5,tblCommentary[Key_Day],0)),"") | C88: =IFERROR(INDEX(tblCommentary[Comment],MATCH(rpt_Date&"|"&5,tblCommentary[Key_Day],0)),"")
B89: =IFERROR(INDEX(tblCommentary[Area],MATCH(rpt_Date&"|"&6,tblCommentary[Key_Day],0)),"") | C89: =IFERROR(INDEX(tblCommentary[Comment],MATCH(rpt_Date&"|"&6,tblCommentary[Key_Day],0)),"")
B90: =IFERROR(INDEX(tblCommentary[Area],MATCH(rpt_Date&"|"&7,tblCommentary[Key_Day],0)),"") | C90: =IFERROR(INDEX(tblCommentary[Comment],MATCH(rpt_Date&"|"&7,tblCommentary[Key_Day],0)),"")
B91: =IFERROR(INDEX(tblCommentary[Area],MATCH(rpt_Date&"|"&8,tblCommentary[Key_Day],0)),"") | C91: =IFERROR(INDEX(tblCommentary[Comment],MATCH(rpt_Date&"|"&8,tblCommentary[Key_Day],0)),"")
B92: =IFERROR(INDEX(tblCommentary[Area],MATCH(rpt_Date&"|"&9,tblCommentary[Key_Day],0)),"") | C92: =IFERROR(INDEX(tblCommentary[Comment],MATCH(rpt_Date&"|"&9,tblCommentary[Key_Day],0)),"")
B93: =IFERROR(INDEX(tblCommentary[Area],MATCH(rpt_Date&"|"&10,tblCommentary[Key_Day],0)),"") | C93: =IFERROR(INDEX(tblCommentary[Comment],MATCH(rpt_Date&"|"&10,tblCommentary[Key_Day],0)),"")
B94: =IFERROR(INDEX(tblCommentary[Area],MATCH(rpt_Date&"|"&11,tblCommentary[Key_Day],0)),"") | C94: =IFERROR(INDEX(tblCommentary[Comment],MATCH(rpt_Date&"|"&11,tblCommentary[Key_Day],0)),"")
B95: =IFERROR(INDEX(tblCommentary[Area],MATCH(rpt_Date&"|"&12,tblCommentary[Key_Day],0)),"") | C95: =IFERROR(INDEX(tblCommentary[Comment],MATCH(rpt_Date&"|"&12,tblCommentary[Key_Day],0)),"")
B96: =IFERROR(INDEX(tblCommentary[Area],MATCH(rpt_Date&"|"&13,tblCommentary[Key_Day],0)),"") | C96: =IFERROR(INDEX(tblCommentary[Comment],MATCH(rpt_Date&"|"&13,tblCommentary[Key_Day],0)),"")
B97: =IFERROR(INDEX(tblCommentary[Area],MATCH(rpt_Date&"|"&14,tblCommentary[Key_Day],0)),"") | C97: =IFERROR(INDEX(tblCommentary[Comment],MATCH(rpt_Date&"|"&14,tblCommentary[Key_Day],0)),"")
B98: =IFERROR(INDEX(tblCommentary[Area],MATCH(rpt_Date&"|"&15,tblCommentary[Key_Day],0)),"") | C98: =IFERROR(INDEX(tblCommentary[Comment],MATCH(rpt_Date&"|"&15,tblCommentary[Key_Day],0)),"")
B100: ="Generated by the Mako Production System workbook. Printed "&DAY(NOW())&" "&CHOOSE(MONTH(NOW()),"Jan","Feb","Mar","Apr","May","Jun","Jul","Aug","Sep","Oct","Nov","Dec")&" "&YEAR(NOW())&" "&TEXT(HOUR(NOW()),"00")&":"&TEXT(MINUTE(NOW()),"00")

Sheet Dashboard
B2: =cfg_Site&" dashboard "&cfg_Year
B3: ="Data to "&IF(N(cfg_LastDataDate)>0,DAY(cfg_LastDataDate)&" "&CHOOSE(MONTH(cfg_LastDataDate),"Jan","Feb","Mar","Apr","May","Jun","Jul","Aug","Sep","Oct","Nov","Dec")&" "&YEAR(cfg_LastDataDate),"(no plant data yet)")

Sheet Monthly_Summary
B2: =cfg_Site&" monthly summary "&cfg_Year
B3: ="Actuals to "&IF(N(cfg_LastDataDate)>0,DAY(cfg_LastDataDate)&" "&CHOOSE(MONTH(cfg_LastDataDate),"Jan","Feb","Mar","Apr","May","Jun","Jul","Aug","Sep","Oct","Nov","Dec")&" "&YEAR(cfg_LastDataDate),"(no plant data yet)")&". Budget from the Budget sheet, pro-rata to that date for the current month and the Year column; full month otherwise. Ratios are month values, not averages of days."
B5: KPI | D5: 46023 | E5: 46054 | F5: 46082 | G5: 46113 | H5: 46143 | I5: 46174 | J5: 46204 | K5: 46235 | L5: 46266 | M5: 46296 | N5: 46327 | O5: 46357 | P5: Year
B6: Hours worked | C6: Actual | D6: =IF(DATE(cfg_Year,1,1)>cfg_LastDataDate,"",IFERROR(INDEX(cd_Hours_Worked_MTD,MATCH(MIN(EOMONTH(DATE(cfg_Year,1,1),0),cfg_LastDataDate),cd_Date,0)),"")) | E6: =IF(DATE(cfg_Year,2,1)>cfg_LastDataDate,"",IFERROR(INDEX(cd_Hours_Worked_MTD,MATCH(MIN(EOMONTH(DATE(cfg_Year,2,1),0),cfg_LastDataDate),cd_Date,0)),"")) | F6: =IF(DATE(cfg_Year,3,1)>cfg_LastDataDate,"",IFERROR(INDEX(cd_Hours_Worked_MTD,MATCH(MIN(EOMONTH(DATE(cfg_Year,3,1),0),cfg_LastDataDate),cd_Date,0)),"")) | G6: =IF(DATE(cfg_Year,4,1)>cfg_LastDataDate,"",IFERROR(INDEX(cd_Hours_Worked_MTD,MATCH(MIN(EOMONTH(DATE(cfg_Year,4,1),0),cfg_LastDataDate),cd_Date,0)),"")) | H6: =IF(DATE(cfg_Year,5,1)>cfg_LastDataDate,"",IFERROR(INDEX(cd_Hours_Worked_MTD,MATCH(MIN(EOMONTH(DATE(cfg_Year,5,1),0),cfg_LastDataDate),cd_Date,0)),"")) | I6: =IF(DATE(cfg_Year,6,1)>cfg_LastDataDate,"",IFERROR(INDEX(cd_Hours_Worked_MTD,MATCH(MIN(EOMONTH(DATE(cfg_Year,6,1),0),cfg_LastDataDate),cd_Date,0)),"")) | J6: =IF(DATE(cfg_Year,7,1)>cfg_LastDataDate,"",IFERROR(INDEX(cd_Hours_Worked_MTD,MATCH(MIN(EOMONTH(DATE(cfg_Year,7,1),0),cfg_LastDataDate),cd_Date,0)),"")) | K6: =IF(DATE(cfg_Year,8,1)>cfg_LastDataDate,"",IFERROR(INDEX(cd_Hours_Worked_MTD,MATCH(MIN(EOMONTH(DATE(cfg_Year,8,1),0),cfg_LastDataDate),cd_Date,0)),"")) | L6: =IF(DATE(cfg_Year,9,1)>cfg_LastDataDate,"",IFERROR(INDEX(cd_Hours_Worked_MTD,MATCH(MIN(EOMONTH(DATE(cfg_Year,9,1),0),cfg_LastDataDate),cd_Date,0)),"")) | M6: =IF(DATE(cfg_Year,10,1)>cfg_LastDataDate,"",IFERROR(INDEX(cd_Hours_Worked_MTD,MATCH(MIN(EOMONTH(DATE(cfg_Year,10,1),0),cfg_LastDataDate),cd_Date,0)),"")) | N6: =IF(DATE(cfg_Year,11,1)>cfg_LastDataDate,"",IFERROR(INDEX(cd_Hours_Worked_MTD,MATCH(MIN(EOMONTH(DATE(cfg_Year,11,1),0),cfg_LastDataDate),cd_Date,0)),"")) | O6: =IF(DATE(cfg_Year,12,1)>cfg_LastDataDate,"",IFERROR(INDEX(cd_Hours_Worked_MTD,MATCH(MIN(EOMONTH(DATE(cfg_Year,12,1),0),cfg_LastDataDate),cd_Date,0)),"")) | P6: =IFERROR(INDEX(cd_Hours_Worked_YTD,MATCH(MIN(cfg_YearEnd,cfg_LastDataDate),cd_Date,0)),"")
C7: Budget | D7: =IF(DATE(cfg_Year,1,1)>cfg_LastDataDate,IFERROR(INDEX(cd_Bud_Hours_Worked_Month,MATCH(DATE(cfg_Year,1,1),cd_Date,0)),""),IFERROR(INDEX(cd_Bud_Hours_Worked_MTD,MATCH(MIN(EOMONTH(DATE(cfg_Year,1,1),0),cfg_LastDataDate),cd_Date,0)),"")) | E7: =IF(DATE(cfg_Year,2,1)>cfg_LastDataDate,IFERROR(INDEX(cd_Bud_Hours_Worked_Month,MATCH(DATE(cfg_Year,2,1),cd_Date,0)),""),IFERROR(INDEX(cd_Bud_Hours_Worked_MTD,MATCH(MIN(EOMONTH(DATE(cfg_Year,2,1),0),cfg_LastDataDate),cd_Date,0)),"")) | F7: =IF(DATE(cfg_Year,3,1)>cfg_LastDataDate,IFERROR(INDEX(cd_Bud_Hours_Worked_Month,MATCH(DATE(cfg_Year,3,1),cd_Date,0)),""),IFERROR(INDEX(cd_Bud_Hours_Worked_MTD,MATCH(MIN(EOMONTH(DATE(cfg_Year,3,1),0),cfg_LastDataDate),cd_Date,0)),"")) | G7: =IF(DATE(cfg_Year,4,1)>cfg_LastDataDate,IFERROR(INDEX(cd_Bud_Hours_Worked_Month,MATCH(DATE(cfg_Year,4,1),cd_Date,0)),""),IFERROR(INDEX(cd_Bud_Hours_Worked_MTD,MATCH(MIN(EOMONTH(DATE(cfg_Year,4,1),0),cfg_LastDataDate),cd_Date,0)),"")) | H7: =IF(DATE(cfg_Year,5,1)>cfg_LastDataDate,IFERROR(INDEX(cd_Bud_Hours_Worked_Month,MATCH(DATE(cfg_Year,5,1),cd_Date,0)),""),IFERROR(INDEX(cd_Bud_Hours_Worked_MTD,MATCH(MIN(EOMONTH(DATE(cfg_Year,5,1),0),cfg_LastDataDate),cd_Date,0)),"")) | I7: =IF(DATE(cfg_Year,6,1)>cfg_LastDataDate,IFERROR(INDEX(cd_Bud_Hours_Worked_Month,MATCH(DATE(cfg_Year,6,1),cd_Date,0)),""),IFERROR(INDEX(cd_Bud_Hours_Worked_MTD,MATCH(MIN(EOMONTH(DATE(cfg_Year,6,1),0),cfg_LastDataDate),cd_Date,0)),"")) | J7: =IF(DATE(cfg_Year,7,1)>cfg_LastDataDate,IFERROR(INDEX(cd_Bud_Hours_Worked_Month,MATCH(DATE(cfg_Year,7,1),cd_Date,0)),""),IFERROR(INDEX(cd_Bud_Hours_Worked_MTD,MATCH(MIN(EOMONTH(DATE(cfg_Year,7,1),0),cfg_LastDataDate),cd_Date,0)),"")) | K7: =IF(DATE(cfg_Year,8,1)>cfg_LastDataDate,IFERROR(INDEX(cd_Bud_Hours_Worked_Month,MATCH(DATE(cfg_Year,8,1),cd_Date,0)),""),IFERROR(INDEX(cd_Bud_Hours_Worked_MTD,MATCH(MIN(EOMONTH(DATE(cfg_Year,8,1),0),cfg_LastDataDate),cd_Date,0)),"")) | L7: =IF(DATE(cfg_Year,9,1)>cfg_LastDataDate,IFERROR(INDEX(cd_Bud_Hours_Worked_Month,MATCH(DATE(cfg_Year,9,1),cd_Date,0)),""),IFERROR(INDEX(cd_Bud_Hours_Worked_MTD,MATCH(MIN(EOMONTH(DATE(cfg_Year,9,1),0),cfg_LastDataDate),cd_Date,0)),"")) | M7: =IF(DATE(cfg_Year,10,1)>cfg_LastDataDate,IFERROR(INDEX(cd_Bud_Hours_Worked_Month,MATCH(DATE(cfg_Year,10,1),cd_Date,0)),""),IFERROR(INDEX(cd_Bud_Hours_Worked_MTD,MATCH(MIN(EOMONTH(DATE(cfg_Year,10,1),0),cfg_LastDataDate),cd_Date,0)),"")) | N7: =IF(DATE(cfg_Year,11,1)>cfg_LastDataDate,IFERROR(INDEX(cd_Bud_Hours_Worked_Month,MATCH(DATE(cfg_Year,11,1),cd_Date,0)),""),IFERROR(INDEX(cd_Bud_Hours_Worked_MTD,MATCH(MIN(EOMONTH(DATE(cfg_Year,11,1),0),cfg_LastDataDate),cd_Date,0)),"")) | O7: =IF(DATE(cfg_Year,12,1)>cfg_LastDataDate,IFERROR(INDEX(cd_Bud_Hours_Worked_Month,MATCH(DATE(cfg_Year,12,1),cd_Date,0)),""),IFERROR(INDEX(cd_Bud_Hours_Worked_MTD,MATCH(MIN(EOMONTH(DATE(cfg_Year,12,1),0),cfg_LastDataDate),cd_Date,0)),"")) | P7: =IFERROR(INDEX(cd_Bud_Hours_Worked_YTD,MATCH(IF(N(cfg_LastDataDate)>0,MIN(cfg_YearEnd,cfg_LastDataDate),cfg_YearEnd),cd_Date,0)),"")
C8: Variance | D8: =IF(AND(ISNUMBER(D6),ISNUMBER(D7),D7<>0),D6/D7-1,"") | E8: =IF(AND(ISNUMBER(E6),ISNUMBER(E7),E7<>0),E6/E7-1,"") | F8: =IF(AND(ISNUMBER(F6),ISNUMBER(F7),F7<>0),F6/F7-1,"") | G8: =IF(AND(ISNUMBER(G6),ISNUMBER(G7),G7<>0),G6/G7-1,"") | H8: =IF(AND(ISNUMBER(H6),ISNUMBER(H7),H7<>0),H6/H7-1,"") | I8: =IF(AND(ISNUMBER(I6),ISNUMBER(I7),I7<>0),I6/I7-1,"") | J8: =IF(AND(ISNUMBER(J6),ISNUMBER(J7),J7<>0),J6/J7-1,"") | K8: =IF(AND(ISNUMBER(K6),ISNUMBER(K7),K7<>0),K6/K7-1,"") | ... P8: =IF(AND(ISNUMBER(P6),ISNUMBER(P7),P7<>0),P6/P7-1,"")
B10: Recordable injuries | C10: Actual | D10: =IF(DATE(cfg_Year,1,1)>cfg_LastDataDate,"",IFERROR(INDEX(cd_Recordables_MTD,MATCH(MIN(EOMONTH(DATE(cfg_Year,1,1),0),cfg_LastDataDate),cd_Date,0)),"")) | E10: =IF(DATE(cfg_Year,2,1)>cfg_LastDataDate,"",IFERROR(INDEX(cd_Recordables_MTD,MATCH(MIN(EOMONTH(DATE(cfg_Year,2,1),0),cfg_LastDataDate),cd_Date,0)),"")) | F10: =IF(DATE(cfg_Year,3,1)>cfg_LastDataDate,"",IFERROR(INDEX(cd_Recordables_MTD,MATCH(MIN(EOMONTH(DATE(cfg_Year,3,1),0),cfg_LastDataDate),cd_Date,0)),"")) | G10: =IF(DATE(cfg_Year,4,1)>cfg_LastDataDate,"",IFERROR(INDEX(cd_Recordables_MTD,MATCH(MIN(EOMONTH(DATE(cfg_Year,4,1),0),cfg_LastDataDate),cd_Date,0)),"")) | H10: =IF(DATE(cfg_Year,5,1)>cfg_LastDataDate,"",IFERROR(INDEX(cd_Recordables_MTD,MATCH(MIN(EOMONTH(DATE(cfg_Year,5,1),0),cfg_LastDataDate),cd_Date,0)),"")) | I10: =IF(DATE(cfg_Year,6,1)>cfg_LastDataDate,"",IFERROR(INDEX(cd_Recordables_MTD,MATCH(MIN(EOMONTH(DATE(cfg_Year,6,1),0),cfg_LastDataDate),cd_Date,0)),"")) | J10: =IF(DATE(cfg_Year,7,1)>cfg_LastDataDate,"",IFERROR(INDEX(cd_Recordables_MTD,MATCH(MIN(EOMONTH(DATE(cfg_Year,7,1),0),cfg_LastDataDate),cd_Date,0)),"")) | K10: =IF(DATE(cfg_Year,8,1)>cfg_LastDataDate,"",IFERROR(INDEX(cd_Recordables_MTD,MATCH(MIN(EOMONTH(DATE(cfg_Year,8,1),0),cfg_LastDataDate),cd_Date,0)),"")) | L10: =IF(DATE(cfg_Year,9,1)>cfg_LastDataDate,"",IFERROR(INDEX(cd_Recordables_MTD,MATCH(MIN(EOMONTH(DATE(cfg_Year,9,1),0),cfg_LastDataDate),cd_Date,0)),"")) | M10: =IF(DATE(cfg_Year,10,1)>cfg_LastDataDate,"",IFERROR(INDEX(cd_Recordables_MTD,MATCH(MIN(EOMONTH(DATE(cfg_Year,10,1),0),cfg_LastDataDate),cd_Date,0)),"")) | N10: =IF(DATE(cfg_Year,11,1)>cfg_LastDataDate,"",IFERROR(INDEX(cd_Recordables_MTD,MATCH(MIN(EOMONTH(DATE(cfg_Year,11,1),0),cfg_LastDataDate),cd_Date,0)),"")) | O10: =IF(DATE(cfg_Year,12,1)>cfg_LastDataDate,"",IFERROR(INDEX(cd_Recordables_MTD,MATCH(MIN(EOMONTH(DATE(cfg_Year,12,1),0),cfg_LastDataDate),cd_Date,0)),"")) | P10: =IFERROR(INDEX(cd_Recordables_YTD,MATCH(MIN(cfg_YearEnd,cfg_LastDataDate),cd_Date,0)),"")
B11: Lost time injuries | C11: Actual | D11: =IF(DATE(cfg_Year,1,1)>cfg_LastDataDate,"",IFERROR(INDEX(cd_LTI_MTD,MATCH(MIN(EOMONTH(DATE(cfg_Year,1,1),0),cfg_LastDataDate),cd_Date,0)),"")) | E11: =IF(DATE(cfg_Year,2,1)>cfg_LastDataDate,"",IFERROR(INDEX(cd_LTI_MTD,MATCH(MIN(EOMONTH(DATE(cfg_Year,2,1),0),cfg_LastDataDate),cd_Date,0)),"")) | F11: =IF(DATE(cfg_Year,3,1)>cfg_LastDataDate,"",IFERROR(INDEX(cd_LTI_MTD,MATCH(MIN(EOMONTH(DATE(cfg_Year,3,1),0),cfg_LastDataDate),cd_Date,0)),"")) | G11: =IF(DATE(cfg_Year,4,1)>cfg_LastDataDate,"",IFERROR(INDEX(cd_LTI_MTD,MATCH(MIN(EOMONTH(DATE(cfg_Year,4,1),0),cfg_LastDataDate),cd_Date,0)),"")) | H11: =IF(DATE(cfg_Year,5,1)>cfg_LastDataDate,"",IFERROR(INDEX(cd_LTI_MTD,MATCH(MIN(EOMONTH(DATE(cfg_Year,5,1),0),cfg_LastDataDate),cd_Date,0)),"")) | I11: =IF(DATE(cfg_Year,6,1)>cfg_LastDataDate,"",IFERROR(INDEX(cd_LTI_MTD,MATCH(MIN(EOMONTH(DATE(cfg_Year,6,1),0),cfg_LastDataDate),cd_Date,0)),"")) | J11: =IF(DATE(cfg_Year,7,1)>cfg_LastDataDate,"",IFERROR(INDEX(cd_LTI_MTD,MATCH(MIN(EOMONTH(DATE(cfg_Year,7,1),0),cfg_LastDataDate),cd_Date,0)),"")) | K11: =IF(DATE(cfg_Year,8,1)>cfg_LastDataDate,"",IFERROR(INDEX(cd_LTI_MTD,MATCH(MIN(EOMONTH(DATE(cfg_Year,8,1),0),cfg_LastDataDate),cd_Date,0)),"")) | L11: =IF(DATE(cfg_Year,9,1)>cfg_LastDataDate,"",IFERROR(INDEX(cd_LTI_MTD,MATCH(MIN(EOMONTH(DATE(cfg_Year,9,1),0),cfg_LastDataDate),cd_Date,0)),"")) | M11: =IF(DATE(cfg_Year,10,1)>cfg_LastDataDate,"",IFERROR(INDEX(cd_LTI_MTD,MATCH(MIN(EOMONTH(DATE(cfg_Year,10,1),0),cfg_LastDataDate),cd_Date,0)),"")) | N11: =IF(DATE(cfg_Year,11,1)>cfg_LastDataDate,"",IFERROR(INDEX(cd_LTI_MTD,MATCH(MIN(EOMONTH(DATE(cfg_Year,11,1),0),cfg_LastDataDate),cd_Date,0)),"")) | O11: =IF(DATE(cfg_Year,12,1)>cfg_LastDataDate,"",IFERROR(INDEX(cd_LTI_MTD,MATCH(MIN(EOMONTH(DATE(cfg_Year,12,1),0),cfg_LastDataDate),cd_Date,0)),"")) | P11: =IFERROR(INDEX(cd_LTI_YTD,MATCH(MIN(cfg_YearEnd,cfg_LastDataDate),cd_Date,0)),"")
B12: TRIFR, rolling 12 months + MTD | C12: Actual | D12: =IF(DATE(cfg_Year,1,1)>cfg_LastDataDate,"",IFERROR(INDEX(cd_TRIFR_12m,MATCH(MIN(EOMONTH(DATE(cfg_Year,1,1),0),cfg_LastDataDate),cd_Date,0)),"")) | E12: =IF(DATE(cfg_Year,2,1)>cfg_LastDataDate,"",IFERROR(INDEX(cd_TRIFR_12m,MATCH(MIN(EOMONTH(DATE(cfg_Year,2,1),0),cfg_LastDataDate),cd_Date,0)),"")) | F12: =IF(DATE(cfg_Year,3,1)>cfg_LastDataDate,"",IFERROR(INDEX(cd_TRIFR_12m,MATCH(MIN(EOMONTH(DATE(cfg_Year,3,1),0),cfg_LastDataDate),cd_Date,0)),"")) | G12: =IF(DATE(cfg_Year,4,1)>cfg_LastDataDate,"",IFERROR(INDEX(cd_TRIFR_12m,MATCH(MIN(EOMONTH(DATE(cfg_Year,4,1),0),cfg_LastDataDate),cd_Date,0)),"")) | H12: =IF(DATE(cfg_Year,5,1)>cfg_LastDataDate,"",IFERROR(INDEX(cd_TRIFR_12m,MATCH(MIN(EOMONTH(DATE(cfg_Year,5,1),0),cfg_LastDataDate),cd_Date,0)),"")) | I12: =IF(DATE(cfg_Year,6,1)>cfg_LastDataDate,"",IFERROR(INDEX(cd_TRIFR_12m,MATCH(MIN(EOMONTH(DATE(cfg_Year,6,1),0),cfg_LastDataDate),cd_Date,0)),"")) | J12: =IF(DATE(cfg_Year,7,1)>cfg_LastDataDate,"",IFERROR(INDEX(cd_TRIFR_12m,MATCH(MIN(EOMONTH(DATE(cfg_Year,7,1),0),cfg_LastDataDate),cd_Date,0)),"")) | K12: =IF(DATE(cfg_Year,8,1)>cfg_LastDataDate,"",IFERROR(INDEX(cd_TRIFR_12m,MATCH(MIN(EOMONTH(DATE(cfg_Year,8,1),0),cfg_LastDataDate),cd_Date,0)),"")) | L12: =IF(DATE(cfg_Year,9,1)>cfg_LastDataDate,"",IFERROR(INDEX(cd_TRIFR_12m,MATCH(MIN(EOMONTH(DATE(cfg_Year,9,1),0),cfg_LastDataDate),cd_Date,0)),"")) | M12: =IF(DATE(cfg_Year,10,1)>cfg_LastDataDate,"",IFERROR(INDEX(cd_TRIFR_12m,MATCH(MIN(EOMONTH(DATE(cfg_Year,10,1),0),cfg_LastDataDate),cd_Date,0)),"")) | N12: =IF(DATE(cfg_Year,11,1)>cfg_LastDataDate,"",IFERROR(INDEX(cd_TRIFR_12m,MATCH(MIN(EOMONTH(DATE(cfg_Year,11,1),0),cfg_LastDataDate),cd_Date,0)),"")) | O12: =IF(DATE(cfg_Year,12,1)>cfg_LastDataDate,"",IFERROR(INDEX(cd_TRIFR_12m,MATCH(MIN(EOMONTH(DATE(cfg_Year,12,1),0),cfg_LastDataDate),cd_Date,0)),"")) | P12: =IFERROR(INDEX(cd_TRIFR_12m,MATCH(MIN(cfg_YearEnd,cfg_LastDataDate),cd_Date,0)),"")
B13: Ore mined (ex-pit) | C13: Actual | D13: =IF(DATE(cfg_Year,1,1)>cfg_LastDataDate,"",IFERROR(INDEX(cd_Ore_Mined_t_MTD,MATCH(MIN(EOMONTH(DATE(cfg_Year,1,1),0),cfg_LastDataDate),cd_Date,0)),"")) | E13: =IF(DATE(cfg_Year,2,1)>cfg_LastDataDate,"",IFERROR(INDEX(cd_Ore_Mined_t_MTD,MATCH(MIN(EOMONTH(DATE(cfg_Year,2,1),0),cfg_LastDataDate),cd_Date,0)),"")) | F13: =IF(DATE(cfg_Year,3,1)>cfg_LastDataDate,"",IFERROR(INDEX(cd_Ore_Mined_t_MTD,MATCH(MIN(EOMONTH(DATE(cfg_Year,3,1),0),cfg_LastDataDate),cd_Date,0)),"")) | G13: =IF(DATE(cfg_Year,4,1)>cfg_LastDataDate,"",IFERROR(INDEX(cd_Ore_Mined_t_MTD,MATCH(MIN(EOMONTH(DATE(cfg_Year,4,1),0),cfg_LastDataDate),cd_Date,0)),"")) | H13: =IF(DATE(cfg_Year,5,1)>cfg_LastDataDate,"",IFERROR(INDEX(cd_Ore_Mined_t_MTD,MATCH(MIN(EOMONTH(DATE(cfg_Year,5,1),0),cfg_LastDataDate),cd_Date,0)),"")) | I13: =IF(DATE(cfg_Year,6,1)>cfg_LastDataDate,"",IFERROR(INDEX(cd_Ore_Mined_t_MTD,MATCH(MIN(EOMONTH(DATE(cfg_Year,6,1),0),cfg_LastDataDate),cd_Date,0)),"")) | J13: =IF(DATE(cfg_Year,7,1)>cfg_LastDataDate,"",IFERROR(INDEX(cd_Ore_Mined_t_MTD,MATCH(MIN(EOMONTH(DATE(cfg_Year,7,1),0),cfg_LastDataDate),cd_Date,0)),"")) | K13: =IF(DATE(cfg_Year,8,1)>cfg_LastDataDate,"",IFERROR(INDEX(cd_Ore_Mined_t_MTD,MATCH(MIN(EOMONTH(DATE(cfg_Year,8,1),0),cfg_LastDataDate),cd_Date,0)),"")) | L13: =IF(DATE(cfg_Year,9,1)>cfg_LastDataDate,"",IFERROR(INDEX(cd_Ore_Mined_t_MTD,MATCH(MIN(EOMONTH(DATE(cfg_Year,9,1),0),cfg_LastDataDate),cd_Date,0)),"")) | M13: =IF(DATE(cfg_Year,10,1)>cfg_LastDataDate,"",IFERROR(INDEX(cd_Ore_Mined_t_MTD,MATCH(MIN(EOMONTH(DATE(cfg_Year,10,1),0),cfg_LastDataDate),cd_Date,0)),"")) | N13: =IF(DATE(cfg_Year,11,1)>cfg_LastDataDate,"",IFERROR(INDEX(cd_Ore_Mined_t_MTD,MATCH(MIN(EOMONTH(DATE(cfg_Year,11,1),0),cfg_LastDataDate),cd_Date,0)),"")) | O13: =IF(DATE(cfg_Year,12,1)>cfg_LastDataDate,"",IFERROR(INDEX(cd_Ore_Mined_t_MTD,MATCH(MIN(EOMONTH(DATE(cfg_Year,12,1),0),cfg_LastDataDate),cd_Date,0)),"")) | P13: =IFERROR(INDEX(cd_Ore_Mined_t_YTD,MATCH(MIN(cfg_YearEnd,cfg_LastDataDate),cd_Date,0)),"")
C14: Budget | D14: =IF(DATE(cfg_Year,1,1)>cfg_LastDataDate,IFERROR(INDEX(cd_Bud_Ore_Mined_t_Month,MATCH(DATE(cfg_Year,1,1),cd_Date,0)),""),IFERROR(INDEX(cd_Bud_Ore_Mined_t_MTD,MATCH(MIN(EOMONTH(DATE(cfg_Year,1,1),0),cfg_LastDataDate),cd_Date,0)),"")) | E14: =IF(DATE(cfg_Year,2,1)>cfg_LastDataDate,IFERROR(INDEX(cd_Bud_Ore_Mined_t_Month,MATCH(DATE(cfg_Year,2,1),cd_Date,0)),""),IFERROR(INDEX(cd_Bud_Ore_Mined_t_MTD,MATCH(MIN(EOMONTH(DATE(cfg_Year,2,1),0),cfg_LastDataDate),cd_Date,0)),"")) | F14: =IF(DATE(cfg_Year,3,1)>cfg_LastDataDate,IFERROR(INDEX(cd_Bud_Ore_Mined_t_Month,MATCH(DATE(cfg_Year,3,1),cd_Date,0)),""),IFERROR(INDEX(cd_Bud_Ore_Mined_t_MTD,MATCH(MIN(EOMONTH(DATE(cfg_Year,3,1),0),cfg_LastDataDate),cd_Date,0)),"")) | G14: =IF(DATE(cfg_Year,4,1)>cfg_LastDataDate,IFERROR(INDEX(cd_Bud_Ore_Mined_t_Month,MATCH(DATE(cfg_Year,4,1),cd_Date,0)),""),IFERROR(INDEX(cd_Bud_Ore_Mined_t_MTD,MATCH(MIN(EOMONTH(DATE(cfg_Year,4,1),0),cfg_LastDataDate),cd_Date,0)),"")) | H14: =IF(DATE(cfg_Year,5,1)>cfg_LastDataDate,IFERROR(INDEX(cd_Bud_Ore_Mined_t_Month,MATCH(DATE(cfg_Year,5,1),cd_Date,0)),""),IFERROR(INDEX(cd_Bud_Ore_Mined_t_MTD,MATCH(MIN(EOMONTH(DATE(cfg_Year,5,1),0),cfg_LastDataDate),cd_Date,0)),"")) | I14: =IF(DATE(cfg_Year,6,1)>cfg_LastDataDate,IFERROR(INDEX(cd_Bud_Ore_Mined_t_Month,MATCH(DATE(cfg_Year,6,1),cd_Date,0)),""),IFERROR(INDEX(cd_Bud_Ore_Mined_t_MTD,MATCH(MIN(EOMONTH(DATE(cfg_Year,6,1),0),cfg_LastDataDate),cd_Date,0)),"")) | J14: =IF(DATE(cfg_Year,7,1)>cfg_LastDataDate,IFERROR(INDEX(cd_Bud_Ore_Mined_t_Month,MATCH(DATE(cfg_Year,7,1),cd_Date,0)),""),IFERROR(INDEX(cd_Bud_Ore_Mined_t_MTD,MATCH(MIN(EOMONTH(DATE(cfg_Year,7,1),0),cfg_LastDataDate),cd_Date,0)),"")) | K14: =IF(DATE(cfg_Year,8,1)>cfg_LastDataDate,IFERROR(INDEX(cd_Bud_Ore_Mined_t_Month,MATCH(DATE(cfg_Year,8,1),cd_Date,0)),""),IFERROR(INDEX(cd_Bud_Ore_Mined_t_MTD,MATCH(MIN(EOMONTH(DATE(cfg_Year,8,1),0),cfg_LastDataDate),cd_Date,0)),"")) | L14: =IF(DATE(cfg_Year,9,1)>cfg_LastDataDate,IFERROR(INDEX(cd_Bud_Ore_Mined_t_Month,MATCH(DATE(cfg_Year,9,1),cd_Date,0)),""),IFERROR(INDEX(cd_Bud_Ore_Mined_t_MTD,MATCH(MIN(EOMONTH(DATE(cfg_Year,9,1),0),cfg_LastDataDate),cd_Date,0)),"")) | M14: =IF(DATE(cfg_Year,10,1)>cfg_LastDataDate,IFERROR(INDEX(cd_Bud_Ore_Mined_t_Month,MATCH(DATE(cfg_Year,10,1),cd_Date,0)),""),IFERROR(INDEX(cd_Bud_Ore_Mined_t_MTD,MATCH(MIN(EOMONTH(DATE(cfg_Year,10,1),0),cfg_LastDataDate),cd_Date,0)),"")) | N14: =IF(DATE(cfg_Year,11,1)>cfg_LastDataDate,IFERROR(INDEX(cd_Bud_Ore_Mined_t_Month,MATCH(DATE(cfg_Year,11,1),cd_Date,0)),""),IFERROR(INDEX(cd_Bud_Ore_Mined_t_MTD,MATCH(MIN(EOMONTH(DATE(cfg_Year,11,1),0),cfg_LastDataDate),cd_Date,0)),"")) | O14: =IF(DATE(cfg_Year,12,1)>cfg_LastDataDate,IFERROR(INDEX(cd_Bud_Ore_Mined_t_Month,MATCH(DATE(cfg_Year,12,1),cd_Date,0)),""),IFERROR(INDEX(cd_Bud_Ore_Mined_t_MTD,MATCH(MIN(EOMONTH(DATE(cfg_Year,12,1),0),cfg_LastDataDate),cd_Date,0)),"")) | P14: =IFERROR(INDEX(cd_Bud_Ore_Mined_t_YTD,MATCH(IF(N(cfg_LastDataDate)>0,MIN(cfg_YearEnd,cfg_LastDataDate),cfg_YearEnd),cd_Date,0)),"")
C15: Variance | D15: =IF(AND(ISNUMBER(D13),ISNUMBER(D14),D14<>0),D13/D14-1,"") | E15: =IF(AND(ISNUMBER(E13),ISNUMBER(E14),E14<>0),E13/E14-1,"") | F15: =IF(AND(ISNUMBER(F13),ISNUMBER(F14),F14<>0),F13/F14-1,"") | G15: =IF(AND(ISNUMBER(G13),ISNUMBER(G14),G14<>0),G13/G14-1,"") | H15: =IF(AND(ISNUMBER(H13),ISNUMBER(H14),H14<>0),H13/H14-1,"") | I15: =IF(AND(ISNUMBER(I13),ISNUMBER(I14),I14<>0),I13/I14-1,"") | J15: =IF(AND(ISNUMBER(J13),ISNUMBER(J14),J14<>0),J13/J14-1,"") | K15: =IF(AND(ISNUMBER(K13),ISNUMBER(K14),K14<>0),K13/K14-1,"") | ... P15: =IF(AND(ISNUMBER(P13),ISNUMBER(P14),P14<>0),P13/P14-1,"")
B17: Ore grade mined | C17: Actual | D17: =IF(DATE(cfg_Year,1,1)>cfg_LastDataDate,"",IFERROR(INDEX(cd_Ore_Grade_gpt_MTD,MATCH(MIN(EOMONTH(DATE(cfg_Year,1,1),0),cfg_LastDataDate),cd_Date,0)),"")) | E17: =IF(DATE(cfg_Year,2,1)>cfg_LastDataDate,"",IFERROR(INDEX(cd_Ore_Grade_gpt_MTD,MATCH(MIN(EOMONTH(DATE(cfg_Year,2,1),0),cfg_LastDataDate),cd_Date,0)),"")) | F17: =IF(DATE(cfg_Year,3,1)>cfg_LastDataDate,"",IFERROR(INDEX(cd_Ore_Grade_gpt_MTD,MATCH(MIN(EOMONTH(DATE(cfg_Year,3,1),0),cfg_LastDataDate),cd_Date,0)),"")) | G17: =IF(DATE(cfg_Year,4,1)>cfg_LastDataDate,"",IFERROR(INDEX(cd_Ore_Grade_gpt_MTD,MATCH(MIN(EOMONTH(DATE(cfg_Year,4,1),0),cfg_LastDataDate),cd_Date,0)),"")) | H17: =IF(DATE(cfg_Year,5,1)>cfg_LastDataDate,"",IFERROR(INDEX(cd_Ore_Grade_gpt_MTD,MATCH(MIN(EOMONTH(DATE(cfg_Year,5,1),0),cfg_LastDataDate),cd_Date,0)),"")) | I17: =IF(DATE(cfg_Year,6,1)>cfg_LastDataDate,"",IFERROR(INDEX(cd_Ore_Grade_gpt_MTD,MATCH(MIN(EOMONTH(DATE(cfg_Year,6,1),0),cfg_LastDataDate),cd_Date,0)),"")) | J17: =IF(DATE(cfg_Year,7,1)>cfg_LastDataDate,"",IFERROR(INDEX(cd_Ore_Grade_gpt_MTD,MATCH(MIN(EOMONTH(DATE(cfg_Year,7,1),0),cfg_LastDataDate),cd_Date,0)),"")) | K17: =IF(DATE(cfg_Year,8,1)>cfg_LastDataDate,"",IFERROR(INDEX(cd_Ore_Grade_gpt_MTD,MATCH(MIN(EOMONTH(DATE(cfg_Year,8,1),0),cfg_LastDataDate),cd_Date,0)),"")) | L17: =IF(DATE(cfg_Year,9,1)>cfg_LastDataDate,"",IFERROR(INDEX(cd_Ore_Grade_gpt_MTD,MATCH(MIN(EOMONTH(DATE(cfg_Year,9,1),0),cfg_LastDataDate),cd_Date,0)),"")) | M17: =IF(DATE(cfg_Year,10,1)>cfg_LastDataDate,"",IFERROR(INDEX(cd_Ore_Grade_gpt_MTD,MATCH(MIN(EOMONTH(DATE(cfg_Year,10,1),0),cfg_LastDataDate),cd_Date,0)),"")) | N17: =IF(DATE(cfg_Year,11,1)>cfg_LastDataDate,"",IFERROR(INDEX(cd_Ore_Grade_gpt_MTD,MATCH(MIN(EOMONTH(DATE(cfg_Year,11,1),0),cfg_LastDataDate),cd_Date,0)),"")) | O17: =IF(DATE(cfg_Year,12,1)>cfg_LastDataDate,"",IFERROR(INDEX(cd_Ore_Grade_gpt_MTD,MATCH(MIN(EOMONTH(DATE(cfg_Year,12,1),0),cfg_LastDataDate),cd_Date,0)),"")) | P17: =IFERROR(INDEX(cd_Ore_Grade_gpt_YTD,MATCH(MIN(cfg_YearEnd,cfg_LastDataDate),cd_Date,0)),"")
C18: Budget | D18: =IF(DATE(cfg_Year,1,1)>cfg_LastDataDate,IFERROR(INDEX(cd_Bud_Ore_Grade_gpt_Month,MATCH(DATE(cfg_Year,1,1),cd_Date,0)),""),IFERROR(INDEX(cd_Bud_Ore_Grade_gpt_MTD,MATCH(MIN(EOMONTH(DATE(cfg_Year,1,1),0),cfg_LastDataDate),cd_Date,0)),"")) | E18: =IF(DATE(cfg_Year,2,1)>cfg_LastDataDate,IFERROR(INDEX(cd_Bud_Ore_Grade_gpt_Month,MATCH(DATE(cfg_Year,2,1),cd_Date,0)),""),IFERROR(INDEX(cd_Bud_Ore_Grade_gpt_MTD,MATCH(MIN(EOMONTH(DATE(cfg_Year,2,1),0),cfg_LastDataDate),cd_Date,0)),"")) | F18: =IF(DATE(cfg_Year,3,1)>cfg_LastDataDate,IFERROR(INDEX(cd_Bud_Ore_Grade_gpt_Month,MATCH(DATE(cfg_Year,3,1),cd_Date,0)),""),IFERROR(INDEX(cd_Bud_Ore_Grade_gpt_MTD,MATCH(MIN(EOMONTH(DATE(cfg_Year,3,1),0),cfg_LastDataDate),cd_Date,0)),"")) | G18: =IF(DATE(cfg_Year,4,1)>cfg_LastDataDate,IFERROR(INDEX(cd_Bud_Ore_Grade_gpt_Month,MATCH(DATE(cfg_Year,4,1),cd_Date,0)),""),IFERROR(INDEX(cd_Bud_Ore_Grade_gpt_MTD,MATCH(MIN(EOMONTH(DATE(cfg_Year,4,1),0),cfg_LastDataDate),cd_Date,0)),"")) | H18: =IF(DATE(cfg_Year,5,1)>cfg_LastDataDate,IFERROR(INDEX(cd_Bud_Ore_Grade_gpt_Month,MATCH(DATE(cfg_Year,5,1),cd_Date,0)),""),IFERROR(INDEX(cd_Bud_Ore_Grade_gpt_MTD,MATCH(MIN(EOMONTH(DATE(cfg_Year,5,1),0),cfg_LastDataDate),cd_Date,0)),"")) | I18: =IF(DATE(cfg_Year,6,1)>cfg_LastDataDate,IFERROR(INDEX(cd_Bud_Ore_Grade_gpt_Month,MATCH(DATE(cfg_Year,6,1),cd_Date,0)),""),IFERROR(INDEX(cd_Bud_Ore_Grade_gpt_MTD,MATCH(MIN(EOMONTH(DATE(cfg_Year,6,1),0),cfg_LastDataDate),cd_Date,0)),"")) | J18: =IF(DATE(cfg_Year,7,1)>cfg_LastDataDate,IFERROR(INDEX(cd_Bud_Ore_Grade_gpt_Month,MATCH(DATE(cfg_Year,7,1),cd_Date,0)),""),IFERROR(INDEX(cd_Bud_Ore_Grade_gpt_MTD,MATCH(MIN(EOMONTH(DATE(cfg_Year,7,1),0),cfg_LastDataDate),cd_Date,0)),"")) | K18: =IF(DATE(cfg_Year,8,1)>cfg_LastDataDate,IFERROR(INDEX(cd_Bud_Ore_Grade_gpt_Month,MATCH(DATE(cfg_Year,8,1),cd_Date,0)),""),IFERROR(INDEX(cd_Bud_Ore_Grade_gpt_MTD,MATCH(MIN(EOMONTH(DATE(cfg_Year,8,1),0),cfg_LastDataDate),cd_Date,0)),"")) | L18: =IF(DATE(cfg_Year,9,1)>cfg_LastDataDate,IFERROR(INDEX(cd_Bud_Ore_Grade_gpt_Month,MATCH(DATE(cfg_Year,9,1),cd_Date,0)),""),IFERROR(INDEX(cd_Bud_Ore_Grade_gpt_MTD,MATCH(MIN(EOMONTH(DATE(cfg_Year,9,1),0),cfg_LastDataDate),cd_Date,0)),"")) | M18: =IF(DATE(cfg_Year,10,1)>cfg_LastDataDate,IFERROR(INDEX(cd_Bud_Ore_Grade_gpt_Month,MATCH(DATE(cfg_Year,10,1),cd_Date,0)),""),IFERROR(INDEX(cd_Bud_Ore_Grade_gpt_MTD,MATCH(MIN(EOMONTH(DATE(cfg_Year,10,1),0),cfg_LastDataDate),cd_Date,0)),"")) | N18: =IF(DATE(cfg_Year,11,1)>cfg_LastDataDate,IFERROR(INDEX(cd_Bud_Ore_Grade_gpt_Month,MATCH(DATE(cfg_Year,11,1),cd_Date,0)),""),IFERROR(INDEX(cd_Bud_Ore_Grade_gpt_MTD,MATCH(MIN(EOMONTH(DATE(cfg_Year,11,1),0),cfg_LastDataDate),cd_Date,0)),"")) | O18: =IF(DATE(cfg_Year,12,1)>cfg_LastDataDate,IFERROR(INDEX(cd_Bud_Ore_Grade_gpt_Month,MATCH(DATE(cfg_Year,12,1),cd_Date,0)),""),IFERROR(INDEX(cd_Bud_Ore_Grade_gpt_MTD,MATCH(MIN(EOMONTH(DATE(cfg_Year,12,1),0),cfg_LastDataDate),cd_Date,0)),"")) | P18: =IFERROR(INDEX(cd_Bud_Ore_Grade_gpt_YTD,MATCH(IF(N(cfg_LastDataDate)>0,MIN(cfg_YearEnd,cfg_LastDataDate),cfg_YearEnd),cd_Date,0)),"")
C19: Variance | D19: =IF(AND(ISNUMBER(D17),ISNUMBER(D18),D18<>0),D17/D18-1,"") | E19: =IF(AND(ISNUMBER(E17),ISNUMBER(E18),E18<>0),E17/E18-1,"") | F19: =IF(AND(ISNUMBER(F17),ISNUMBER(F18),F18<>0),F17/F18-1,"") | G19: =IF(AND(ISNUMBER(G17),ISNUMBER(G18),G18<>0),G17/G18-1,"") | H19: =IF(AND(ISNUMBER(H17),ISNUMBER(H18),H18<>0),H17/H18-1,"") | I19: =IF(AND(ISNUMBER(I17),ISNUMBER(I18),I18<>0),I17/I18-1,"") | J19: =IF(AND(ISNUMBER(J17),ISNUMBER(J18),J18<>0),J17/J18-1,"") | K19: =IF(AND(ISNUMBER(K17),ISNUMBER(K18),K18<>0),K17/K18-1,"") | ... P19: =IF(AND(ISNUMBER(P17),ISNUMBER(P18),P18<>0),P17/P18-1,"")
B21: Contained gold mined | C21: Actual | D21: =IF(DATE(cfg_Year,1,1)>cfg_LastDataDate,"",IFERROR(INDEX(cd_Ore_Mined_oz_MTD,MATCH(MIN(EOMONTH(DATE(cfg_Year,1,1),0),cfg_LastDataDate),cd_Date,0)),"")) | E21: =IF(DATE(cfg_Year,2,1)>cfg_LastDataDate,"",IFERROR(INDEX(cd_Ore_Mined_oz_MTD,MATCH(MIN(EOMONTH(DATE(cfg_Year,2,1),0),cfg_LastDataDate),cd_Date,0)),"")) | F21: =IF(DATE(cfg_Year,3,1)>cfg_LastDataDate,"",IFERROR(INDEX(cd_Ore_Mined_oz_MTD,MATCH(MIN(EOMONTH(DATE(cfg_Year,3,1),0),cfg_LastDataDate),cd_Date,0)),"")) | G21: =IF(DATE(cfg_Year,4,1)>cfg_LastDataDate,"",IFERROR(INDEX(cd_Ore_Mined_oz_MTD,MATCH(MIN(EOMONTH(DATE(cfg_Year,4,1),0),cfg_LastDataDate),cd_Date,0)),"")) | H21: =IF(DATE(cfg_Year,5,1)>cfg_LastDataDate,"",IFERROR(INDEX(cd_Ore_Mined_oz_MTD,MATCH(MIN(EOMONTH(DATE(cfg_Year,5,1),0),cfg_LastDataDate),cd_Date,0)),"")) | I21: =IF(DATE(cfg_Year,6,1)>cfg_LastDataDate,"",IFERROR(INDEX(cd_Ore_Mined_oz_MTD,MATCH(MIN(EOMONTH(DATE(cfg_Year,6,1),0),cfg_LastDataDate),cd_Date,0)),"")) | J21: =IF(DATE(cfg_Year,7,1)>cfg_LastDataDate,"",IFERROR(INDEX(cd_Ore_Mined_oz_MTD,MATCH(MIN(EOMONTH(DATE(cfg_Year,7,1),0),cfg_LastDataDate),cd_Date,0)),"")) | K21: =IF(DATE(cfg_Year,8,1)>cfg_LastDataDate,"",IFERROR(INDEX(cd_Ore_Mined_oz_MTD,MATCH(MIN(EOMONTH(DATE(cfg_Year,8,1),0),cfg_LastDataDate),cd_Date,0)),"")) | L21: =IF(DATE(cfg_Year,9,1)>cfg_LastDataDate,"",IFERROR(INDEX(cd_Ore_Mined_oz_MTD,MATCH(MIN(EOMONTH(DATE(cfg_Year,9,1),0),cfg_LastDataDate),cd_Date,0)),"")) | M21: =IF(DATE(cfg_Year,10,1)>cfg_LastDataDate,"",IFERROR(INDEX(cd_Ore_Mined_oz_MTD,MATCH(MIN(EOMONTH(DATE(cfg_Year,10,1),0),cfg_LastDataDate),cd_Date,0)),"")) | N21: =IF(DATE(cfg_Year,11,1)>cfg_LastDataDate,"",IFERROR(INDEX(cd_Ore_Mined_oz_MTD,MATCH(MIN(EOMONTH(DATE(cfg_Year,11,1),0),cfg_LastDataDate),cd_Date,0)),"")) | O21: =IF(DATE(cfg_Year,12,1)>cfg_LastDataDate,"",IFERROR(INDEX(cd_Ore_Mined_oz_MTD,MATCH(MIN(EOMONTH(DATE(cfg_Year,12,1),0),cfg_LastDataDate),cd_Date,0)),"")) | P21: =IFERROR(INDEX(cd_Ore_Mined_oz_YTD,MATCH(MIN(cfg_YearEnd,cfg_LastDataDate),cd_Date,0)),"")
C22: Budget | D22: =IF(DATE(cfg_Year,1,1)>cfg_LastDataDate,IFERROR(INDEX(cd_Bud_Ore_Mined_oz_Month,MATCH(DATE(cfg_Year,1,1),cd_Date,0)),""),IFERROR(INDEX(cd_Bud_Ore_Mined_oz_MTD,MATCH(MIN(EOMONTH(DATE(cfg_Year,1,1),0),cfg_LastDataDate),cd_Date,0)),"")) | E22: =IF(DATE(cfg_Year,2,1)>cfg_LastDataDate,IFERROR(INDEX(cd_Bud_Ore_Mined_oz_Month,MATCH(DATE(cfg_Year,2,1),cd_Date,0)),""),IFERROR(INDEX(cd_Bud_Ore_Mined_oz_MTD,MATCH(MIN(EOMONTH(DATE(cfg_Year,2,1),0),cfg_LastDataDate),cd_Date,0)),"")) | F22: =IF(DATE(cfg_Year,3,1)>cfg_LastDataDate,IFERROR(INDEX(cd_Bud_Ore_Mined_oz_Month,MATCH(DATE(cfg_Year,3,1),cd_Date,0)),""),IFERROR(INDEX(cd_Bud_Ore_Mined_oz_MTD,MATCH(MIN(EOMONTH(DATE(cfg_Year,3,1),0),cfg_LastDataDate),cd_Date,0)),"")) | G22: =IF(DATE(cfg_Year,4,1)>cfg_LastDataDate,IFERROR(INDEX(cd_Bud_Ore_Mined_oz_Month,MATCH(DATE(cfg_Year,4,1),cd_Date,0)),""),IFERROR(INDEX(cd_Bud_Ore_Mined_oz_MTD,MATCH(MIN(EOMONTH(DATE(cfg_Year,4,1),0),cfg_LastDataDate),cd_Date,0)),"")) | H22: =IF(DATE(cfg_Year,5,1)>cfg_LastDataDate,IFERROR(INDEX(cd_Bud_Ore_Mined_oz_Month,MATCH(DATE(cfg_Year,5,1),cd_Date,0)),""),IFERROR(INDEX(cd_Bud_Ore_Mined_oz_MTD,MATCH(MIN(EOMONTH(DATE(cfg_Year,5,1),0),cfg_LastDataDate),cd_Date,0)),"")) | I22: =IF(DATE(cfg_Year,6,1)>cfg_LastDataDate,IFERROR(INDEX(cd_Bud_Ore_Mined_oz_Month,MATCH(DATE(cfg_Year,6,1),cd_Date,0)),""),IFERROR(INDEX(cd_Bud_Ore_Mined_oz_MTD,MATCH(MIN(EOMONTH(DATE(cfg_Year,6,1),0),cfg_LastDataDate),cd_Date,0)),"")) | J22: =IF(DATE(cfg_Year,7,1)>cfg_LastDataDate,IFERROR(INDEX(cd_Bud_Ore_Mined_oz_Month,MATCH(DATE(cfg_Year,7,1),cd_Date,0)),""),IFERROR(INDEX(cd_Bud_Ore_Mined_oz_MTD,MATCH(MIN(EOMONTH(DATE(cfg_Year,7,1),0),cfg_LastDataDate),cd_Date,0)),"")) | K22: =IF(DATE(cfg_Year,8,1)>cfg_LastDataDate,IFERROR(INDEX(cd_Bud_Ore_Mined_oz_Month,MATCH(DATE(cfg_Year,8,1),cd_Date,0)),""),IFERROR(INDEX(cd_Bud_Ore_Mined_oz_MTD,MATCH(MIN(EOMONTH(DATE(cfg_Year,8,1),0),cfg_LastDataDate),cd_Date,0)),"")) | L22: =IF(DATE(cfg_Year,9,1)>cfg_LastDataDate,IFERROR(INDEX(cd_Bud_Ore_Mined_oz_Month,MATCH(DATE(cfg_Year,9,1),cd_Date,0)),""),IFERROR(INDEX(cd_Bud_Ore_Mined_oz_MTD,MATCH(MIN(EOMONTH(DATE(cfg_Year,9,1),0),cfg_LastDataDate),cd_Date,0)),"")) | M22: =IF(DATE(cfg_Year,10,1)>cfg_LastDataDate,IFERROR(INDEX(cd_Bud_Ore_Mined_oz_Month,MATCH(DATE(cfg_Year,10,1),cd_Date,0)),""),IFERROR(INDEX(cd_Bud_Ore_Mined_oz_MTD,MATCH(MIN(EOMONTH(DATE(cfg_Year,10,1),0),cfg_LastDataDate),cd_Date,0)),"")) | N22: =IF(DATE(cfg_Year,11,1)>cfg_LastDataDate,IFERROR(INDEX(cd_Bud_Ore_Mined_oz_Month,MATCH(DATE(cfg_Year,11,1),cd_Date,0)),""),IFERROR(INDEX(cd_Bud_Ore_Mined_oz_MTD,MATCH(MIN(EOMONTH(DATE(cfg_Year,11,1),0),cfg_LastDataDate),cd_Date,0)),"")) | O22: =IF(DATE(cfg_Year,12,1)>cfg_LastDataDate,IFERROR(INDEX(cd_Bud_Ore_Mined_oz_Month,MATCH(DATE(cfg_Year,12,1),cd_Date,0)),""),IFERROR(INDEX(cd_Bud_Ore_Mined_oz_MTD,MATCH(MIN(EOMONTH(DATE(cfg_Year,12,1),0),cfg_LastDataDate),cd_Date,0)),"")) | P22: =IFERROR(INDEX(cd_Bud_Ore_Mined_oz_YTD,MATCH(IF(N(cfg_LastDataDate)>0,MIN(cfg_YearEnd,cfg_LastDataDate),cfg_YearEnd),cd_Date,0)),"")
C23: Variance | D23: =IF(AND(ISNUMBER(D21),ISNUMBER(D22),D22<>0),D21/D22-1,"") | E23: =IF(AND(ISNUMBER(E21),ISNUMBER(E22),E22<>0),E21/E22-1,"") | F23: =IF(AND(ISNUMBER(F21),ISNUMBER(F22),F22<>0),F21/F22-1,"") | G23: =IF(AND(ISNUMBER(G21),ISNUMBER(G22),G22<>0),G21/G22-1,"") | H23: =IF(AND(ISNUMBER(H21),ISNUMBER(H22),H22<>0),H21/H22-1,"") | I23: =IF(AND(ISNUMBER(I21),ISNUMBER(I22),I22<>0),I21/I22-1,"") | J23: =IF(AND(ISNUMBER(J21),ISNUMBER(J22),J22<>0),J21/J22-1,"") | K23: =IF(AND(ISNUMBER(K21),ISNUMBER(K22),K22<>0),K21/K22-1,"") | ... P23: =IF(AND(ISNUMBER(P21),ISNUMBER(P22),P22<>0),P21/P22-1,"")
B25: Waste mined | C25: Actual | D25: =IF(DATE(cfg_Year,1,1)>cfg_LastDataDate,"",IFERROR(INDEX(cd_Waste_t_MTD,MATCH(MIN(EOMONTH(DATE(cfg_Year,1,1),0),cfg_LastDataDate),cd_Date,0)),"")) | E25: =IF(DATE(cfg_Year,2,1)>cfg_LastDataDate,"",IFERROR(INDEX(cd_Waste_t_MTD,MATCH(MIN(EOMONTH(DATE(cfg_Year,2,1),0),cfg_LastDataDate),cd_Date,0)),"")) | F25: =IF(DATE(cfg_Year,3,1)>cfg_LastDataDate,"",IFERROR(INDEX(cd_Waste_t_MTD,MATCH(MIN(EOMONTH(DATE(cfg_Year,3,1),0),cfg_LastDataDate),cd_Date,0)),"")) | G25: =IF(DATE(cfg_Year,4,1)>cfg_LastDataDate,"",IFERROR(INDEX(cd_Waste_t_MTD,MATCH(MIN(EOMONTH(DATE(cfg_Year,4,1),0),cfg_LastDataDate),cd_Date,0)),"")) | H25: =IF(DATE(cfg_Year,5,1)>cfg_LastDataDate,"",IFERROR(INDEX(cd_Waste_t_MTD,MATCH(MIN(EOMONTH(DATE(cfg_Year,5,1),0),cfg_LastDataDate),cd_Date,0)),"")) | I25: =IF(DATE(cfg_Year,6,1)>cfg_LastDataDate,"",IFERROR(INDEX(cd_Waste_t_MTD,MATCH(MIN(EOMONTH(DATE(cfg_Year,6,1),0),cfg_LastDataDate),cd_Date,0)),"")) | J25: =IF(DATE(cfg_Year,7,1)>cfg_LastDataDate,"",IFERROR(INDEX(cd_Waste_t_MTD,MATCH(MIN(EOMONTH(DATE(cfg_Year,7,1),0),cfg_LastDataDate),cd_Date,0)),"")) | K25: =IF(DATE(cfg_Year,8,1)>cfg_LastDataDate,"",IFERROR(INDEX(cd_Waste_t_MTD,MATCH(MIN(EOMONTH(DATE(cfg_Year,8,1),0),cfg_LastDataDate),cd_Date,0)),"")) | L25: =IF(DATE(cfg_Year,9,1)>cfg_LastDataDate,"",IFERROR(INDEX(cd_Waste_t_MTD,MATCH(MIN(EOMONTH(DATE(cfg_Year,9,1),0),cfg_LastDataDate),cd_Date,0)),"")) | M25: =IF(DATE(cfg_Year,10,1)>cfg_LastDataDate,"",IFERROR(INDEX(cd_Waste_t_MTD,MATCH(MIN(EOMONTH(DATE(cfg_Year,10,1),0),cfg_LastDataDate),cd_Date,0)),"")) | N25: =IF(DATE(cfg_Year,11,1)>cfg_LastDataDate,"",IFERROR(INDEX(cd_Waste_t_MTD,MATCH(MIN(EOMONTH(DATE(cfg_Year,11,1),0),cfg_LastDataDate),cd_Date,0)),"")) | O25: =IF(DATE(cfg_Year,12,1)>cfg_LastDataDate,"",IFERROR(INDEX(cd_Waste_t_MTD,MATCH(MIN(EOMONTH(DATE(cfg_Year,12,1),0),cfg_LastDataDate),cd_Date,0)),"")) | P25: =IFERROR(INDEX(cd_Waste_t_YTD,MATCH(MIN(cfg_YearEnd,cfg_LastDataDate),cd_Date,0)),"")
C26: Budget | D26: =IF(DATE(cfg_Year,1,1)>cfg_LastDataDate,IFERROR(INDEX(cd_Bud_Waste_t_Month,MATCH(DATE(cfg_Year,1,1),cd_Date,0)),""),IFERROR(INDEX(cd_Bud_Waste_t_MTD,MATCH(MIN(EOMONTH(DATE(cfg_Year,1,1),0),cfg_LastDataDate),cd_Date,0)),"")) | E26: =IF(DATE(cfg_Year,2,1)>cfg_LastDataDate,IFERROR(INDEX(cd_Bud_Waste_t_Month,MATCH(DATE(cfg_Year,2,1),cd_Date,0)),""),IFERROR(INDEX(cd_Bud_Waste_t_MTD,MATCH(MIN(EOMONTH(DATE(cfg_Year,2,1),0),cfg_LastDataDate),cd_Date,0)),"")) | F26: =IF(DATE(cfg_Year,3,1)>cfg_LastDataDate,IFERROR(INDEX(cd_Bud_Waste_t_Month,MATCH(DATE(cfg_Year,3,1),cd_Date,0)),""),IFERROR(INDEX(cd_Bud_Waste_t_MTD,MATCH(MIN(EOMONTH(DATE(cfg_Year,3,1),0),cfg_LastDataDate),cd_Date,0)),"")) | G26: =IF(DATE(cfg_Year,4,1)>cfg_LastDataDate,IFERROR(INDEX(cd_Bud_Waste_t_Month,MATCH(DATE(cfg_Year,4,1),cd_Date,0)),""),IFERROR(INDEX(cd_Bud_Waste_t_MTD,MATCH(MIN(EOMONTH(DATE(cfg_Year,4,1),0),cfg_LastDataDate),cd_Date,0)),"")) | H26: =IF(DATE(cfg_Year,5,1)>cfg_LastDataDate,IFERROR(INDEX(cd_Bud_Waste_t_Month,MATCH(DATE(cfg_Year,5,1),cd_Date,0)),""),IFERROR(INDEX(cd_Bud_Waste_t_MTD,MATCH(MIN(EOMONTH(DATE(cfg_Year,5,1),0),cfg_LastDataDate),cd_Date,0)),"")) | I26: =IF(DATE(cfg_Year,6,1)>cfg_LastDataDate,IFERROR(INDEX(cd_Bud_Waste_t_Month,MATCH(DATE(cfg_Year,6,1),cd_Date,0)),""),IFERROR(INDEX(cd_Bud_Waste_t_MTD,MATCH(MIN(EOMONTH(DATE(cfg_Year,6,1),0),cfg_LastDataDate),cd_Date,0)),"")) | J26: =IF(DATE(cfg_Year,7,1)>cfg_LastDataDate,IFERROR(INDEX(cd_Bud_Waste_t_Month,MATCH(DATE(cfg_Year,7,1),cd_Date,0)),""),IFERROR(INDEX(cd_Bud_Waste_t_MTD,MATCH(MIN(EOMONTH(DATE(cfg_Year,7,1),0),cfg_LastDataDate),cd_Date,0)),"")) | K26: =IF(DATE(cfg_Year,8,1)>cfg_LastDataDate,IFERROR(INDEX(cd_Bud_Waste_t_Month,MATCH(DATE(cfg_Year,8,1),cd_Date,0)),""),IFERROR(INDEX(cd_Bud_Waste_t_MTD,MATCH(MIN(EOMONTH(DATE(cfg_Year,8,1),0),cfg_LastDataDate),cd_Date,0)),"")) | L26: =IF(DATE(cfg_Year,9,1)>cfg_LastDataDate,IFERROR(INDEX(cd_Bud_Waste_t_Month,MATCH(DATE(cfg_Year,9,1),cd_Date,0)),""),IFERROR(INDEX(cd_Bud_Waste_t_MTD,MATCH(MIN(EOMONTH(DATE(cfg_Year,9,1),0),cfg_LastDataDate),cd_Date,0)),"")) | M26: =IF(DATE(cfg_Year,10,1)>cfg_LastDataDate,IFERROR(INDEX(cd_Bud_Waste_t_Month,MATCH(DATE(cfg_Year,10,1),cd_Date,0)),""),IFERROR(INDEX(cd_Bud_Waste_t_MTD,MATCH(MIN(EOMONTH(DATE(cfg_Year,10,1),0),cfg_LastDataDate),cd_Date,0)),"")) | N26: =IF(DATE(cfg_Year,11,1)>cfg_LastDataDate,IFERROR(INDEX(cd_Bud_Waste_t_Month,MATCH(DATE(cfg_Year,11,1),cd_Date,0)),""),IFERROR(INDEX(cd_Bud_Waste_t_MTD,MATCH(MIN(EOMONTH(DATE(cfg_Year,11,1),0),cfg_LastDataDate),cd_Date,0)),"")) | O26: =IF(DATE(cfg_Year,12,1)>cfg_LastDataDate,IFERROR(INDEX(cd_Bud_Waste_t_Month,MATCH(DATE(cfg_Year,12,1),cd_Date,0)),""),IFERROR(INDEX(cd_Bud_Waste_t_MTD,MATCH(MIN(EOMONTH(DATE(cfg_Year,12,1),0),cfg_LastDataDate),cd_Date,0)),"")) | P26: =IFERROR(INDEX(cd_Bud_Waste_t_YTD,MATCH(IF(N(cfg_LastDataDate)>0,MIN(cfg_YearEnd,cfg_LastDataDate),cfg_YearEnd),cd_Date,0)),"")
C27: Variance | D27: =IF(AND(ISNUMBER(D25),ISNUMBER(D26),D26<>0),D25/D26-1,"") | E27: =IF(AND(ISNUMBER(E25),ISNUMBER(E26),E26<>0),E25/E26-1,"") | F27: =IF(AND(ISNUMBER(F25),ISNUMBER(F26),F26<>0),F25/F26-1,"") | G27: =IF(AND(ISNUMBER(G25),ISNUMBER(G26),G26<>0),G25/G26-1,"") | H27: =IF(AND(ISNUMBER(H25),ISNUMBER(H26),H26<>0),H25/H26-1,"") | I27: =IF(AND(ISNUMBER(I25),ISNUMBER(I26),I26<>0),I25/I26-1,"") | J27: =IF(AND(ISNUMBER(J25),ISNUMBER(J26),J26<>0),J25/J26-1,"") | K27: =IF(AND(ISNUMBER(K25),ISNUMBER(K26),K26<>0),K25/K26-1,"") | ... P27: =IF(AND(ISNUMBER(P25),ISNUMBER(P26),P26<>0),P25/P26-1,"")
B29: Total material moved | C29: Actual | D29: =IF(DATE(cfg_Year,1,1)>cfg_LastDataDate,"",IFERROR(INDEX(cd_TMM_t_MTD,MATCH(MIN(EOMONTH(DATE(cfg_Year,1,1),0),cfg_LastDataDate),cd_Date,0)),"")) | E29: =IF(DATE(cfg_Year,2,1)>cfg_LastDataDate,"",IFERROR(INDEX(cd_TMM_t_MTD,MATCH(MIN(EOMONTH(DATE(cfg_Year,2,1),0),cfg_LastDataDate),cd_Date,0)),"")) | F29: =IF(DATE(cfg_Year,3,1)>cfg_LastDataDate,"",IFERROR(INDEX(cd_TMM_t_MTD,MATCH(MIN(EOMONTH(DATE(cfg_Year,3,1),0),cfg_LastDataDate),cd_Date,0)),"")) | G29: =IF(DATE(cfg_Year,4,1)>cfg_LastDataDate,"",IFERROR(INDEX(cd_TMM_t_MTD,MATCH(MIN(EOMONTH(DATE(cfg_Year,4,1),0),cfg_LastDataDate),cd_Date,0)),"")) | H29: =IF(DATE(cfg_Year,5,1)>cfg_LastDataDate,"",IFERROR(INDEX(cd_TMM_t_MTD,MATCH(MIN(EOMONTH(DATE(cfg_Year,5,1),0),cfg_LastDataDate),cd_Date,0)),"")) | I29: =IF(DATE(cfg_Year,6,1)>cfg_LastDataDate,"",IFERROR(INDEX(cd_TMM_t_MTD,MATCH(MIN(EOMONTH(DATE(cfg_Year,6,1),0),cfg_LastDataDate),cd_Date,0)),"")) | J29: =IF(DATE(cfg_Year,7,1)>cfg_LastDataDate,"",IFERROR(INDEX(cd_TMM_t_MTD,MATCH(MIN(EOMONTH(DATE(cfg_Year,7,1),0),cfg_LastDataDate),cd_Date,0)),"")) | K29: =IF(DATE(cfg_Year,8,1)>cfg_LastDataDate,"",IFERROR(INDEX(cd_TMM_t_MTD,MATCH(MIN(EOMONTH(DATE(cfg_Year,8,1),0),cfg_LastDataDate),cd_Date,0)),"")) | L29: =IF(DATE(cfg_Year,9,1)>cfg_LastDataDate,"",IFERROR(INDEX(cd_TMM_t_MTD,MATCH(MIN(EOMONTH(DATE(cfg_Year,9,1),0),cfg_LastDataDate),cd_Date,0)),"")) | M29: =IF(DATE(cfg_Year,10,1)>cfg_LastDataDate,"",IFERROR(INDEX(cd_TMM_t_MTD,MATCH(MIN(EOMONTH(DATE(cfg_Year,10,1),0),cfg_LastDataDate),cd_Date,0)),"")) | N29: =IF(DATE(cfg_Year,11,1)>cfg_LastDataDate,"",IFERROR(INDEX(cd_TMM_t_MTD,MATCH(MIN(EOMONTH(DATE(cfg_Year,11,1),0),cfg_LastDataDate),cd_Date,0)),"")) | O29: =IF(DATE(cfg_Year,12,1)>cfg_LastDataDate,"",IFERROR(INDEX(cd_TMM_t_MTD,MATCH(MIN(EOMONTH(DATE(cfg_Year,12,1),0),cfg_LastDataDate),cd_Date,0)),"")) | P29: =IFERROR(INDEX(cd_TMM_t_YTD,MATCH(MIN(cfg_YearEnd,cfg_LastDataDate),cd_Date,0)),"")
C30: Budget | D30: =IF(DATE(cfg_Year,1,1)>cfg_LastDataDate,IFERROR(INDEX(cd_Bud_TMM_t_Month,MATCH(DATE(cfg_Year,1,1),cd_Date,0)),""),IFERROR(INDEX(cd_Bud_TMM_t_MTD,MATCH(MIN(EOMONTH(DATE(cfg_Year,1,1),0),cfg_LastDataDate),cd_Date,0)),"")) | E30: =IF(DATE(cfg_Year,2,1)>cfg_LastDataDate,IFERROR(INDEX(cd_Bud_TMM_t_Month,MATCH(DATE(cfg_Year,2,1),cd_Date,0)),""),IFERROR(INDEX(cd_Bud_TMM_t_MTD,MATCH(MIN(EOMONTH(DATE(cfg_Year,2,1),0),cfg_LastDataDate),cd_Date,0)),"")) | F30: =IF(DATE(cfg_Year,3,1)>cfg_LastDataDate,IFERROR(INDEX(cd_Bud_TMM_t_Month,MATCH(DATE(cfg_Year,3,1),cd_Date,0)),""),IFERROR(INDEX(cd_Bud_TMM_t_MTD,MATCH(MIN(EOMONTH(DATE(cfg_Year,3,1),0),cfg_LastDataDate),cd_Date,0)),"")) | G30: =IF(DATE(cfg_Year,4,1)>cfg_LastDataDate,IFERROR(INDEX(cd_Bud_TMM_t_Month,MATCH(DATE(cfg_Year,4,1),cd_Date,0)),""),IFERROR(INDEX(cd_Bud_TMM_t_MTD,MATCH(MIN(EOMONTH(DATE(cfg_Year,4,1),0),cfg_LastDataDate),cd_Date,0)),"")) | H30: =IF(DATE(cfg_Year,5,1)>cfg_LastDataDate,IFERROR(INDEX(cd_Bud_TMM_t_Month,MATCH(DATE(cfg_Year,5,1),cd_Date,0)),""),IFERROR(INDEX(cd_Bud_TMM_t_MTD,MATCH(MIN(EOMONTH(DATE(cfg_Year,5,1),0),cfg_LastDataDate),cd_Date,0)),"")) | I30: =IF(DATE(cfg_Year,6,1)>cfg_LastDataDate,IFERROR(INDEX(cd_Bud_TMM_t_Month,MATCH(DATE(cfg_Year,6,1),cd_Date,0)),""),IFERROR(INDEX(cd_Bud_TMM_t_MTD,MATCH(MIN(EOMONTH(DATE(cfg_Year,6,1),0),cfg_LastDataDate),cd_Date,0)),"")) | J30: =IF(DATE(cfg_Year,7,1)>cfg_LastDataDate,IFERROR(INDEX(cd_Bud_TMM_t_Month,MATCH(DATE(cfg_Year,7,1),cd_Date,0)),""),IFERROR(INDEX(cd_Bud_TMM_t_MTD,MATCH(MIN(EOMONTH(DATE(cfg_Year,7,1),0),cfg_LastDataDate),cd_Date,0)),"")) | K30: =IF(DATE(cfg_Year,8,1)>cfg_LastDataDate,IFERROR(INDEX(cd_Bud_TMM_t_Month,MATCH(DATE(cfg_Year,8,1),cd_Date,0)),""),IFERROR(INDEX(cd_Bud_TMM_t_MTD,MATCH(MIN(EOMONTH(DATE(cfg_Year,8,1),0),cfg_LastDataDate),cd_Date,0)),"")) | L30: =IF(DATE(cfg_Year,9,1)>cfg_LastDataDate,IFERROR(INDEX(cd_Bud_TMM_t_Month,MATCH(DATE(cfg_Year,9,1),cd_Date,0)),""),IFERROR(INDEX(cd_Bud_TMM_t_MTD,MATCH(MIN(EOMONTH(DATE(cfg_Year,9,1),0),cfg_LastDataDate),cd_Date,0)),"")) | M30: =IF(DATE(cfg_Year,10,1)>cfg_LastDataDate,IFERROR(INDEX(cd_Bud_TMM_t_Month,MATCH(DATE(cfg_Year,10,1),cd_Date,0)),""),IFERROR(INDEX(cd_Bud_TMM_t_MTD,MATCH(MIN(EOMONTH(DATE(cfg_Year,10,1),0),cfg_LastDataDate),cd_Date,0)),"")) | N30: =IF(DATE(cfg_Year,11,1)>cfg_LastDataDate,IFERROR(INDEX(cd_Bud_TMM_t_Month,MATCH(DATE(cfg_Year,11,1),cd_Date,0)),""),IFERROR(INDEX(cd_Bud_TMM_t_MTD,MATCH(MIN(EOMONTH(DATE(cfg_Year,11,1),0),cfg_LastDataDate),cd_Date,0)),"")) | O30: =IF(DATE(cfg_Year,12,1)>cfg_LastDataDate,IFERROR(INDEX(cd_Bud_TMM_t_Month,MATCH(DATE(cfg_Year,12,1),cd_Date,0)),""),IFERROR(INDEX(cd_Bud_TMM_t_MTD,MATCH(MIN(EOMONTH(DATE(cfg_Year,12,1),0),cfg_LastDataDate),cd_Date,0)),"")) | P30: =IFERROR(INDEX(cd_Bud_TMM_t_YTD,MATCH(IF(N(cfg_LastDataDate)>0,MIN(cfg_YearEnd,cfg_LastDataDate),cfg_YearEnd),cd_Date,0)),"")
C31: Variance | D31: =IF(AND(ISNUMBER(D29),ISNUMBER(D30),D30<>0),D29/D30-1,"") | E31: =IF(AND(ISNUMBER(E29),ISNUMBER(E30),E30<>0),E29/E30-1,"") | F31: =IF(AND(ISNUMBER(F29),ISNUMBER(F30),F30<>0),F29/F30-1,"") | G31: =IF(AND(ISNUMBER(G29),ISNUMBER(G30),G30<>0),G29/G30-1,"") | H31: =IF(AND(ISNUMBER(H29),ISNUMBER(H30),H30<>0),H29/H30-1,"") | I31: =IF(AND(ISNUMBER(I29),ISNUMBER(I30),I30<>0),I29/I30-1,"") | J31: =IF(AND(ISNUMBER(J29),ISNUMBER(J30),J30<>0),J29/J30-1,"") | K31: =IF(AND(ISNUMBER(K29),ISNUMBER(K30),K30<>0),K29/K30-1,"") | ... P31: =IF(AND(ISNUMBER(P29),ISNUMBER(P30),P30<>0),P29/P30-1,"")
B33: Strip ratio (waste : ore) | C33: Actual | D33: =IF(DATE(cfg_Year,1,1)>cfg_LastDataDate,"",IFERROR(INDEX(cd_Strip_Ratio_MTD,MATCH(MIN(EOMONTH(DATE(cfg_Year,1,1),0),cfg_LastDataDate),cd_Date,0)),"")) | E33: =IF(DATE(cfg_Year,2,1)>cfg_LastDataDate,"",IFERROR(INDEX(cd_Strip_Ratio_MTD,MATCH(MIN(EOMONTH(DATE(cfg_Year,2,1),0),cfg_LastDataDate),cd_Date,0)),"")) | F33: =IF(DATE(cfg_Year,3,1)>cfg_LastDataDate,"",IFERROR(INDEX(cd_Strip_Ratio_MTD,MATCH(MIN(EOMONTH(DATE(cfg_Year,3,1),0),cfg_LastDataDate),cd_Date,0)),"")) | G33: =IF(DATE(cfg_Year,4,1)>cfg_LastDataDate,"",IFERROR(INDEX(cd_Strip_Ratio_MTD,MATCH(MIN(EOMONTH(DATE(cfg_Year,4,1),0),cfg_LastDataDate),cd_Date,0)),"")) | H33: =IF(DATE(cfg_Year,5,1)>cfg_LastDataDate,"",IFERROR(INDEX(cd_Strip_Ratio_MTD,MATCH(MIN(EOMONTH(DATE(cfg_Year,5,1),0),cfg_LastDataDate),cd_Date,0)),"")) | I33: =IF(DATE(cfg_Year,6,1)>cfg_LastDataDate,"",IFERROR(INDEX(cd_Strip_Ratio_MTD,MATCH(MIN(EOMONTH(DATE(cfg_Year,6,1),0),cfg_LastDataDate),cd_Date,0)),"")) | J33: =IF(DATE(cfg_Year,7,1)>cfg_LastDataDate,"",IFERROR(INDEX(cd_Strip_Ratio_MTD,MATCH(MIN(EOMONTH(DATE(cfg_Year,7,1),0),cfg_LastDataDate),cd_Date,0)),"")) | K33: =IF(DATE(cfg_Year,8,1)>cfg_LastDataDate,"",IFERROR(INDEX(cd_Strip_Ratio_MTD,MATCH(MIN(EOMONTH(DATE(cfg_Year,8,1),0),cfg_LastDataDate),cd_Date,0)),"")) | L33: =IF(DATE(cfg_Year,9,1)>cfg_LastDataDate,"",IFERROR(INDEX(cd_Strip_Ratio_MTD,MATCH(MIN(EOMONTH(DATE(cfg_Year,9,1),0),cfg_LastDataDate),cd_Date,0)),"")) | M33: =IF(DATE(cfg_Year,10,1)>cfg_LastDataDate,"",IFERROR(INDEX(cd_Strip_Ratio_MTD,MATCH(MIN(EOMONTH(DATE(cfg_Year,10,1),0),cfg_LastDataDate),cd_Date,0)),"")) | N33: =IF(DATE(cfg_Year,11,1)>cfg_LastDataDate,"",IFERROR(INDEX(cd_Strip_Ratio_MTD,MATCH(MIN(EOMONTH(DATE(cfg_Year,11,1),0),cfg_LastDataDate),cd_Date,0)),"")) | O33: =IF(DATE(cfg_Year,12,1)>cfg_LastDataDate,"",IFERROR(INDEX(cd_Strip_Ratio_MTD,MATCH(MIN(EOMONTH(DATE(cfg_Year,12,1),0),cfg_LastDataDate),cd_Date,0)),"")) | P33: =IFERROR(INDEX(cd_Strip_Ratio_YTD,MATCH(MIN(cfg_YearEnd,cfg_LastDataDate),cd_Date,0)),"")
C34: Budget | D34: =IF(DATE(cfg_Year,1,1)>cfg_LastDataDate,IFERROR(INDEX(cd_Bud_Strip_Ratio_Month,MATCH(DATE(cfg_Year,1,1),cd_Date,0)),""),IFERROR(INDEX(cd_Bud_Strip_Ratio_MTD,MATCH(MIN(EOMONTH(DATE(cfg_Year,1,1),0),cfg_LastDataDate),cd_Date,0)),"")) | E34: =IF(DATE(cfg_Year,2,1)>cfg_LastDataDate,IFERROR(INDEX(cd_Bud_Strip_Ratio_Month,MATCH(DATE(cfg_Year,2,1),cd_Date,0)),""),IFERROR(INDEX(cd_Bud_Strip_Ratio_MTD,MATCH(MIN(EOMONTH(DATE(cfg_Year,2,1),0),cfg_LastDataDate),cd_Date,0)),"")) | F34: =IF(DATE(cfg_Year,3,1)>cfg_LastDataDate,IFERROR(INDEX(cd_Bud_Strip_Ratio_Month,MATCH(DATE(cfg_Year,3,1),cd_Date,0)),""),IFERROR(INDEX(cd_Bud_Strip_Ratio_MTD,MATCH(MIN(EOMONTH(DATE(cfg_Year,3,1),0),cfg_LastDataDate),cd_Date,0)),"")) | G34: =IF(DATE(cfg_Year,4,1)>cfg_LastDataDate,IFERROR(INDEX(cd_Bud_Strip_Ratio_Month,MATCH(DATE(cfg_Year,4,1),cd_Date,0)),""),IFERROR(INDEX(cd_Bud_Strip_Ratio_MTD,MATCH(MIN(EOMONTH(DATE(cfg_Year,4,1),0),cfg_LastDataDate),cd_Date,0)),"")) | H34: =IF(DATE(cfg_Year,5,1)>cfg_LastDataDate,IFERROR(INDEX(cd_Bud_Strip_Ratio_Month,MATCH(DATE(cfg_Year,5,1),cd_Date,0)),""),IFERROR(INDEX(cd_Bud_Strip_Ratio_MTD,MATCH(MIN(EOMONTH(DATE(cfg_Year,5,1),0),cfg_LastDataDate),cd_Date,0)),"")) | I34: =IF(DATE(cfg_Year,6,1)>cfg_LastDataDate,IFERROR(INDEX(cd_Bud_Strip_Ratio_Month,MATCH(DATE(cfg_Year,6,1),cd_Date,0)),""),IFERROR(INDEX(cd_Bud_Strip_Ratio_MTD,MATCH(MIN(EOMONTH(DATE(cfg_Year,6,1),0),cfg_LastDataDate),cd_Date,0)),"")) | J34: =IF(DATE(cfg_Year,7,1)>cfg_LastDataDate,IFERROR(INDEX(cd_Bud_Strip_Ratio_Month,MATCH(DATE(cfg_Year,7,1),cd_Date,0)),""),IFERROR(INDEX(cd_Bud_Strip_Ratio_MTD,MATCH(MIN(EOMONTH(DATE(cfg_Year,7,1),0),cfg_LastDataDate),cd_Date,0)),"")) | K34: =IF(DATE(cfg_Year,8,1)>cfg_LastDataDate,IFERROR(INDEX(cd_Bud_Strip_Ratio_Month,MATCH(DATE(cfg_Year,8,1),cd_Date,0)),""),IFERROR(INDEX(cd_Bud_Strip_Ratio_MTD,MATCH(MIN(EOMONTH(DATE(cfg_Year,8,1),0),cfg_LastDataDate),cd_Date,0)),"")) | L34: =IF(DATE(cfg_Year,9,1)>cfg_LastDataDate,IFERROR(INDEX(cd_Bud_Strip_Ratio_Month,MATCH(DATE(cfg_Year,9,1),cd_Date,0)),""),IFERROR(INDEX(cd_Bud_Strip_Ratio_MTD,MATCH(MIN(EOMONTH(DATE(cfg_Year,9,1),0),cfg_LastDataDate),cd_Date,0)),"")) | M34: =IF(DATE(cfg_Year,10,1)>cfg_LastDataDate,IFERROR(INDEX(cd_Bud_Strip_Ratio_Month,MATCH(DATE(cfg_Year,10,1),cd_Date,0)),""),IFERROR(INDEX(cd_Bud_Strip_Ratio_MTD,MATCH(MIN(EOMONTH(DATE(cfg_Year,10,1),0),cfg_LastDataDate),cd_Date,0)),"")) | N34: =IF(DATE(cfg_Year,11,1)>cfg_LastDataDate,IFERROR(INDEX(cd_Bud_Strip_Ratio_Month,MATCH(DATE(cfg_Year,11,1),cd_Date,0)),""),IFERROR(INDEX(cd_Bud_Strip_Ratio_MTD,MATCH(MIN(EOMONTH(DATE(cfg_Year,11,1),0),cfg_LastDataDate),cd_Date,0)),"")) | O34: =IF(DATE(cfg_Year,12,1)>cfg_LastDataDate,IFERROR(INDEX(cd_Bud_Strip_Ratio_Month,MATCH(DATE(cfg_Year,12,1),cd_Date,0)),""),IFERROR(INDEX(cd_Bud_Strip_Ratio_MTD,MATCH(MIN(EOMONTH(DATE(cfg_Year,12,1),0),cfg_LastDataDate),cd_Date,0)),"")) | P34: =IFERROR(INDEX(cd_Bud_Strip_Ratio_YTD,MATCH(IF(N(cfg_LastDataDate)>0,MIN(cfg_YearEnd,cfg_LastDataDate),cfg_YearEnd),cd_Date,0)),"")
C35: Variance | D35: =IF(AND(ISNUMBER(D33),ISNUMBER(D34),D34<>0),D33/D34-1,"") | E35: =IF(AND(ISNUMBER(E33),ISNUMBER(E34),E34<>0),E33/E34-1,"") | F35: =IF(AND(ISNUMBER(F33),ISNUMBER(F34),F34<>0),F33/F34-1,"") | G35: =IF(AND(ISNUMBER(G33),ISNUMBER(G34),G34<>0),G33/G34-1,"") | H35: =IF(AND(ISNUMBER(H33),ISNUMBER(H34),H34<>0),H33/H34-1,"") | I35: =IF(AND(ISNUMBER(I33),ISNUMBER(I34),I34<>0),I33/I34-1,"") | J35: =IF(AND(ISNUMBER(J33),ISNUMBER(J34),J34<>0),J33/J34-1,"") | K35: =IF(AND(ISNUMBER(K33),ISNUMBER(K34),K34<>0),K33/K34-1,"") | ... P35: =IF(AND(ISNUMBER(P33),ISNUMBER(P34),P34<>0),P33/P34-1,"")
B37: Drilled | C37: Actual | D37: =IF(DATE(cfg_Year,1,1)>cfg_LastDataDate,"",IFERROR(INDEX(cd_Drill_m_MTD,MATCH(MIN(EOMONTH(DATE(cfg_Year,1,1),0),cfg_LastDataDate),cd_Date,0)),"")) | E37: =IF(DATE(cfg_Year,2,1)>cfg_LastDataDate,"",IFERROR(INDEX(cd_Drill_m_MTD,MATCH(MIN(EOMONTH(DATE(cfg_Year,2,1),0),cfg_LastDataDate),cd_Date,0)),"")) | F37: =IF(DATE(cfg_Year,3,1)>cfg_LastDataDate,"",IFERROR(INDEX(cd_Drill_m_MTD,MATCH(MIN(EOMONTH(DATE(cfg_Year,3,1),0),cfg_LastDataDate),cd_Date,0)),"")) | G37: =IF(DATE(cfg_Year,4,1)>cfg_LastDataDate,"",IFERROR(INDEX(cd_Drill_m_MTD,MATCH(MIN(EOMONTH(DATE(cfg_Year,4,1),0),cfg_LastDataDate),cd_Date,0)),"")) | H37: =IF(DATE(cfg_Year,5,1)>cfg_LastDataDate,"",IFERROR(INDEX(cd_Drill_m_MTD,MATCH(MIN(EOMONTH(DATE(cfg_Year,5,1),0),cfg_LastDataDate),cd_Date,0)),"")) | I37: =IF(DATE(cfg_Year,6,1)>cfg_LastDataDate,"",IFERROR(INDEX(cd_Drill_m_MTD,MATCH(MIN(EOMONTH(DATE(cfg_Year,6,1),0),cfg_LastDataDate),cd_Date,0)),"")) | J37: =IF(DATE(cfg_Year,7,1)>cfg_LastDataDate,"",IFERROR(INDEX(cd_Drill_m_MTD,MATCH(MIN(EOMONTH(DATE(cfg_Year,7,1),0),cfg_LastDataDate),cd_Date,0)),"")) | K37: =IF(DATE(cfg_Year,8,1)>cfg_LastDataDate,"",IFERROR(INDEX(cd_Drill_m_MTD,MATCH(MIN(EOMONTH(DATE(cfg_Year,8,1),0),cfg_LastDataDate),cd_Date,0)),"")) | L37: =IF(DATE(cfg_Year,9,1)>cfg_LastDataDate,"",IFERROR(INDEX(cd_Drill_m_MTD,MATCH(MIN(EOMONTH(DATE(cfg_Year,9,1),0),cfg_LastDataDate),cd_Date,0)),"")) | M37: =IF(DATE(cfg_Year,10,1)>cfg_LastDataDate,"",IFERROR(INDEX(cd_Drill_m_MTD,MATCH(MIN(EOMONTH(DATE(cfg_Year,10,1),0),cfg_LastDataDate),cd_Date,0)),"")) | N37: =IF(DATE(cfg_Year,11,1)>cfg_LastDataDate,"",IFERROR(INDEX(cd_Drill_m_MTD,MATCH(MIN(EOMONTH(DATE(cfg_Year,11,1),0),cfg_LastDataDate),cd_Date,0)),"")) | O37: =IF(DATE(cfg_Year,12,1)>cfg_LastDataDate,"",IFERROR(INDEX(cd_Drill_m_MTD,MATCH(MIN(EOMONTH(DATE(cfg_Year,12,1),0),cfg_LastDataDate),cd_Date,0)),"")) | P37: =IFERROR(INDEX(cd_Drill_m_YTD,MATCH(MIN(cfg_YearEnd,cfg_LastDataDate),cd_Date,0)),"")
C38: Budget | D38: =IF(DATE(cfg_Year,1,1)>cfg_LastDataDate,IFERROR(INDEX(cd_Bud_Drill_m_Month,MATCH(DATE(cfg_Year,1,1),cd_Date,0)),""),IFERROR(INDEX(cd_Bud_Drill_m_MTD,MATCH(MIN(EOMONTH(DATE(cfg_Year,1,1),0),cfg_LastDataDate),cd_Date,0)),"")) | E38: =IF(DATE(cfg_Year,2,1)>cfg_LastDataDate,IFERROR(INDEX(cd_Bud_Drill_m_Month,MATCH(DATE(cfg_Year,2,1),cd_Date,0)),""),IFERROR(INDEX(cd_Bud_Drill_m_MTD,MATCH(MIN(EOMONTH(DATE(cfg_Year,2,1),0),cfg_LastDataDate),cd_Date,0)),"")) | F38: =IF(DATE(cfg_Year,3,1)>cfg_LastDataDate,IFERROR(INDEX(cd_Bud_Drill_m_Month,MATCH(DATE(cfg_Year,3,1),cd_Date,0)),""),IFERROR(INDEX(cd_Bud_Drill_m_MTD,MATCH(MIN(EOMONTH(DATE(cfg_Year,3,1),0),cfg_LastDataDate),cd_Date,0)),"")) | G38: =IF(DATE(cfg_Year,4,1)>cfg_LastDataDate,IFERROR(INDEX(cd_Bud_Drill_m_Month,MATCH(DATE(cfg_Year,4,1),cd_Date,0)),""),IFERROR(INDEX(cd_Bud_Drill_m_MTD,MATCH(MIN(EOMONTH(DATE(cfg_Year,4,1),0),cfg_LastDataDate),cd_Date,0)),"")) | H38: =IF(DATE(cfg_Year,5,1)>cfg_LastDataDate,IFERROR(INDEX(cd_Bud_Drill_m_Month,MATCH(DATE(cfg_Year,5,1),cd_Date,0)),""),IFERROR(INDEX(cd_Bud_Drill_m_MTD,MATCH(MIN(EOMONTH(DATE(cfg_Year,5,1),0),cfg_LastDataDate),cd_Date,0)),"")) | I38: =IF(DATE(cfg_Year,6,1)>cfg_LastDataDate,IFERROR(INDEX(cd_Bud_Drill_m_Month,MATCH(DATE(cfg_Year,6,1),cd_Date,0)),""),IFERROR(INDEX(cd_Bud_Drill_m_MTD,MATCH(MIN(EOMONTH(DATE(cfg_Year,6,1),0),cfg_LastDataDate),cd_Date,0)),"")) | J38: =IF(DATE(cfg_Year,7,1)>cfg_LastDataDate,IFERROR(INDEX(cd_Bud_Drill_m_Month,MATCH(DATE(cfg_Year,7,1),cd_Date,0)),""),IFERROR(INDEX(cd_Bud_Drill_m_MTD,MATCH(MIN(EOMONTH(DATE(cfg_Year,7,1),0),cfg_LastDataDate),cd_Date,0)),"")) | K38: =IF(DATE(cfg_Year,8,1)>cfg_LastDataDate,IFERROR(INDEX(cd_Bud_Drill_m_Month,MATCH(DATE(cfg_Year,8,1),cd_Date,0)),""),IFERROR(INDEX(cd_Bud_Drill_m_MTD,MATCH(MIN(EOMONTH(DATE(cfg_Year,8,1),0),cfg_LastDataDate),cd_Date,0)),"")) | L38: =IF(DATE(cfg_Year,9,1)>cfg_LastDataDate,IFERROR(INDEX(cd_Bud_Drill_m_Month,MATCH(DATE(cfg_Year,9,1),cd_Date,0)),""),IFERROR(INDEX(cd_Bud_Drill_m_MTD,MATCH(MIN(EOMONTH(DATE(cfg_Year,9,1),0),cfg_LastDataDate),cd_Date,0)),"")) | M38: =IF(DATE(cfg_Year,10,1)>cfg_LastDataDate,IFERROR(INDEX(cd_Bud_Drill_m_Month,MATCH(DATE(cfg_Year,10,1),cd_Date,0)),""),IFERROR(INDEX(cd_Bud_Drill_m_MTD,MATCH(MIN(EOMONTH(DATE(cfg_Year,10,1),0),cfg_LastDataDate),cd_Date,0)),"")) | N38: =IF(DATE(cfg_Year,11,1)>cfg_LastDataDate,IFERROR(INDEX(cd_Bud_Drill_m_Month,MATCH(DATE(cfg_Year,11,1),cd_Date,0)),""),IFERROR(INDEX(cd_Bud_Drill_m_MTD,MATCH(MIN(EOMONTH(DATE(cfg_Year,11,1),0),cfg_LastDataDate),cd_Date,0)),"")) | O38: =IF(DATE(cfg_Year,12,1)>cfg_LastDataDate,IFERROR(INDEX(cd_Bud_Drill_m_Month,MATCH(DATE(cfg_Year,12,1),cd_Date,0)),""),IFERROR(INDEX(cd_Bud_Drill_m_MTD,MATCH(MIN(EOMONTH(DATE(cfg_Year,12,1),0),cfg_LastDataDate),cd_Date,0)),"")) | P38: =IFERROR(INDEX(cd_Bud_Drill_m_YTD,MATCH(IF(N(cfg_LastDataDate)>0,MIN(cfg_YearEnd,cfg_LastDataDate),cfg_YearEnd),cd_Date,0)),"")
C39: Variance | D39: =IF(AND(ISNUMBER(D37),ISNUMBER(D38),D38<>0),D37/D38-1,"") | E39: =IF(AND(ISNUMBER(E37),ISNUMBER(E38),E38<>0),E37/E38-1,"") | F39: =IF(AND(ISNUMBER(F37),ISNUMBER(F38),F38<>0),F37/F38-1,"") | G39: =IF(AND(ISNUMBER(G37),ISNUMBER(G38),G38<>0),G37/G38-1,"") | H39: =IF(AND(ISNUMBER(H37),ISNUMBER(H38),H38<>0),H37/H38-1,"") | I39: =IF(AND(ISNUMBER(I37),ISNUMBER(I38),I38<>0),I37/I38-1,"") | J39: =IF(AND(ISNUMBER(J37),ISNUMBER(J38),J38<>0),J37/J38-1,"") | K39: =IF(AND(ISNUMBER(K37),ISNUMBER(K38),K38<>0),K37/K38-1,"") | ... P39: =IF(AND(ISNUMBER(P37),ISNUMBER(P38),P38<>0),P37/P38-1,"")
B41: Milled | C41: Actual | D41: =IF(DATE(cfg_Year,1,1)>cfg_LastDataDate,"",IFERROR(INDEX(cd_Milled_t_MTD,MATCH(MIN(EOMONTH(DATE(cfg_Year,1,1),0),cfg_LastDataDate),cd_Date,0)),"")) | E41: =IF(DATE(cfg_Year,2,1)>cfg_LastDataDate,"",IFERROR(INDEX(cd_Milled_t_MTD,MATCH(MIN(EOMONTH(DATE(cfg_Year,2,1),0),cfg_LastDataDate),cd_Date,0)),"")) | F41: =IF(DATE(cfg_Year,3,1)>cfg_LastDataDate,"",IFERROR(INDEX(cd_Milled_t_MTD,MATCH(MIN(EOMONTH(DATE(cfg_Year,3,1),0),cfg_LastDataDate),cd_Date,0)),"")) | G41: =IF(DATE(cfg_Year,4,1)>cfg_LastDataDate,"",IFERROR(INDEX(cd_Milled_t_MTD,MATCH(MIN(EOMONTH(DATE(cfg_Year,4,1),0),cfg_LastDataDate),cd_Date,0)),"")) | H41: =IF(DATE(cfg_Year,5,1)>cfg_LastDataDate,"",IFERROR(INDEX(cd_Milled_t_MTD,MATCH(MIN(EOMONTH(DATE(cfg_Year,5,1),0),cfg_LastDataDate),cd_Date,0)),"")) | I41: =IF(DATE(cfg_Year,6,1)>cfg_LastDataDate,"",IFERROR(INDEX(cd_Milled_t_MTD,MATCH(MIN(EOMONTH(DATE(cfg_Year,6,1),0),cfg_LastDataDate),cd_Date,0)),"")) | J41: =IF(DATE(cfg_Year,7,1)>cfg_LastDataDate,"",IFERROR(INDEX(cd_Milled_t_MTD,MATCH(MIN(EOMONTH(DATE(cfg_Year,7,1),0),cfg_LastDataDate),cd_Date,0)),"")) | K41: =IF(DATE(cfg_Year,8,1)>cfg_LastDataDate,"",IFERROR(INDEX(cd_Milled_t_MTD,MATCH(MIN(EOMONTH(DATE(cfg_Year,8,1),0),cfg_LastDataDate),cd_Date,0)),"")) | L41: =IF(DATE(cfg_Year,9,1)>cfg_LastDataDate,"",IFERROR(INDEX(cd_Milled_t_MTD,MATCH(MIN(EOMONTH(DATE(cfg_Year,9,1),0),cfg_LastDataDate),cd_Date,0)),"")) | M41: =IF(DATE(cfg_Year,10,1)>cfg_LastDataDate,"",IFERROR(INDEX(cd_Milled_t_MTD,MATCH(MIN(EOMONTH(DATE(cfg_Year,10,1),0),cfg_LastDataDate),cd_Date,0)),"")) | N41: =IF(DATE(cfg_Year,11,1)>cfg_LastDataDate,"",IFERROR(INDEX(cd_Milled_t_MTD,MATCH(MIN(EOMONTH(DATE(cfg_Year,11,1),0),cfg_LastDataDate),cd_Date,0)),"")) | O41: =IF(DATE(cfg_Year,12,1)>cfg_LastDataDate,"",IFERROR(INDEX(cd_Milled_t_MTD,MATCH(MIN(EOMONTH(DATE(cfg_Year,12,1),0),cfg_LastDataDate),cd_Date,0)),"")) | P41: =IFERROR(INDEX(cd_Milled_t_YTD,MATCH(MIN(cfg_YearEnd,cfg_LastDataDate),cd_Date,0)),"")
C42: Budget | D42: =IF(DATE(cfg_Year,1,1)>cfg_LastDataDate,IFERROR(INDEX(cd_Bud_Milled_t_Month,MATCH(DATE(cfg_Year,1,1),cd_Date,0)),""),IFERROR(INDEX(cd_Bud_Milled_t_MTD,MATCH(MIN(EOMONTH(DATE(cfg_Year,1,1),0),cfg_LastDataDate),cd_Date,0)),"")) | E42: =IF(DATE(cfg_Year,2,1)>cfg_LastDataDate,IFERROR(INDEX(cd_Bud_Milled_t_Month,MATCH(DATE(cfg_Year,2,1),cd_Date,0)),""),IFERROR(INDEX(cd_Bud_Milled_t_MTD,MATCH(MIN(EOMONTH(DATE(cfg_Year,2,1),0),cfg_LastDataDate),cd_Date,0)),"")) | F42: =IF(DATE(cfg_Year,3,1)>cfg_LastDataDate,IFERROR(INDEX(cd_Bud_Milled_t_Month,MATCH(DATE(cfg_Year,3,1),cd_Date,0)),""),IFERROR(INDEX(cd_Bud_Milled_t_MTD,MATCH(MIN(EOMONTH(DATE(cfg_Year,3,1),0),cfg_LastDataDate),cd_Date,0)),"")) | G42: =IF(DATE(cfg_Year,4,1)>cfg_LastDataDate,IFERROR(INDEX(cd_Bud_Milled_t_Month,MATCH(DATE(cfg_Year,4,1),cd_Date,0)),""),IFERROR(INDEX(cd_Bud_Milled_t_MTD,MATCH(MIN(EOMONTH(DATE(cfg_Year,4,1),0),cfg_LastDataDate),cd_Date,0)),"")) | H42: =IF(DATE(cfg_Year,5,1)>cfg_LastDataDate,IFERROR(INDEX(cd_Bud_Milled_t_Month,MATCH(DATE(cfg_Year,5,1),cd_Date,0)),""),IFERROR(INDEX(cd_Bud_Milled_t_MTD,MATCH(MIN(EOMONTH(DATE(cfg_Year,5,1),0),cfg_LastDataDate),cd_Date,0)),"")) | I42: =IF(DATE(cfg_Year,6,1)>cfg_LastDataDate,IFERROR(INDEX(cd_Bud_Milled_t_Month,MATCH(DATE(cfg_Year,6,1),cd_Date,0)),""),IFERROR(INDEX(cd_Bud_Milled_t_MTD,MATCH(MIN(EOMONTH(DATE(cfg_Year,6,1),0),cfg_LastDataDate),cd_Date,0)),"")) | J42: =IF(DATE(cfg_Year,7,1)>cfg_LastDataDate,IFERROR(INDEX(cd_Bud_Milled_t_Month,MATCH(DATE(cfg_Year,7,1),cd_Date,0)),""),IFERROR(INDEX(cd_Bud_Milled_t_MTD,MATCH(MIN(EOMONTH(DATE(cfg_Year,7,1),0),cfg_LastDataDate),cd_Date,0)),"")) | K42: =IF(DATE(cfg_Year,8,1)>cfg_LastDataDate,IFERROR(INDEX(cd_Bud_Milled_t_Month,MATCH(DATE(cfg_Year,8,1),cd_Date,0)),""),IFERROR(INDEX(cd_Bud_Milled_t_MTD,MATCH(MIN(EOMONTH(DATE(cfg_Year,8,1),0),cfg_LastDataDate),cd_Date,0)),"")) | L42: =IF(DATE(cfg_Year,9,1)>cfg_LastDataDate,IFERROR(INDEX(cd_Bud_Milled_t_Month,MATCH(DATE(cfg_Year,9,1),cd_Date,0)),""),IFERROR(INDEX(cd_Bud_Milled_t_MTD,MATCH(MIN(EOMONTH(DATE(cfg_Year,9,1),0),cfg_LastDataDate),cd_Date,0)),"")) | M42: =IF(DATE(cfg_Year,10,1)>cfg_LastDataDate,IFERROR(INDEX(cd_Bud_Milled_t_Month,MATCH(DATE(cfg_Year,10,1),cd_Date,0)),""),IFERROR(INDEX(cd_Bud_Milled_t_MTD,MATCH(MIN(EOMONTH(DATE(cfg_Year,10,1),0),cfg_LastDataDate),cd_Date,0)),"")) | N42: =IF(DATE(cfg_Year,11,1)>cfg_LastDataDate,IFERROR(INDEX(cd_Bud_Milled_t_Month,MATCH(DATE(cfg_Year,11,1),cd_Date,0)),""),IFERROR(INDEX(cd_Bud_Milled_t_MTD,MATCH(MIN(EOMONTH(DATE(cfg_Year,11,1),0),cfg_LastDataDate),cd_Date,0)),"")) | O42: =IF(DATE(cfg_Year,12,1)>cfg_LastDataDate,IFERROR(INDEX(cd_Bud_Milled_t_Month,MATCH(DATE(cfg_Year,12,1),cd_Date,0)),""),IFERROR(INDEX(cd_Bud_Milled_t_MTD,MATCH(MIN(EOMONTH(DATE(cfg_Year,12,1),0),cfg_LastDataDate),cd_Date,0)),"")) | P42: =IFERROR(INDEX(cd_Bud_Milled_t_YTD,MATCH(IF(N(cfg_LastDataDate)>0,MIN(cfg_YearEnd,cfg_LastDataDate),cfg_YearEnd),cd_Date,0)),"")
C43: Variance | D43: =IF(AND(ISNUMBER(D41),ISNUMBER(D42),D42<>0),D41/D42-1,"") | E43: =IF(AND(ISNUMBER(E41),ISNUMBER(E42),E42<>0),E41/E42-1,"") | F43: =IF(AND(ISNUMBER(F41),ISNUMBER(F42),F42<>0),F41/F42-1,"") | G43: =IF(AND(ISNUMBER(G41),ISNUMBER(G42),G42<>0),G41/G42-1,"") | H43: =IF(AND(ISNUMBER(H41),ISNUMBER(H42),H42<>0),H41/H42-1,"") | I43: =IF(AND(ISNUMBER(I41),ISNUMBER(I42),I42<>0),I41/I42-1,"") | J43: =IF(AND(ISNUMBER(J41),ISNUMBER(J42),J42<>0),J41/J42-1,"") | K43: =IF(AND(ISNUMBER(K41),ISNUMBER(K42),K42<>0),K41/K42-1,"") | ... P43: =IF(AND(ISNUMBER(P41),ISNUMBER(P42),P42<>0),P41/P42-1,"")
B45: Head grade | C45: Actual | D45: =IF(DATE(cfg_Year,1,1)>cfg_LastDataDate,"",IFERROR(INDEX(cd_Head_Grade_gpt_MTD,MATCH(MIN(EOMONTH(DATE(cfg_Year,1,1),0),cfg_LastDataDate),cd_Date,0)),"")) | E45: =IF(DATE(cfg_Year,2,1)>cfg_LastDataDate,"",IFERROR(INDEX(cd_Head_Grade_gpt_MTD,MATCH(MIN(EOMONTH(DATE(cfg_Year,2,1),0),cfg_LastDataDate),cd_Date,0)),"")) | F45: =IF(DATE(cfg_Year,3,1)>cfg_LastDataDate,"",IFERROR(INDEX(cd_Head_Grade_gpt_MTD,MATCH(MIN(EOMONTH(DATE(cfg_Year,3,1),0),cfg_LastDataDate),cd_Date,0)),"")) | G45: =IF(DATE(cfg_Year,4,1)>cfg_LastDataDate,"",IFERROR(INDEX(cd_Head_Grade_gpt_MTD,MATCH(MIN(EOMONTH(DATE(cfg_Year,4,1),0),cfg_LastDataDate),cd_Date,0)),"")) | H45: =IF(DATE(cfg_Year,5,1)>cfg_LastDataDate,"",IFERROR(INDEX(cd_Head_Grade_gpt_MTD,MATCH(MIN(EOMONTH(DATE(cfg_Year,5,1),0),cfg_LastDataDate),cd_Date,0)),"")) | I45: =IF(DATE(cfg_Year,6,1)>cfg_LastDataDate,"",IFERROR(INDEX(cd_Head_Grade_gpt_MTD,MATCH(MIN(EOMONTH(DATE(cfg_Year,6,1),0),cfg_LastDataDate),cd_Date,0)),"")) | J45: =IF(DATE(cfg_Year,7,1)>cfg_LastDataDate,"",IFERROR(INDEX(cd_Head_Grade_gpt_MTD,MATCH(MIN(EOMONTH(DATE(cfg_Year,7,1),0),cfg_LastDataDate),cd_Date,0)),"")) | K45: =IF(DATE(cfg_Year,8,1)>cfg_LastDataDate,"",IFERROR(INDEX(cd_Head_Grade_gpt_MTD,MATCH(MIN(EOMONTH(DATE(cfg_Year,8,1),0),cfg_LastDataDate),cd_Date,0)),"")) | L45: =IF(DATE(cfg_Year,9,1)>cfg_LastDataDate,"",IFERROR(INDEX(cd_Head_Grade_gpt_MTD,MATCH(MIN(EOMONTH(DATE(cfg_Year,9,1),0),cfg_LastDataDate),cd_Date,0)),"")) | M45: =IF(DATE(cfg_Year,10,1)>cfg_LastDataDate,"",IFERROR(INDEX(cd_Head_Grade_gpt_MTD,MATCH(MIN(EOMONTH(DATE(cfg_Year,10,1),0),cfg_LastDataDate),cd_Date,0)),"")) | N45: =IF(DATE(cfg_Year,11,1)>cfg_LastDataDate,"",IFERROR(INDEX(cd_Head_Grade_gpt_MTD,MATCH(MIN(EOMONTH(DATE(cfg_Year,11,1),0),cfg_LastDataDate),cd_Date,0)),"")) | O45: =IF(DATE(cfg_Year,12,1)>cfg_LastDataDate,"",IFERROR(INDEX(cd_Head_Grade_gpt_MTD,MATCH(MIN(EOMONTH(DATE(cfg_Year,12,1),0),cfg_LastDataDate),cd_Date,0)),"")) | P45: =IFERROR(INDEX(cd_Head_Grade_gpt_YTD,MATCH(MIN(cfg_YearEnd,cfg_LastDataDate),cd_Date,0)),"")
C46: Budget | D46: =IF(DATE(cfg_Year,1,1)>cfg_LastDataDate,IFERROR(INDEX(cd_Bud_Head_Grade_gpt_Month,MATCH(DATE(cfg_Year,1,1),cd_Date,0)),""),IFERROR(INDEX(cd_Bud_Head_Grade_gpt_MTD,MATCH(MIN(EOMONTH(DATE(cfg_Year,1,1),0),cfg_LastDataDate),cd_Date,0)),"")) | E46: =IF(DATE(cfg_Year,2,1)>cfg_LastDataDate,IFERROR(INDEX(cd_Bud_Head_Grade_gpt_Month,MATCH(DATE(cfg_Year,2,1),cd_Date,0)),""),IFERROR(INDEX(cd_Bud_Head_Grade_gpt_MTD,MATCH(MIN(EOMONTH(DATE(cfg_Year,2,1),0),cfg_LastDataDate),cd_Date,0)),"")) | F46: =IF(DATE(cfg_Year,3,1)>cfg_LastDataDate,IFERROR(INDEX(cd_Bud_Head_Grade_gpt_Month,MATCH(DATE(cfg_Year,3,1),cd_Date,0)),""),IFERROR(INDEX(cd_Bud_Head_Grade_gpt_MTD,MATCH(MIN(EOMONTH(DATE(cfg_Year,3,1),0),cfg_LastDataDate),cd_Date,0)),"")) | G46: =IF(DATE(cfg_Year,4,1)>cfg_LastDataDate,IFERROR(INDEX(cd_Bud_Head_Grade_gpt_Month,MATCH(DATE(cfg_Year,4,1),cd_Date,0)),""),IFERROR(INDEX(cd_Bud_Head_Grade_gpt_MTD,MATCH(MIN(EOMONTH(DATE(cfg_Year,4,1),0),cfg_LastDataDate),cd_Date,0)),"")) | H46: =IF(DATE(cfg_Year,5,1)>cfg_LastDataDate,IFERROR(INDEX(cd_Bud_Head_Grade_gpt_Month,MATCH(DATE(cfg_Year,5,1),cd_Date,0)),""),IFERROR(INDEX(cd_Bud_Head_Grade_gpt_MTD,MATCH(MIN(EOMONTH(DATE(cfg_Year,5,1),0),cfg_LastDataDate),cd_Date,0)),"")) | I46: =IF(DATE(cfg_Year,6,1)>cfg_LastDataDate,IFERROR(INDEX(cd_Bud_Head_Grade_gpt_Month,MATCH(DATE(cfg_Year,6,1),cd_Date,0)),""),IFERROR(INDEX(cd_Bud_Head_Grade_gpt_MTD,MATCH(MIN(EOMONTH(DATE(cfg_Year,6,1),0),cfg_LastDataDate),cd_Date,0)),"")) | J46: =IF(DATE(cfg_Year,7,1)>cfg_LastDataDate,IFERROR(INDEX(cd_Bud_Head_Grade_gpt_Month,MATCH(DATE(cfg_Year,7,1),cd_Date,0)),""),IFERROR(INDEX(cd_Bud_Head_Grade_gpt_MTD,MATCH(MIN(EOMONTH(DATE(cfg_Year,7,1),0),cfg_LastDataDate),cd_Date,0)),"")) | K46: =IF(DATE(cfg_Year,8,1)>cfg_LastDataDate,IFERROR(INDEX(cd_Bud_Head_Grade_gpt_Month,MATCH(DATE(cfg_Year,8,1),cd_Date,0)),""),IFERROR(INDEX(cd_Bud_Head_Grade_gpt_MTD,MATCH(MIN(EOMONTH(DATE(cfg_Year,8,1),0),cfg_LastDataDate),cd_Date,0)),"")) | L46: =IF(DATE(cfg_Year,9,1)>cfg_LastDataDate,IFERROR(INDEX(cd_Bud_Head_Grade_gpt_Month,MATCH(DATE(cfg_Year,9,1),cd_Date,0)),""),IFERROR(INDEX(cd_Bud_Head_Grade_gpt_MTD,MATCH(MIN(EOMONTH(DATE(cfg_Year,9,1),0),cfg_LastDataDate),cd_Date,0)),"")) | M46: =IF(DATE(cfg_Year,10,1)>cfg_LastDataDate,IFERROR(INDEX(cd_Bud_Head_Grade_gpt_Month,MATCH(DATE(cfg_Year,10,1),cd_Date,0)),""),IFERROR(INDEX(cd_Bud_Head_Grade_gpt_MTD,MATCH(MIN(EOMONTH(DATE(cfg_Year,10,1),0),cfg_LastDataDate),cd_Date,0)),"")) | N46: =IF(DATE(cfg_Year,11,1)>cfg_LastDataDate,IFERROR(INDEX(cd_Bud_Head_Grade_gpt_Month,MATCH(DATE(cfg_Year,11,1),cd_Date,0)),""),IFERROR(INDEX(cd_Bud_Head_Grade_gpt_MTD,MATCH(MIN(EOMONTH(DATE(cfg_Year,11,1),0),cfg_LastDataDate),cd_Date,0)),"")) | O46: =IF(DATE(cfg_Year,12,1)>cfg_LastDataDate,IFERROR(INDEX(cd_Bud_Head_Grade_gpt_Month,MATCH(DATE(cfg_Year,12,1),cd_Date,0)),""),IFERROR(INDEX(cd_Bud_Head_Grade_gpt_MTD,MATCH(MIN(EOMONTH(DATE(cfg_Year,12,1),0),cfg_LastDataDate),cd_Date,0)),"")) | P46: =IFERROR(INDEX(cd_Bud_Head_Grade_gpt_YTD,MATCH(IF(N(cfg_LastDataDate)>0,MIN(cfg_YearEnd,cfg_LastDataDate),cfg_YearEnd),cd_Date,0)),"")
C47: Variance | D47: =IF(AND(ISNUMBER(D45),ISNUMBER(D46),D46<>0),D45/D46-1,"") | E47: =IF(AND(ISNUMBER(E45),ISNUMBER(E46),E46<>0),E45/E46-1,"") | F47: =IF(AND(ISNUMBER(F45),ISNUMBER(F46),F46<>0),F45/F46-1,"") | G47: =IF(AND(ISNUMBER(G45),ISNUMBER(G46),G46<>0),G45/G46-1,"") | H47: =IF(AND(ISNUMBER(H45),ISNUMBER(H46),H46<>0),H45/H46-1,"") | I47: =IF(AND(ISNUMBER(I45),ISNUMBER(I46),I46<>0),I45/I46-1,"") | J47: =IF(AND(ISNUMBER(J45),ISNUMBER(J46),J46<>0),J45/J46-1,"") | K47: =IF(AND(ISNUMBER(K45),ISNUMBER(K46),K46<>0),K45/K46-1,"") | ... P47: =IF(AND(ISNUMBER(P45),ISNUMBER(P46),P46<>0),P45/P46-1,"")
B49: Recovery | C49: Actual | D49: =IF(DATE(cfg_Year,1,1)>cfg_LastDataDate,"",IFERROR(INDEX(cd_Recovery_pct_MTD,MATCH(MIN(EOMONTH(DATE(cfg_Year,1,1),0),cfg_LastDataDate),cd_Date,0)),"")) | E49: =IF(DATE(cfg_Year,2,1)>cfg_LastDataDate,"",IFERROR(INDEX(cd_Recovery_pct_MTD,MATCH(MIN(EOMONTH(DATE(cfg_Year,2,1),0),cfg_LastDataDate),cd_Date,0)),"")) | F49: =IF(DATE(cfg_Year,3,1)>cfg_LastDataDate,"",IFERROR(INDEX(cd_Recovery_pct_MTD,MATCH(MIN(EOMONTH(DATE(cfg_Year,3,1),0),cfg_LastDataDate),cd_Date,0)),"")) | G49: =IF(DATE(cfg_Year,4,1)>cfg_LastDataDate,"",IFERROR(INDEX(cd_Recovery_pct_MTD,MATCH(MIN(EOMONTH(DATE(cfg_Year,4,1),0),cfg_LastDataDate),cd_Date,0)),"")) | H49: =IF(DATE(cfg_Year,5,1)>cfg_LastDataDate,"",IFERROR(INDEX(cd_Recovery_pct_MTD,MATCH(MIN(EOMONTH(DATE(cfg_Year,5,1),0),cfg_LastDataDate),cd_Date,0)),"")) | I49: =IF(DATE(cfg_Year,6,1)>cfg_LastDataDate,"",IFERROR(INDEX(cd_Recovery_pct_MTD,MATCH(MIN(EOMONTH(DATE(cfg_Year,6,1),0),cfg_LastDataDate),cd_Date,0)),"")) | J49: =IF(DATE(cfg_Year,7,1)>cfg_LastDataDate,"",IFERROR(INDEX(cd_Recovery_pct_MTD,MATCH(MIN(EOMONTH(DATE(cfg_Year,7,1),0),cfg_LastDataDate),cd_Date,0)),"")) | K49: =IF(DATE(cfg_Year,8,1)>cfg_LastDataDate,"",IFERROR(INDEX(cd_Recovery_pct_MTD,MATCH(MIN(EOMONTH(DATE(cfg_Year,8,1),0),cfg_LastDataDate),cd_Date,0)),"")) | L49: =IF(DATE(cfg_Year,9,1)>cfg_LastDataDate,"",IFERROR(INDEX(cd_Recovery_pct_MTD,MATCH(MIN(EOMONTH(DATE(cfg_Year,9,1),0),cfg_LastDataDate),cd_Date,0)),"")) | M49: =IF(DATE(cfg_Year,10,1)>cfg_LastDataDate,"",IFERROR(INDEX(cd_Recovery_pct_MTD,MATCH(MIN(EOMONTH(DATE(cfg_Year,10,1),0),cfg_LastDataDate),cd_Date,0)),"")) | N49: =IF(DATE(cfg_Year,11,1)>cfg_LastDataDate,"",IFERROR(INDEX(cd_Recovery_pct_MTD,MATCH(MIN(EOMONTH(DATE(cfg_Year,11,1),0),cfg_LastDataDate),cd_Date,0)),"")) | O49: =IF(DATE(cfg_Year,12,1)>cfg_LastDataDate,"",IFERROR(INDEX(cd_Recovery_pct_MTD,MATCH(MIN(EOMONTH(DATE(cfg_Year,12,1),0),cfg_LastDataDate),cd_Date,0)),"")) | P49: =IFERROR(INDEX(cd_Recovery_pct_YTD,MATCH(MIN(cfg_YearEnd,cfg_LastDataDate),cd_Date,0)),"")
C50: Budget | D50: =IF(DATE(cfg_Year,1,1)>cfg_LastDataDate,IFERROR(INDEX(cd_Bud_Recovery_pct_Month,MATCH(DATE(cfg_Year,1,1),cd_Date,0)),""),IFERROR(INDEX(cd_Bud_Recovery_pct_MTD,MATCH(MIN(EOMONTH(DATE(cfg_Year,1,1),0),cfg_LastDataDate),cd_Date,0)),"")) | E50: =IF(DATE(cfg_Year,2,1)>cfg_LastDataDate,IFERROR(INDEX(cd_Bud_Recovery_pct_Month,MATCH(DATE(cfg_Year,2,1),cd_Date,0)),""),IFERROR(INDEX(cd_Bud_Recovery_pct_MTD,MATCH(MIN(EOMONTH(DATE(cfg_Year,2,1),0),cfg_LastDataDate),cd_Date,0)),"")) | F50: =IF(DATE(cfg_Year,3,1)>cfg_LastDataDate,IFERROR(INDEX(cd_Bud_Recovery_pct_Month,MATCH(DATE(cfg_Year,3,1),cd_Date,0)),""),IFERROR(INDEX(cd_Bud_Recovery_pct_MTD,MATCH(MIN(EOMONTH(DATE(cfg_Year,3,1),0),cfg_LastDataDate),cd_Date,0)),"")) | G50: =IF(DATE(cfg_Year,4,1)>cfg_LastDataDate,IFERROR(INDEX(cd_Bud_Recovery_pct_Month,MATCH(DATE(cfg_Year,4,1),cd_Date,0)),""),IFERROR(INDEX(cd_Bud_Recovery_pct_MTD,MATCH(MIN(EOMONTH(DATE(cfg_Year,4,1),0),cfg_LastDataDate),cd_Date,0)),"")) | H50: =IF(DATE(cfg_Year,5,1)>cfg_LastDataDate,IFERROR(INDEX(cd_Bud_Recovery_pct_Month,MATCH(DATE(cfg_Year,5,1),cd_Date,0)),""),IFERROR(INDEX(cd_Bud_Recovery_pct_MTD,MATCH(MIN(EOMONTH(DATE(cfg_Year,5,1),0),cfg_LastDataDate),cd_Date,0)),"")) | I50: =IF(DATE(cfg_Year,6,1)>cfg_LastDataDate,IFERROR(INDEX(cd_Bud_Recovery_pct_Month,MATCH(DATE(cfg_Year,6,1),cd_Date,0)),""),IFERROR(INDEX(cd_Bud_Recovery_pct_MTD,MATCH(MIN(EOMONTH(DATE(cfg_Year,6,1),0),cfg_LastDataDate),cd_Date,0)),"")) | J50: =IF(DATE(cfg_Year,7,1)>cfg_LastDataDate,IFERROR(INDEX(cd_Bud_Recovery_pct_Month,MATCH(DATE(cfg_Year,7,1),cd_Date,0)),""),IFERROR(INDEX(cd_Bud_Recovery_pct_MTD,MATCH(MIN(EOMONTH(DATE(cfg_Year,7,1),0),cfg_LastDataDate),cd_Date,0)),"")) | K50: =IF(DATE(cfg_Year,8,1)>cfg_LastDataDate,IFERROR(INDEX(cd_Bud_Recovery_pct_Month,MATCH(DATE(cfg_Year,8,1),cd_Date,0)),""),IFERROR(INDEX(cd_Bud_Recovery_pct_MTD,MATCH(MIN(EOMONTH(DATE(cfg_Year,8,1),0),cfg_LastDataDate),cd_Date,0)),"")) | L50: =IF(DATE(cfg_Year,9,1)>cfg_LastDataDate,IFERROR(INDEX(cd_Bud_Recovery_pct_Month,MATCH(DATE(cfg_Year,9,1),cd_Date,0)),""),IFERROR(INDEX(cd_Bud_Recovery_pct_MTD,MATCH(MIN(EOMONTH(DATE(cfg_Year,9,1),0),cfg_LastDataDate),cd_Date,0)),"")) | M50: =IF(DATE(cfg_Year,10,1)>cfg_LastDataDate,IFERROR(INDEX(cd_Bud_Recovery_pct_Month,MATCH(DATE(cfg_Year,10,1),cd_Date,0)),""),IFERROR(INDEX(cd_Bud_Recovery_pct_MTD,MATCH(MIN(EOMONTH(DATE(cfg_Year,10,1),0),cfg_LastDataDate),cd_Date,0)),"")) | N50: =IF(DATE(cfg_Year,11,1)>cfg_LastDataDate,IFERROR(INDEX(cd_Bud_Recovery_pct_Month,MATCH(DATE(cfg_Year,11,1),cd_Date,0)),""),IFERROR(INDEX(cd_Bud_Recovery_pct_MTD,MATCH(MIN(EOMONTH(DATE(cfg_Year,11,1),0),cfg_LastDataDate),cd_Date,0)),"")) | O50: =IF(DATE(cfg_Year,12,1)>cfg_LastDataDate,IFERROR(INDEX(cd_Bud_Recovery_pct_Month,MATCH(DATE(cfg_Year,12,1),cd_Date,0)),""),IFERROR(INDEX(cd_Bud_Recovery_pct_MTD,MATCH(MIN(EOMONTH(DATE(cfg_Year,12,1),0),cfg_LastDataDate),cd_Date,0)),"")) | P50: =IFERROR(INDEX(cd_Bud_Recovery_pct_YTD,MATCH(IF(N(cfg_LastDataDate)>0,MIN(cfg_YearEnd,cfg_LastDataDate),cfg_YearEnd),cd_Date,0)),"")
C51: Variance | D51: =IF(AND(ISNUMBER(D49),ISNUMBER(D50),D50<>0),D49/D50-1,"") | E51: =IF(AND(ISNUMBER(E49),ISNUMBER(E50),E50<>0),E49/E50-1,"") | F51: =IF(AND(ISNUMBER(F49),ISNUMBER(F50),F50<>0),F49/F50-1,"") | G51: =IF(AND(ISNUMBER(G49),ISNUMBER(G50),G50<>0),G49/G50-1,"") | H51: =IF(AND(ISNUMBER(H49),ISNUMBER(H50),H50<>0),H49/H50-1,"") | I51: =IF(AND(ISNUMBER(I49),ISNUMBER(I50),I50<>0),I49/I50-1,"") | J51: =IF(AND(ISNUMBER(J49),ISNUMBER(J50),J50<>0),J49/J50-1,"") | K51: =IF(AND(ISNUMBER(K49),ISNUMBER(K50),K50<>0),K49/K50-1,"") | ... P51: =IF(AND(ISNUMBER(P49),ISNUMBER(P50),P50<>0),P49/P50-1,"")
B53: Gold recovered | C53: Actual | D53: =IF(DATE(cfg_Year,1,1)>cfg_LastDataDate,"",IFERROR(INDEX(cd_Recovered_oz_MTD,MATCH(MIN(EOMONTH(DATE(cfg_Year,1,1),0),cfg_LastDataDate),cd_Date,0)),"")) | E53: =IF(DATE(cfg_Year,2,1)>cfg_LastDataDate,"",IFERROR(INDEX(cd_Recovered_oz_MTD,MATCH(MIN(EOMONTH(DATE(cfg_Year,2,1),0),cfg_LastDataDate),cd_Date,0)),"")) | F53: =IF(DATE(cfg_Year,3,1)>cfg_LastDataDate,"",IFERROR(INDEX(cd_Recovered_oz_MTD,MATCH(MIN(EOMONTH(DATE(cfg_Year,3,1),0),cfg_LastDataDate),cd_Date,0)),"")) | G53: =IF(DATE(cfg_Year,4,1)>cfg_LastDataDate,"",IFERROR(INDEX(cd_Recovered_oz_MTD,MATCH(MIN(EOMONTH(DATE(cfg_Year,4,1),0),cfg_LastDataDate),cd_Date,0)),"")) | H53: =IF(DATE(cfg_Year,5,1)>cfg_LastDataDate,"",IFERROR(INDEX(cd_Recovered_oz_MTD,MATCH(MIN(EOMONTH(DATE(cfg_Year,5,1),0),cfg_LastDataDate),cd_Date,0)),"")) | I53: =IF(DATE(cfg_Year,6,1)>cfg_LastDataDate,"",IFERROR(INDEX(cd_Recovered_oz_MTD,MATCH(MIN(EOMONTH(DATE(cfg_Year,6,1),0),cfg_LastDataDate),cd_Date,0)),"")) | J53: =IF(DATE(cfg_Year,7,1)>cfg_LastDataDate,"",IFERROR(INDEX(cd_Recovered_oz_MTD,MATCH(MIN(EOMONTH(DATE(cfg_Year,7,1),0),cfg_LastDataDate),cd_Date,0)),"")) | K53: =IF(DATE(cfg_Year,8,1)>cfg_LastDataDate,"",IFERROR(INDEX(cd_Recovered_oz_MTD,MATCH(MIN(EOMONTH(DATE(cfg_Year,8,1),0),cfg_LastDataDate),cd_Date,0)),"")) | L53: =IF(DATE(cfg_Year,9,1)>cfg_LastDataDate,"",IFERROR(INDEX(cd_Recovered_oz_MTD,MATCH(MIN(EOMONTH(DATE(cfg_Year,9,1),0),cfg_LastDataDate),cd_Date,0)),"")) | M53: =IF(DATE(cfg_Year,10,1)>cfg_LastDataDate,"",IFERROR(INDEX(cd_Recovered_oz_MTD,MATCH(MIN(EOMONTH(DATE(cfg_Year,10,1),0),cfg_LastDataDate),cd_Date,0)),"")) | N53: =IF(DATE(cfg_Year,11,1)>cfg_LastDataDate,"",IFERROR(INDEX(cd_Recovered_oz_MTD,MATCH(MIN(EOMONTH(DATE(cfg_Year,11,1),0),cfg_LastDataDate),cd_Date,0)),"")) | O53: =IF(DATE(cfg_Year,12,1)>cfg_LastDataDate,"",IFERROR(INDEX(cd_Recovered_oz_MTD,MATCH(MIN(EOMONTH(DATE(cfg_Year,12,1),0),cfg_LastDataDate),cd_Date,0)),"")) | P53: =IFERROR(INDEX(cd_Recovered_oz_YTD,MATCH(MIN(cfg_YearEnd,cfg_LastDataDate),cd_Date,0)),"")
C54: Budget | D54: =IF(DATE(cfg_Year,1,1)>cfg_LastDataDate,IFERROR(INDEX(cd_Bud_Recovered_oz_Month,MATCH(DATE(cfg_Year,1,1),cd_Date,0)),""),IFERROR(INDEX(cd_Bud_Recovered_oz_MTD,MATCH(MIN(EOMONTH(DATE(cfg_Year,1,1),0),cfg_LastDataDate),cd_Date,0)),"")) | E54: =IF(DATE(cfg_Year,2,1)>cfg_LastDataDate,IFERROR(INDEX(cd_Bud_Recovered_oz_Month,MATCH(DATE(cfg_Year,2,1),cd_Date,0)),""),IFERROR(INDEX(cd_Bud_Recovered_oz_MTD,MATCH(MIN(EOMONTH(DATE(cfg_Year,2,1),0),cfg_LastDataDate),cd_Date,0)),"")) | F54: =IF(DATE(cfg_Year,3,1)>cfg_LastDataDate,IFERROR(INDEX(cd_Bud_Recovered_oz_Month,MATCH(DATE(cfg_Year,3,1),cd_Date,0)),""),IFERROR(INDEX(cd_Bud_Recovered_oz_MTD,MATCH(MIN(EOMONTH(DATE(cfg_Year,3,1),0),cfg_LastDataDate),cd_Date,0)),"")) | G54: =IF(DATE(cfg_Year,4,1)>cfg_LastDataDate,IFERROR(INDEX(cd_Bud_Recovered_oz_Month,MATCH(DATE(cfg_Year,4,1),cd_Date,0)),""),IFERROR(INDEX(cd_Bud_Recovered_oz_MTD,MATCH(MIN(EOMONTH(DATE(cfg_Year,4,1),0),cfg_LastDataDate),cd_Date,0)),"")) | H54: =IF(DATE(cfg_Year,5,1)>cfg_LastDataDate,IFERROR(INDEX(cd_Bud_Recovered_oz_Month,MATCH(DATE(cfg_Year,5,1),cd_Date,0)),""),IFERROR(INDEX(cd_Bud_Recovered_oz_MTD,MATCH(MIN(EOMONTH(DATE(cfg_Year,5,1),0),cfg_LastDataDate),cd_Date,0)),"")) | I54: =IF(DATE(cfg_Year,6,1)>cfg_LastDataDate,IFERROR(INDEX(cd_Bud_Recovered_oz_Month,MATCH(DATE(cfg_Year,6,1),cd_Date,0)),""),IFERROR(INDEX(cd_Bud_Recovered_oz_MTD,MATCH(MIN(EOMONTH(DATE(cfg_Year,6,1),0),cfg_LastDataDate),cd_Date,0)),"")) | J54: =IF(DATE(cfg_Year,7,1)>cfg_LastDataDate,IFERROR(INDEX(cd_Bud_Recovered_oz_Month,MATCH(DATE(cfg_Year,7,1),cd_Date,0)),""),IFERROR(INDEX(cd_Bud_Recovered_oz_MTD,MATCH(MIN(EOMONTH(DATE(cfg_Year,7,1),0),cfg_LastDataDate),cd_Date,0)),"")) | K54: =IF(DATE(cfg_Year,8,1)>cfg_LastDataDate,IFERROR(INDEX(cd_Bud_Recovered_oz_Month,MATCH(DATE(cfg_Year,8,1),cd_Date,0)),""),IFERROR(INDEX(cd_Bud_Recovered_oz_MTD,MATCH(MIN(EOMONTH(DATE(cfg_Year,8,1),0),cfg_LastDataDate),cd_Date,0)),"")) | L54: =IF(DATE(cfg_Year,9,1)>cfg_LastDataDate,IFERROR(INDEX(cd_Bud_Recovered_oz_Month,MATCH(DATE(cfg_Year,9,1),cd_Date,0)),""),IFERROR(INDEX(cd_Bud_Recovered_oz_MTD,MATCH(MIN(EOMONTH(DATE(cfg_Year,9,1),0),cfg_LastDataDate),cd_Date,0)),"")) | M54: =IF(DATE(cfg_Year,10,1)>cfg_LastDataDate,IFERROR(INDEX(cd_Bud_Recovered_oz_Month,MATCH(DATE(cfg_Year,10,1),cd_Date,0)),""),IFERROR(INDEX(cd_Bud_Recovered_oz_MTD,MATCH(MIN(EOMONTH(DATE(cfg_Year,10,1),0),cfg_LastDataDate),cd_Date,0)),"")) | N54: =IF(DATE(cfg_Year,11,1)>cfg_LastDataDate,IFERROR(INDEX(cd_Bud_Recovered_oz_Month,MATCH(DATE(cfg_Year,11,1),cd_Date,0)),""),IFERROR(INDEX(cd_Bud_Recovered_oz_MTD,MATCH(MIN(EOMONTH(DATE(cfg_Year,11,1),0),cfg_LastDataDate),cd_Date,0)),"")) | O54: =IF(DATE(cfg_Year,12,1)>cfg_LastDataDate,IFERROR(INDEX(cd_Bud_Recovered_oz_Month,MATCH(DATE(cfg_Year,12,1),cd_Date,0)),""),IFERROR(INDEX(cd_Bud_Recovered_oz_MTD,MATCH(MIN(EOMONTH(DATE(cfg_Year,12,1),0),cfg_LastDataDate),cd_Date,0)),"")) | P54: =IFERROR(INDEX(cd_Bud_Recovered_oz_YTD,MATCH(IF(N(cfg_LastDataDate)>0,MIN(cfg_YearEnd,cfg_LastDataDate),cfg_YearEnd),cd_Date,0)),"")
C55: Variance | D55: =IF(AND(ISNUMBER(D53),ISNUMBER(D54),D54<>0),D53/D54-1,"") | E55: =IF(AND(ISNUMBER(E53),ISNUMBER(E54),E54<>0),E53/E54-1,"") | F55: =IF(AND(ISNUMBER(F53),ISNUMBER(F54),F54<>0),F53/F54-1,"") | G55: =IF(AND(ISNUMBER(G53),ISNUMBER(G54),G54<>0),G53/G54-1,"") | H55: =IF(AND(ISNUMBER(H53),ISNUMBER(H54),H54<>0),H53/H54-1,"") | I55: =IF(AND(ISNUMBER(I53),ISNUMBER(I54),I54<>0),I53/I54-1,"") | J55: =IF(AND(ISNUMBER(J53),ISNUMBER(J54),J54<>0),J53/J54-1,"") | K55: =IF(AND(ISNUMBER(K53),ISNUMBER(K54),K54<>0),K53/K54-1,"") | ... P55: =IF(AND(ISNUMBER(P53),ISNUMBER(P54),P54<>0),P53/P54-1,"")
B57: Gold poured | C57: Actual | D57: =IF(DATE(cfg_Year,1,1)>cfg_LastDataDate,"",IFERROR(INDEX(cd_Gold_Poured_oz_MTD,MATCH(MIN(EOMONTH(DATE(cfg_Year,1,1),0),cfg_LastDataDate),cd_Date,0)),"")) | E57: =IF(DATE(cfg_Year,2,1)>cfg_LastDataDate,"",IFERROR(INDEX(cd_Gold_Poured_oz_MTD,MATCH(MIN(EOMONTH(DATE(cfg_Year,2,1),0),cfg_LastDataDate),cd_Date,0)),"")) | F57: =IF(DATE(cfg_Year,3,1)>cfg_LastDataDate,"",IFERROR(INDEX(cd_Gold_Poured_oz_MTD,MATCH(MIN(EOMONTH(DATE(cfg_Year,3,1),0),cfg_LastDataDate),cd_Date,0)),"")) | G57: =IF(DATE(cfg_Year,4,1)>cfg_LastDataDate,"",IFERROR(INDEX(cd_Gold_Poured_oz_MTD,MATCH(MIN(EOMONTH(DATE(cfg_Year,4,1),0),cfg_LastDataDate),cd_Date,0)),"")) | H57: =IF(DATE(cfg_Year,5,1)>cfg_LastDataDate,"",IFERROR(INDEX(cd_Gold_Poured_oz_MTD,MATCH(MIN(EOMONTH(DATE(cfg_Year,5,1),0),cfg_LastDataDate),cd_Date,0)),"")) | I57: =IF(DATE(cfg_Year,6,1)>cfg_LastDataDate,"",IFERROR(INDEX(cd_Gold_Poured_oz_MTD,MATCH(MIN(EOMONTH(DATE(cfg_Year,6,1),0),cfg_LastDataDate),cd_Date,0)),"")) | J57: =IF(DATE(cfg_Year,7,1)>cfg_LastDataDate,"",IFERROR(INDEX(cd_Gold_Poured_oz_MTD,MATCH(MIN(EOMONTH(DATE(cfg_Year,7,1),0),cfg_LastDataDate),cd_Date,0)),"")) | K57: =IF(DATE(cfg_Year,8,1)>cfg_LastDataDate,"",IFERROR(INDEX(cd_Gold_Poured_oz_MTD,MATCH(MIN(EOMONTH(DATE(cfg_Year,8,1),0),cfg_LastDataDate),cd_Date,0)),"")) | L57: =IF(DATE(cfg_Year,9,1)>cfg_LastDataDate,"",IFERROR(INDEX(cd_Gold_Poured_oz_MTD,MATCH(MIN(EOMONTH(DATE(cfg_Year,9,1),0),cfg_LastDataDate),cd_Date,0)),"")) | M57: =IF(DATE(cfg_Year,10,1)>cfg_LastDataDate,"",IFERROR(INDEX(cd_Gold_Poured_oz_MTD,MATCH(MIN(EOMONTH(DATE(cfg_Year,10,1),0),cfg_LastDataDate),cd_Date,0)),"")) | N57: =IF(DATE(cfg_Year,11,1)>cfg_LastDataDate,"",IFERROR(INDEX(cd_Gold_Poured_oz_MTD,MATCH(MIN(EOMONTH(DATE(cfg_Year,11,1),0),cfg_LastDataDate),cd_Date,0)),"")) | O57: =IF(DATE(cfg_Year,12,1)>cfg_LastDataDate,"",IFERROR(INDEX(cd_Gold_Poured_oz_MTD,MATCH(MIN(EOMONTH(DATE(cfg_Year,12,1),0),cfg_LastDataDate),cd_Date,0)),"")) | P57: =IFERROR(INDEX(cd_Gold_Poured_oz_YTD,MATCH(MIN(cfg_YearEnd,cfg_LastDataDate),cd_Date,0)),"")
C58: Budget | D58: =IF(DATE(cfg_Year,1,1)>cfg_LastDataDate,IFERROR(INDEX(cd_Bud_Gold_Poured_oz_Month,MATCH(DATE(cfg_Year,1,1),cd_Date,0)),""),IFERROR(INDEX(cd_Bud_Gold_Poured_oz_MTD,MATCH(MIN(EOMONTH(DATE(cfg_Year,1,1),0),cfg_LastDataDate),cd_Date,0)),"")) | E58: =IF(DATE(cfg_Year,2,1)>cfg_LastDataDate,IFERROR(INDEX(cd_Bud_Gold_Poured_oz_Month,MATCH(DATE(cfg_Year,2,1),cd_Date,0)),""),IFERROR(INDEX(cd_Bud_Gold_Poured_oz_MTD,MATCH(MIN(EOMONTH(DATE(cfg_Year,2,1),0),cfg_LastDataDate),cd_Date,0)),"")) | F58: =IF(DATE(cfg_Year,3,1)>cfg_LastDataDate,IFERROR(INDEX(cd_Bud_Gold_Poured_oz_Month,MATCH(DATE(cfg_Year,3,1),cd_Date,0)),""),IFERROR(INDEX(cd_Bud_Gold_Poured_oz_MTD,MATCH(MIN(EOMONTH(DATE(cfg_Year,3,1),0),cfg_LastDataDate),cd_Date,0)),"")) | G58: =IF(DATE(cfg_Year,4,1)>cfg_LastDataDate,IFERROR(INDEX(cd_Bud_Gold_Poured_oz_Month,MATCH(DATE(cfg_Year,4,1),cd_Date,0)),""),IFERROR(INDEX(cd_Bud_Gold_Poured_oz_MTD,MATCH(MIN(EOMONTH(DATE(cfg_Year,4,1),0),cfg_LastDataDate),cd_Date,0)),"")) | H58: =IF(DATE(cfg_Year,5,1)>cfg_LastDataDate,IFERROR(INDEX(cd_Bud_Gold_Poured_oz_Month,MATCH(DATE(cfg_Year,5,1),cd_Date,0)),""),IFERROR(INDEX(cd_Bud_Gold_Poured_oz_MTD,MATCH(MIN(EOMONTH(DATE(cfg_Year,5,1),0),cfg_LastDataDate),cd_Date,0)),"")) | I58: =IF(DATE(cfg_Year,6,1)>cfg_LastDataDate,IFERROR(INDEX(cd_Bud_Gold_Poured_oz_Month,MATCH(DATE(cfg_Year,6,1),cd_Date,0)),""),IFERROR(INDEX(cd_Bud_Gold_Poured_oz_MTD,MATCH(MIN(EOMONTH(DATE(cfg_Year,6,1),0),cfg_LastDataDate),cd_Date,0)),"")) | J58: =IF(DATE(cfg_Year,7,1)>cfg_LastDataDate,IFERROR(INDEX(cd_Bud_Gold_Poured_oz_Month,MATCH(DATE(cfg_Year,7,1),cd_Date,0)),""),IFERROR(INDEX(cd_Bud_Gold_Poured_oz_MTD,MATCH(MIN(EOMONTH(DATE(cfg_Year,7,1),0),cfg_LastDataDate),cd_Date,0)),"")) | K58: =IF(DATE(cfg_Year,8,1)>cfg_LastDataDate,IFERROR(INDEX(cd_Bud_Gold_Poured_oz_Month,MATCH(DATE(cfg_Year,8,1),cd_Date,0)),""),IFERROR(INDEX(cd_Bud_Gold_Poured_oz_MTD,MATCH(MIN(EOMONTH(DATE(cfg_Year,8,1),0),cfg_LastDataDate),cd_Date,0)),"")) | L58: =IF(DATE(cfg_Year,9,1)>cfg_LastDataDate,IFERROR(INDEX(cd_Bud_Gold_Poured_oz_Month,MATCH(DATE(cfg_Year,9,1),cd_Date,0)),""),IFERROR(INDEX(cd_Bud_Gold_Poured_oz_MTD,MATCH(MIN(EOMONTH(DATE(cfg_Year,9,1),0),cfg_LastDataDate),cd_Date,0)),"")) | M58: =IF(DATE(cfg_Year,10,1)>cfg_LastDataDate,IFERROR(INDEX(cd_Bud_Gold_Poured_oz_Month,MATCH(DATE(cfg_Year,10,1),cd_Date,0)),""),IFERROR(INDEX(cd_Bud_Gold_Poured_oz_MTD,MATCH(MIN(EOMONTH(DATE(cfg_Year,10,1),0),cfg_LastDataDate),cd_Date,0)),"")) | N58: =IF(DATE(cfg_Year,11,1)>cfg_LastDataDate,IFERROR(INDEX(cd_Bud_Gold_Poured_oz_Month,MATCH(DATE(cfg_Year,11,1),cd_Date,0)),""),IFERROR(INDEX(cd_Bud_Gold_Poured_oz_MTD,MATCH(MIN(EOMONTH(DATE(cfg_Year,11,1),0),cfg_LastDataDate),cd_Date,0)),"")) | O58: =IF(DATE(cfg_Year,12,1)>cfg_LastDataDate,IFERROR(INDEX(cd_Bud_Gold_Poured_oz_Month,MATCH(DATE(cfg_Year,12,1),cd_Date,0)),""),IFERROR(INDEX(cd_Bud_Gold_Poured_oz_MTD,MATCH(MIN(EOMONTH(DATE(cfg_Year,12,1),0),cfg_LastDataDate),cd_Date,0)),"")) | P58: =IFERROR(INDEX(cd_Bud_Gold_Poured_oz_YTD,MATCH(IF(N(cfg_LastDataDate)>0,MIN(cfg_YearEnd,cfg_LastDataDate),cfg_YearEnd),cd_Date,0)),"")
C59: Variance | D59: =IF(AND(ISNUMBER(D57),ISNUMBER(D58),D58<>0),D57/D58-1,"") | E59: =IF(AND(ISNUMBER(E57),ISNUMBER(E58),E58<>0),E57/E58-1,"") | F59: =IF(AND(ISNUMBER(F57),ISNUMBER(F58),F58<>0),F57/F58-1,"") | G59: =IF(AND(ISNUMBER(G57),ISNUMBER(G58),G58<>0),G57/G58-1,"") | H59: =IF(AND(ISNUMBER(H57),ISNUMBER(H58),H58<>0),H57/H58-1,"") | I59: =IF(AND(ISNUMBER(I57),ISNUMBER(I58),I58<>0),I57/I58-1,"") | J59: =IF(AND(ISNUMBER(J57),ISNUMBER(J58),J58<>0),J57/J58-1,"") | K59: =IF(AND(ISNUMBER(K57),ISNUMBER(K58),K58<>0),K57/K58-1,"") | ... P59: =IF(AND(ISNUMBER(P57),ISNUMBER(P58),P58<>0),P57/P58-1,"")
B61: Gold sold | C61: Actual | D61: =IF(DATE(cfg_Year,1,1)>cfg_LastDataDate,"",IFERROR(INDEX(cd_Gold_Sold_oz_MTD,MATCH(MIN(EOMONTH(DATE(cfg_Year,1,1),0),cfg_LastDataDate),cd_Date,0)),"")) | E61: =IF(DATE(cfg_Year,2,1)>cfg_LastDataDate,"",IFERROR(INDEX(cd_Gold_Sold_oz_MTD,MATCH(MIN(EOMONTH(DATE(cfg_Year,2,1),0),cfg_LastDataDate),cd_Date,0)),"")) | F61: =IF(DATE(cfg_Year,3,1)>cfg_LastDataDate,"",IFERROR(INDEX(cd_Gold_Sold_oz_MTD,MATCH(MIN(EOMONTH(DATE(cfg_Year,3,1),0),cfg_LastDataDate),cd_Date,0)),"")) | G61: =IF(DATE(cfg_Year,4,1)>cfg_LastDataDate,"",IFERROR(INDEX(cd_Gold_Sold_oz_MTD,MATCH(MIN(EOMONTH(DATE(cfg_Year,4,1),0),cfg_LastDataDate),cd_Date,0)),"")) | H61: =IF(DATE(cfg_Year,5,1)>cfg_LastDataDate,"",IFERROR(INDEX(cd_Gold_Sold_oz_MTD,MATCH(MIN(EOMONTH(DATE(cfg_Year,5,1),0),cfg_LastDataDate),cd_Date,0)),"")) | I61: =IF(DATE(cfg_Year,6,1)>cfg_LastDataDate,"",IFERROR(INDEX(cd_Gold_Sold_oz_MTD,MATCH(MIN(EOMONTH(DATE(cfg_Year,6,1),0),cfg_LastDataDate),cd_Date,0)),"")) | J61: =IF(DATE(cfg_Year,7,1)>cfg_LastDataDate,"",IFERROR(INDEX(cd_Gold_Sold_oz_MTD,MATCH(MIN(EOMONTH(DATE(cfg_Year,7,1),0),cfg_LastDataDate),cd_Date,0)),"")) | K61: =IF(DATE(cfg_Year,8,1)>cfg_LastDataDate,"",IFERROR(INDEX(cd_Gold_Sold_oz_MTD,MATCH(MIN(EOMONTH(DATE(cfg_Year,8,1),0),cfg_LastDataDate),cd_Date,0)),"")) | L61: =IF(DATE(cfg_Year,9,1)>cfg_LastDataDate,"",IFERROR(INDEX(cd_Gold_Sold_oz_MTD,MATCH(MIN(EOMONTH(DATE(cfg_Year,9,1),0),cfg_LastDataDate),cd_Date,0)),"")) | M61: =IF(DATE(cfg_Year,10,1)>cfg_LastDataDate,"",IFERROR(INDEX(cd_Gold_Sold_oz_MTD,MATCH(MIN(EOMONTH(DATE(cfg_Year,10,1),0),cfg_LastDataDate),cd_Date,0)),"")) | N61: =IF(DATE(cfg_Year,11,1)>cfg_LastDataDate,"",IFERROR(INDEX(cd_Gold_Sold_oz_MTD,MATCH(MIN(EOMONTH(DATE(cfg_Year,11,1),0),cfg_LastDataDate),cd_Date,0)),"")) | O61: =IF(DATE(cfg_Year,12,1)>cfg_LastDataDate,"",IFERROR(INDEX(cd_Gold_Sold_oz_MTD,MATCH(MIN(EOMONTH(DATE(cfg_Year,12,1),0),cfg_LastDataDate),cd_Date,0)),"")) | P61: =IFERROR(INDEX(cd_Gold_Sold_oz_YTD,MATCH(MIN(cfg_YearEnd,cfg_LastDataDate),cd_Date,0)),"")
B62: Mill throughput | C62: Actual | D62: =IF(DATE(cfg_Year,1,1)>cfg_LastDataDate,"",IFERROR(INDEX(cd_Throughput_tph_MTD,MATCH(MIN(EOMONTH(DATE(cfg_Year,1,1),0),cfg_LastDataDate),cd_Date,0)),"")) | E62: =IF(DATE(cfg_Year,2,1)>cfg_LastDataDate,"",IFERROR(INDEX(cd_Throughput_tph_MTD,MATCH(MIN(EOMONTH(DATE(cfg_Year,2,1),0),cfg_LastDataDate),cd_Date,0)),"")) | F62: =IF(DATE(cfg_Year,3,1)>cfg_LastDataDate,"",IFERROR(INDEX(cd_Throughput_tph_MTD,MATCH(MIN(EOMONTH(DATE(cfg_Year,3,1),0),cfg_LastDataDate),cd_Date,0)),"")) | G62: =IF(DATE(cfg_Year,4,1)>cfg_LastDataDate,"",IFERROR(INDEX(cd_Throughput_tph_MTD,MATCH(MIN(EOMONTH(DATE(cfg_Year,4,1),0),cfg_LastDataDate),cd_Date,0)),"")) | H62: =IF(DATE(cfg_Year,5,1)>cfg_LastDataDate,"",IFERROR(INDEX(cd_Throughput_tph_MTD,MATCH(MIN(EOMONTH(DATE(cfg_Year,5,1),0),cfg_LastDataDate),cd_Date,0)),"")) | I62: =IF(DATE(cfg_Year,6,1)>cfg_LastDataDate,"",IFERROR(INDEX(cd_Throughput_tph_MTD,MATCH(MIN(EOMONTH(DATE(cfg_Year,6,1),0),cfg_LastDataDate),cd_Date,0)),"")) | J62: =IF(DATE(cfg_Year,7,1)>cfg_LastDataDate,"",IFERROR(INDEX(cd_Throughput_tph_MTD,MATCH(MIN(EOMONTH(DATE(cfg_Year,7,1),0),cfg_LastDataDate),cd_Date,0)),"")) | K62: =IF(DATE(cfg_Year,8,1)>cfg_LastDataDate,"",IFERROR(INDEX(cd_Throughput_tph_MTD,MATCH(MIN(EOMONTH(DATE(cfg_Year,8,1),0),cfg_LastDataDate),cd_Date,0)),"")) | L62: =IF(DATE(cfg_Year,9,1)>cfg_LastDataDate,"",IFERROR(INDEX(cd_Throughput_tph_MTD,MATCH(MIN(EOMONTH(DATE(cfg_Year,9,1),0),cfg_LastDataDate),cd_Date,0)),"")) | M62: =IF(DATE(cfg_Year,10,1)>cfg_LastDataDate,"",IFERROR(INDEX(cd_Throughput_tph_MTD,MATCH(MIN(EOMONTH(DATE(cfg_Year,10,1),0),cfg_LastDataDate),cd_Date,0)),"")) | N62: =IF(DATE(cfg_Year,11,1)>cfg_LastDataDate,"",IFERROR(INDEX(cd_Throughput_tph_MTD,MATCH(MIN(EOMONTH(DATE(cfg_Year,11,1),0),cfg_LastDataDate),cd_Date,0)),"")) | O62: =IF(DATE(cfg_Year,12,1)>cfg_LastDataDate,"",IFERROR(INDEX(cd_Throughput_tph_MTD,MATCH(MIN(EOMONTH(DATE(cfg_Year,12,1),0),cfg_LastDataDate),cd_Date,0)),"")) | P62: =IFERROR(INDEX(cd_Throughput_tph_YTD,MATCH(MIN(cfg_YearEnd,cfg_LastDataDate),cd_Date,0)),"")
B63: Mill availability | C63: Actual | D63: =IF(DATE(cfg_Year,1,1)>cfg_LastDataDate,"",IFERROR(INDEX(cd_Mill_Availability_pct_MTD,MATCH(MIN(EOMONTH(DATE(cfg_Year,1,1),0),cfg_LastDataDate),cd_Date,0)),"")) | E63: =IF(DATE(cfg_Year,2,1)>cfg_LastDataDate,"",IFERROR(INDEX(cd_Mill_Availability_pct_MTD,MATCH(MIN(EOMONTH(DATE(cfg_Year,2,1),0),cfg_LastDataDate),cd_Date,0)),"")) | F63: =IF(DATE(cfg_Year,3,1)>cfg_LastDataDate,"",IFERROR(INDEX(cd_Mill_Availability_pct_MTD,MATCH(MIN(EOMONTH(DATE(cfg_Year,3,1),0),cfg_LastDataDate),cd_Date,0)),"")) | G63: =IF(DATE(cfg_Year,4,1)>cfg_LastDataDate,"",IFERROR(INDEX(cd_Mill_Availability_pct_MTD,MATCH(MIN(EOMONTH(DATE(cfg_Year,4,1),0),cfg_LastDataDate),cd_Date,0)),"")) | H63: =IF(DATE(cfg_Year,5,1)>cfg_LastDataDate,"",IFERROR(INDEX(cd_Mill_Availability_pct_MTD,MATCH(MIN(EOMONTH(DATE(cfg_Year,5,1),0),cfg_LastDataDate),cd_Date,0)),"")) | I63: =IF(DATE(cfg_Year,6,1)>cfg_LastDataDate,"",IFERROR(INDEX(cd_Mill_Availability_pct_MTD,MATCH(MIN(EOMONTH(DATE(cfg_Year,6,1),0),cfg_LastDataDate),cd_Date,0)),"")) | J63: =IF(DATE(cfg_Year,7,1)>cfg_LastDataDate,"",IFERROR(INDEX(cd_Mill_Availability_pct_MTD,MATCH(MIN(EOMONTH(DATE(cfg_Year,7,1),0),cfg_LastDataDate),cd_Date,0)),"")) | K63: =IF(DATE(cfg_Year,8,1)>cfg_LastDataDate,"",IFERROR(INDEX(cd_Mill_Availability_pct_MTD,MATCH(MIN(EOMONTH(DATE(cfg_Year,8,1),0),cfg_LastDataDate),cd_Date,0)),"")) | L63: =IF(DATE(cfg_Year,9,1)>cfg_LastDataDate,"",IFERROR(INDEX(cd_Mill_Availability_pct_MTD,MATCH(MIN(EOMONTH(DATE(cfg_Year,9,1),0),cfg_LastDataDate),cd_Date,0)),"")) | M63: =IF(DATE(cfg_Year,10,1)>cfg_LastDataDate,"",IFERROR(INDEX(cd_Mill_Availability_pct_MTD,MATCH(MIN(EOMONTH(DATE(cfg_Year,10,1),0),cfg_LastDataDate),cd_Date,0)),"")) | N63: =IF(DATE(cfg_Year,11,1)>cfg_LastDataDate,"",IFERROR(INDEX(cd_Mill_Availability_pct_MTD,MATCH(MIN(EOMONTH(DATE(cfg_Year,11,1),0),cfg_LastDataDate),cd_Date,0)),"")) | O63: =IF(DATE(cfg_Year,12,1)>cfg_LastDataDate,"",IFERROR(INDEX(cd_Mill_Availability_pct_MTD,MATCH(MIN(EOMONTH(DATE(cfg_Year,12,1),0),cfg_LastDataDate),cd_Date,0)),"")) | P63: =IFERROR(INDEX(cd_Mill_Availability_pct_YTD,MATCH(MIN(cfg_YearEnd,cfg_LastDataDate),cd_Date,0)),"")
B64: Mill utilisation | C64: Actual | D64: =IF(DATE(cfg_Year,1,1)>cfg_LastDataDate,"",IFERROR(INDEX(cd_Mill_Utilisation_pct_MTD,MATCH(MIN(EOMONTH(DATE(cfg_Year,1,1),0),cfg_LastDataDate),cd_Date,0)),"")) | E64: =IF(DATE(cfg_Year,2,1)>cfg_LastDataDate,"",IFERROR(INDEX(cd_Mill_Utilisation_pct_MTD,MATCH(MIN(EOMONTH(DATE(cfg_Year,2,1),0),cfg_LastDataDate),cd_Date,0)),"")) | F64: =IF(DATE(cfg_Year,3,1)>cfg_LastDataDate,"",IFERROR(INDEX(cd_Mill_Utilisation_pct_MTD,MATCH(MIN(EOMONTH(DATE(cfg_Year,3,1),0),cfg_LastDataDate),cd_Date,0)),"")) | G64: =IF(DATE(cfg_Year,4,1)>cfg_LastDataDate,"",IFERROR(INDEX(cd_Mill_Utilisation_pct_MTD,MATCH(MIN(EOMONTH(DATE(cfg_Year,4,1),0),cfg_LastDataDate),cd_Date,0)),"")) | H64: =IF(DATE(cfg_Year,5,1)>cfg_LastDataDate,"",IFERROR(INDEX(cd_Mill_Utilisation_pct_MTD,MATCH(MIN(EOMONTH(DATE(cfg_Year,5,1),0),cfg_LastDataDate),cd_Date,0)),"")) | I64: =IF(DATE(cfg_Year,6,1)>cfg_LastDataDate,"",IFERROR(INDEX(cd_Mill_Utilisation_pct_MTD,MATCH(MIN(EOMONTH(DATE(cfg_Year,6,1),0),cfg_LastDataDate),cd_Date,0)),"")) | J64: =IF(DATE(cfg_Year,7,1)>cfg_LastDataDate,"",IFERROR(INDEX(cd_Mill_Utilisation_pct_MTD,MATCH(MIN(EOMONTH(DATE(cfg_Year,7,1),0),cfg_LastDataDate),cd_Date,0)),"")) | K64: =IF(DATE(cfg_Year,8,1)>cfg_LastDataDate,"",IFERROR(INDEX(cd_Mill_Utilisation_pct_MTD,MATCH(MIN(EOMONTH(DATE(cfg_Year,8,1),0),cfg_LastDataDate),cd_Date,0)),"")) | L64: =IF(DATE(cfg_Year,9,1)>cfg_LastDataDate,"",IFERROR(INDEX(cd_Mill_Utilisation_pct_MTD,MATCH(MIN(EOMONTH(DATE(cfg_Year,9,1),0),cfg_LastDataDate),cd_Date,0)),"")) | M64: =IF(DATE(cfg_Year,10,1)>cfg_LastDataDate,"",IFERROR(INDEX(cd_Mill_Utilisation_pct_MTD,MATCH(MIN(EOMONTH(DATE(cfg_Year,10,1),0),cfg_LastDataDate),cd_Date,0)),"")) | N64: =IF(DATE(cfg_Year,11,1)>cfg_LastDataDate,"",IFERROR(INDEX(cd_Mill_Utilisation_pct_MTD,MATCH(MIN(EOMONTH(DATE(cfg_Year,11,1),0),cfg_LastDataDate),cd_Date,0)),"")) | O64: =IF(DATE(cfg_Year,12,1)>cfg_LastDataDate,"",IFERROR(INDEX(cd_Mill_Utilisation_pct_MTD,MATCH(MIN(EOMONTH(DATE(cfg_Year,12,1),0),cfg_LastDataDate),cd_Date,0)),"")) | P64: =IFERROR(INDEX(cd_Mill_Utilisation_pct_YTD,MATCH(MIN(cfg_YearEnd,cfg_LastDataDate),cd_Date,0)),"")
B65: Cyanide consumption | C65: Actual | D65: =IF(DATE(cfg_Year,1,1)>cfg_LastDataDate,"",IFERROR(INDEX(cd_Cyanide_kgpt_MTD,MATCH(MIN(EOMONTH(DATE(cfg_Year,1,1),0),cfg_LastDataDate),cd_Date,0)),"")) | E65: =IF(DATE(cfg_Year,2,1)>cfg_LastDataDate,"",IFERROR(INDEX(cd_Cyanide_kgpt_MTD,MATCH(MIN(EOMONTH(DATE(cfg_Year,2,1),0),cfg_LastDataDate),cd_Date,0)),"")) | F65: =IF(DATE(cfg_Year,3,1)>cfg_LastDataDate,"",IFERROR(INDEX(cd_Cyanide_kgpt_MTD,MATCH(MIN(EOMONTH(DATE(cfg_Year,3,1),0),cfg_LastDataDate),cd_Date,0)),"")) | G65: =IF(DATE(cfg_Year,4,1)>cfg_LastDataDate,"",IFERROR(INDEX(cd_Cyanide_kgpt_MTD,MATCH(MIN(EOMONTH(DATE(cfg_Year,4,1),0),cfg_LastDataDate),cd_Date,0)),"")) | H65: =IF(DATE(cfg_Year,5,1)>cfg_LastDataDate,"",IFERROR(INDEX(cd_Cyanide_kgpt_MTD,MATCH(MIN(EOMONTH(DATE(cfg_Year,5,1),0),cfg_LastDataDate),cd_Date,0)),"")) | I65: =IF(DATE(cfg_Year,6,1)>cfg_LastDataDate,"",IFERROR(INDEX(cd_Cyanide_kgpt_MTD,MATCH(MIN(EOMONTH(DATE(cfg_Year,6,1),0),cfg_LastDataDate),cd_Date,0)),"")) | J65: =IF(DATE(cfg_Year,7,1)>cfg_LastDataDate,"",IFERROR(INDEX(cd_Cyanide_kgpt_MTD,MATCH(MIN(EOMONTH(DATE(cfg_Year,7,1),0),cfg_LastDataDate),cd_Date,0)),"")) | K65: =IF(DATE(cfg_Year,8,1)>cfg_LastDataDate,"",IFERROR(INDEX(cd_Cyanide_kgpt_MTD,MATCH(MIN(EOMONTH(DATE(cfg_Year,8,1),0),cfg_LastDataDate),cd_Date,0)),"")) | L65: =IF(DATE(cfg_Year,9,1)>cfg_LastDataDate,"",IFERROR(INDEX(cd_Cyanide_kgpt_MTD,MATCH(MIN(EOMONTH(DATE(cfg_Year,9,1),0),cfg_LastDataDate),cd_Date,0)),"")) | M65: =IF(DATE(cfg_Year,10,1)>cfg_LastDataDate,"",IFERROR(INDEX(cd_Cyanide_kgpt_MTD,MATCH(MIN(EOMONTH(DATE(cfg_Year,10,1),0),cfg_LastDataDate),cd_Date,0)),"")) | N65: =IF(DATE(cfg_Year,11,1)>cfg_LastDataDate,"",IFERROR(INDEX(cd_Cyanide_kgpt_MTD,MATCH(MIN(EOMONTH(DATE(cfg_Year,11,1),0),cfg_LastDataDate),cd_Date,0)),"")) | O65: =IF(DATE(cfg_Year,12,1)>cfg_LastDataDate,"",IFERROR(INDEX(cd_Cyanide_kgpt_MTD,MATCH(MIN(EOMONTH(DATE(cfg_Year,12,1),0),cfg_LastDataDate),cd_Date,0)),"")) | P65: =IFERROR(INDEX(cd_Cyanide_kgpt_YTD,MATCH(MIN(cfg_YearEnd,cfg_LastDataDate),cd_Date,0)),"")
B66: Power consumption | C66: Actual | D66: =IF(DATE(cfg_Year,1,1)>cfg_LastDataDate,"",IFERROR(INDEX(cd_Power_kWhpt_MTD,MATCH(MIN(EOMONTH(DATE(cfg_Year,1,1),0),cfg_LastDataDate),cd_Date,0)),"")) | E66: =IF(DATE(cfg_Year,2,1)>cfg_LastDataDate,"",IFERROR(INDEX(cd_Power_kWhpt_MTD,MATCH(MIN(EOMONTH(DATE(cfg_Year,2,1),0),cfg_LastDataDate),cd_Date,0)),"")) | F66: =IF(DATE(cfg_Year,3,1)>cfg_LastDataDate,"",IFERROR(INDEX(cd_Power_kWhpt_MTD,MATCH(MIN(EOMONTH(DATE(cfg_Year,3,1),0),cfg_LastDataDate),cd_Date,0)),"")) | G66: =IF(DATE(cfg_Year,4,1)>cfg_LastDataDate,"",IFERROR(INDEX(cd_Power_kWhpt_MTD,MATCH(MIN(EOMONTH(DATE(cfg_Year,4,1),0),cfg_LastDataDate),cd_Date,0)),"")) | H66: =IF(DATE(cfg_Year,5,1)>cfg_LastDataDate,"",IFERROR(INDEX(cd_Power_kWhpt_MTD,MATCH(MIN(EOMONTH(DATE(cfg_Year,5,1),0),cfg_LastDataDate),cd_Date,0)),"")) | I66: =IF(DATE(cfg_Year,6,1)>cfg_LastDataDate,"",IFERROR(INDEX(cd_Power_kWhpt_MTD,MATCH(MIN(EOMONTH(DATE(cfg_Year,6,1),0),cfg_LastDataDate),cd_Date,0)),"")) | J66: =IF(DATE(cfg_Year,7,1)>cfg_LastDataDate,"",IFERROR(INDEX(cd_Power_kWhpt_MTD,MATCH(MIN(EOMONTH(DATE(cfg_Year,7,1),0),cfg_LastDataDate),cd_Date,0)),"")) | K66: =IF(DATE(cfg_Year,8,1)>cfg_LastDataDate,"",IFERROR(INDEX(cd_Power_kWhpt_MTD,MATCH(MIN(EOMONTH(DATE(cfg_Year,8,1),0),cfg_LastDataDate),cd_Date,0)),"")) | L66: =IF(DATE(cfg_Year,9,1)>cfg_LastDataDate,"",IFERROR(INDEX(cd_Power_kWhpt_MTD,MATCH(MIN(EOMONTH(DATE(cfg_Year,9,1),0),cfg_LastDataDate),cd_Date,0)),"")) | M66: =IF(DATE(cfg_Year,10,1)>cfg_LastDataDate,"",IFERROR(INDEX(cd_Power_kWhpt_MTD,MATCH(MIN(EOMONTH(DATE(cfg_Year,10,1),0),cfg_LastDataDate),cd_Date,0)),"")) | N66: =IF(DATE(cfg_Year,11,1)>cfg_LastDataDate,"",IFERROR(INDEX(cd_Power_kWhpt_MTD,MATCH(MIN(EOMONTH(DATE(cfg_Year,11,1),0),cfg_LastDataDate),cd_Date,0)),"")) | O66: =IF(DATE(cfg_Year,12,1)>cfg_LastDataDate,"",IFERROR(INDEX(cd_Power_kWhpt_MTD,MATCH(MIN(EOMONTH(DATE(cfg_Year,12,1),0),cfg_LastDataDate),cd_Date,0)),"")) | P66: =IFERROR(INDEX(cd_Power_kWhpt_YTD,MATCH(MIN(cfg_YearEnd,cfg_LastDataDate),cd_Date,0)),"")

Sheet Plant
A1: Processing plant, one row per day
A2: Owner: Processing (met accountant / shift supervisor). Type only in the blue-headed columns; grey-headed columns are formulas. Add rows at the bottom only; never insert columns. Paste with Paste Special > Values only. Red cells need attention (missing or unknown value, duplicate date).
A4: Date | B4: Crushed (t) | C4: Milled (t) | D4: Head grade (g/t) | E4: Tails grade (g/t) | F4: Gravity gold (oz) | G4: Gold poured (oz) | H4: Mill run hours (h) | I4: Planned maintenance (h) | J4: Unplanned downtime (h) | K4: Crusher run hours (h) | L4: Cyanide (kg) | M4: Lime (kg) | N4: Grinding media (kg) | O4: Power (kWh) | P4: Raw water (m3) | Q4: Gold in circuit (oz) | R4: Comments | S4: Contained gold in feed (oz) | T4: Gold lost to tails (oz) | U4: Gold recovered (oz) | V4: Recovery (%) | W4: Throughput (t/h) | X4: Mill availability (%) | Y4: Mill utilisation (%)
A5: Date | B5: Crushed_t | C5: Milled_t | D5: Head_Grade_gpt | E5: Tails_Grade_gpt | F5: Gravity_Gold_oz | G5: Gold_Poured_oz | H5: Mill_Run_h | I5: Mill_Planned_Maint_h | J5: Mill_Unplanned_Down_h | K5: Crusher_Run_h | L5: Cyanide_kg | M5: Lime_kg | N5: Grinding_Media_kg | O5: Power_kWh | P5: Raw_Water_m3 | Q5: GIC_oz | R5: Comments | S5: Feed_oz | T5: Tails_oz | U5: Recovered_oz | V5: Recovery_pct | W5: Throughput_tph | X5: Availability_pct | Y5: Utilisation_pct
A6: 46023 | S6: =IF(OR(tblPlant[[#This Row],[Milled_t]]="",tblPlant[[#This Row],[Head_Grade_gpt]]=""),"",tblPlant[[#This Row],[Milled_t]]*tblPlant[[#This Row],[Head_Grade_gpt]]/cfg_TroyOz) | T6: =IF(OR(tblPlant[[#This Row],[Milled_t]]="",tblPlant[[#This Row],[Tails_Grade_gpt]]=""),"",tblPlant[[#This Row],[Milled_t]]*tblPlant[[#This Row],[Tails_Grade_gpt]]/cfg_TroyOz) | U6: =IF(OR(tblPlant[[#This Row],[Milled_t]]="",tblPlant[[#This Row],[Head_Grade_gpt]]="",tblPlant[[#This Row],[Tails_Grade_gpt]]=""),"",tblPlant[[#This Row],[Feed_oz]]-tblPlant[[#This Row],[Tails_oz]]) | V6: =IF(AND(ISNUMBER(tblPlant[[#This Row],[Recovered_oz]]),tblPlant[[#This Row],[Feed_oz]]>0),tblPlant[[#This Row],[Recovered_oz]]/tblPlant[[#This Row],[Feed_oz]],"") | W6: =IF(AND(tblPlant[[#This Row],[Milled_t]]<>"",tblPlant[[#This Row],[Mill_Run_h]]>0),tblPlant[[#This Row],[Milled_t]]/tblPlant[[#This Row],[Mill_Run_h]],"") | X6: =IF(AND(tblPlant[[#This Row],[Mill_Run_h]]="",tblPlant[[#This Row],[Mill_Planned_Maint_h]]="",tblPlant[[#This Row],[Mill_Unplanned_Down_h]]=""),"",(cfg_HoursPerDay-tblPlant[[#This Row],[Mill_Planned_Maint_h]]-tblPlant[[#This Row],[Mill_Unplanned_Down_h]])/cfg_HoursPerDay) | Y6: =IF(AND(NOT(AND(tblPlant[[#This Row],[Mill_Run_h]]="",tblPlant[[#This Row],[Mill_Planned_Maint_h]]="",tblPlant[[#This Row],[Mill_Unplanned_Down_h]]="")),(cfg_HoursPerDay-tblPlant[[#This Row],[Mill_Planned_Maint_h]]-tblPlant[[#This Row],[Mill_Unplanned_Down_h]])>0),tblPlant[[#This Row],[Mill_Run_h]]/(cfg_HoursPerDay-tblPlant[[#This Row],[Mill_Planned_Maint_h]]-tblPlant[[#This Row],[Mill_Unplanned_Down_h]]),"")
A7: 46024 | S7: =IF(OR(tblPlant[[#This Row],[Milled_t]]="",tblPlant[[#This Row],[Head_Grade_gpt]]=""),"",tblPlant[[#This Row],[Milled_t]]*tblPlant[[#This Row],[Head_Grade_gpt]]/cfg_TroyOz) | T7: =IF(OR(tblPlant[[#This Row],[Milled_t]]="",tblPlant[[#This Row],[Tails_Grade_gpt]]=""),"",tblPlant[[#This Row],[Milled_t]]*tblPlant[[#This Row],[Tails_Grade_gpt]]/cfg_TroyOz) | U7: =IF(OR(tblPlant[[#This Row],[Milled_t]]="",tblPlant[[#This Row],[Head_Grade_gpt]]="",tblPlant[[#This Row],[Tails_Grade_gpt]]=""),"",tblPlant[[#This Row],[Feed_oz]]-tblPlant[[#This Row],[Tails_oz]]) | V7: =IF(AND(ISNUMBER(tblPlant[[#This Row],[Recovered_oz]]),tblPlant[[#This Row],[Feed_oz]]>0),tblPlant[[#This Row],[Recovered_oz]]/tblPlant[[#This Row],[Feed_oz]],"") | W7: =IF(AND(tblPlant[[#This Row],[Milled_t]]<>"",tblPlant[[#This Row],[Mill_Run_h]]>0),tblPlant[[#This Row],[Milled_t]]/tblPlant[[#This Row],[Mill_Run_h]],"") | X7: =IF(AND(tblPlant[[#This Row],[Mill_Run_h]]="",tblPlant[[#This Row],[Mill_Planned_Maint_h]]="",tblPlant[[#This Row],[Mill_Unplanned_Down_h]]=""),"",(cfg_HoursPerDay-tblPlant[[#This Row],[Mill_Planned_Maint_h]]-tblPlant[[#This Row],[Mill_Unplanned_Down_h]])/cfg_HoursPerDay) | Y7: =IF(AND(NOT(AND(tblPlant[[#This Row],[Mill_Run_h]]="",tblPlant[[#This Row],[Mill_Planned_Maint_h]]="",tblPlant[[#This Row],[Mill_Unplanned_Down_h]]="")),(cfg_HoursPerDay-tblPlant[[#This Row],[Mill_Planned_Maint_h]]-tblPlant[[#This Row],[Mill_Unplanned_Down_h]])>0),tblPlant[[#This Row],[Mill_Run_h]]/(cfg_HoursPerDay-tblPlant[[#This Row],[Mill_Planned_Maint_h]]-tblPlant[[#This Row],[Mill_Unplanned_Down_h]]),"")
A8: 46025 | S8: =IF(OR(tblPlant[[#This Row],[Milled_t]]="",tblPlant[[#This Row],[Head_Grade_gpt]]=""),"",tblPlant[[#This Row],[Milled_t]]*tblPlant[[#This Row],[Head_Grade_gpt]]/cfg_TroyOz) | T8: =IF(OR(tblPlant[[#This Row],[Milled_t]]="",tblPlant[[#This Row],[Tails_Grade_gpt]]=""),"",tblPlant[[#This Row],[Milled_t]]*tblPlant[[#This Row],[Tails_Grade_gpt]]/cfg_TroyOz) | U8: =IF(OR(tblPlant[[#This Row],[Milled_t]]="",tblPlant[[#This Row],[Head_Grade_gpt]]="",tblPlant[[#This Row],[Tails_Grade_gpt]]=""),"",tblPlant[[#This Row],[Feed_oz]]-tblPlant[[#This Row],[Tails_oz]]) | V8: =IF(AND(ISNUMBER(tblPlant[[#This Row],[Recovered_oz]]),tblPlant[[#This Row],[Feed_oz]]>0),tblPlant[[#This Row],[Recovered_oz]]/tblPlant[[#This Row],[Feed_oz]],"") | W8: =IF(AND(tblPlant[[#This Row],[Milled_t]]<>"",tblPlant[[#This Row],[Mill_Run_h]]>0),tblPlant[[#This Row],[Milled_t]]/tblPlant[[#This Row],[Mill_Run_h]],"") | X8: =IF(AND(tblPlant[[#This Row],[Mill_Run_h]]="",tblPlant[[#This Row],[Mill_Planned_Maint_h]]="",tblPlant[[#This Row],[Mill_Unplanned_Down_h]]=""),"",(cfg_HoursPerDay-tblPlant[[#This Row],[Mill_Planned_Maint_h]]-tblPlant[[#This Row],[Mill_Unplanned_Down_h]])/cfg_HoursPerDay) | Y8: =IF(AND(NOT(AND(tblPlant[[#This Row],[Mill_Run_h]]="",tblPlant[[#This Row],[Mill_Planned_Maint_h]]="",tblPlant[[#This Row],[Mill_Unplanned_Down_h]]="")),(cfg_HoursPerDay-tblPlant[[#This Row],[Mill_Planned_Maint_h]]-tblPlant[[#This Row],[Mill_Unplanned_Down_h]])>0),tblPlant[[#This Row],[Mill_Run_h]]/(cfg_HoursPerDay-tblPlant[[#This Row],[Mill_Planned_Maint_h]]-tblPlant[[#This Row],[Mill_Unplanned_Down_h]]),"")
A9: 46026 | S9: =IF(OR(tblPlant[[#This Row],[Milled_t]]="",tblPlant[[#This Row],[Head_Grade_gpt]]=""),"",tblPlant[[#This Row],[Milled_t]]*tblPlant[[#This Row],[Head_Grade_gpt]]/cfg_TroyOz) | T9: =IF(OR(tblPlant[[#This Row],[Milled_t]]="",tblPlant[[#This Row],[Tails_Grade_gpt]]=""),"",tblPlant[[#This Row],[Milled_t]]*tblPlant[[#This Row],[Tails_Grade_gpt]]/cfg_TroyOz) | U9: =IF(OR(tblPlant[[#This Row],[Milled_t]]="",tblPlant[[#This Row],[Head_Grade_gpt]]="",tblPlant[[#This Row],[Tails_Grade_gpt]]=""),"",tblPlant[[#This Row],[Feed_oz]]-tblPlant[[#This Row],[Tails_oz]]) | V9: =IF(AND(ISNUMBER(tblPlant[[#This Row],[Recovered_oz]]),tblPlant[[#This Row],[Feed_oz]]>0),tblPlant[[#This Row],[Recovered_oz]]/tblPlant[[#This Row],[Feed_oz]],"") | W9: =IF(AND(tblPlant[[#This Row],[Milled_t]]<>"",tblPlant[[#This Row],[Mill_Run_h]]>0),tblPlant[[#This Row],[Milled_t]]/tblPlant[[#This Row],[Mill_Run_h]],"") | X9: =IF(AND(tblPlant[[#This Row],[Mill_Run_h]]="",tblPlant[[#This Row],[Mill_Planned_Maint_h]]="",tblPlant[[#This Row],[Mill_Unplanned_Down_h]]=""),"",(cfg_HoursPerDay-tblPlant[[#This Row],[Mill_Planned_Maint_h]]-tblPlant[[#This Row],[Mill_Unplanned_Down_h]])/cfg_HoursPerDay) | Y9: =IF(AND(NOT(AND(tblPlant[[#This Row],[Mill_Run_h]]="",tblPlant[[#This Row],[Mill_Planned_Maint_h]]="",tblPlant[[#This Row],[Mill_Unplanned_Down_h]]="")),(cfg_HoursPerDay-tblPlant[[#This Row],[Mill_Planned_Maint_h]]-tblPlant[[#This Row],[Mill_Unplanned_Down_h]])>0),tblPlant[[#This Row],[Mill_Run_h]]/(cfg_HoursPerDay-tblPlant[[#This Row],[Mill_Planned_Maint_h]]-tblPlant[[#This Row],[Mill_Unplanned_Down_h]]),"")
A10: 46027 | S10: =IF(OR(tblPlant[[#This Row],[Milled_t]]="",tblPlant[[#This Row],[Head_Grade_gpt]]=""),"",tblPlant[[#This Row],[Milled_t]]*tblPlant[[#This Row],[Head_Grade_gpt]]/cfg_TroyOz) | T10: =IF(OR(tblPlant[[#This Row],[Milled_t]]="",tblPlant[[#This Row],[Tails_Grade_gpt]]=""),"",tblPlant[[#This Row],[Milled_t]]*tblPlant[[#This Row],[Tails_Grade_gpt]]/cfg_TroyOz) | U10: =IF(OR(tblPlant[[#This Row],[Milled_t]]="",tblPlant[[#This Row],[Head_Grade_gpt]]="",tblPlant[[#This Row],[Tails_Grade_gpt]]=""),"",tblPlant[[#This Row],[Feed_oz]]-tblPlant[[#This Row],[Tails_oz]]) | V10: =IF(AND(ISNUMBER(tblPlant[[#This Row],[Recovered_oz]]),tblPlant[[#This Row],[Feed_oz]]>0),tblPlant[[#This Row],[Recovered_oz]]/tblPlant[[#This Row],[Feed_oz]],"") | W10: =IF(AND(tblPlant[[#This Row],[Milled_t]]<>"",tblPlant[[#This Row],[Mill_Run_h]]>0),tblPlant[[#This Row],[Milled_t]]/tblPlant[[#This Row],[Mill_Run_h]],"") | X10: =IF(AND(tblPlant[[#This Row],[Mill_Run_h]]="",tblPlant[[#This Row],[Mill_Planned_Maint_h]]="",tblPlant[[#This Row],[Mill_Unplanned_Down_h]]=""),"",(cfg_HoursPerDay-tblPlant[[#This Row],[Mill_Planned_Maint_h]]-tblPlant[[#This Row],[Mill_Unplanned_Down_h]])/cfg_HoursPerDay) | Y10: =IF(AND(NOT(AND(tblPlant[[#This Row],[Mill_Run_h]]="",tblPlant[[#This Row],[Mill_Planned_Maint_h]]="",tblPlant[[#This Row],[Mill_Unplanned_Down_h]]="")),(cfg_HoursPerDay-tblPlant[[#This Row],[Mill_Planned_Maint_h]]-tblPlant[[#This Row],[Mill_Unplanned_Down_h]])>0),tblPlant[[#This Row],[Mill_Run_h]]/(cfg_HoursPerDay-tblPlant[[#This Row],[Mill_Planned_Maint_h]]-tblPlant[[#This Row],[Mill_Unplanned_Down_h]]),"")
A11: 46028 | S11: =IF(OR(tblPlant[[#This Row],[Milled_t]]="",tblPlant[[#This Row],[Head_Grade_gpt]]=""),"",tblPlant[[#This Row],[Milled_t]]*tblPlant[[#This Row],[Head_Grade_gpt]]/cfg_TroyOz) | T11: =IF(OR(tblPlant[[#This Row],[Milled_t]]="",tblPlant[[#This Row],[Tails_Grade_gpt]]=""),"",tblPlant[[#This Row],[Milled_t]]*tblPlant[[#This Row],[Tails_Grade_gpt]]/cfg_TroyOz) | U11: =IF(OR(tblPlant[[#This Row],[Milled_t]]="",tblPlant[[#This Row],[Head_Grade_gpt]]="",tblPlant[[#This Row],[Tails_Grade_gpt]]=""),"",tblPlant[[#This Row],[Feed_oz]]-tblPlant[[#This Row],[Tails_oz]]) | V11: =IF(AND(ISNUMBER(tblPlant[[#This Row],[Recovered_oz]]),tblPlant[[#This Row],[Feed_oz]]>0),tblPlant[[#This Row],[Recovered_oz]]/tblPlant[[#This Row],[Feed_oz]],"") | W11: =IF(AND(tblPlant[[#This Row],[Milled_t]]<>"",tblPlant[[#This Row],[Mill_Run_h]]>0),tblPlant[[#This Row],[Milled_t]]/tblPlant[[#This Row],[Mill_Run_h]],"") | X11: =IF(AND(tblPlant[[#This Row],[Mill_Run_h]]="",tblPlant[[#This Row],[Mill_Planned_Maint_h]]="",tblPlant[[#This Row],[Mill_Unplanned_Down_h]]=""),"",(cfg_HoursPerDay-tblPlant[[#This Row],[Mill_Planned_Maint_h]]-tblPlant[[#This Row],[Mill_Unplanned_Down_h]])/cfg_HoursPerDay) | Y11: =IF(AND(NOT(AND(tblPlant[[#This Row],[Mill_Run_h]]="",tblPlant[[#This Row],[Mill_Planned_Maint_h]]="",tblPlant[[#This Row],[Mill_Unplanned_Down_h]]="")),(cfg_HoursPerDay-tblPlant[[#This Row],[Mill_Planned_Maint_h]]-tblPlant[[#This Row],[Mill_Unplanned_Down_h]])>0),tblPlant[[#This Row],[Mill_Run_h]]/(cfg_HoursPerDay-tblPlant[[#This Row],[Mill_Planned_Maint_h]]-tblPlant[[#This Row],[Mill_Unplanned_Down_h]]),"")
A12: 46029 | S12: =IF(OR(tblPlant[[#This Row],[Milled_t]]="",tblPlant[[#This Row],[Head_Grade_gpt]]=""),"",tblPlant[[#This Row],[Milled_t]]*tblPlant[[#This Row],[Head_Grade_gpt]]/cfg_TroyOz) | T12: =IF(OR(tblPlant[[#This Row],[Milled_t]]="",tblPlant[[#This Row],[Tails_Grade_gpt]]=""),"",tblPlant[[#This Row],[Milled_t]]*tblPlant[[#This Row],[Tails_Grade_gpt]]/cfg_TroyOz) | U12: =IF(OR(tblPlant[[#This Row],[Milled_t]]="",tblPlant[[#This Row],[Head_Grade_gpt]]="",tblPlant[[#This Row],[Tails_Grade_gpt]]=""),"",tblPlant[[#This Row],[Feed_oz]]-tblPlant[[#This Row],[Tails_oz]]) | V12: =IF(AND(ISNUMBER(tblPlant[[#This Row],[Recovered_oz]]),tblPlant[[#This Row],[Feed_oz]]>0),tblPlant[[#This Row],[Recovered_oz]]/tblPlant[[#This Row],[Feed_oz]],"") | W12: =IF(AND(tblPlant[[#This Row],[Milled_t]]<>"",tblPlant[[#This Row],[Mill_Run_h]]>0),tblPlant[[#This Row],[Milled_t]]/tblPlant[[#This Row],[Mill_Run_h]],"") | X12: =IF(AND(tblPlant[[#This Row],[Mill_Run_h]]="",tblPlant[[#This Row],[Mill_Planned_Maint_h]]="",tblPlant[[#This Row],[Mill_Unplanned_Down_h]]=""),"",(cfg_HoursPerDay-tblPlant[[#This Row],[Mill_Planned_Maint_h]]-tblPlant[[#This Row],[Mill_Unplanned_Down_h]])/cfg_HoursPerDay) | Y12: =IF(AND(NOT(AND(tblPlant[[#This Row],[Mill_Run_h]]="",tblPlant[[#This Row],[Mill_Planned_Maint_h]]="",tblPlant[[#This Row],[Mill_Unplanned_Down_h]]="")),(cfg_HoursPerDay-tblPlant[[#This Row],[Mill_Planned_Maint_h]]-tblPlant[[#This Row],[Mill_Unplanned_Down_h]])>0),tblPlant[[#This Row],[Mill_Run_h]]/(cfg_HoursPerDay-tblPlant[[#This Row],[Mill_Planned_Maint_h]]-tblPlant[[#This Row],[Mill_Unplanned_Down_h]]),"")
A13: 46030 | S13: =IF(OR(tblPlant[[#This Row],[Milled_t]]="",tblPlant[[#This Row],[Head_Grade_gpt]]=""),"",tblPlant[[#This Row],[Milled_t]]*tblPlant[[#This Row],[Head_Grade_gpt]]/cfg_TroyOz) | T13: =IF(OR(tblPlant[[#This Row],[Milled_t]]="",tblPlant[[#This Row],[Tails_Grade_gpt]]=""),"",tblPlant[[#This Row],[Milled_t]]*tblPlant[[#This Row],[Tails_Grade_gpt]]/cfg_TroyOz) | U13: =IF(OR(tblPlant[[#This Row],[Milled_t]]="",tblPlant[[#This Row],[Head_Grade_gpt]]="",tblPlant[[#This Row],[Tails_Grade_gpt]]=""),"",tblPlant[[#This Row],[Feed_oz]]-tblPlant[[#This Row],[Tails_oz]]) | V13: =IF(AND(ISNUMBER(tblPlant[[#This Row],[Recovered_oz]]),tblPlant[[#This Row],[Feed_oz]]>0),tblPlant[[#This Row],[Recovered_oz]]/tblPlant[[#This Row],[Feed_oz]],"") | W13: =IF(AND(tblPlant[[#This Row],[Milled_t]]<>"",tblPlant[[#This Row],[Mill_Run_h]]>0),tblPlant[[#This Row],[Milled_t]]/tblPlant[[#This Row],[Mill_Run_h]],"") | X13: =IF(AND(tblPlant[[#This Row],[Mill_Run_h]]="",tblPlant[[#This Row],[Mill_Planned_Maint_h]]="",tblPlant[[#This Row],[Mill_Unplanned_Down_h]]=""),"",(cfg_HoursPerDay-tblPlant[[#This Row],[Mill_Planned_Maint_h]]-tblPlant[[#This Row],[Mill_Unplanned_Down_h]])/cfg_HoursPerDay) | Y13: =IF(AND(NOT(AND(tblPlant[[#This Row],[Mill_Run_h]]="",tblPlant[[#This Row],[Mill_Planned_Maint_h]]="",tblPlant[[#This Row],[Mill_Unplanned_Down_h]]="")),(cfg_HoursPerDay-tblPlant[[#This Row],[Mill_Planned_Maint_h]]-tblPlant[[#This Row],[Mill_Unplanned_Down_h]])>0),tblPlant[[#This Row],[Mill_Run_h]]/(cfg_HoursPerDay-tblPlant[[#This Row],[Mill_Planned_Maint_h]]-tblPlant[[#This Row],[Mill_Unplanned_Down_h]]),"")
A14: 46031 | S14: =IF(OR(tblPlant[[#This Row],[Milled_t]]="",tblPlant[[#This Row],[Head_Grade_gpt]]=""),"",tblPlant[[#This Row],[Milled_t]]*tblPlant[[#This Row],[Head_Grade_gpt]]/cfg_TroyOz) | T14: =IF(OR(tblPlant[[#This Row],[Milled_t]]="",tblPlant[[#This Row],[Tails_Grade_gpt]]=""),"",tblPlant[[#This Row],[Milled_t]]*tblPlant[[#This Row],[Tails_Grade_gpt]]/cfg_TroyOz) | U14: =IF(OR(tblPlant[[#This Row],[Milled_t]]="",tblPlant[[#This Row],[Head_Grade_gpt]]="",tblPlant[[#This Row],[Tails_Grade_gpt]]=""),"",tblPlant[[#This Row],[Feed_oz]]-tblPlant[[#This Row],[Tails_oz]]) | V14: =IF(AND(ISNUMBER(tblPlant[[#This Row],[Recovered_oz]]),tblPlant[[#This Row],[Feed_oz]]>0),tblPlant[[#This Row],[Recovered_oz]]/tblPlant[[#This Row],[Feed_oz]],"") | W14: =IF(AND(tblPlant[[#This Row],[Milled_t]]<>"",tblPlant[[#This Row],[Mill_Run_h]]>0),tblPlant[[#This Row],[Milled_t]]/tblPlant[[#This Row],[Mill_Run_h]],"") | X14: =IF(AND(tblPlant[[#This Row],[Mill_Run_h]]="",tblPlant[[#This Row],[Mill_Planned_Maint_h]]="",tblPlant[[#This Row],[Mill_Unplanned_Down_h]]=""),"",(cfg_HoursPerDay-tblPlant[[#This Row],[Mill_Planned_Maint_h]]-tblPlant[[#This Row],[Mill_Unplanned_Down_h]])/cfg_HoursPerDay) | Y14: =IF(AND(NOT(AND(tblPlant[[#This Row],[Mill_Run_h]]="",tblPlant[[#This Row],[Mill_Planned_Maint_h]]="",tblPlant[[#This Row],[Mill_Unplanned_Down_h]]="")),(cfg_HoursPerDay-tblPlant[[#This Row],[Mill_Planned_Maint_h]]-tblPlant[[#This Row],[Mill_Unplanned_Down_h]])>0),tblPlant[[#This Row],[Mill_Run_h]]/(cfg_HoursPerDay-tblPlant[[#This Row],[Mill_Planned_Maint_h]]-tblPlant[[#This Row],[Mill_Unplanned_Down_h]]),"")
A15: 46032 | S15: =IF(OR(tblPlant[[#This Row],[Milled_t]]="",tblPlant[[#This Row],[Head_Grade_gpt]]=""),"",tblPlant[[#This Row],[Milled_t]]*tblPlant[[#This Row],[Head_Grade_gpt]]/cfg_TroyOz) | T15: =IF(OR(tblPlant[[#This Row],[Milled_t]]="",tblPlant[[#This Row],[Tails_Grade_gpt]]=""),"",tblPlant[[#This Row],[Milled_t]]*tblPlant[[#This Row],[Tails_Grade_gpt]]/cfg_TroyOz) | U15: =IF(OR(tblPlant[[#This Row],[Milled_t]]="",tblPlant[[#This Row],[Head_Grade_gpt]]="",tblPlant[[#This Row],[Tails_Grade_gpt]]=""),"",tblPlant[[#This Row],[Feed_oz]]-tblPlant[[#This Row],[Tails_oz]]) | V15: =IF(AND(ISNUMBER(tblPlant[[#This Row],[Recovered_oz]]),tblPlant[[#This Row],[Feed_oz]]>0),tblPlant[[#This Row],[Recovered_oz]]/tblPlant[[#This Row],[Feed_oz]],"") | W15: =IF(AND(tblPlant[[#This Row],[Milled_t]]<>"",tblPlant[[#This Row],[Mill_Run_h]]>0),tblPlant[[#This Row],[Milled_t]]/tblPlant[[#This Row],[Mill_Run_h]],"") | X15: =IF(AND(tblPlant[[#This Row],[Mill_Run_h]]="",tblPlant[[#This Row],[Mill_Planned_Maint_h]]="",tblPlant[[#This Row],[Mill_Unplanned_Down_h]]=""),"",(cfg_HoursPerDay-tblPlant[[#This Row],[Mill_Planned_Maint_h]]-tblPlant[[#This Row],[Mill_Unplanned_Down_h]])/cfg_HoursPerDay) | Y15: =IF(AND(NOT(AND(tblPlant[[#This Row],[Mill_Run_h]]="",tblPlant[[#This Row],[Mill_Planned_Maint_h]]="",tblPlant[[#This Row],[Mill_Unplanned_Down_h]]="")),(cfg_HoursPerDay-tblPlant[[#This Row],[Mill_Planned_Maint_h]]-tblPlant[[#This Row],[Mill_Unplanned_Down_h]])>0),tblPlant[[#This Row],[Mill_Run_h]]/(cfg_HoursPerDay-tblPlant[[#This Row],[Mill_Planned_Maint_h]]-tblPlant[[#This Row],[Mill_Unplanned_Down_h]]),"")
A16: 46033 | S16: =IF(OR(tblPlant[[#This Row],[Milled_t]]="",tblPlant[[#This Row],[Head_Grade_gpt]]=""),"",tblPlant[[#This Row],[Milled_t]]*tblPlant[[#This Row],[Head_Grade_gpt]]/cfg_TroyOz) | T16: =IF(OR(tblPlant[[#This Row],[Milled_t]]="",tblPlant[[#This Row],[Tails_Grade_gpt]]=""),"",tblPlant[[#This Row],[Milled_t]]*tblPlant[[#This Row],[Tails_Grade_gpt]]/cfg_TroyOz) | U16: =IF(OR(tblPlant[[#This Row],[Milled_t]]="",tblPlant[[#This Row],[Head_Grade_gpt]]="",tblPlant[[#This Row],[Tails_Grade_gpt]]=""),"",tblPlant[[#This Row],[Feed_oz]]-tblPlant[[#This Row],[Tails_oz]]) | V16: =IF(AND(ISNUMBER(tblPlant[[#This Row],[Recovered_oz]]),tblPlant[[#This Row],[Feed_oz]]>0),tblPlant[[#This Row],[Recovered_oz]]/tblPlant[[#This Row],[Feed_oz]],"") | W16: =IF(AND(tblPlant[[#This Row],[Milled_t]]<>"",tblPlant[[#This Row],[Mill_Run_h]]>0),tblPlant[[#This Row],[Milled_t]]/tblPlant[[#This Row],[Mill_Run_h]],"") | X16: =IF(AND(tblPlant[[#This Row],[Mill_Run_h]]="",tblPlant[[#This Row],[Mill_Planned_Maint_h]]="",tblPlant[[#This Row],[Mill_Unplanned_Down_h]]=""),"",(cfg_HoursPerDay-tblPlant[[#This Row],[Mill_Planned_Maint_h]]-tblPlant[[#This Row],[Mill_Unplanned_Down_h]])/cfg_HoursPerDay) | Y16: =IF(AND(NOT(AND(tblPlant[[#This Row],[Mill_Run_h]]="",tblPlant[[#This Row],[Mill_Planned_Maint_h]]="",tblPlant[[#This Row],[Mill_Unplanned_Down_h]]="")),(cfg_HoursPerDay-tblPlant[[#This Row],[Mill_Planned_Maint_h]]-tblPlant[[#This Row],[Mill_Unplanned_Down_h]])>0),tblPlant[[#This Row],[Mill_Run_h]]/(cfg_HoursPerDay-tblPlant[[#This Row],[Mill_Planned_Maint_h]]-tblPlant[[#This Row],[Mill_Unplanned_Down_h]]),"")
A17: 46034 | S17: =IF(OR(tblPlant[[#This Row],[Milled_t]]="",tblPlant[[#This Row],[Head_Grade_gpt]]=""),"",tblPlant[[#This Row],[Milled_t]]*tblPlant[[#This Row],[Head_Grade_gpt]]/cfg_TroyOz) | T17: =IF(OR(tblPlant[[#This Row],[Milled_t]]="",tblPlant[[#This Row],[Tails_Grade_gpt]]=""),"",tblPlant[[#This Row],[Milled_t]]*tblPlant[[#This Row],[Tails_Grade_gpt]]/cfg_TroyOz) | U17: =IF(OR(tblPlant[[#This Row],[Milled_t]]="",tblPlant[[#This Row],[Head_Grade_gpt]]="",tblPlant[[#This Row],[Tails_Grade_gpt]]=""),"",tblPlant[[#This Row],[Feed_oz]]-tblPlant[[#This Row],[Tails_oz]]) | V17: =IF(AND(ISNUMBER(tblPlant[[#This Row],[Recovered_oz]]),tblPlant[[#This Row],[Feed_oz]]>0),tblPlant[[#This Row],[Recovered_oz]]/tblPlant[[#This Row],[Feed_oz]],"") | W17: =IF(AND(tblPlant[[#This Row],[Milled_t]]<>"",tblPlant[[#This Row],[Mill_Run_h]]>0),tblPlant[[#This Row],[Milled_t]]/tblPlant[[#This Row],[Mill_Run_h]],"") | X17: =IF(AND(tblPlant[[#This Row],[Mill_Run_h]]="",tblPlant[[#This Row],[Mill_Planned_Maint_h]]="",tblPlant[[#This Row],[Mill_Unplanned_Down_h]]=""),"",(cfg_HoursPerDay-tblPlant[[#This Row],[Mill_Planned_Maint_h]]-tblPlant[[#This Row],[Mill_Unplanned_Down_h]])/cfg_HoursPerDay) | Y17: =IF(AND(NOT(AND(tblPlant[[#This Row],[Mill_Run_h]]="",tblPlant[[#This Row],[Mill_Planned_Maint_h]]="",tblPlant[[#This Row],[Mill_Unplanned_Down_h]]="")),(cfg_HoursPerDay-tblPlant[[#This Row],[Mill_Planned_Maint_h]]-tblPlant[[#This Row],[Mill_Unplanned_Down_h]])>0),tblPlant[[#This Row],[Mill_Run_h]]/(cfg_HoursPerDay-tblPlant[[#This Row],[Mill_Planned_Maint_h]]-tblPlant[[#This Row],[Mill_Unplanned_Down_h]]),"")
... A370: 46387 | S370: =IF(OR(tblPlant[[#This Row],[Milled_t]]="",tblPlant[[#This Row],[Head_Grade_gpt]]=""),"",tblPlant[[#This Row],[Milled_t]]*tblPlant[[#This Row],[Head_Grade_gpt]]/cfg_TroyOz) | T370: =IF(OR(tblPlant[[#This Row],[Milled_t]]="",tblPlant[[#This Row],[Tails_Grade_gpt]]=""),"",tblPlant[[#This Row],[Milled_t]]*tblPlant[[#This Row],[Tails_Grade_gpt]]/cfg_TroyOz) | U370: =IF(OR(tblPlant[[#This Row],[Milled_t]]="",tblPlant[[#This Row],[Head_Grade_gpt]]="",tblPlant[[#This Row],[Tails_Grade_gpt]]=""),"",tblPlant[[#This Row],[Feed_oz]]-tblPlant[[#This Row],[Tails_oz]]) | V370: =IF(AND(ISNUMBER(tblPlant[[#This Row],[Recovered_oz]]),tblPlant[[#This Row],[Feed_oz]]>0),tblPlant[[#This Row],[Recovered_oz]]/tblPlant[[#This Row],[Feed_oz]],"") | W370: =IF(AND(tblPlant[[#This Row],[Milled_t]]<>"",tblPlant[[#This Row],[Mill_Run_h]]>0),tblPlant[[#This Row],[Milled_t]]/tblPlant[[#This Row],[Mill_Run_h]],"") | X370: =IF(AND(tblPlant[[#This Row],[Mill_Run_h]]="",tblPlant[[#This Row],[Mill_Planned_Maint_h]]="",tblPlant[[#This Row],[Mill_Unplanned_Down_h]]=""),"",(cfg_HoursPerDay-tblPlant[[#This Row],[Mill_Planned_Maint_h]]-tblPlant[[#This Row],[Mill_Unplanned_Down_h]])/cfg_HoursPerDay) | Y370: =IF(AND(NOT(AND(tblPlant[[#This Row],[Mill_Run_h]]="",tblPlant[[#This Row],[Mill_Planned_Maint_h]]="",tblPlant[[#This Row],[Mill_Unplanned_Down_h]]="")),(cfg_HoursPerDay-tblPlant[[#This Row],[Mill_Planned_Maint_h]]-tblPlant[[#This Row],[Mill_Unplanned_Down_h]])>0),tblPlant[[#This Row],[Mill_Run_h]]/(cfg_HoursPerDay-tblPlant[[#This Row],[Mill_Planned_Maint_h]]-tblPlant[[#This Row],[Mill_Unplanned_Down_h]]),"")

Sheet Mining_Movements
A1: Material movements, one row per source, material and destination per day (or per shift)
A2: Owner: Mining (dispatch / production engineer). Type only in the blue-headed columns; grey-headed columns are formulas. Add rows at the bottom only; never insert columns. Paste with Paste Special > Values only. Red cells need attention (missing or unknown value, duplicate date).
A4: Date | B4: Shift | C4: Source | D4: Material | E4: Destination | F4: Tonnes (t) | G4: Grade (g/t) | H4: Volume (bcm) | I4: Truck loads | J4: Comments | K4: Source type | L4: Destination type | M4: Ore flag | N4: Contained gold (oz) | O4: Ore gold (oz)
A5: Date | B5: Shift | C5: Source | D5: Material | E5: Destination | F5: Tonnes_t | G5: Grade_gpt | H5: BCM | I5: Loads | J5: Comments | K5: Source_Type | L5: Dest_Type | M5: Is_Ore | N5: Contained_oz | O5: Ore_oz
K6: =IF(tblMovement[[#This Row],[Source]]="","",IFERROR(INDEX(tblSources[Type],MATCH(tblMovement[[#This Row],[Source]],tblSources[Source],0)),"?")) | L6: =IF(tblMovement[[#This Row],[Destination]]="","",IFERROR(INDEX(tblDestinations[Type],MATCH(tblMovement[[#This Row],[Destination]],tblDestinations[Destination],0)),"?")) | M6: =IF(tblMovement[[#This Row],[Material]]="","",IF(LEFT(tblMovement[[#This Row],[Material]],3)="Ore",1,0)) | N6: =IF(OR(tblMovement[[#This Row],[Tonnes_t]]="",tblMovement[[#This Row],[Grade_gpt]]=""),0,tblMovement[[#This Row],[Tonnes_t]]*tblMovement[[#This Row],[Grade_gpt]]/cfg_TroyOz) | O6: =IF(tblMovement[[#This Row],[Is_Ore]]=1,tblMovement[[#This Row],[Contained_oz]],0)
K7: =IF(tblMovement[[#This Row],[Source]]="","",IFERROR(INDEX(tblSources[Type],MATCH(tblMovement[[#This Row],[Source]],tblSources[Source],0)),"?")) | L7: =IF(tblMovement[[#This Row],[Destination]]="","",IFERROR(INDEX(tblDestinations[Type],MATCH(tblMovement[[#This Row],[Destination]],tblDestinations[Destination],0)),"?")) | M7: =IF(tblMovement[[#This Row],[Material]]="","",IF(LEFT(tblMovement[[#This Row],[Material]],3)="Ore",1,0)) | N7: =IF(OR(tblMovement[[#This Row],[Tonnes_t]]="",tblMovement[[#This Row],[Grade_gpt]]=""),0,tblMovement[[#This Row],[Tonnes_t]]*tblMovement[[#This Row],[Grade_gpt]]/cfg_TroyOz) | O7: =IF(tblMovement[[#This Row],[Is_Ore]]=1,tblMovement[[#This Row],[Contained_oz]],0)
K8: =IF(tblMovement[[#This Row],[Source]]="","",IFERROR(INDEX(tblSources[Type],MATCH(tblMovement[[#This Row],[Source]],tblSources[Source],0)),"?")) | L8: =IF(tblMovement[[#This Row],[Destination]]="","",IFERROR(INDEX(tblDestinations[Type],MATCH(tblMovement[[#This Row],[Destination]],tblDestinations[Destination],0)),"?")) | M8: =IF(tblMovement[[#This Row],[Material]]="","",IF(LEFT(tblMovement[[#This Row],[Material]],3)="Ore",1,0)) | N8: =IF(OR(tblMovement[[#This Row],[Tonnes_t]]="",tblMovement[[#This Row],[Grade_gpt]]=""),0,tblMovement[[#This Row],[Tonnes_t]]*tblMovement[[#This Row],[Grade_gpt]]/cfg_TroyOz) | O8: =IF(tblMovement[[#This Row],[Is_Ore]]=1,tblMovement[[#This Row],[Contained_oz]],0)
K9: =IF(tblMovement[[#This Row],[Source]]="","",IFERROR(INDEX(tblSources[Type],MATCH(tblMovement[[#This Row],[Source]],tblSources[Source],0)),"?")) | L9: =IF(tblMovement[[#This Row],[Destination]]="","",IFERROR(INDEX(tblDestinations[Type],MATCH(tblMovement[[#This Row],[Destination]],tblDestinations[Destination],0)),"?")) | M9: =IF(tblMovement[[#This Row],[Material]]="","",IF(LEFT(tblMovement[[#This Row],[Material]],3)="Ore",1,0)) | N9: =IF(OR(tblMovement[[#This Row],[Tonnes_t]]="",tblMovement[[#This Row],[Grade_gpt]]=""),0,tblMovement[[#This Row],[Tonnes_t]]*tblMovement[[#This Row],[Grade_gpt]]/cfg_TroyOz) | O9: =IF(tblMovement[[#This Row],[Is_Ore]]=1,tblMovement[[#This Row],[Contained_oz]],0)
K10: =IF(tblMovement[[#This Row],[Source]]="","",IFERROR(INDEX(tblSources[Type],MATCH(tblMovement[[#This Row],[Source]],tblSources[Source],0)),"?")) | L10: =IF(tblMovement[[#This Row],[Destination]]="","",IFERROR(INDEX(tblDestinations[Type],MATCH(tblMovement[[#This Row],[Destination]],tblDestinations[Destination],0)),"?")) | M10: =IF(tblMovement[[#This Row],[Material]]="","",IF(LEFT(tblMovement[[#This Row],[Material]],3)="Ore",1,0)) | N10: =IF(OR(tblMovement[[#This Row],[Tonnes_t]]="",tblMovement[[#This Row],[Grade_gpt]]=""),0,tblMovement[[#This Row],[Tonnes_t]]*tblMovement[[#This Row],[Grade_gpt]]/cfg_TroyOz) | O10: =IF(tblMovement[[#This Row],[Is_Ore]]=1,tblMovement[[#This Row],[Contained_oz]],0)
K11: =IF(tblMovement[[#This Row],[Source]]="","",IFERROR(INDEX(tblSources[Type],MATCH(tblMovement[[#This Row],[Source]],tblSources[Source],0)),"?")) | L11: =IF(tblMovement[[#This Row],[Destination]]="","",IFERROR(INDEX(tblDestinations[Type],MATCH(tblMovement[[#This Row],[Destination]],tblDestinations[Destination],0)),"?")) | M11: =IF(tblMovement[[#This Row],[Material]]="","",IF(LEFT(tblMovement[[#This Row],[Material]],3)="Ore",1,0)) | N11: =IF(OR(tblMovement[[#This Row],[Tonnes_t]]="",tblMovement[[#This Row],[Grade_gpt]]=""),0,tblMovement[[#This Row],[Tonnes_t]]*tblMovement[[#This Row],[Grade_gpt]]/cfg_TroyOz) | O11: =IF(tblMovement[[#This Row],[Is_Ore]]=1,tblMovement[[#This Row],[Contained_oz]],0)
K12: =IF(tblMovement[[#This Row],[Source]]="","",IFERROR(INDEX(tblSources[Type],MATCH(tblMovement[[#This Row],[Source]],tblSources[Source],0)),"?")) | L12: =IF(tblMovement[[#This Row],[Destination]]="","",IFERROR(INDEX(tblDestinations[Type],MATCH(tblMovement[[#This Row],[Destination]],tblDestinations[Destination],0)),"?")) | M12: =IF(tblMovement[[#This Row],[Material]]="","",IF(LEFT(tblMovement[[#This Row],[Material]],3)="Ore",1,0)) | N12: =IF(OR(tblMovement[[#This Row],[Tonnes_t]]="",tblMovement[[#This Row],[Grade_gpt]]=""),0,tblMovement[[#This Row],[Tonnes_t]]*tblMovement[[#This Row],[Grade_gpt]]/cfg_TroyOz) | O12: =IF(tblMovement[[#This Row],[Is_Ore]]=1,tblMovement[[#This Row],[Contained_oz]],0)
K13: =IF(tblMovement[[#This Row],[Source]]="","",IFERROR(INDEX(tblSources[Type],MATCH(tblMovement[[#This Row],[Source]],tblSources[Source],0)),"?")) | L13: =IF(tblMovement[[#This Row],[Destination]]="","",IFERROR(INDEX(tblDestinations[Type],MATCH(tblMovement[[#This Row],[Destination]],tblDestinations[Destination],0)),"?")) | M13: =IF(tblMovement[[#This Row],[Material]]="","",IF(LEFT(tblMovement[[#This Row],[Material]],3)="Ore",1,0)) | N13: =IF(OR(tblMovement[[#This Row],[Tonnes_t]]="",tblMovement[[#This Row],[Grade_gpt]]=""),0,tblMovement[[#This Row],[Tonnes_t]]*tblMovement[[#This Row],[Grade_gpt]]/cfg_TroyOz) | O13: =IF(tblMovement[[#This Row],[Is_Ore]]=1,tblMovement[[#This Row],[Contained_oz]],0)
K14: =IF(tblMovement[[#This Row],[Source]]="","",IFERROR(INDEX(tblSources[Type],MATCH(tblMovement[[#This Row],[Source]],tblSources[Source],0)),"?")) | L14: =IF(tblMovement[[#This Row],[Destination]]="","",IFERROR(INDEX(tblDestinations[Type],MATCH(tblMovement[[#This Row],[Destination]],tblDestinations[Destination],0)),"?")) | M14: =IF(tblMovement[[#This Row],[Material]]="","",IF(LEFT(tblMovement[[#This Row],[Material]],3)="Ore",1,0)) | N14: =IF(OR(tblMovement[[#This Row],[Tonnes_t]]="",tblMovement[[#This Row],[Grade_gpt]]=""),0,tblMovement[[#This Row],[Tonnes_t]]*tblMovement[[#This Row],[Grade_gpt]]/cfg_TroyOz) | O14: =IF(tblMovement[[#This Row],[Is_Ore]]=1,tblMovement[[#This Row],[Contained_oz]],0)
K15: =IF(tblMovement[[#This Row],[Source]]="","",IFERROR(INDEX(tblSources[Type],MATCH(tblMovement[[#This Row],[Source]],tblSources[Source],0)),"?")) | L15: =IF(tblMovement[[#This Row],[Destination]]="","",IFERROR(INDEX(tblDestinations[Type],MATCH(tblMovement[[#This Row],[Destination]],tblDestinations[Destination],0)),"?")) | M15: =IF(tblMovement[[#This Row],[Material]]="","",IF(LEFT(tblMovement[[#This Row],[Material]],3)="Ore",1,0)) | N15: =IF(OR(tblMovement[[#This Row],[Tonnes_t]]="",tblMovement[[#This Row],[Grade_gpt]]=""),0,tblMovement[[#This Row],[Tonnes_t]]*tblMovement[[#This Row],[Grade_gpt]]/cfg_TroyOz) | O15: =IF(tblMovement[[#This Row],[Is_Ore]]=1,tblMovement[[#This Row],[Contained_oz]],0)
K16: =IF(tblMovement[[#This Row],[Source]]="","",IFERROR(INDEX(tblSources[Type],MATCH(tblMovement[[#This Row],[Source]],tblSources[Source],0)),"?")) | L16: =IF(tblMovement[[#This Row],[Destination]]="","",IFERROR(INDEX(tblDestinations[Type],MATCH(tblMovement[[#This Row],[Destination]],tblDestinations[Destination],0)),"?")) | M16: =IF(tblMovement[[#This Row],[Material]]="","",IF(LEFT(tblMovement[[#This Row],[Material]],3)="Ore",1,0)) | N16: =IF(OR(tblMovement[[#This Row],[Tonnes_t]]="",tblMovement[[#This Row],[Grade_gpt]]=""),0,tblMovement[[#This Row],[Tonnes_t]]*tblMovement[[#This Row],[Grade_gpt]]/cfg_TroyOz) | O16: =IF(tblMovement[[#This Row],[Is_Ore]]=1,tblMovement[[#This Row],[Contained_oz]],0)
K17: =IF(tblMovement[[#This Row],[Source]]="","",IFERROR(INDEX(tblSources[Type],MATCH(tblMovement[[#This Row],[Source]],tblSources[Source],0)),"?")) | L17: =IF(tblMovement[[#This Row],[Destination]]="","",IFERROR(INDEX(tblDestinations[Type],MATCH(tblMovement[[#This Row],[Destination]],tblDestinations[Destination],0)),"?")) | M17: =IF(tblMovement[[#This Row],[Material]]="","",IF(LEFT(tblMovement[[#This Row],[Material]],3)="Ore",1,0)) | N17: =IF(OR(tblMovement[[#This Row],[Tonnes_t]]="",tblMovement[[#This Row],[Grade_gpt]]=""),0,tblMovement[[#This Row],[Tonnes_t]]*tblMovement[[#This Row],[Grade_gpt]]/cfg_TroyOz) | O17: =IF(tblMovement[[#This Row],[Is_Ore]]=1,tblMovement[[#This Row],[Contained_oz]],0)
... K5005: =IF(tblMovement[[#This Row],[Source]]="","",IFERROR(INDEX(tblSources[Type],MATCH(tblMovement[[#This Row],[Source]],tblSources[Source],0)),"?")) | L5005: =IF(tblMovement[[#This Row],[Destination]]="","",IFERROR(INDEX(tblDestinations[Type],MATCH(tblMovement[[#This Row],[Destination]],tblDestinations[Destination],0)),"?")) | M5005: =IF(tblMovement[[#This Row],[Material]]="","",IF(LEFT(tblMovement[[#This Row],[Material]],3)="Ore",1,0)) | N5005: =IF(OR(tblMovement[[#This Row],[Tonnes_t]]="",tblMovement[[#This Row],[Grade_gpt]]=""),0,tblMovement[[#This Row],[Tonnes_t]]*tblMovement[[#This Row],[Grade_gpt]]/cfg_TroyOz) | O5005: =IF(tblMovement[[#This Row],[Is_Ore]]=1,tblMovement[[#This Row],[Contained_oz]],0)

Sheet Mining_Daily
A1: Mining daily totals, one row per day
A2: Owner: Mining (production engineer). Type only in the blue-headed columns; grey-headed columns are formulas. Add rows at the bottom only; never insert columns. Paste with Paste Special > Values only. Red cells need attention (missing or unknown value, duplicate date).
A4: Date | B4: Drilled (m) | C4: Grade control drilled (m) | D4: Blasted (t) | E4: Explosives (kg) | F4: Diesel (L) | G4: Dewatering (m3) | H4: Comments | I4: Powder factor (kg/t)
A5: Date | B5: Drill_m | C5: GC_Drill_m | D5: Blast_t | E5: Explosives_kg | F5: Diesel_L | G5: Dewatering_m3 | H5: Comments | I5: Powder_Factor_kgpt
A6: 46023 | I6: =IF(AND(tblMiningDaily[[#This Row],[Blast_t]]<>"",tblMiningDaily[[#This Row],[Blast_t]]>0),tblMiningDaily[[#This Row],[Explosives_kg]]/tblMiningDaily[[#This Row],[Blast_t]],"")
A7: 46024 | I7: =IF(AND(tblMiningDaily[[#This Row],[Blast_t]]<>"",tblMiningDaily[[#This Row],[Blast_t]]>0),tblMiningDaily[[#This Row],[Explosives_kg]]/tblMiningDaily[[#This Row],[Blast_t]],"")
A8: 46025 | I8: =IF(AND(tblMiningDaily[[#This Row],[Blast_t]]<>"",tblMiningDaily[[#This Row],[Blast_t]]>0),tblMiningDaily[[#This Row],[Explosives_kg]]/tblMiningDaily[[#This Row],[Blast_t]],"")
A9: 46026 | I9: =IF(AND(tblMiningDaily[[#This Row],[Blast_t]]<>"",tblMiningDaily[[#This Row],[Blast_t]]>0),tblMiningDaily[[#This Row],[Explosives_kg]]/tblMiningDaily[[#This Row],[Blast_t]],"")
A10: 46027 | I10: =IF(AND(tblMiningDaily[[#This Row],[Blast_t]]<>"",tblMiningDaily[[#This Row],[Blast_t]]>0),tblMiningDaily[[#This Row],[Explosives_kg]]/tblMiningDaily[[#This Row],[Blast_t]],"")
A11: 46028 | I11: =IF(AND(tblMiningDaily[[#This Row],[Blast_t]]<>"",tblMiningDaily[[#This Row],[Blast_t]]>0),tblMiningDaily[[#This Row],[Explosives_kg]]/tblMiningDaily[[#This Row],[Blast_t]],"")
A12: 46029 | I12: =IF(AND(tblMiningDaily[[#This Row],[Blast_t]]<>"",tblMiningDaily[[#This Row],[Blast_t]]>0),tblMiningDaily[[#This Row],[Explosives_kg]]/tblMiningDaily[[#This Row],[Blast_t]],"")
A13: 46030 | I13: =IF(AND(tblMiningDaily[[#This Row],[Blast_t]]<>"",tblMiningDaily[[#This Row],[Blast_t]]>0),tblMiningDaily[[#This Row],[Explosives_kg]]/tblMiningDaily[[#This Row],[Blast_t]],"")
A14: 46031 | I14: =IF(AND(tblMiningDaily[[#This Row],[Blast_t]]<>"",tblMiningDaily[[#This Row],[Blast_t]]>0),tblMiningDaily[[#This Row],[Explosives_kg]]/tblMiningDaily[[#This Row],[Blast_t]],"")
A15: 46032 | I15: =IF(AND(tblMiningDaily[[#This Row],[Blast_t]]<>"",tblMiningDaily[[#This Row],[Blast_t]]>0),tblMiningDaily[[#This Row],[Explosives_kg]]/tblMiningDaily[[#This Row],[Blast_t]],"")
A16: 46033 | I16: =IF(AND(tblMiningDaily[[#This Row],[Blast_t]]<>"",tblMiningDaily[[#This Row],[Blast_t]]>0),tblMiningDaily[[#This Row],[Explosives_kg]]/tblMiningDaily[[#This Row],[Blast_t]],"")
A17: 46034 | I17: =IF(AND(tblMiningDaily[[#This Row],[Blast_t]]<>"",tblMiningDaily[[#This Row],[Blast_t]]>0),tblMiningDaily[[#This Row],[Explosives_kg]]/tblMiningDaily[[#This Row],[Blast_t]],"")
... A370: 46387 | I370: =IF(AND(tblMiningDaily[[#This Row],[Blast_t]]<>"",tblMiningDaily[[#This Row],[Blast_t]]>0),tblMiningDaily[[#This Row],[Explosives_kg]]/tblMiningDaily[[#This Row],[Blast_t]],"")

Sheet Fleet
A1: Mining fleet time model, one row per equipment class per day
A2: Owner: Mining (dispatch / maintenance planner). Type only in the blue-headed columns; grey-headed columns are formulas. Add rows at the bottom only; never insert columns. Paste with Paste Special > Values only. Red cells need attention (missing or unknown value, duplicate date).
A4: Date | B4: Equipment class | C4: Units in fleet | D4: Down hours (h) | E4: Operating hours (h) | F4: Comments | G4: Calendar hours (h) | H4: Available hours (h) | I4: Availability (%) | J4: Utilisation (%)
A5: Date | B5: Equipment_Class | C5: Units | D5: Down_h | E5: Operating_h | F5: Comments | G5: Calendar_h | H5: Available_h | I5: Availability_pct | J5: Utilisation_pct
G6: =IF(tblFleet[[#This Row],[Units]]="","",tblFleet[[#This Row],[Units]]*cfg_HoursPerDay) | H6: =IF(tblFleet[[#This Row],[Units]]="","",tblFleet[[#This Row],[Calendar_h]]-tblFleet[[#This Row],[Down_h]]) | I6: =IF(AND(tblFleet[[#This Row],[Units]]<>"",tblFleet[[#This Row],[Calendar_h]]>0),tblFleet[[#This Row],[Available_h]]/tblFleet[[#This Row],[Calendar_h]],"") | J6: =IF(AND(tblFleet[[#This Row],[Units]]<>"",tblFleet[[#This Row],[Available_h]]>0),tblFleet[[#This Row],[Operating_h]]/tblFleet[[#This Row],[Available_h]],"")
G7: =IF(tblFleet[[#This Row],[Units]]="","",tblFleet[[#This Row],[Units]]*cfg_HoursPerDay) | H7: =IF(tblFleet[[#This Row],[Units]]="","",tblFleet[[#This Row],[Calendar_h]]-tblFleet[[#This Row],[Down_h]]) | I7: =IF(AND(tblFleet[[#This Row],[Units]]<>"",tblFleet[[#This Row],[Calendar_h]]>0),tblFleet[[#This Row],[Available_h]]/tblFleet[[#This Row],[Calendar_h]],"") | J7: =IF(AND(tblFleet[[#This Row],[Units]]<>"",tblFleet[[#This Row],[Available_h]]>0),tblFleet[[#This Row],[Operating_h]]/tblFleet[[#This Row],[Available_h]],"")
G8: =IF(tblFleet[[#This Row],[Units]]="","",tblFleet[[#This Row],[Units]]*cfg_HoursPerDay) | H8: =IF(tblFleet[[#This Row],[Units]]="","",tblFleet[[#This Row],[Calendar_h]]-tblFleet[[#This Row],[Down_h]]) | I8: =IF(AND(tblFleet[[#This Row],[Units]]<>"",tblFleet[[#This Row],[Calendar_h]]>0),tblFleet[[#This Row],[Available_h]]/tblFleet[[#This Row],[Calendar_h]],"") | J8: =IF(AND(tblFleet[[#This Row],[Units]]<>"",tblFleet[[#This Row],[Available_h]]>0),tblFleet[[#This Row],[Operating_h]]/tblFleet[[#This Row],[Available_h]],"")
G9: =IF(tblFleet[[#This Row],[Units]]="","",tblFleet[[#This Row],[Units]]*cfg_HoursPerDay) | H9: =IF(tblFleet[[#This Row],[Units]]="","",tblFleet[[#This Row],[Calendar_h]]-tblFleet[[#This Row],[Down_h]]) | I9: =IF(AND(tblFleet[[#This Row],[Units]]<>"",tblFleet[[#This Row],[Calendar_h]]>0),tblFleet[[#This Row],[Available_h]]/tblFleet[[#This Row],[Calendar_h]],"") | J9: =IF(AND(tblFleet[[#This Row],[Units]]<>"",tblFleet[[#This Row],[Available_h]]>0),tblFleet[[#This Row],[Operating_h]]/tblFleet[[#This Row],[Available_h]],"")
G10: =IF(tblFleet[[#This Row],[Units]]="","",tblFleet[[#This Row],[Units]]*cfg_HoursPerDay) | H10: =IF(tblFleet[[#This Row],[Units]]="","",tblFleet[[#This Row],[Calendar_h]]-tblFleet[[#This Row],[Down_h]]) | I10: =IF(AND(tblFleet[[#This Row],[Units]]<>"",tblFleet[[#This Row],[Calendar_h]]>0),tblFleet[[#This Row],[Available_h]]/tblFleet[[#This Row],[Calendar_h]],"") | J10: =IF(AND(tblFleet[[#This Row],[Units]]<>"",tblFleet[[#This Row],[Available_h]]>0),tblFleet[[#This Row],[Operating_h]]/tblFleet[[#This Row],[Available_h]],"")
G11: =IF(tblFleet[[#This Row],[Units]]="","",tblFleet[[#This Row],[Units]]*cfg_HoursPerDay) | H11: =IF(tblFleet[[#This Row],[Units]]="","",tblFleet[[#This Row],[Calendar_h]]-tblFleet[[#This Row],[Down_h]]) | I11: =IF(AND(tblFleet[[#This Row],[Units]]<>"",tblFleet[[#This Row],[Calendar_h]]>0),tblFleet[[#This Row],[Available_h]]/tblFleet[[#This Row],[Calendar_h]],"") | J11: =IF(AND(tblFleet[[#This Row],[Units]]<>"",tblFleet[[#This Row],[Available_h]]>0),tblFleet[[#This Row],[Operating_h]]/tblFleet[[#This Row],[Available_h]],"")
G12: =IF(tblFleet[[#This Row],[Units]]="","",tblFleet[[#This Row],[Units]]*cfg_HoursPerDay) | H12: =IF(tblFleet[[#This Row],[Units]]="","",tblFleet[[#This Row],[Calendar_h]]-tblFleet[[#This Row],[Down_h]]) | I12: =IF(AND(tblFleet[[#This Row],[Units]]<>"",tblFleet[[#This Row],[Calendar_h]]>0),tblFleet[[#This Row],[Available_h]]/tblFleet[[#This Row],[Calendar_h]],"") | J12: =IF(AND(tblFleet[[#This Row],[Units]]<>"",tblFleet[[#This Row],[Available_h]]>0),tblFleet[[#This Row],[Operating_h]]/tblFleet[[#This Row],[Available_h]],"")
G13: =IF(tblFleet[[#This Row],[Units]]="","",tblFleet[[#This Row],[Units]]*cfg_HoursPerDay) | H13: =IF(tblFleet[[#This Row],[Units]]="","",tblFleet[[#This Row],[Calendar_h]]-tblFleet[[#This Row],[Down_h]]) | I13: =IF(AND(tblFleet[[#This Row],[Units]]<>"",tblFleet[[#This Row],[Calendar_h]]>0),tblFleet[[#This Row],[Available_h]]/tblFleet[[#This Row],[Calendar_h]],"") | J13: =IF(AND(tblFleet[[#This Row],[Units]]<>"",tblFleet[[#This Row],[Available_h]]>0),tblFleet[[#This Row],[Operating_h]]/tblFleet[[#This Row],[Available_h]],"")
G14: =IF(tblFleet[[#This Row],[Units]]="","",tblFleet[[#This Row],[Units]]*cfg_HoursPerDay) | H14: =IF(tblFleet[[#This Row],[Units]]="","",tblFleet[[#This Row],[Calendar_h]]-tblFleet[[#This Row],[Down_h]]) | I14: =IF(AND(tblFleet[[#This Row],[Units]]<>"",tblFleet[[#This Row],[Calendar_h]]>0),tblFleet[[#This Row],[Available_h]]/tblFleet[[#This Row],[Calendar_h]],"") | J14: =IF(AND(tblFleet[[#This Row],[Units]]<>"",tblFleet[[#This Row],[Available_h]]>0),tblFleet[[#This Row],[Operating_h]]/tblFleet[[#This Row],[Available_h]],"")
G15: =IF(tblFleet[[#This Row],[Units]]="","",tblFleet[[#This Row],[Units]]*cfg_HoursPerDay) | H15: =IF(tblFleet[[#This Row],[Units]]="","",tblFleet[[#This Row],[Calendar_h]]-tblFleet[[#This Row],[Down_h]]) | I15: =IF(AND(tblFleet[[#This Row],[Units]]<>"",tblFleet[[#This Row],[Calendar_h]]>0),tblFleet[[#This Row],[Available_h]]/tblFleet[[#This Row],[Calendar_h]],"") | J15: =IF(AND(tblFleet[[#This Row],[Units]]<>"",tblFleet[[#This Row],[Available_h]]>0),tblFleet[[#This Row],[Operating_h]]/tblFleet[[#This Row],[Available_h]],"")
G16: =IF(tblFleet[[#This Row],[Units]]="","",tblFleet[[#This Row],[Units]]*cfg_HoursPerDay) | H16: =IF(tblFleet[[#This Row],[Units]]="","",tblFleet[[#This Row],[Calendar_h]]-tblFleet[[#This Row],[Down_h]]) | I16: =IF(AND(tblFleet[[#This Row],[Units]]<>"",tblFleet[[#This Row],[Calendar_h]]>0),tblFleet[[#This Row],[Available_h]]/tblFleet[[#This Row],[Calendar_h]],"") | J16: =IF(AND(tblFleet[[#This Row],[Units]]<>"",tblFleet[[#This Row],[Available_h]]>0),tblFleet[[#This Row],[Operating_h]]/tblFleet[[#This Row],[Available_h]],"")
G17: =IF(tblFleet[[#This Row],[Units]]="","",tblFleet[[#This Row],[Units]]*cfg_HoursPerDay) | H17: =IF(tblFleet[[#This Row],[Units]]="","",tblFleet[[#This Row],[Calendar_h]]-tblFleet[[#This Row],[Down_h]]) | I17: =IF(AND(tblFleet[[#This Row],[Units]]<>"",tblFleet[[#This Row],[Calendar_h]]>0),tblFleet[[#This Row],[Available_h]]/tblFleet[[#This Row],[Calendar_h]],"") | J17: =IF(AND(tblFleet[[#This Row],[Units]]<>"",tblFleet[[#This Row],[Available_h]]>0),tblFleet[[#This Row],[Operating_h]]/tblFleet[[#This Row],[Available_h]],"")
... G3005: =IF(tblFleet[[#This Row],[Units]]="","",tblFleet[[#This Row],[Units]]*cfg_HoursPerDay) | H3005: =IF(tblFleet[[#This Row],[Units]]="","",tblFleet[[#This Row],[Calendar_h]]-tblFleet[[#This Row],[Down_h]]) | I3005: =IF(AND(tblFleet[[#This Row],[Units]]<>"",tblFleet[[#This Row],[Calendar_h]]>0),tblFleet[[#This Row],[Available_h]]/tblFleet[[#This Row],[Calendar_h]],"") | J3005: =IF(AND(tblFleet[[#This Row],[Units]]<>"",tblFleet[[#This Row],[Available_h]]>0),tblFleet[[#This Row],[Operating_h]]/tblFleet[[#This Row],[Available_h]],"")

Sheet Safety
A1: Safety, health, environment and community, one row per day
A2: Owner: HSE. Type only in the blue-headed columns; grey-headed columns are formulas. Add rows at the bottom only; never insert columns. Paste with Paste Special > Values only. Red cells need attention (missing or unknown value, duplicate date).
A4: Date | B4: Hours worked, employees (h) | C4: Hours worked, contractors (h) | D4: Fatalities | E4: Lost time injuries | F4: Restricted work injuries | G4: Medical treatment injuries | H4: First aid injuries | I4: Near misses | J4: Hazard reports | K4: High potential incidents | L4: Environmental incidents | M4: Community incidents or grievances | N4: Vehicle incidents | O4: Toolbox talks | P4: Inspections and audits | Q4: Comments | R4: Hours worked, total (h) | S4: Recordable injuries
A5: Date | B5: Hours_Employees | C5: Hours_Contractors | D5: Fatality | E5: LTI | F5: RWI | G5: MTI | H5: FAI | I5: Near_Miss | J5: Hazard_Reports | K5: HPI | L5: Env_Incidents | M5: Community_Incidents | N5: Vehicle_Incidents | O5: Toolbox_Talks | P5: Inspections | Q5: Comments | R5: Hours_Total | S5: Recordables
A6: 46023 | R6: =IF(AND(tblSafety[[#This Row],[Hours_Employees]]="",tblSafety[[#This Row],[Hours_Contractors]]=""),"",N(tblSafety[[#This Row],[Hours_Employees]])+N(tblSafety[[#This Row],[Hours_Contractors]])) | S6: =IF(AND(tblSafety[[#This Row],[Fatality]]="",tblSafety[[#This Row],[LTI]]="",tblSafety[[#This Row],[RWI]]="",tblSafety[[#This Row],[MTI]]=""),"",N(tblSafety[[#This Row],[Fatality]])+N(tblSafety[[#This Row],[LTI]])+N(tblSafety[[#This Row],[RWI]])+N(tblSafety[[#This Row],[MTI]]))
A7: 46024 | R7: =IF(AND(tblSafety[[#This Row],[Hours_Employees]]="",tblSafety[[#This Row],[Hours_Contractors]]=""),"",N(tblSafety[[#This Row],[Hours_Employees]])+N(tblSafety[[#This Row],[Hours_Contractors]])) | S7: =IF(AND(tblSafety[[#This Row],[Fatality]]="",tblSafety[[#This Row],[LTI]]="",tblSafety[[#This Row],[RWI]]="",tblSafety[[#This Row],[MTI]]=""),"",N(tblSafety[[#This Row],[Fatality]])+N(tblSafety[[#This Row],[LTI]])+N(tblSafety[[#This Row],[RWI]])+N(tblSafety[[#This Row],[MTI]]))
A8: 46025 | R8: =IF(AND(tblSafety[[#This Row],[Hours_Employees]]="",tblSafety[[#This Row],[Hours_Contractors]]=""),"",N(tblSafety[[#This Row],[Hours_Employees]])+N(tblSafety[[#This Row],[Hours_Contractors]])) | S8: =IF(AND(tblSafety[[#This Row],[Fatality]]="",tblSafety[[#This Row],[LTI]]="",tblSafety[[#This Row],[RWI]]="",tblSafety[[#This Row],[MTI]]=""),"",N(tblSafety[[#This Row],[Fatality]])+N(tblSafety[[#This Row],[LTI]])+N(tblSafety[[#This Row],[RWI]])+N(tblSafety[[#This Row],[MTI]]))
A9: 46026 | R9: =IF(AND(tblSafety[[#This Row],[Hours_Employees]]="",tblSafety[[#This Row],[Hours_Contractors]]=""),"",N(tblSafety[[#This Row],[Hours_Employees]])+N(tblSafety[[#This Row],[Hours_Contractors]])) | S9: =IF(AND(tblSafety[[#This Row],[Fatality]]="",tblSafety[[#This Row],[LTI]]="",tblSafety[[#This Row],[RWI]]="",tblSafety[[#This Row],[MTI]]=""),"",N(tblSafety[[#This Row],[Fatality]])+N(tblSafety[[#This Row],[LTI]])+N(tblSafety[[#This Row],[RWI]])+N(tblSafety[[#This Row],[MTI]]))
A10: 46027 | R10: =IF(AND(tblSafety[[#This Row],[Hours_Employees]]="",tblSafety[[#This Row],[Hours_Contractors]]=""),"",N(tblSafety[[#This Row],[Hours_Employees]])+N(tblSafety[[#This Row],[Hours_Contractors]])) | S10: =IF(AND(tblSafety[[#This Row],[Fatality]]="",tblSafety[[#This Row],[LTI]]="",tblSafety[[#This Row],[RWI]]="",tblSafety[[#This Row],[MTI]]=""),"",N(tblSafety[[#This Row],[Fatality]])+N(tblSafety[[#This Row],[LTI]])+N(tblSafety[[#This Row],[RWI]])+N(tblSafety[[#This Row],[MTI]]))
A11: 46028 | R11: =IF(AND(tblSafety[[#This Row],[Hours_Employees]]="",tblSafety[[#This Row],[Hours_Contractors]]=""),"",N(tblSafety[[#This Row],[Hours_Employees]])+N(tblSafety[[#This Row],[Hours_Contractors]])) | S11: =IF(AND(tblSafety[[#This Row],[Fatality]]="",tblSafety[[#This Row],[LTI]]="",tblSafety[[#This Row],[RWI]]="",tblSafety[[#This Row],[MTI]]=""),"",N(tblSafety[[#This Row],[Fatality]])+N(tblSafety[[#This Row],[LTI]])+N(tblSafety[[#This Row],[RWI]])+N(tblSafety[[#This Row],[MTI]]))
A12: 46029 | R12: =IF(AND(tblSafety[[#This Row],[Hours_Employees]]="",tblSafety[[#This Row],[Hours_Contractors]]=""),"",N(tblSafety[[#This Row],[Hours_Employees]])+N(tblSafety[[#This Row],[Hours_Contractors]])) | S12: =IF(AND(tblSafety[[#This Row],[Fatality]]="",tblSafety[[#This Row],[LTI]]="",tblSafety[[#This Row],[RWI]]="",tblSafety[[#This Row],[MTI]]=""),"",N(tblSafety[[#This Row],[Fatality]])+N(tblSafety[[#This Row],[LTI]])+N(tblSafety[[#This Row],[RWI]])+N(tblSafety[[#This Row],[MTI]]))
A13: 46030 | R13: =IF(AND(tblSafety[[#This Row],[Hours_Employees]]="",tblSafety[[#This Row],[Hours_Contractors]]=""),"",N(tblSafety[[#This Row],[Hours_Employees]])+N(tblSafety[[#This Row],[Hours_Contractors]])) | S13: =IF(AND(tblSafety[[#This Row],[Fatality]]="",tblSafety[[#This Row],[LTI]]="",tblSafety[[#This Row],[RWI]]="",tblSafety[[#This Row],[MTI]]=""),"",N(tblSafety[[#This Row],[Fatality]])+N(tblSafety[[#This Row],[LTI]])+N(tblSafety[[#This Row],[RWI]])+N(tblSafety[[#This Row],[MTI]]))
A14: 46031 | R14: =IF(AND(tblSafety[[#This Row],[Hours_Employees]]="",tblSafety[[#This Row],[Hours_Contractors]]=""),"",N(tblSafety[[#This Row],[Hours_Employees]])+N(tblSafety[[#This Row],[Hours_Contractors]])) | S14: =IF(AND(tblSafety[[#This Row],[Fatality]]="",tblSafety[[#This Row],[LTI]]="",tblSafety[[#This Row],[RWI]]="",tblSafety[[#This Row],[MTI]]=""),"",N(tblSafety[[#This Row],[Fatality]])+N(tblSafety[[#This Row],[LTI]])+N(tblSafety[[#This Row],[RWI]])+N(tblSafety[[#This Row],[MTI]]))
A15: 46032 | R15: =IF(AND(tblSafety[[#This Row],[Hours_Employees]]="",tblSafety[[#This Row],[Hours_Contractors]]=""),"",N(tblSafety[[#This Row],[Hours_Employees]])+N(tblSafety[[#This Row],[Hours_Contractors]])) | S15: =IF(AND(tblSafety[[#This Row],[Fatality]]="",tblSafety[[#This Row],[LTI]]="",tblSafety[[#This Row],[RWI]]="",tblSafety[[#This Row],[MTI]]=""),"",N(tblSafety[[#This Row],[Fatality]])+N(tblSafety[[#This Row],[LTI]])+N(tblSafety[[#This Row],[RWI]])+N(tblSafety[[#This Row],[MTI]]))
A16: 46033 | R16: =IF(AND(tblSafety[[#This Row],[Hours_Employees]]="",tblSafety[[#This Row],[Hours_Contractors]]=""),"",N(tblSafety[[#This Row],[Hours_Employees]])+N(tblSafety[[#This Row],[Hours_Contractors]])) | S16: =IF(AND(tblSafety[[#This Row],[Fatality]]="",tblSafety[[#This Row],[LTI]]="",tblSafety[[#This Row],[RWI]]="",tblSafety[[#This Row],[MTI]]=""),"",N(tblSafety[[#This Row],[Fatality]])+N(tblSafety[[#This Row],[LTI]])+N(tblSafety[[#This Row],[RWI]])+N(tblSafety[[#This Row],[MTI]]))
A17: 46034 | R17: =IF(AND(tblSafety[[#This Row],[Hours_Employees]]="",tblSafety[[#This Row],[Hours_Contractors]]=""),"",N(tblSafety[[#This Row],[Hours_Employees]])+N(tblSafety[[#This Row],[Hours_Contractors]])) | S17: =IF(AND(tblSafety[[#This Row],[Fatality]]="",tblSafety[[#This Row],[LTI]]="",tblSafety[[#This Row],[RWI]]="",tblSafety[[#This Row],[MTI]]=""),"",N(tblSafety[[#This Row],[Fatality]])+N(tblSafety[[#This Row],[LTI]])+N(tblSafety[[#This Row],[RWI]])+N(tblSafety[[#This Row],[MTI]]))
... A370: 46387 | R370: =IF(AND(tblSafety[[#This Row],[Hours_Employees]]="",tblSafety[[#This Row],[Hours_Contractors]]=""),"",N(tblSafety[[#This Row],[Hours_Employees]])+N(tblSafety[[#This Row],[Hours_Contractors]])) | S370: =IF(AND(tblSafety[[#This Row],[Fatality]]="",tblSafety[[#This Row],[LTI]]="",tblSafety[[#This Row],[RWI]]="",tblSafety[[#This Row],[MTI]]=""),"",N(tblSafety[[#This Row],[Fatality]])+N(tblSafety[[#This Row],[LTI]])+N(tblSafety[[#This Row],[RWI]])+N(tblSafety[[#This Row],[MTI]]))

Sheet Gold
A1: Gold shipments and sales
A2: Owner: Finance / gold room. Type only in the blue-headed columns; grey-headed columns are formulas. Add rows at the bottom only; never insert columns. Paste with Paste Special > Values only. Red cells need attention (missing or unknown value, duplicate date).
A4: Date | B4: Type | C4: Dore weight (kg) | D4: Gold (oz) | E4: Silver (oz) | F4: Reference | G4: Comments
A5: Date | B5: Type | C5: Dore_kg | D5: Gold_oz | E5: Silver_oz | F5: Reference | G5: Comments

Sheet Budget
A1: Monthly budget (or latest forecast), one row per month
A2: Owner: Technical services / finance. Type only in the blue-headed columns; grey-headed columns are formulas. Add rows at the bottom only; never insert columns. Paste with Paste Special > Values only. Red cells need attention (missing or unknown value, duplicate date).
A4: Month | B4: Ore mined (t) | C4: Ore grade mined (g/t) | D4: Waste mined (t) | E4: Milled (t) | F4: Head grade (g/t) | G4: Recovery (%) | H4: Gold poured (oz) | I4: Hours worked (h) | J4: Drilled (m) | K4: Mining diesel (L) | L4: Days in month | M4: Ore gold mined (oz) | N4: Total material moved (t) | O4: Contained gold in feed (oz) | P4: Gold recovered (oz)
A5: Month | B5: Ore_Mined_t | C5: Ore_Grade_gpt | D5: Waste_t | E5: Milled_t | F5: Head_Grade_gpt | G5: Recovery_pct | H5: Gold_Poured_oz | I5: Hours_Worked | J5: Drill_m | K5: Diesel_L | L5: Days | M5: Ore_oz | N5: TMM_t | O5: Feed_oz | P5: Recovered_oz
A6: 46023 | L6: =DAY(EOMONTH(tblBudget[[#This Row],[Month]],0)) | M6: =N(tblBudget[[#This Row],[Ore_Mined_t]])*N(tblBudget[[#This Row],[Ore_Grade_gpt]])/cfg_TroyOz | N6: =N(tblBudget[[#This Row],[Ore_Mined_t]])+N(tblBudget[[#This Row],[Waste_t]]) | O6: =N(tblBudget[[#This Row],[Milled_t]])*N(tblBudget[[#This Row],[Head_Grade_gpt]])/cfg_TroyOz | P6: =tblBudget[[#This Row],[Feed_oz]]*N(tblBudget[[#This Row],[Recovery_pct]])
A7: 46054 | L7: =DAY(EOMONTH(tblBudget[[#This Row],[Month]],0)) | M7: =N(tblBudget[[#This Row],[Ore_Mined_t]])*N(tblBudget[[#This Row],[Ore_Grade_gpt]])/cfg_TroyOz | N7: =N(tblBudget[[#This Row],[Ore_Mined_t]])+N(tblBudget[[#This Row],[Waste_t]]) | O7: =N(tblBudget[[#This Row],[Milled_t]])*N(tblBudget[[#This Row],[Head_Grade_gpt]])/cfg_TroyOz | P7: =tblBudget[[#This Row],[Feed_oz]]*N(tblBudget[[#This Row],[Recovery_pct]])
A8: 46082 | L8: =DAY(EOMONTH(tblBudget[[#This Row],[Month]],0)) | M8: =N(tblBudget[[#This Row],[Ore_Mined_t]])*N(tblBudget[[#This Row],[Ore_Grade_gpt]])/cfg_TroyOz | N8: =N(tblBudget[[#This Row],[Ore_Mined_t]])+N(tblBudget[[#This Row],[Waste_t]]) | O8: =N(tblBudget[[#This Row],[Milled_t]])*N(tblBudget[[#This Row],[Head_Grade_gpt]])/cfg_TroyOz | P8: =tblBudget[[#This Row],[Feed_oz]]*N(tblBudget[[#This Row],[Recovery_pct]])
A9: 46113 | L9: =DAY(EOMONTH(tblBudget[[#This Row],[Month]],0)) | M9: =N(tblBudget[[#This Row],[Ore_Mined_t]])*N(tblBudget[[#This Row],[Ore_Grade_gpt]])/cfg_TroyOz | N9: =N(tblBudget[[#This Row],[Ore_Mined_t]])+N(tblBudget[[#This Row],[Waste_t]]) | O9: =N(tblBudget[[#This Row],[Milled_t]])*N(tblBudget[[#This Row],[Head_Grade_gpt]])/cfg_TroyOz | P9: =tblBudget[[#This Row],[Feed_oz]]*N(tblBudget[[#This Row],[Recovery_pct]])
A10: 46143 | L10: =DAY(EOMONTH(tblBudget[[#This Row],[Month]],0)) | M10: =N(tblBudget[[#This Row],[Ore_Mined_t]])*N(tblBudget[[#This Row],[Ore_Grade_gpt]])/cfg_TroyOz | N10: =N(tblBudget[[#This Row],[Ore_Mined_t]])+N(tblBudget[[#This Row],[Waste_t]]) | O10: =N(tblBudget[[#This Row],[Milled_t]])*N(tblBudget[[#This Row],[Head_Grade_gpt]])/cfg_TroyOz | P10: =tblBudget[[#This Row],[Feed_oz]]*N(tblBudget[[#This Row],[Recovery_pct]])
A11: 46174 | L11: =DAY(EOMONTH(tblBudget[[#This Row],[Month]],0)) | M11: =N(tblBudget[[#This Row],[Ore_Mined_t]])*N(tblBudget[[#This Row],[Ore_Grade_gpt]])/cfg_TroyOz | N11: =N(tblBudget[[#This Row],[Ore_Mined_t]])+N(tblBudget[[#This Row],[Waste_t]]) | O11: =N(tblBudget[[#This Row],[Milled_t]])*N(tblBudget[[#This Row],[Head_Grade_gpt]])/cfg_TroyOz | P11: =tblBudget[[#This Row],[Feed_oz]]*N(tblBudget[[#This Row],[Recovery_pct]])
A12: 46204 | L12: =DAY(EOMONTH(tblBudget[[#This Row],[Month]],0)) | M12: =N(tblBudget[[#This Row],[Ore_Mined_t]])*N(tblBudget[[#This Row],[Ore_Grade_gpt]])/cfg_TroyOz | N12: =N(tblBudget[[#This Row],[Ore_Mined_t]])+N(tblBudget[[#This Row],[Waste_t]]) | O12: =N(tblBudget[[#This Row],[Milled_t]])*N(tblBudget[[#This Row],[Head_Grade_gpt]])/cfg_TroyOz | P12: =tblBudget[[#This Row],[Feed_oz]]*N(tblBudget[[#This Row],[Recovery_pct]])
A13: 46235 | L13: =DAY(EOMONTH(tblBudget[[#This Row],[Month]],0)) | M13: =N(tblBudget[[#This Row],[Ore_Mined_t]])*N(tblBudget[[#This Row],[Ore_Grade_gpt]])/cfg_TroyOz | N13: =N(tblBudget[[#This Row],[Ore_Mined_t]])+N(tblBudget[[#This Row],[Waste_t]]) | O13: =N(tblBudget[[#This Row],[Milled_t]])*N(tblBudget[[#This Row],[Head_Grade_gpt]])/cfg_TroyOz | P13: =tblBudget[[#This Row],[Feed_oz]]*N(tblBudget[[#This Row],[Recovery_pct]])
A14: 46266 | L14: =DAY(EOMONTH(tblBudget[[#This Row],[Month]],0)) | M14: =N(tblBudget[[#This Row],[Ore_Mined_t]])*N(tblBudget[[#This Row],[Ore_Grade_gpt]])/cfg_TroyOz | N14: =N(tblBudget[[#This Row],[Ore_Mined_t]])+N(tblBudget[[#This Row],[Waste_t]]) | O14: =N(tblBudget[[#This Row],[Milled_t]])*N(tblBudget[[#This Row],[Head_Grade_gpt]])/cfg_TroyOz | P14: =tblBudget[[#This Row],[Feed_oz]]*N(tblBudget[[#This Row],[Recovery_pct]])
A15: 46296 | L15: =DAY(EOMONTH(tblBudget[[#This Row],[Month]],0)) | M15: =N(tblBudget[[#This Row],[Ore_Mined_t]])*N(tblBudget[[#This Row],[Ore_Grade_gpt]])/cfg_TroyOz | N15: =N(tblBudget[[#This Row],[Ore_Mined_t]])+N(tblBudget[[#This Row],[Waste_t]]) | O15: =N(tblBudget[[#This Row],[Milled_t]])*N(tblBudget[[#This Row],[Head_Grade_gpt]])/cfg_TroyOz | P15: =tblBudget[[#This Row],[Feed_oz]]*N(tblBudget[[#This Row],[Recovery_pct]])
A16: 46327 | L16: =DAY(EOMONTH(tblBudget[[#This Row],[Month]],0)) | M16: =N(tblBudget[[#This Row],[Ore_Mined_t]])*N(tblBudget[[#This Row],[Ore_Grade_gpt]])/cfg_TroyOz | N16: =N(tblBudget[[#This Row],[Ore_Mined_t]])+N(tblBudget[[#This Row],[Waste_t]]) | O16: =N(tblBudget[[#This Row],[Milled_t]])*N(tblBudget[[#This Row],[Head_Grade_gpt]])/cfg_TroyOz | P16: =tblBudget[[#This Row],[Feed_oz]]*N(tblBudget[[#This Row],[Recovery_pct]])
A17: 46357 | L17: =DAY(EOMONTH(tblBudget[[#This Row],[Month]],0)) | M17: =N(tblBudget[[#This Row],[Ore_Mined_t]])*N(tblBudget[[#This Row],[Ore_Grade_gpt]])/cfg_TroyOz | N17: =N(tblBudget[[#This Row],[Ore_Mined_t]])+N(tblBudget[[#This Row],[Waste_t]]) | O17: =N(tblBudget[[#This Row],[Milled_t]])*N(tblBudget[[#This Row],[Head_Grade_gpt]])/cfg_TroyOz | P17: =tblBudget[[#This Row],[Feed_oz]]*N(tblBudget[[#This Row],[Recovery_pct]])

Sheet Commentary
A1: Daily report narrative, one row per comment
A2: Owner: All departments; compiled by the production engineer. Type only in the blue-headed columns; grey-headed columns are formulas. Add rows at the bottom only; never insert columns. Paste with Paste Special > Values only. Red cells need attention (missing or unknown value, duplicate date).
A4: Date | B4: Area | C4: Comment | D4: Author | E4: Sequence in day | F4: Day key
A5: Date | B5: Area | C5: Comment | D5: Author | E5: Seq_Day | F5: Key_Day
E6: =IF(tblCommentary[[#This Row],[Date]]="","",COUNTIFS(INDEX(tblCommentary[Date],1):tblCommentary[[#This Row],[Date]],tblCommentary[[#This Row],[Date]])) | F6: =IF(tblCommentary[[#This Row],[Date]]="","",tblCommentary[[#This Row],[Date]]&"|"&tblCommentary[[#This Row],[Seq_Day]])
E7: =IF(tblCommentary[[#This Row],[Date]]="","",COUNTIFS(INDEX(tblCommentary[Date],1):tblCommentary[[#This Row],[Date]],tblCommentary[[#This Row],[Date]])) | F7: =IF(tblCommentary[[#This Row],[Date]]="","",tblCommentary[[#This Row],[Date]]&"|"&tblCommentary[[#This Row],[Seq_Day]])
E8: =IF(tblCommentary[[#This Row],[Date]]="","",COUNTIFS(INDEX(tblCommentary[Date],1):tblCommentary[[#This Row],[Date]],tblCommentary[[#This Row],[Date]])) | F8: =IF(tblCommentary[[#This Row],[Date]]="","",tblCommentary[[#This Row],[Date]]&"|"&tblCommentary[[#This Row],[Seq_Day]])
E9: =IF(tblCommentary[[#This Row],[Date]]="","",COUNTIFS(INDEX(tblCommentary[Date],1):tblCommentary[[#This Row],[Date]],tblCommentary[[#This Row],[Date]])) | F9: =IF(tblCommentary[[#This Row],[Date]]="","",tblCommentary[[#This Row],[Date]]&"|"&tblCommentary[[#This Row],[Seq_Day]])
E10: =IF(tblCommentary[[#This Row],[Date]]="","",COUNTIFS(INDEX(tblCommentary[Date],1):tblCommentary[[#This Row],[Date]],tblCommentary[[#This Row],[Date]])) | F10: =IF(tblCommentary[[#This Row],[Date]]="","",tblCommentary[[#This Row],[Date]]&"|"&tblCommentary[[#This Row],[Seq_Day]])
E11: =IF(tblCommentary[[#This Row],[Date]]="","",COUNTIFS(INDEX(tblCommentary[Date],1):tblCommentary[[#This Row],[Date]],tblCommentary[[#This Row],[Date]])) | F11: =IF(tblCommentary[[#This Row],[Date]]="","",tblCommentary[[#This Row],[Date]]&"|"&tblCommentary[[#This Row],[Seq_Day]])
E12: =IF(tblCommentary[[#This Row],[Date]]="","",COUNTIFS(INDEX(tblCommentary[Date],1):tblCommentary[[#This Row],[Date]],tblCommentary[[#This Row],[Date]])) | F12: =IF(tblCommentary[[#This Row],[Date]]="","",tblCommentary[[#This Row],[Date]]&"|"&tblCommentary[[#This Row],[Seq_Day]])
E13: =IF(tblCommentary[[#This Row],[Date]]="","",COUNTIFS(INDEX(tblCommentary[Date],1):tblCommentary[[#This Row],[Date]],tblCommentary[[#This Row],[Date]])) | F13: =IF(tblCommentary[[#This Row],[Date]]="","",tblCommentary[[#This Row],[Date]]&"|"&tblCommentary[[#This Row],[Seq_Day]])
E14: =IF(tblCommentary[[#This Row],[Date]]="","",COUNTIFS(INDEX(tblCommentary[Date],1):tblCommentary[[#This Row],[Date]],tblCommentary[[#This Row],[Date]])) | F14: =IF(tblCommentary[[#This Row],[Date]]="","",tblCommentary[[#This Row],[Date]]&"|"&tblCommentary[[#This Row],[Seq_Day]])
