Workbook
Name lst_Shift: Lists!$A$6:INDEX(Lists!$A:$A,COUNTA(Lists!$A:$A))
Name lst_Material: Lists!$C$6:INDEX(Lists!$C:$C,COUNTA(Lists!$C:$C))
Name lst_Area: Lists!$E$6:INDEX(Lists!$E:$E,COUNTA(Lists!$E:$E))
Name lst_Equipment_Class: Lists!$G$6:INDEX(Lists!$G:$G,COUNTA(Lists!$G:$G))
Name lst_Gold_Movement_Type: Lists!$I$6:INDEX(Lists!$I:$I,COUNTA(Lists!$I:$I))
Name lst_Yes_No: Lists!$K$6:INDEX(Lists!$K:$K,COUNTA(Lists!$K:$K))
Name lst_Source_Type: Lists!$M$6:INDEX(Lists!$M:$M,COUNTA(Lists!$M:$M))
Name lst_Destination_Type: Lists!$O$6:INDEX(Lists!$O:$O,COUNTA(Lists!$O:$O))
Name lst_Source: Lists!$R$6:INDEX(Lists!$R:$R,COUNTA(Lists!$R:$R))
Name lst_Destination: Lists!$U$6:INDEX(Lists!$U:$U,COUNTA(Lists!$U:$U))
Name cfg_Site: Config!$B$5
Name cfg_Company: Config!$B$6
Name cfg_Year: Config!$B$7
Name cfg_YearStart: Config!$B$8
Name cfg_YearEnd: Config!$B$9
Name cfg_TroyOz: Config!$B$10
Name cfg_PriorLTIDate: Config!$B$11
Name cfg_LastDataDate: Config!$B$12
Name cfg_ReportTitle: Config!$B$13
Name cd_Date: Calc_Daily!$A$2:$A$366
Name cd_Month: Calc_Daily!$B$2:$B$366
Name cd_Day: Calc_Daily!$C$2:$C$366
Name cd_Days_In_Month: Calc_Daily!$D$2:$D$366
Name cd_Month_Start: Calc_Daily!$E$2:$E$366
Name cd_Ore_Mined_t: Calc_Daily!$F$2:$F$366
Name cd_Ore_Mined_t_MTD: Calc_Daily!$G$2:$G$366
Name cd_Ore_Mined_t_YTD: Calc_Daily!$H$2:$H$366
Name cd_Ore_Mined_oz: Calc_Daily!$I$2:$I$366
Name cd_Ore_Mined_oz_MTD: Calc_Daily!$J$2:$J$366
Name cd_Ore_Mined_oz_YTD: Calc_Daily!$K$2:$K$366
Name cd_Ore_Grade_gpt: Calc_Daily!$L$2:$L$366
Name cd_Ore_Grade_gpt_MTD: Calc_Daily!$M$2:$M$366
Name cd_Ore_Grade_gpt_YTD: Calc_Daily!$N$2:$N$366
Name cd_Waste_t: Calc_Daily!$O$2:$O$366
Name cd_Waste_t_MTD: Calc_Daily!$P$2:$P$366
Name cd_Waste_t_YTD: Calc_Daily!$Q$2:$Q$366
Name cd_TMM_t: Calc_Daily!$R$2:$R$366
Name cd_TMM_t_MTD: Calc_Daily!$S$2:$S$366
Name cd_TMM_t_YTD: Calc_Daily!$T$2:$T$366
Name cd_Strip_Ratio: Calc_Daily!$U$2:$U$366
Name cd_Strip_Ratio_MTD: Calc_Daily!$V$2:$V$366
Name cd_Strip_Ratio_YTD: Calc_Daily!$W$2:$W$366
Name cd_Rehandle_t: Calc_Daily!$X$2:$X$366
Name cd_Rehandle_t_MTD: Calc_Daily!$Y$2:$Y$366
Name cd_Rehandle_t_YTD: Calc_Daily!$Z$2:$Z$366
Name cd_Drill_m: Calc_Daily!$AA$2:$AA$366
Name cd_Drill_m_MTD: Calc_Daily!$AB$2:$AB$366
Name cd_Drill_m_YTD: Calc_Daily!$AC$2:$AC$366
Name cd_Blast_t: Calc_Daily!$AD$2:$AD$366
Name cd_Blast_t_MTD: Calc_Daily!$AE$2:$AE$366
Name cd_Blast_t_YTD: Calc_Daily!$AF$2:$AF$366
Name cd_Explosives_kg: Calc_Daily!$AG$2:$AG$366
Name cd_Explosives_kg_MTD: Calc_Daily!$AH$2:$AH$366
Name cd_Explosives_kg_YTD: Calc_Daily!$AI$2:$AI$366
Name cd_Powder_Factor_kgpt: Calc_Daily!$AJ$2:$AJ$366
Name cd_Powder_Factor_kgpt_MTD: Calc_Daily!$AK$2:$AK$366
Name cd_Powder_Factor_kgpt_YTD: Calc_Daily!$AL$2:$AL$366
Name cd_Diesel_Mining_L: Calc_Daily!$AM$2:$AM$366
Name cd_Diesel_Mining_L_MTD: Calc_Daily!$AN$2:$AN$366
Name cd_Diesel_Mining_L_YTD: Calc_Daily!$AO$2:$AO$366

Sheet README
B2: Mako Gold Mine Production System, 2026
B3: Petowal Mining Company S.A.. Version 0.1.0. Generated workbook: do not restructure by hand; change the schema and regenerate.
B5: How the workbook works
B6: 1. Inputs are the green tabs: Plant, Mining_Movements, Mining_Daily, Fleet, Safety, Gold, Commentary, Budget. Each is an Excel table. Type in the blue-headed columns only; grey-headed columns are formulas that fill automatically.
B7: 2. Calc_Daily rebuilds every KPI per day from the tables (day, month to date, year to date, budget). Daily_Report, Monthly_Summary and Dashboard read only from Calc_Daily.
B8: 3. There are no links to other workbooks and no macros. Copying the file anywhere keeps it working.
B9: 4. Lists holds every drop-down. Add a new pit, stockpile or equipment class there; do not type free text into list columns.
B10: 5. Config holds the year, the stockpile opening balances (survey at 1 January) and the prior-year safety history used for rolling 12-month rates.
B12: Daily routine
B13: Plant: enter the row for the day (dates are pre-filled). Mining: add one movement row per source, material and destination; add the Mining_Daily row and one Fleet row per equipment class. HSE: enter the Safety row. Everyone: one Commentary row per topic. Then open Daily_Report, check the date in C5, and print or export to PDF.
B15: Rules
B16: Do not insert columns inside tables, rename headers or move sheets. Add rows at the bottom of a table only. Blank means not reported; zero means reported as zero. Grades in g/t, tonnes dry metric, gold in troy ounces (31.1035 g).
... B22: Schema and generator: mps_schema.json and build_workbook.py in the MPS tools folder. Report issues to the Director, Operations and Projects.

Sheet Daily_Report
B2: =cfg_ReportTitle
B3: =cfg_Company&" | "&cfg_Site
L4: row
B5: Report date | C5: =MAX(cfg_YearStart,MIN(TODAY()-1,cfg_YearEnd,IF(N(cfg_LastDataDate)>0,cfg_LastDataDate,cfg_YearEnd))) | F5: Type a date to change the report day. To restore the default enter =MIN(TODAY()-1,cfg_LastDataDate) | L5: =IFERROR(MATCH($C$5,cd_Date,0),NA())
B6: ="Data to "&IF(N(cfg_LastDataDate)>0,TEXT(cfg_LastDataDate,"dd mmm yyyy"),"(no plant data yet)")&" | Week "&_xlfn.ISOWEEKNUM($C$5)&" | Day "&DAY($C$5)&" of "&DAY(EOMONTH($C$5,0))
B8: SAFETY | C8: Unit | D8: Day | E8: MTD | F8: MTD budget | G8: Var % | H8: YTD | I8: YTD budget | J8: Var %
B9: Hours worked | C9: h | D9: =IFERROR(INDEX(cd_Hours_Worked,rpt_Row),"") | E9: =IFERROR(INDEX(cd_Hours_Worked_MTD,rpt_Row),"") | F9: =IFERROR(INDEX(cd_Bud_Hours_Worked_MTD,rpt_Row),"") | G9: =IF(AND(ISNUMBER(F9),ISNUMBER(E9),F9<>0),E9/F9-1,"") | H9: =IFERROR(INDEX(cd_Hours_Worked_YTD,rpt_Row),"") | I9: =IFERROR(INDEX(cd_Bud_Hours_Worked_YTD,rpt_Row),"") | J9: =IF(AND(ISNUMBER(I9),ISNUMBER(H9),I9<>0),H9/I9-1,"")
B10: Recordable injuries | D10: =IFERROR(INDEX(cd_Recordables,rpt_Row),"") | E10: =IFERROR(INDEX(cd_Recordables_MTD,rpt_Row),"") | H10: =IFERROR(INDEX(cd_Recordables_YTD,rpt_Row),"")
B11: Lost time injuries | D11: =IFERROR(INDEX(cd_LTI,rpt_Row),"") | E11: =IFERROR(INDEX(cd_LTI_MTD,rpt_Row),"") | H11: =IFERROR(INDEX(cd_LTI_YTD,rpt_Row),"")
B12: Restricted work injuries | D12: =IFERROR(INDEX(cd_RWI,rpt_Row),"") | E12: =IFERROR(INDEX(cd_RWI_MTD,rpt_Row),"") | H12: =IFERROR(INDEX(cd_RWI_YTD,rpt_Row),"")
B13: Medical treatment injuries | D13: =IFERROR(INDEX(cd_MTI,rpt_Row),"") | E13: =IFERROR(INDEX(cd_MTI_MTD,rpt_Row),"") | H13: =IFERROR(INDEX(cd_MTI_YTD,rpt_Row),"")
B14: First aid injuries | D14: =IFERROR(INDEX(cd_FAI,rpt_Row),"") | E14: =IFERROR(INDEX(cd_FAI_MTD,rpt_Row),"") | H14: =IFERROR(INDEX(cd_FAI_YTD,rpt_Row),"")
B15: Near misses | D15: =IFERROR(INDEX(cd_Near_Miss,rpt_Row),"") | E15: =IFERROR(INDEX(cd_Near_Miss_MTD,rpt_Row),"") | H15: =IFERROR(INDEX(cd_Near_Miss_YTD,rpt_Row),"")
B16: Hazard reports | D16: =IFERROR(INDEX(cd_Hazard_Reports,rpt_Row),"") | E16: =IFERROR(INDEX(cd_Hazard_Reports_MTD,rpt_Row),"") | H16: =IFERROR(INDEX(cd_Hazard_Reports_YTD,rpt_Row),"")
B17: High potential incidents | D17: =IFERROR(INDEX(cd_HPI,rpt_Row),"") | E17: =IFERROR(INDEX(cd_HPI_MTD,rpt_Row),"") | H17: =IFERROR(INDEX(cd_HPI_YTD,rpt_Row),"")
B18: Environmental incidents | D18: =IFERROR(INDEX(cd_Env_Incidents,rpt_Row),"") | E18: =IFERROR(INDEX(cd_Env_Incidents_MTD,rpt_Row),"") | H18: =IFERROR(INDEX(cd_Env_Incidents_YTD,rpt_Row),"")
B19: Community incidents | D19: =IFERROR(INDEX(cd_Community_Incidents,rpt_Row),"") | E19: =IFERROR(INDEX(cd_Community_Incidents_MTD,rpt_Row),"") | H19: =IFERROR(INDEX(cd_Community_Incidents_YTD,rpt_Row),"")
B20: Vehicle incidents | D20: =IFERROR(INDEX(cd_Vehicle_Incidents,rpt_Row),"") | E20: =IFERROR(INDEX(cd_Vehicle_Incidents_MTD,rpt_Row),"") | H20: =IFERROR(INDEX(cd_Vehicle_Incidents_YTD,rpt_Row),"")
B21: TRIFR, rolling 12 months + MTD | D21: =IFERROR(INDEX(cd_TRIFR_12m,rpt_Row),"")
B22: LTIFR, rolling 12 months + MTD | D22: =IFERROR(INDEX(cd_LTIFR_12m,rpt_Row),"")
B23: Days since last LTI | D23: =IFERROR(INDEX(cd_Days_Since_LTI,rpt_Row),"")
B25: MINING | C25: Unit | D25: Day | E25: MTD | F25: MTD budget | G25: Var % | H25: YTD | I25: YTD budget | J25: Var %
B26: Ore mined (ex-pit) | C26: t | D26: =IFERROR(INDEX(cd_Ore_Mined_t,rpt_Row),"") | E26: =IFERROR(INDEX(cd_Ore_Mined_t_MTD,rpt_Row),"") | F26: =IFERROR(INDEX(cd_Bud_Ore_Mined_t_MTD,rpt_Row),"") | G26: =IF(AND(ISNUMBER(F26),ISNUMBER(E26),F26<>0),E26/F26-1,"") | H26: =IFERROR(INDEX(cd_Ore_Mined_t_YTD,rpt_Row),"") | I26: =IFERROR(INDEX(cd_Bud_Ore_Mined_t_YTD,rpt_Row),"") | J26: =IF(AND(ISNUMBER(I26),ISNUMBER(H26),I26<>0),H26/I26-1,"")
B27: Ore grade mined | C27: g/t | D27: =IFERROR(INDEX(cd_Ore_Grade_gpt,rpt_Row),"") | E27: =IFERROR(INDEX(cd_Ore_Grade_gpt_MTD,rpt_Row),"") | F27: =IFERROR(INDEX(cd_Bud_Ore_Grade_gpt_MTD,rpt_Row),"") | G27: =IF(AND(ISNUMBER(F27),ISNUMBER(E27),F27<>0),E27/F27-1,"") | H27: =IFERROR(INDEX(cd_Ore_Grade_gpt_YTD,rpt_Row),"") | I27: =IFERROR(INDEX(cd_Bud_Ore_Grade_gpt_YTD,rpt_Row),"") | J27: =IF(AND(ISNUMBER(I27),ISNUMBER(H27),I27<>0),H27/I27-1,"")
B28: Contained gold mined | C28: oz | D28: =IFERROR(INDEX(cd_Ore_Mined_oz,rpt_Row),"") | E28: =IFERROR(INDEX(cd_Ore_Mined_oz_MTD,rpt_Row),"") | F28: =IFERROR(INDEX(cd_Bud_Ore_Mined_oz_MTD,rpt_Row),"") | G28: =IF(AND(ISNUMBER(F28),ISNUMBER(E28),F28<>0),E28/F28-1,"") | H28: =IFERROR(INDEX(cd_Ore_Mined_oz_YTD,rpt_Row),"") | I28: =IFERROR(INDEX(cd_Bud_Ore_Mined_oz_YTD,rpt_Row),"") | J28: =IF(AND(ISNUMBER(I28),ISNUMBER(H28),I28<>0),H28/I28-1,"")
B29: Waste mined | C29: t | D29: =IFERROR(INDEX(cd_Waste_t,rpt_Row),"") | E29: =IFERROR(INDEX(cd_Waste_t_MTD,rpt_Row),"") | F29: =IFERROR(INDEX(cd_Bud_Waste_t_MTD,rpt_Row),"") | G29: =IF(AND(ISNUMBER(F29),ISNUMBER(E29),F29<>0),E29/F29-1,"") | H29: =IFERROR(INDEX(cd_Waste_t_YTD,rpt_Row),"") | I29: =IFERROR(INDEX(cd_Bud_Waste_t_YTD,rpt_Row),"") | J29: =IF(AND(ISNUMBER(I29),ISNUMBER(H29),I29<>0),H29/I29-1,"")
B30: Total material moved | C30: t | D30: =IFERROR(INDEX(cd_TMM_t,rpt_Row),"") | E30: =IFERROR(INDEX(cd_TMM_t_MTD,rpt_Row),"") | F30: =IFERROR(INDEX(cd_Bud_TMM_t_MTD,rpt_Row),"") | G30: =IF(AND(ISNUMBER(F30),ISNUMBER(E30),F30<>0),E30/F30-1,"") | H30: =IFERROR(INDEX(cd_TMM_t_YTD,rpt_Row),"") | I30: =IFERROR(INDEX(cd_Bud_TMM_t_YTD,rpt_Row),"") | J30: =IF(AND(ISNUMBER(I30),ISNUMBER(H30),I30<>0),H30/I30-1,"")
B31: Strip ratio (waste : ore) | D31: =IFERROR(INDEX(cd_Strip_Ratio,rpt_Row),"") | E31: =IFERROR(INDEX(cd_Strip_Ratio_MTD,rpt_Row),"") | F31: =IFERROR(INDEX(cd_Bud_Strip_Ratio_MTD,rpt_Row),"") | G31: =IF(AND(ISNUMBER(F31),ISNUMBER(E31),F31<>0),E31/F31-1,"") | H31: =IFERROR(INDEX(cd_Strip_Ratio_YTD,rpt_Row),"") | I31: =IFERROR(INDEX(cd_Bud_Strip_Ratio_YTD,rpt_Row),"") | J31: =IF(AND(ISNUMBER(I31),ISNUMBER(H31),I31<>0),H31/I31-1,"")
B32: Rehandle from stockpiles | C32: t | D32: =IFERROR(INDEX(cd_Rehandle_t,rpt_Row),"") | E32: =IFERROR(INDEX(cd_Rehandle_t_MTD,rpt_Row),"") | H32: =IFERROR(INDEX(cd_Rehandle_t_YTD,rpt_Row),"")
B33: Drilled | C33: m | D33: =IFERROR(INDEX(cd_Drill_m,rpt_Row),"") | E33: =IFERROR(INDEX(cd_Drill_m_MTD,rpt_Row),"") | F33: =IFERROR(INDEX(cd_Bud_Drill_m_MTD,rpt_Row),"") | G33: =IF(AND(ISNUMBER(F33),ISNUMBER(E33),F33<>0),E33/F33-1,"") | H33: =IFERROR(INDEX(cd_Drill_m_YTD,rpt_Row),"") | I33: =IFERROR(INDEX(cd_Bud_Drill_m_YTD,rpt_Row),"") | J33: =IF(AND(ISNUMBER(I33),ISNUMBER(H33),I33<>0),H33/I33-1,"")
B34: Blasted | C34: t | D34: =IFERROR(INDEX(cd_Blast_t,rpt_Row),"") | E34: =IFERROR(INDEX(cd_Blast_t_MTD,rpt_Row),"") | H34: =IFERROR(INDEX(cd_Blast_t_YTD,rpt_Row),"")
B35: Powder factor | C35: kg/t | D35: =IFERROR(INDEX(cd_Powder_Factor_kgpt,rpt_Row),"") | E35: =IFERROR(INDEX(cd_Powder_Factor_kgpt_MTD,rpt_Row),"") | H35: =IFERROR(INDEX(cd_Powder_Factor_kgpt_YTD,rpt_Row),"")
B36: Mining diesel | C36: L | D36: =IFERROR(INDEX(cd_Diesel_Mining_L,rpt_Row),"") | E36: =IFERROR(INDEX(cd_Diesel_Mining_L_MTD,rpt_Row),"") | F36: =IFERROR(INDEX(cd_Bud_Diesel_Mining_L_MTD,rpt_Row),"") | G36: =IF(AND(ISNUMBER(F36),ISNUMBER(E36),F36<>0),E36/F36-1,"") | H36: =IFERROR(INDEX(cd_Diesel_Mining_L_YTD,rpt_Row),"") | I36: =IFERROR(INDEX(cd_Bud_Diesel_Mining_L_YTD,rpt_Row),"") | J36: =IF(AND(ISNUMBER(I36),ISNUMBER(H36),I36<>0),H36/I36-1,"")
B37: Excavator availability | C37: % | D37: =IFERROR(INDEX(cd_Exc_Availability_pct,rpt_Row),"") | E37: =IFERROR(INDEX(cd_Exc_Availability_pct_MTD,rpt_Row),"") | H37: =IFERROR(INDEX(cd_Exc_Availability_pct_YTD,rpt_Row),"")
B38: Excavator utilisation | C38: % | D38: =IFERROR(INDEX(cd_Exc_Utilisation_pct,rpt_Row),"") | E38: =IFERROR(INDEX(cd_Exc_Utilisation_pct_MTD,rpt_Row),"") | H38: =IFERROR(INDEX(cd_Exc_Utilisation_pct_YTD,rpt_Row),"")
B39: Truck availability | C39: % | D39: =IFERROR(INDEX(cd_Trk_Availability_pct,rpt_Row),"") | E39: =IFERROR(INDEX(cd_Trk_Availability_pct_MTD,rpt_Row),"") | H39: =IFERROR(INDEX(cd_Trk_Availability_pct_YTD,rpt_Row),"")
B40: Truck utilisation | C40: % | D40: =IFERROR(INDEX(cd_Trk_Utilisation_pct,rpt_Row),"") | E40: =IFERROR(INDEX(cd_Trk_Utilisation_pct_MTD,rpt_Row),"") | H40: =IFERROR(INDEX(cd_Trk_Utilisation_pct_YTD,rpt_Row),"")
B42: PROCESSING | C42: Unit | D42: Day | E42: MTD | F42: MTD budget | G42: Var % | H42: YTD | I42: YTD budget | J42: Var %
B43: Crushed | C43: t | D43: =IFERROR(INDEX(cd_Crushed_t,rpt_Row),"") | E43: =IFERROR(INDEX(cd_Crushed_t_MTD,rpt_Row),"") | H43: =IFERROR(INDEX(cd_Crushed_t_YTD,rpt_Row),"")
B44: Milled | C44: t | D44: =IFERROR(INDEX(cd_Milled_t,rpt_Row),"") | E44: =IFERROR(INDEX(cd_Milled_t_MTD,rpt_Row),"") | F44: =IFERROR(INDEX(cd_Bud_Milled_t_MTD,rpt_Row),"") | G44: =IF(AND(ISNUMBER(F44),ISNUMBER(E44),F44<>0),E44/F44-1,"") | H44: =IFERROR(INDEX(cd_Milled_t_YTD,rpt_Row),"") | I44: =IFERROR(INDEX(cd_Bud_Milled_t_YTD,rpt_Row),"") | J44: =IF(AND(ISNUMBER(I44),ISNUMBER(H44),I44<>0),H44/I44-1,"")
B45: Head grade | C45: g/t | D45: =IFERROR(INDEX(cd_Head_Grade_gpt,rpt_Row),"") | E45: =IFERROR(INDEX(cd_Head_Grade_gpt_MTD,rpt_Row),"") | F45: =IFERROR(INDEX(cd_Bud_Head_Grade_gpt_MTD,rpt_Row),"") | G45: =IF(AND(ISNUMBER(F45),ISNUMBER(E45),F45<>0),E45/F45-1,"") | H45: =IFERROR(INDEX(cd_Head_Grade_gpt_YTD,rpt_Row),"") | I45: =IFERROR(INDEX(cd_Bud_Head_Grade_gpt_YTD,rpt_Row),"") | J45: =IF(AND(ISNUMBER(I45),ISNUMBER(H45),I45<>0),H45/I45-1,"")
B46: Contained gold in feed | C46: oz | D46: =IFERROR(INDEX(cd_Feed_oz,rpt_Row),"") | E46: =IFERROR(INDEX(cd_Feed_oz_MTD,rpt_Row),"") | F46: =IFERROR(INDEX(cd_Bud_Feed_oz_MTD,rpt_Row),"") | G46: =IF(AND(ISNUMBER(F46),ISNUMBER(E46),F46<>0),E46/F46-1,"") | H46: =IFERROR(INDEX(cd_Feed_oz_YTD,rpt_Row),"") | I46: =IFERROR(INDEX(cd_Bud_Feed_oz_YTD,rpt_Row),"") | J46: =IF(AND(ISNUMBER(I46),ISNUMBER(H46),I46<>0),H46/I46-1,"")
B47: Recovery | C47: % | D47: =IFERROR(INDEX(cd_Recovery_pct,rpt_Row),"") | E47: =IFERROR(INDEX(cd_Recovery_pct_MTD,rpt_Row),"") | F47: =IFERROR(INDEX(cd_Bud_Recovery_pct_MTD,rpt_Row),"") | G47: =IF(AND(ISNUMBER(F47),ISNUMBER(E47),F47<>0),E47/F47-1,"") | H47: =IFERROR(INDEX(cd_Recovery_pct_YTD,rpt_Row),"") | I47: =IFERROR(INDEX(cd_Bud_Recovery_pct_YTD,rpt_Row),"") | J47: =IF(AND(ISNUMBER(I47),ISNUMBER(H47),I47<>0),H47/I47-1,"")
B48: Gold recovered | C48: oz | D48: =IFERROR(INDEX(cd_Recovered_oz,rpt_Row),"") | E48: =IFERROR(INDEX(cd_Recovered_oz_MTD,rpt_Row),"") | F48: =IFERROR(INDEX(cd_Bud_Recovered_oz_MTD,rpt_Row),"") | G48: =IF(AND(ISNUMBER(F48),ISNUMBER(E48),F48<>0),E48/F48-1,"") | H48: =IFERROR(INDEX(cd_Recovered_oz_YTD,rpt_Row),"") | I48: =IFERROR(INDEX(cd_Bud_Recovered_oz_YTD,rpt_Row),"") | J48: =IF(AND(ISNUMBER(I48),ISNUMBER(H48),I48<>0),H48/I48-1,"")
B49: Gravity gold | C49: oz | D49: =IFERROR(INDEX(cd_Gravity_Gold_oz,rpt_Row),"") | E49: =IFERROR(INDEX(cd_Gravity_Gold_oz_MTD,rpt_Row),"") | H49: =IFERROR(INDEX(cd_Gravity_Gold_oz_YTD,rpt_Row),"")
B50: Gold poured | C50: oz | D50: =IFERROR(INDEX(cd_Gold_Poured_oz,rpt_Row),"") | E50: =IFERROR(INDEX(cd_Gold_Poured_oz_MTD,rpt_Row),"") | F50: =IFERROR(INDEX(cd_Bud_Gold_Poured_oz_MTD,rpt_Row),"") | G50: =IF(AND(ISNUMBER(F50),ISNUMBER(E50),F50<>0),E50/F50-1,"") | H50: =IFERROR(INDEX(cd_Gold_Poured_oz_YTD,rpt_Row),"") | I50: =IFERROR(INDEX(cd_Bud_Gold_Poured_oz_YTD,rpt_Row),"") | J50: =IF(AND(ISNUMBER(I50),ISNUMBER(H50),I50<>0),H50/I50-1,"")
B51: Mill throughput | C51: t/h | D51: =IFERROR(INDEX(cd_Throughput_tph,rpt_Row),"") | E51: =IFERROR(INDEX(cd_Throughput_tph_MTD,rpt_Row),"") | H51: =IFERROR(INDEX(cd_Throughput_tph_YTD,rpt_Row),"")
B52: Mill run hours | C52: h | D52: =IFERROR(INDEX(cd_Mill_Run_h,rpt_Row),"") | E52: =IFERROR(INDEX(cd_Mill_Run_h_MTD,rpt_Row),"") | H52: =IFERROR(INDEX(cd_Mill_Run_h_YTD,rpt_Row),"")
B53: Mill availability | C53: % | D53: =IFERROR(INDEX(cd_Mill_Availability_pct,rpt_Row),"") | E53: =IFERROR(INDEX(cd_Mill_Availability_pct_MTD,rpt_Row),"") | H53: =IFERROR(INDEX(cd_Mill_Availability_pct_YTD,rpt_Row),"")
B54: Mill utilisation | C54: % | D54: =IFERROR(INDEX(cd_Mill_Utilisation_pct,rpt_Row),"") | E54: =IFERROR(INDEX(cd_Mill_Utilisation_pct_MTD,rpt_Row),"") | H54: =IFERROR(INDEX(cd_Mill_Utilisation_pct_YTD,rpt_Row),"")
B55: Cyanide consumption | C55: kg/t | D55: =IFERROR(INDEX(cd_Cyanide_kgpt,rpt_Row),"") | E55: =IFERROR(INDEX(cd_Cyanide_kgpt_MTD,rpt_Row),"") | H55: =IFERROR(INDEX(cd_Cyanide_kgpt_YTD,rpt_Row),"")
B56: Lime consumption | C56: kg/t | D56: =IFERROR(INDEX(cd_Lime_kgpt,rpt_Row),"") | E56: =IFERROR(INDEX(cd_Lime_kgpt_MTD,rpt_Row),"") | H56: =IFERROR(INDEX(cd_Lime_kgpt_YTD,rpt_Row),"")
B57: Power consumption | C57: kWh/t | D57: =IFERROR(INDEX(cd_Power_kWhpt,rpt_Row),"") | E57: =IFERROR(INDEX(cd_Power_kWhpt_MTD,rpt_Row),"") | H57: =IFERROR(INDEX(cd_Power_kWhpt_YTD,rpt_Row),"")
B58: Gold in circuit (end of day) | C58: oz | D58: =IFERROR(INDEX(cd_GIC_oz,rpt_Row),"")
B60: GOLD | C60: Unit | D60: Day | E60: MTD | F60: MTD budget | G60: Var % | H60: YTD | I60: YTD budget | J60: Var %
B61: Gold shipped | C61: oz | D61: =IFERROR(INDEX(cd_Gold_Shipped_oz,rpt_Row),"") | E61: =IFERROR(INDEX(cd_Gold_Shipped_oz_MTD,rpt_Row),"") | H61: =IFERROR(INDEX(cd_Gold_Shipped_oz_YTD,rpt_Row),"")
B62: Gold sold | C62: oz | D62: =IFERROR(INDEX(cd_Gold_Sold_oz,rpt_Row),"") | E62: =IFERROR(INDEX(cd_Gold_Sold_oz_MTD,rpt_Row),"") | H62: =IFERROR(INDEX(cd_Gold_Sold_oz_YTD,rpt_Row),"")
B63: Dore shipped | C63: kg | D63: =IFERROR(INDEX(cd_Dore_Shipped_kg,rpt_Row),"") | E63: =IFERROR(INDEX(cd_Dore_Shipped_kg_MTD,rpt_Row),"") | H63: =IFERROR(INDEX(cd_Dore_Shipped_kg_YTD,rpt_Row),"")
B65: STOCKPILES (to report date) | D65: Opening t | E65: Opening g/t | F65: In t | G65: Out t | H65: Plant feed t | I65: Balance t | J65: Balance g/t
B66: =INDEX(tblStockpiles[Stockpile],1) | D66: =INDEX(tblStockpiles[Opening_t],1) | E66: =INDEX(tblStockpiles[Opening_gpt],1) | F66: =SUMIFS(tblMovement[Tonnes_t],tblMovement[Destination],INDEX(tblStockpiles[Stockpile],1),tblMovement[Date],"<="&rpt_Date) | G66: =SUMIFS(tblMovement[Tonnes_t],tblMovement[Source],INDEX(tblStockpiles[Stockpile],1),tblMovement[Date],"<="&rpt_Date) | H66: =IF(INDEX(tblStockpiles[Plant_Feed],1)="Y",SUMIFS(tblPlant[Milled_t],tblPlant[Date],"<="&rpt_Date)-SUMIFS(tblMovement[Tonnes_t],tblMovement[Dest_Type],"Plant",tblMovement[Date],"<="&rpt_Date),0) | I66: =D66+F66-G66-H66 | J66: =IFERROR(IF(I66>0,(D66*E66/cfg_TroyOz+SUMIFS(tblMovement[Contained_oz],tblMovement[Destination],INDEX(tblStockpiles[Stockpile],1),tblMovement[Date],"<="&rpt_Date)-SUMIFS(tblMovement[Contained_oz],tblMovement[Source],INDEX(tblStockpiles[Stockpile],1),tblMovement[Date],"<="&rpt_Date)-IF(INDEX(tblStockpiles[Plant_Feed],1)="Y",SUMIFS(tblPlant[Feed_oz],tblPlant[Date],"<="&rpt_Date)-SUMIFS(tblMovement[Contained_oz],tblMovement[Dest_Type],"Plant",tblMovement[Date],"<="&rpt_Date),0))*cfg_TroyOz/I66,""),"")
B67: =INDEX(tblStockpiles[Stockpile],2) | D67: =INDEX(tblStockpiles[Opening_t],2) | E67: =INDEX(tblStockpiles[Opening_gpt],2) | F67: =SUMIFS(tblMovement[Tonnes_t],tblMovement[Destination],INDEX(tblStockpiles[Stockpile],2),tblMovement[Date],"<="&rpt_Date) | G67: =SUMIFS(tblMovement[Tonnes_t],tblMovement[Source],INDEX(tblStockpiles[Stockpile],2),tblMovement[Date],"<="&rpt_Date) | H67: =IF(INDEX(tblStockpiles[Plant_Feed],2)="Y",SUMIFS(tblPlant[Milled_t],tblPlant[Date],"<="&rpt_Date)-SUMIFS(tblMovement[Tonnes_t],tblMovement[Dest_Type],"Plant",tblMovement[Date],"<="&rpt_Date),0) | I67: =D67+F67-G67-H67 | J67: =IFERROR(IF(I67>0,(D67*E67/cfg_TroyOz+SUMIFS(tblMovement[Contained_oz],tblMovement[Destination],INDEX(tblStockpiles[Stockpile],2),tblMovement[Date],"<="&rpt_Date)-SUMIFS(tblMovement[Contained_oz],tblMovement[Source],INDEX(tblStockpiles[Stockpile],2),tblMovement[Date],"<="&rpt_Date)-IF(INDEX(tblStockpiles[Plant_Feed],2)="Y",SUMIFS(tblPlant[Feed_oz],tblPlant[Date],"<="&rpt_Date)-SUMIFS(tblMovement[Contained_oz],tblMovement[Dest_Type],"Plant",tblMovement[Date],"<="&rpt_Date),0))*cfg_TroyOz/I67,""),"")
B68: =INDEX(tblStockpiles[Stockpile],3) | D68: =INDEX(tblStockpiles[Opening_t],3) | E68: =INDEX(tblStockpiles[Opening_gpt],3) | F68: =SUMIFS(tblMovement[Tonnes_t],tblMovement[Destination],INDEX(tblStockpiles[Stockpile],3),tblMovement[Date],"<="&rpt_Date) | G68: =SUMIFS(tblMovement[Tonnes_t],tblMovement[Source],INDEX(tblStockpiles[Stockpile],3),tblMovement[Date],"<="&rpt_Date) | H68: =IF(INDEX(tblStockpiles[Plant_Feed],3)="Y",SUMIFS(tblPlant[Milled_t],tblPlant[Date],"<="&rpt_Date)-SUMIFS(tblMovement[Tonnes_t],tblMovement[Dest_Type],"Plant",tblMovement[Date],"<="&rpt_Date),0) | I68: =D68+F68-G68-H68 | J68: =IFERROR(IF(I68>0,(D68*E68/cfg_TroyOz+SUMIFS(tblMovement[Contained_oz],tblMovement[Destination],INDEX(tblStockpiles[Stockpile],3),tblMovement[Date],"<="&rpt_Date)-SUMIFS(tblMovement[Contained_oz],tblMovement[Source],INDEX(tblStockpiles[Stockpile],3),tblMovement[Date],"<="&rpt_Date)-IF(INDEX(tblStockpiles[Plant_Feed],3)="Y",SUMIFS(tblPlant[Feed_oz],tblPlant[Date],"<="&rpt_Date)-SUMIFS(tblMovement[Contained_oz],tblMovement[Dest_Type],"Plant",tblMovement[Date],"<="&rpt_Date),0))*cfg_TroyOz/I68,""),"")
B69: =INDEX(tblStockpiles[Stockpile],4) | D69: =INDEX(tblStockpiles[Opening_t],4) | E69: =INDEX(tblStockpiles[Opening_gpt],4) | F69: =SUMIFS(tblMovement[Tonnes_t],tblMovement[Destination],INDEX(tblStockpiles[Stockpile],4),tblMovement[Date],"<="&rpt_Date) | G69: =SUMIFS(tblMovement[Tonnes_t],tblMovement[Source],INDEX(tblStockpiles[Stockpile],4),tblMovement[Date],"<="&rpt_Date) | H69: =IF(INDEX(tblStockpiles[Plant_Feed],4)="Y",SUMIFS(tblPlant[Milled_t],tblPlant[Date],"<="&rpt_Date)-SUMIFS(tblMovement[Tonnes_t],tblMovement[Dest_Type],"Plant",tblMovement[Date],"<="&rpt_Date),0) | I69: =D69+F69-G69-H69 | J69: =IFERROR(IF(I69>0,(D69*E69/cfg_TroyOz+SUMIFS(tblMovement[Contained_oz],tblMovement[Destination],INDEX(tblStockpiles[Stockpile],4),tblMovement[Date],"<="&rpt_Date)-SUMIFS(tblMovement[Contained_oz],tblMovement[Source],INDEX(tblStockpiles[Stockpile],4),tblMovement[Date],"<="&rpt_Date)-IF(INDEX(tblStockpiles[Plant_Feed],4)="Y",SUMIFS(tblPlant[Feed_oz],tblPlant[Date],"<="&rpt_Date)-SUMIFS(tblMovement[Contained_oz],tblMovement[Dest_Type],"Plant",tblMovement[Date],"<="&rpt_Date),0))*cfg_TroyOz/I69,""),"")
B70: =INDEX(tblStockpiles[Stockpile],5) | D70: =INDEX(tblStockpiles[Opening_t],5) | E70: =INDEX(tblStockpiles[Opening_gpt],5) | F70: =SUMIFS(tblMovement[Tonnes_t],tblMovement[Destination],INDEX(tblStockpiles[Stockpile],5),tblMovement[Date],"<="&rpt_Date) | G70: =SUMIFS(tblMovement[Tonnes_t],tblMovement[Source],INDEX(tblStockpiles[Stockpile],5),tblMovement[Date],"<="&rpt_Date) | H70: =IF(INDEX(tblStockpiles[Plant_Feed],5)="Y",SUMIFS(tblPlant[Milled_t],tblPlant[Date],"<="&rpt_Date)-SUMIFS(tblMovement[Tonnes_t],tblMovement[Dest_Type],"Plant",tblMovement[Date],"<="&rpt_Date),0) | I70: =D70+F70-G70-H70 | J70: =IFERROR(IF(I70>0,(D70*E70/cfg_TroyOz+SUMIFS(tblMovement[Contained_oz],tblMovement[Destination],INDEX(tblStockpiles[Stockpile],5),tblMovement[Date],"<="&rpt_Date)-SUMIFS(tblMovement[Contained_oz],tblMovement[Source],INDEX(tblStockpiles[Stockpile],5),tblMovement[Date],"<="&rpt_Date)-IF(INDEX(tblStockpiles[Plant_Feed],5)="Y",SUMIFS(tblPlant[Feed_oz],tblPlant[Date],"<="&rpt_Date)-SUMIFS(tblMovement[Contained_oz],tblMovement[Dest_Type],"Plant",tblMovement[Date],"<="&rpt_Date),0))*cfg_TroyOz/I70,""),"")
B72: COMMENTARY | C72: Area
B73: =IFERROR(INDEX(tblCommentary[Area],MATCH(rpt_Date&"|"&1,tblCommentary[Key_Day],0)),"") | C73: =IFERROR(INDEX(tblCommentary[Comment],MATCH(rpt_Date&"|"&1,tblCommentary[Key_Day],0)),"")
B74: =IFERROR(INDEX(tblCommentary[Area],MATCH(rpt_Date&"|"&2,tblCommentary[Key_Day],0)),"") | C74: =IFERROR(INDEX(tblCommentary[Comment],MATCH(rpt_Date&"|"&2,tblCommentary[Key_Day],0)),"")
B75: =IFERROR(INDEX(tblCommentary[Area],MATCH(rpt_Date&"|"&3,tblCommentary[Key_Day],0)),"") | C75: =IFERROR(INDEX(tblCommentary[Comment],MATCH(rpt_Date&"|"&3,tblCommentary[Key_Day],0)),"")
B76: =IFERROR(INDEX(tblCommentary[Area],MATCH(rpt_Date&"|"&4,tblCommentary[Key_Day],0)),"") | C76: =IFERROR(INDEX(tblCommentary[Comment],MATCH(rpt_Date&"|"&4,tblCommentary[Key_Day],0)),"")
B77: =IFERROR(INDEX(tblCommentary[Area],MATCH(rpt_Date&"|"&5,tblCommentary[Key_Day],0)),"") | C77: =IFERROR(INDEX(tblCommentary[Comment],MATCH(rpt_Date&"|"&5,tblCommentary[Key_Day],0)),"")
B78: =IFERROR(INDEX(tblCommentary[Area],MATCH(rpt_Date&"|"&6,tblCommentary[Key_Day],0)),"") | C78: =IFERROR(INDEX(tblCommentary[Comment],MATCH(rpt_Date&"|"&6,tblCommentary[Key_Day],0)),"")
B79: =IFERROR(INDEX(tblCommentary[Area],MATCH(rpt_Date&"|"&7,tblCommentary[Key_Day],0)),"") | C79: =IFERROR(INDEX(tblCommentary[Comment],MATCH(rpt_Date&"|"&7,tblCommentary[Key_Day],0)),"")
B80: =IFERROR(INDEX(tblCommentary[Area],MATCH(rpt_Date&"|"&8,tblCommentary[Key_Day],0)),"") | C80: =IFERROR(INDEX(tblCommentary[Comment],MATCH(rpt_Date&"|"&8,tblCommentary[Key_Day],0)),"")
B81: =IFERROR(INDEX(tblCommentary[Area],MATCH(rpt_Date&"|"&9,tblCommentary[Key_Day],0)),"") | C81: =IFERROR(INDEX(tblCommentary[Comment],MATCH(rpt_Date&"|"&9,tblCommentary[Key_Day],0)),"")
B82: =IFERROR(INDEX(tblCommentary[Area],MATCH(rpt_Date&"|"&10,tblCommentary[Key_Day],0)),"") | C82: =IFERROR(INDEX(tblCommentary[Comment],MATCH(rpt_Date&"|"&10,tblCommentary[Key_Day],0)),"")
B83: =IFERROR(INDEX(tblCommentary[Area],MATCH(rpt_Date&"|"&11,tblCommentary[Key_Day],0)),"") | C83: =IFERROR(INDEX(tblCommentary[Comment],MATCH(rpt_Date&"|"&11,tblCommentary[Key_Day],0)),"")
B84: =IFERROR(INDEX(tblCommentary[Area],MATCH(rpt_Date&"|"&12,tblCommentary[Key_Day],0)),"") | C84: =IFERROR(INDEX(tblCommentary[Comment],MATCH(rpt_Date&"|"&12,tblCommentary[Key_Day],0)),"")
B85: =IFERROR(INDEX(tblCommentary[Area],MATCH(rpt_Date&"|"&13,tblCommentary[Key_Day],0)),"") | C85: =IFERROR(INDEX(tblCommentary[Comment],MATCH(rpt_Date&"|"&13,tblCommentary[Key_Day],0)),"")
B86: =IFERROR(INDEX(tblCommentary[Area],MATCH(rpt_Date&"|"&14,tblCommentary[Key_Day],0)),"") | C86: =IFERROR(INDEX(tblCommentary[Comment],MATCH(rpt_Date&"|"&14,tblCommentary[Key_Day],0)),"")
B87: =IFERROR(INDEX(tblCommentary[Area],MATCH(rpt_Date&"|"&15,tblCommentary[Key_Day],0)),"") | C87: =IFERROR(INDEX(tblCommentary[Comment],MATCH(rpt_Date&"|"&15,tblCommentary[Key_Day],0)),"")
B89: ="Generated by the Mako Production System workbook. Printed "&TEXT(NOW(),"dd mmm yyyy hh:mm")

Sheet Dashboard
B2: =cfg_Site&" dashboard "&cfg_Year
B3: ="Data to "&IF(N(cfg_LastDataDate)>0,TEXT(cfg_LastDataDate,"dd mmm yyyy"),"(no plant data yet)")

Sheet Monthly_Summary
B2: =cfg_Site&" monthly summary "&cfg_Year
B3: ="Actuals to "&IF(N(cfg_LastDataDate)>0,TEXT(cfg_LastDataDate,"dd mmm yyyy"),"(no plant data yet)")&". Budget from the Budget sheet. Ratios are month values, not averages of days."
B5: KPI | D5: 46023 | E5: 46054 | F5: 46082 | G5: 46113 | H5: 46143 | I5: 46174 | J5: 46204 | K5: 46235 | L5: 46266 | M5: 46296 | N5: 46327 | O5: 46357 | P5: Year
B6: Hours worked | C6: Actual | D6: =IF(DATE(cfg_Year,1,1)>cfg_LastDataDate,"",IFERROR(INDEX(cd_Hours_Worked_MTD,MATCH(MIN(EOMONTH(DATE(cfg_Year,1,1),0),cfg_LastDataDate),cd_Date,0)),"")) | E6: =IF(DATE(cfg_Year,2,1)>cfg_LastDataDate,"",IFERROR(INDEX(cd_Hours_Worked_MTD,MATCH(MIN(EOMONTH(DATE(cfg_Year,2,1),0),cfg_LastDataDate),cd_Date,0)),"")) | F6: =IF(DATE(cfg_Year,3,1)>cfg_LastDataDate,"",IFERROR(INDEX(cd_Hours_Worked_MTD,MATCH(MIN(EOMONTH(DATE(cfg_Year,3,1),0),cfg_LastDataDate),cd_Date,0)),"")) | G6: =IF(DATE(cfg_Year,4,1)>cfg_LastDataDate,"",IFERROR(INDEX(cd_Hours_Worked_MTD,MATCH(MIN(EOMONTH(DATE(cfg_Year,4,1),0),cfg_LastDataDate),cd_Date,0)),"")) | H6: =IF(DATE(cfg_Year,5,1)>cfg_LastDataDate,"",IFERROR(INDEX(cd_Hours_Worked_MTD,MATCH(MIN(EOMONTH(DATE(cfg_Year,5,1),0),cfg_LastDataDate),cd_Date,0)),"")) | I6: =IF(DATE(cfg_Year,6,1)>cfg_LastDataDate,"",IFERROR(INDEX(cd_Hours_Worked_MTD,MATCH(MIN(EOMONTH(DATE(cfg_Year,6,1),0),cfg_LastDataDate),cd_Date,0)),"")) | J6: =IF(DATE(cfg_Year,7,1)>cfg_LastDataDate,"",IFERROR(INDEX(cd_Hours_Worked_MTD,MATCH(MIN(EOMONTH(DATE(cfg_Year,7,1),0),cfg_LastDataDate),cd_Date,0)),"")) | K6: =IF(DATE(cfg_Year,8,1)>cfg_LastDataDate,"",IFERROR(INDEX(cd_Hours_Worked_MTD,MATCH(MIN(EOMONTH(DATE(cfg_Year,8,1),0),cfg_LastDataDate),cd_Date,0)),"")) | L6: =IF(DATE(cfg_Year,9,1)>cfg_LastDataDate,"",IFERROR(INDEX(cd_Hours_Worked_MTD,MATCH(MIN(EOMONTH(DATE(cfg_Year,9,1),0),cfg_LastDataDate),cd_Date,0)),"")) | M6: =IF(DATE(cfg_Year,10,1)>cfg_LastDataDate,"",IFERROR(INDEX(cd_Hours_Worked_MTD,MATCH(MIN(EOMONTH(DATE(cfg_Year,10,1),0),cfg_LastDataDate),cd_Date,0)),"")) | N6: =IF(DATE(cfg_Year,11,1)>cfg_LastDataDate,"",IFERROR(INDEX(cd_Hours_Worked_MTD,MATCH(MIN(EOMONTH(DATE(cfg_Year,11,1),0),cfg_LastDataDate),cd_Date,0)),"")) | O6: =IF(DATE(cfg_Year,12,1)>cfg_LastDataDate,"",IFERROR(INDEX(cd_Hours_Worked_MTD,MATCH(MIN(EOMONTH(DATE(cfg_Year,12,1),0),cfg_LastDataDate),cd_Date,0)),"")) | P6: =IFERROR(INDEX(cd_Hours_Worked_YTD,MATCH(MIN(cfg_YearEnd,cfg_LastDataDate),cd_Date,0)),"")
C7: Budget | D7: =IFERROR(INDEX(cd_Bud_Hours_Worked_Month,MATCH(DATE(cfg_Year,1,1),cd_Date,0)),"") | E7: =IFERROR(INDEX(cd_Bud_Hours_Worked_Month,MATCH(DATE(cfg_Year,2,1),cd_Date,0)),"") | F7: =IFERROR(INDEX(cd_Bud_Hours_Worked_Month,MATCH(DATE(cfg_Year,3,1),cd_Date,0)),"") | G7: =IFERROR(INDEX(cd_Bud_Hours_Worked_Month,MATCH(DATE(cfg_Year,4,1),cd_Date,0)),"") | H7: =IFERROR(INDEX(cd_Bud_Hours_Worked_Month,MATCH(DATE(cfg_Year,5,1),cd_Date,0)),"") | I7: =IFERROR(INDEX(cd_Bud_Hours_Worked_Month,MATCH(DATE(cfg_Year,6,1),cd_Date,0)),"") | J7: =IFERROR(INDEX(cd_Bud_Hours_Worked_Month,MATCH(DATE(cfg_Year,7,1),cd_Date,0)),"") | K7: =IFERROR(INDEX(cd_Bud_Hours_Worked_Month,MATCH(DATE(cfg_Year,8,1),cd_Date,0)),"") | L7: =IFERROR(INDEX(cd_Bud_Hours_Worked_Month,MATCH(DATE(cfg_Year,9,1),cd_Date,0)),"") | M7: =IFERROR(INDEX(cd_Bud_Hours_Worked_Month,MATCH(DATE(cfg_Year,10,1),cd_Date,0)),"") | N7: =IFERROR(INDEX(cd_Bud_Hours_Worked_Month,MATCH(DATE(cfg_Year,11,1),cd_Date,0)),"") | O7: =IFERROR(INDEX(cd_Bud_Hours_Worked_Month,MATCH(DATE(cfg_Year,12,1),cd_Date,0)),"") | P7: =IFERROR(INDEX(cd_Bud_Hours_Worked_YTD,MATCH(cfg_YearEnd,cd_Date,0)),"")
C8: Variance | D8: =IF(AND(ISNUMBER(D6),ISNUMBER(D7),D7<>0),D6/D7-1,"") | E8: =IF(AND(ISNUMBER(E6),ISNUMBER(E7),E7<>0),E6/E7-1,"") | F8: =IF(AND(ISNUMBER(F6),ISNUMBER(F7),F7<>0),F6/F7-1,"") | G8: =IF(AND(ISNUMBER(G6),ISNUMBER(G7),G7<>0),G6/G7-1,"") | H8: =IF(AND(ISNUMBER(H6),ISNUMBER(H7),H7<>0),H6/H7-1,"") | I8: =IF(AND(ISNUMBER(I6),ISNUMBER(I7),I7<>0),I6/I7-1,"") | J8: =IF(AND(ISNUMBER(J6),ISNUMBER(J7),J7<>0),J6/J7-1,"") | K8: =IF(AND(ISNUMBER(K6),ISNUMBER(K7),K7<>0),K6/K7-1,"") | ... P8: =IF(AND(ISNUMBER(P6),ISNUMBER(P7),P7<>0),P6/P7-1,"")
B10: Recordable injuries | C10: Actual | D10: =IF(DATE(cfg_Year,1,1)>cfg_LastDataDate,"",IFERROR(INDEX(cd_Recordables_MTD,MATCH(MIN(EOMONTH(DATE(cfg_Year,1,1),0),cfg_LastDataDate),cd_Date,0)),"")) | E10: =IF(DATE(cfg_Year,2,1)>cfg_LastDataDate,"",IFERROR(INDEX(cd_Recordables_MTD,MATCH(MIN(EOMONTH(DATE(cfg_Year,2,1),0),cfg_LastDataDate),cd_Date,0)),"")) | F10: =IF(DATE(cfg_Year,3,1)>cfg_LastDataDate,"",IFERROR(INDEX(cd_Recordables_MTD,MATCH(MIN(EOMONTH(DATE(cfg_Year,3,1),0),cfg_LastDataDate),cd_Date,0)),"")) | G10: =IF(DATE(cfg_Year,4,1)>cfg_LastDataDate,"",IFERROR(INDEX(cd_Recordables_MTD,MATCH(MIN(EOMONTH(DATE(cfg_Year,4,1),0),cfg_LastDataDate),cd_Date,0)),"")) | H10: =IF(DATE(cfg_Year,5,1)>cfg_LastDataDate,"",IFERROR(INDEX(cd_Recordables_MTD,MATCH(MIN(EOMONTH(DATE(cfg_Year,5,1),0),cfg_LastDataDate),cd_Date,0)),"")) | I10: =IF(DATE(cfg_Year,6,1)>cfg_LastDataDate,"",IFERROR(INDEX(cd_Recordables_MTD,MATCH(MIN(EOMONTH(DATE(cfg_Year,6,1),0),cfg_LastDataDate),cd_Date,0)),"")) | J10: =IF(DATE(cfg_Year,7,1)>cfg_LastDataDate,"",IFERROR(INDEX(cd_Recordables_MTD,MATCH(MIN(EOMONTH(DATE(cfg_Year,7,1),0),cfg_LastDataDate),cd_Date,0)),"")) | K10: =IF(DATE(cfg_Year,8,1)>cfg_LastDataDate,"",IFERROR(INDEX(cd_Recordables_MTD,MATCH(MIN(EOMONTH(DATE(cfg_Year,8,1),0),cfg_LastDataDate),cd_Date,0)),"")) | L10: =IF(DATE(cfg_Year,9,1)>cfg_LastDataDate,"",IFERROR(INDEX(cd_Recordables_MTD,MATCH(MIN(EOMONTH(DATE(cfg_Year,9,1),0),cfg_LastDataDate),cd_Date,0)),"")) | M10: =IF(DATE(cfg_Year,10,1)>cfg_LastDataDate,"",IFERROR(INDEX(cd_Recordables_MTD,MATCH(MIN(EOMONTH(DATE(cfg_Year,10,1),0),cfg_LastDataDate),cd_Date,0)),"")) | N10: =IF(DATE(cfg_Year,11,1)>cfg_LastDataDate,"",IFERROR(INDEX(cd_Recordables_MTD,MATCH(MIN(EOMONTH(DATE(cfg_Year,11,1),0),cfg_LastDataDate),cd_Date,0)),"")) | O10: =IF(DATE(cfg_Year,12,1)>cfg_LastDataDate,"",IFERROR(INDEX(cd_Recordables_MTD,MATCH(MIN(EOMONTH(DATE(cfg_Year,12,1),0),cfg_LastDataDate),cd_Date,0)),"")) | P10: =IFERROR(INDEX(cd_Recordables_YTD,MATCH(MIN(cfg_YearEnd,cfg_LastDataDate),cd_Date,0)),"")
B11: Lost time injuries | C11: Actual | D11: =IF(DATE(cfg_Year,1,1)>cfg_LastDataDate,"",IFERROR(INDEX(cd_LTI_MTD,MATCH(MIN(EOMONTH(DATE(cfg_Year,1,1),0),cfg_LastDataDate),cd_Date,0)),"")) | E11: =IF(DATE(cfg_Year,2,1)>cfg_LastDataDate,"",IFERROR(INDEX(cd_LTI_MTD,MATCH(MIN(EOMONTH(DATE(cfg_Year,2,1),0),cfg_LastDataDate),cd_Date,0)),"")) | F11: =IF(DATE(cfg_Year,3,1)>cfg_LastDataDate,"",IFERROR(INDEX(cd_LTI_MTD,MATCH(MIN(EOMONTH(DATE(cfg_Year,3,1),0),cfg_LastDataDate),cd_Date,0)),"")) | G11: =IF(DATE(cfg_Year,4,1)>cfg_LastDataDate,"",IFERROR(INDEX(cd_LTI_MTD,MATCH(MIN(EOMONTH(DATE(cfg_Year,4,1),0),cfg_LastDataDate),cd_Date,0)),"")) | H11: =IF(DATE(cfg_Year,5,1)>cfg_LastDataDate,"",IFERROR(INDEX(cd_LTI_MTD,MATCH(MIN(EOMONTH(DATE(cfg_Year,5,1),0),cfg_LastDataDate),cd_Date,0)),"")) | I11: =IF(DATE(cfg_Year,6,1)>cfg_LastDataDate,"",IFERROR(INDEX(cd_LTI_MTD,MATCH(MIN(EOMONTH(DATE(cfg_Year,6,1),0),cfg_LastDataDate),cd_Date,0)),"")) | J11: =IF(DATE(cfg_Year,7,1)>cfg_LastDataDate,"",IFERROR(INDEX(cd_LTI_MTD,MATCH(MIN(EOMONTH(DATE(cfg_Year,7,1),0),cfg_LastDataDate),cd_Date,0)),"")) | K11: =IF(DATE(cfg_Year,8,1)>cfg_LastDataDate,"",IFERROR(INDEX(cd_LTI_MTD,MATCH(MIN(EOMONTH(DATE(cfg_Year,8,1),0),cfg_LastDataDate),cd_Date,0)),"")) | L11: =IF(DATE(cfg_Year,9,1)>cfg_LastDataDate,"",IFERROR(INDEX(cd_LTI_MTD,MATCH(MIN(EOMONTH(DATE(cfg_Year,9,1),0),cfg_LastDataDate),cd_Date,0)),"")) | M11: =IF(DATE(cfg_Year,10,1)>cfg_LastDataDate,"",IFERROR(INDEX(cd_LTI_MTD,MATCH(MIN(EOMONTH(DATE(cfg_Year,10,1),0),cfg_LastDataDate),cd_Date,0)),"")) | N11: =IF(DATE(cfg_Year,11,1)>cfg_LastDataDate,"",IFERROR(INDEX(cd_LTI_MTD,MATCH(MIN(EOMONTH(DATE(cfg_Year,11,1),0),cfg_LastDataDate),cd_Date,0)),"")) | O11: =IF(DATE(cfg_Year,12,1)>cfg_LastDataDate,"",IFERROR(INDEX(cd_LTI_MTD,MATCH(MIN(EOMONTH(DATE(cfg_Year,12,1),0),cfg_LastDataDate),cd_Date,0)),"")) | P11: =IFERROR(INDEX(cd_LTI_YTD,MATCH(MIN(cfg_YearEnd,cfg_LastDataDate),cd_Date,0)),"")
B12: TRIFR, rolling 12 months + MTD | C12: Actual | D12: =IF(DATE(cfg_Year,1,1)>cfg_LastDataDate,"",IFERROR(INDEX(cd_TRIFR_12m,MATCH(MIN(EOMONTH(DATE(cfg_Year,1,1),0),cfg_LastDataDate),cd_Date,0)),"")) | E12: =IF(DATE(cfg_Year,2,1)>cfg_LastDataDate,"",IFERROR(INDEX(cd_TRIFR_12m,MATCH(MIN(EOMONTH(DATE(cfg_Year,2,1),0),cfg_LastDataDate),cd_Date,0)),"")) | F12: =IF(DATE(cfg_Year,3,1)>cfg_LastDataDate,"",IFERROR(INDEX(cd_TRIFR_12m,MATCH(MIN(EOMONTH(DATE(cfg_Year,3,1),0),cfg_LastDataDate),cd_Date,0)),"")) | G12: =IF(DATE(cfg_Year,4,1)>cfg_LastDataDate,"",IFERROR(INDEX(cd_TRIFR_12m,MATCH(MIN(EOMONTH(DATE(cfg_Year,4,1),0),cfg_LastDataDate),cd_Date,0)),"")) | H12: =IF(DATE(cfg_Year,5,1)>cfg_LastDataDate,"",IFERROR(INDEX(cd_TRIFR_12m,MATCH(MIN(EOMONTH(DATE(cfg_Year,5,1),0),cfg_LastDataDate),cd_Date,0)),"")) | I12: =IF(DATE(cfg_Year,6,1)>cfg_LastDataDate,"",IFERROR(INDEX(cd_TRIFR_12m,MATCH(MIN(EOMONTH(DATE(cfg_Year,6,1),0),cfg_LastDataDate),cd_Date,0)),"")) | J12: =IF(DATE(cfg_Year,7,1)>cfg_LastDataDate,"",IFERROR(INDEX(cd_TRIFR_12m,MATCH(MIN(EOMONTH(DATE(cfg_Year,7,1),0),cfg_LastDataDate),cd_Date,0)),"")) | K12: =IF(DATE(cfg_Year,8,1)>cfg_LastDataDate,"",IFERROR(INDEX(cd_TRIFR_12m,MATCH(MIN(EOMONTH(DATE(cfg_Year,8,1),0),cfg_LastDataDate),cd_Date,0)),"")) | L12: =IF(DATE(cfg_Year,9,1)>cfg_LastDataDate,"",IFERROR(INDEX(cd_TRIFR_12m,MATCH(MIN(EOMONTH(DATE(cfg_Year,9,1),0),cfg_LastDataDate),cd_Date,0)),"")) | M12: =IF(DATE(cfg_Year,10,1)>cfg_LastDataDate,"",IFERROR(INDEX(cd_TRIFR_12m,MATCH(MIN(EOMONTH(DATE(cfg_Year,10,1),0),cfg_LastDataDate),cd_Date,0)),"")) | N12: =IF(DATE(cfg_Year,11,1)>cfg_LastDataDate,"",IFERROR(INDEX(cd_TRIFR_12m,MATCH(MIN(EOMONTH(DATE(cfg_Year,11,1),0),cfg_LastDataDate),cd_Date,0)),"")) | O12: =IF(DATE(cfg_Year,12,1)>cfg_LastDataDate,"",IFERROR(INDEX(cd_TRIFR_12m,MATCH(MIN(EOMONTH(DATE(cfg_Year,12,1),0),cfg_LastDataDate),cd_Date,0)),"")) | P12: =IFERROR(INDEX(cd_TRIFR_12m,MATCH(MIN(cfg_YearEnd,cfg_LastDataDate),cd_Date,0)),"")
B13: Ore mined (ex-pit) | C13: Actual | D13: =IF(DATE(cfg_Year,1,1)>cfg_LastDataDate,"",IFERROR(INDEX(cd_Ore_Mined_t_MTD,MATCH(MIN(EOMONTH(DATE(cfg_Year,1,1),0),cfg_LastDataDate),cd_Date,0)),"")) | E13: =IF(DATE(cfg_Year,2,1)>cfg_LastDataDate,"",IFERROR(INDEX(cd_Ore_Mined_t_MTD,MATCH(MIN(EOMONTH(DATE(cfg_Year,2,1),0),cfg_LastDataDate),cd_Date,0)),"")) | F13: =IF(DATE(cfg_Year,3,1)>cfg_LastDataDate,"",IFERROR(INDEX(cd_Ore_Mined_t_MTD,MATCH(MIN(EOMONTH(DATE(cfg_Year,3,1),0),cfg_LastDataDate),cd_Date,0)),"")) | G13: =IF(DATE(cfg_Year,4,1)>cfg_LastDataDate,"",IFERROR(INDEX(cd_Ore_Mined_t_MTD,MATCH(MIN(EOMONTH(DATE(cfg_Year,4,1),0),cfg_LastDataDate),cd_Date,0)),"")) | H13: =IF(DATE(cfg_Year,5,1)>cfg_LastDataDate,"",IFERROR(INDEX(cd_Ore_Mined_t_MTD,MATCH(MIN(EOMONTH(DATE(cfg_Year,5,1),0),cfg_LastDataDate),cd_Date,0)),"")) | I13: =IF(DATE(cfg_Year,6,1)>cfg_LastDataDate,"",IFERROR(INDEX(cd_Ore_Mined_t_MTD,MATCH(MIN(EOMONTH(DATE(cfg_Year,6,1),0),cfg_LastDataDate),cd_Date,0)),"")) | J13: =IF(DATE(cfg_Year,7,1)>cfg_LastDataDate,"",IFERROR(INDEX(cd_Ore_Mined_t_MTD,MATCH(MIN(EOMONTH(DATE(cfg_Year,7,1),0),cfg_LastDataDate),cd_Date,0)),"")) | K13: =IF(DATE(cfg_Year,8,1)>cfg_LastDataDate,"",IFERROR(INDEX(cd_Ore_Mined_t_MTD,MATCH(MIN(EOMONTH(DATE(cfg_Year,8,1),0),cfg_LastDataDate),cd_Date,0)),"")) | L13: =IF(DATE(cfg_Year,9,1)>cfg_LastDataDate,"",IFERROR(INDEX(cd_Ore_Mined_t_MTD,MATCH(MIN(EOMONTH(DATE(cfg_Year,9,1),0),cfg_LastDataDate),cd_Date,0)),"")) | M13: =IF(DATE(cfg_Year,10,1)>cfg_LastDataDate,"",IFERROR(INDEX(cd_Ore_Mined_t_MTD,MATCH(MIN(EOMONTH(DATE(cfg_Year,10,1),0),cfg_LastDataDate),cd_Date,0)),"")) | N13: =IF(DATE(cfg_Year,11,1)>cfg_LastDataDate,"",IFERROR(INDEX(cd_Ore_Mined_t_MTD,MATCH(MIN(EOMONTH(DATE(cfg_Year,11,1),0),cfg_LastDataDate),cd_Date,0)),"")) | O13: =IF(DATE(cfg_Year,12,1)>cfg_LastDataDate,"",IFERROR(INDEX(cd_Ore_Mined_t_MTD,MATCH(MIN(EOMONTH(DATE(cfg_Year,12,1),0),cfg_LastDataDate),cd_Date,0)),"")) | P13: =IFERROR(INDEX(cd_Ore_Mined_t_YTD,MATCH(MIN(cfg_YearEnd,cfg_LastDataDate),cd_Date,0)),"")
C14: Budget | D14: =IFERROR(INDEX(cd_Bud_Ore_Mined_t_Month,MATCH(DATE(cfg_Year,1,1),cd_Date,0)),"") | E14: =IFERROR(INDEX(cd_Bud_Ore_Mined_t_Month,MATCH(DATE(cfg_Year,2,1),cd_Date,0)),"") | F14: =IFERROR(INDEX(cd_Bud_Ore_Mined_t_Month,MATCH(DATE(cfg_Year,3,1),cd_Date,0)),"") | G14: =IFERROR(INDEX(cd_Bud_Ore_Mined_t_Month,MATCH(DATE(cfg_Year,4,1),cd_Date,0)),"") | H14: =IFERROR(INDEX(cd_Bud_Ore_Mined_t_Month,MATCH(DATE(cfg_Year,5,1),cd_Date,0)),"") | I14: =IFERROR(INDEX(cd_Bud_Ore_Mined_t_Month,MATCH(DATE(cfg_Year,6,1),cd_Date,0)),"") | J14: =IFERROR(INDEX(cd_Bud_Ore_Mined_t_Month,MATCH(DATE(cfg_Year,7,1),cd_Date,0)),"") | K14: =IFERROR(INDEX(cd_Bud_Ore_Mined_t_Month,MATCH(DATE(cfg_Year,8,1),cd_Date,0)),"") | L14: =IFERROR(INDEX(cd_Bud_Ore_Mined_t_Month,MATCH(DATE(cfg_Year,9,1),cd_Date,0)),"") | M14: =IFERROR(INDEX(cd_Bud_Ore_Mined_t_Month,MATCH(DATE(cfg_Year,10,1),cd_Date,0)),"") | N14: =IFERROR(INDEX(cd_Bud_Ore_Mined_t_Month,MATCH(DATE(cfg_Year,11,1),cd_Date,0)),"") | O14: =IFERROR(INDEX(cd_Bud_Ore_Mined_t_Month,MATCH(DATE(cfg_Year,12,1),cd_Date,0)),"") | P14: =IFERROR(INDEX(cd_Bud_Ore_Mined_t_YTD,MATCH(cfg_YearEnd,cd_Date,0)),"")
C15: Variance | D15: =IF(AND(ISNUMBER(D13),ISNUMBER(D14),D14<>0),D13/D14-1,"") | E15: =IF(AND(ISNUMBER(E13),ISNUMBER(E14),E14<>0),E13/E14-1,"") | F15: =IF(AND(ISNUMBER(F13),ISNUMBER(F14),F14<>0),F13/F14-1,"") | G15: =IF(AND(ISNUMBER(G13),ISNUMBER(G14),G14<>0),G13/G14-1,"") | H15: =IF(AND(ISNUMBER(H13),ISNUMBER(H14),H14<>0),H13/H14-1,"") | I15: =IF(AND(ISNUMBER(I13),ISNUMBER(I14),I14<>0),I13/I14-1,"") | J15: =IF(AND(ISNUMBER(J13),ISNUMBER(J14),J14<>0),J13/J14-1,"") | K15: =IF(AND(ISNUMBER(K13),ISNUMBER(K14),K14<>0),K13/K14-1,"") | ... P15: =IF(AND(ISNUMBER(P13),ISNUMBER(P14),P14<>0),P13/P14-1,"")
B17: Ore grade mined | C17: Actual | D17: =IF(DATE(cfg_Year,1,1)>cfg_LastDataDate,"",IFERROR(INDEX(cd_Ore_Grade_gpt_MTD,MATCH(MIN(EOMONTH(DATE(cfg_Year,1,1),0),cfg_LastDataDate),cd_Date,0)),"")) | E17: =IF(DATE(cfg_Year,2,1)>cfg_LastDataDate,"",IFERROR(INDEX(cd_Ore_Grade_gpt_MTD,MATCH(MIN(EOMONTH(DATE(cfg_Year,2,1),0),cfg_LastDataDate),cd_Date,0)),"")) | F17: =IF(DATE(cfg_Year,3,1)>cfg_LastDataDate,"",IFERROR(INDEX(cd_Ore_Grade_gpt_MTD,MATCH(MIN(EOMONTH(DATE(cfg_Year,3,1),0),cfg_LastDataDate),cd_Date,0)),"")) | G17: =IF(DATE(cfg_Year,4,1)>cfg_LastDataDate,"",IFERROR(INDEX(cd_Ore_Grade_gpt_MTD,MATCH(MIN(EOMONTH(DATE(cfg_Year,4,1),0),cfg_LastDataDate),cd_Date,0)),"")) | H17: =IF(DATE(cfg_Year,5,1)>cfg_LastDataDate,"",IFERROR(INDEX(cd_Ore_Grade_gpt_MTD,MATCH(MIN(EOMONTH(DATE(cfg_Year,5,1),0),cfg_LastDataDate),cd_Date,0)),"")) | I17: =IF(DATE(cfg_Year,6,1)>cfg_LastDataDate,"",IFERROR(INDEX(cd_Ore_Grade_gpt_MTD,MATCH(MIN(EOMONTH(DATE(cfg_Year,6,1),0),cfg_LastDataDate),cd_Date,0)),"")) | J17: =IF(DATE(cfg_Year,7,1)>cfg_LastDataDate,"",IFERROR(INDEX(cd_Ore_Grade_gpt_MTD,MATCH(MIN(EOMONTH(DATE(cfg_Year,7,1),0),cfg_LastDataDate),cd_Date,0)),"")) | K17: =IF(DATE(cfg_Year,8,1)>cfg_LastDataDate,"",IFERROR(INDEX(cd_Ore_Grade_gpt_MTD,MATCH(MIN(EOMONTH(DATE(cfg_Year,8,1),0),cfg_LastDataDate),cd_Date,0)),"")) | L17: =IF(DATE(cfg_Year,9,1)>cfg_LastDataDate,"",IFERROR(INDEX(cd_Ore_Grade_gpt_MTD,MATCH(MIN(EOMONTH(DATE(cfg_Year,9,1),0),cfg_LastDataDate),cd_Date,0)),"")) | M17: =IF(DATE(cfg_Year,10,1)>cfg_LastDataDate,"",IFERROR(INDEX(cd_Ore_Grade_gpt_MTD,MATCH(MIN(EOMONTH(DATE(cfg_Year,10,1),0),cfg_LastDataDate),cd_Date,0)),"")) | N17: =IF(DATE(cfg_Year,11,1)>cfg_LastDataDate,"",IFERROR(INDEX(cd_Ore_Grade_gpt_MTD,MATCH(MIN(EOMONTH(DATE(cfg_Year,11,1),0),cfg_LastDataDate),cd_Date,0)),"")) | O17: =IF(DATE(cfg_Year,12,1)>cfg_LastDataDate,"",IFERROR(INDEX(cd_Ore_Grade_gpt_MTD,MATCH(MIN(EOMONTH(DATE(cfg_Year,12,1),0),cfg_LastDataDate),cd_Date,0)),"")) | P17: =IFERROR(INDEX(cd_Ore_Grade_gpt_YTD,MATCH(MIN(cfg_YearEnd,cfg_LastDataDate),cd_Date,0)),"")
C18: Budget | D18: =IFERROR(INDEX(cd_Bud_Ore_Grade_gpt_Month,MATCH(DATE(cfg_Year,1,1),cd_Date,0)),"") | E18: =IFERROR(INDEX(cd_Bud_Ore_Grade_gpt_Month,MATCH(DATE(cfg_Year,2,1),cd_Date,0)),"") | F18: =IFERROR(INDEX(cd_Bud_Ore_Grade_gpt_Month,MATCH(DATE(cfg_Year,3,1),cd_Date,0)),"") | G18: =IFERROR(INDEX(cd_Bud_Ore_Grade_gpt_Month,MATCH(DATE(cfg_Year,4,1),cd_Date,0)),"") | H18: =IFERROR(INDEX(cd_Bud_Ore_Grade_gpt_Month,MATCH(DATE(cfg_Year,5,1),cd_Date,0)),"") | I18: =IFERROR(INDEX(cd_Bud_Ore_Grade_gpt_Month,MATCH(DATE(cfg_Year,6,1),cd_Date,0)),"") | J18: =IFERROR(INDEX(cd_Bud_Ore_Grade_gpt_Month,MATCH(DATE(cfg_Year,7,1),cd_Date,0)),"") | K18: =IFERROR(INDEX(cd_Bud_Ore_Grade_gpt_Month,MATCH(DATE(cfg_Year,8,1),cd_Date,0)),"") | L18: =IFERROR(INDEX(cd_Bud_Ore_Grade_gpt_Month,MATCH(DATE(cfg_Year,9,1),cd_Date,0)),"") | M18: =IFERROR(INDEX(cd_Bud_Ore_Grade_gpt_Month,MATCH(DATE(cfg_Year,10,1),cd_Date,0)),"") | N18: =IFERROR(INDEX(cd_Bud_Ore_Grade_gpt_Month,MATCH(DATE(cfg_Year,11,1),cd_Date,0)),"") | O18: =IFERROR(INDEX(cd_Bud_Ore_Grade_gpt_Month,MATCH(DATE(cfg_Year,12,1),cd_Date,0)),"") | P18: =IFERROR(INDEX(cd_Bud_Ore_Grade_gpt_YTD,MATCH(cfg_YearEnd,cd_Date,0)),"")
C19: Variance | D19: =IF(AND(ISNUMBER(D17),ISNUMBER(D18),D18<>0),D17/D18-1,"") | E19: =IF(AND(ISNUMBER(E17),ISNUMBER(E18),E18<>0),E17/E18-1,"") | F19: =IF(AND(ISNUMBER(F17),ISNUMBER(F18),F18<>0),F17/F18-1,"") | G19: =IF(AND(ISNUMBER(G17),ISNUMBER(G18),G18<>0),G17/G18-1,"") | H19: =IF(AND(ISNUMBER(H17),ISNUMBER(H18),H18<>0),H17/H18-1,"") | I19: =IF(AND(ISNUMBER(I17),ISNUMBER(I18),I18<>0),I17/I18-1,"") | J19: =IF(AND(ISNUMBER(J17),ISNUMBER(J18),J18<>0),J17/J18-1,"") | K19: =IF(AND(ISNUMBER(K17),ISNUMBER(K18),K18<>0),K17/K18-1,"") | ... P19: =IF(AND(ISNUMBER(P17),ISNUMBER(P18),P18<>0),P17/P18-1,"")
B21: Contained gold mined | C21: Actual | D21: =IF(DATE(cfg_Year,1,1)>cfg_LastDataDate,"",IFERROR(INDEX(cd_Ore_Mined_oz_MTD,MATCH(MIN(EOMONTH(DATE(cfg_Year,1,1),0),cfg_LastDataDate),cd_Date,0)),"")) | E21: =IF(DATE(cfg_Year,2,1)>cfg_LastDataDate,"",IFERROR(INDEX(cd_Ore_Mined_oz_MTD,MATCH(MIN(EOMONTH(DATE(cfg_Year,2,1),0),cfg_LastDataDate),cd_Date,0)),"")) | F21: =IF(DATE(cfg_Year,3,1)>cfg_LastDataDate,"",IFERROR(INDEX(cd_Ore_Mined_oz_MTD,MATCH(MIN(EOMONTH(DATE(cfg_Year,3,1),0),cfg_LastDataDate),cd_Date,0)),"")) | G21: =IF(DATE(cfg_Year,4,1)>cfg_LastDataDate,"",IFERROR(INDEX(cd_Ore_Mined_oz_MTD,MATCH(MIN(EOMONTH(DATE(cfg_Year,4,1),0),cfg_LastDataDate),cd_Date,0)),"")) | H21: =IF(DATE(cfg_Year,5,1)>cfg_LastDataDate,"",IFERROR(INDEX(cd_Ore_Mined_oz_MTD,MATCH(MIN(EOMONTH(DATE(cfg_Year,5,1),0),cfg_LastDataDate),cd_Date,0)),"")) | I21: =IF(DATE(cfg_Year,6,1)>cfg_LastDataDate,"",IFERROR(INDEX(cd_Ore_Mined_oz_MTD,MATCH(MIN(EOMONTH(DATE(cfg_Year,6,1),0),cfg_LastDataDate),cd_Date,0)),"")) | J21: =IF(DATE(cfg_Year,7,1)>cfg_LastDataDate,"",IFERROR(INDEX(cd_Ore_Mined_oz_MTD,MATCH(MIN(EOMONTH(DATE(cfg_Year,7,1),0),cfg_LastDataDate),cd_Date,0)),"")) | K21: =IF(DATE(cfg_Year,8,1)>cfg_LastDataDate,"",IFERROR(INDEX(cd_Ore_Mined_oz_MTD,MATCH(MIN(EOMONTH(DATE(cfg_Year,8,1),0),cfg_LastDataDate),cd_Date,0)),"")) | L21: =IF(DATE(cfg_Year,9,1)>cfg_LastDataDate,"",IFERROR(INDEX(cd_Ore_Mined_oz_MTD,MATCH(MIN(EOMONTH(DATE(cfg_Year,9,1),0),cfg_LastDataDate),cd_Date,0)),"")) | M21: =IF(DATE(cfg_Year,10,1)>cfg_LastDataDate,"",IFERROR(INDEX(cd_Ore_Mined_oz_MTD,MATCH(MIN(EOMONTH(DATE(cfg_Year,10,1),0),cfg_LastDataDate),cd_Date,0)),"")) | N21: =IF(DATE(cfg_Year,11,1)>cfg_LastDataDate,"",IFERROR(INDEX(cd_Ore_Mined_oz_MTD,MATCH(MIN(EOMONTH(DATE(cfg_Year,11,1),0),cfg_LastDataDate),cd_Date,0)),"")) | O21: =IF(DATE(cfg_Year,12,1)>cfg_LastDataDate,"",IFERROR(INDEX(cd_Ore_Mined_oz_MTD,MATCH(MIN(EOMONTH(DATE(cfg_Year,12,1),0),cfg_LastDataDate),cd_Date,0)),"")) | P21: =IFERROR(INDEX(cd_Ore_Mined_oz_YTD,MATCH(MIN(cfg_YearEnd,cfg_LastDataDate),cd_Date,0)),"")
C22: Budget | D22: =IFERROR(INDEX(cd_Bud_Ore_Mined_oz_Month,MATCH(DATE(cfg_Year,1,1),cd_Date,0)),"") | E22: =IFERROR(INDEX(cd_Bud_Ore_Mined_oz_Month,MATCH(DATE(cfg_Year,2,1),cd_Date,0)),"") | F22: =IFERROR(INDEX(cd_Bud_Ore_Mined_oz_Month,MATCH(DATE(cfg_Year,3,1),cd_Date,0)),"") | G22: =IFERROR(INDEX(cd_Bud_Ore_Mined_oz_Month,MATCH(DATE(cfg_Year,4,1),cd_Date,0)),"") | H22: =IFERROR(INDEX(cd_Bud_Ore_Mined_oz_Month,MATCH(DATE(cfg_Year,5,1),cd_Date,0)),"") | I22: =IFERROR(INDEX(cd_Bud_Ore_Mined_oz_Month,MATCH(DATE(cfg_Year,6,1),cd_Date,0)),"") | J22: =IFERROR(INDEX(cd_Bud_Ore_Mined_oz_Month,MATCH(DATE(cfg_Year,7,1),cd_Date,0)),"") | K22: =IFERROR(INDEX(cd_Bud_Ore_Mined_oz_Month,MATCH(DATE(cfg_Year,8,1),cd_Date,0)),"") | L22: =IFERROR(INDEX(cd_Bud_Ore_Mined_oz_Month,MATCH(DATE(cfg_Year,9,1),cd_Date,0)),"") | M22: =IFERROR(INDEX(cd_Bud_Ore_Mined_oz_Month,MATCH(DATE(cfg_Year,10,1),cd_Date,0)),"") | N22: =IFERROR(INDEX(cd_Bud_Ore_Mined_oz_Month,MATCH(DATE(cfg_Year,11,1),cd_Date,0)),"") | O22: =IFERROR(INDEX(cd_Bud_Ore_Mined_oz_Month,MATCH(DATE(cfg_Year,12,1),cd_Date,0)),"") | P22: =IFERROR(INDEX(cd_Bud_Ore_Mined_oz_YTD,MATCH(cfg_YearEnd,cd_Date,0)),"")
C23: Variance | D23: =IF(AND(ISNUMBER(D21),ISNUMBER(D22),D22<>0),D21/D22-1,"") | E23: =IF(AND(ISNUMBER(E21),ISNUMBER(E22),E22<>0),E21/E22-1,"") | F23: =IF(AND(ISNUMBER(F21),ISNUMBER(F22),F22<>0),F21/F22-1,"") | G23: =IF(AND(ISNUMBER(G21),ISNUMBER(G22),G22<>0),G21/G22-1,"") | H23: =IF(AND(ISNUMBER(H21),ISNUMBER(H22),H22<>0),H21/H22-1,"") | I23: =IF(AND(ISNUMBER(I21),ISNUMBER(I22),I22<>0),I21/I22-1,"") | J23: =IF(AND(ISNUMBER(J21),ISNUMBER(J22),J22<>0),J21/J22-1,"") | K23: =IF(AND(ISNUMBER(K21),ISNUMBER(K22),K22<>0),K21/K22-1,"") | ... P23: =IF(AND(ISNUMBER(P21),ISNUMBER(P22),P22<>0),P21/P22-1,"")
B25: Waste mined | C25: Actual | D25: =IF(DATE(cfg_Year,1,1)>cfg_LastDataDate,"",IFERROR(INDEX(cd_Waste_t_MTD,MATCH(MIN(EOMONTH(DATE(cfg_Year,1,1),0),cfg_LastDataDate),cd_Date,0)),"")) | E25: =IF(DATE(cfg_Year,2,1)>cfg_LastDataDate,"",IFERROR(INDEX(cd_Waste_t_MTD,MATCH(MIN(EOMONTH(DATE(cfg_Year,2,1),0),cfg_LastDataDate),cd_Date,0)),"")) | F25: =IF(DATE(cfg_Year,3,1)>cfg_LastDataDate,"",IFERROR(INDEX(cd_Waste_t_MTD,MATCH(MIN(EOMONTH(DATE(cfg_Year,3,1),0),cfg_LastDataDate),cd_Date,0)),"")) | G25: =IF(DATE(cfg_Year,4,1)>cfg_LastDataDate,"",IFERROR(INDEX(cd_Waste_t_MTD,MATCH(MIN(EOMONTH(DATE(cfg_Year,4,1),0),cfg_LastDataDate),cd_Date,0)),"")) | H25: =IF(DATE(cfg_Year,5,1)>cfg_LastDataDate,"",IFERROR(INDEX(cd_Waste_t_MTD,MATCH(MIN(EOMONTH(DATE(cfg_Year,5,1),0),cfg_LastDataDate),cd_Date,0)),"")) | I25: =IF(DATE(cfg_Year,6,1)>cfg_LastDataDate,"",IFERROR(INDEX(cd_Waste_t_MTD,MATCH(MIN(EOMONTH(DATE(cfg_Year,6,1),0),cfg_LastDataDate),cd_Date,0)),"")) | J25: =IF(DATE(cfg_Year,7,1)>cfg_LastDataDate,"",IFERROR(INDEX(cd_Waste_t_MTD,MATCH(MIN(EOMONTH(DATE(cfg_Year,7,1),0),cfg_LastDataDate),cd_Date,0)),"")) | K25: =IF(DATE(cfg_Year,8,1)>cfg_LastDataDate,"",IFERROR(INDEX(cd_Waste_t_MTD,MATCH(MIN(EOMONTH(DATE(cfg_Year,8,1),0),cfg_LastDataDate),cd_Date,0)),"")) | L25: =IF(DATE(cfg_Year,9,1)>cfg_LastDataDate,"",IFERROR(INDEX(cd_Waste_t_MTD,MATCH(MIN(EOMONTH(DATE(cfg_Year,9,1),0),cfg_LastDataDate),cd_Date,0)),"")) | M25: =IF(DATE(cfg_Year,10,1)>cfg_LastDataDate,"",IFERROR(INDEX(cd_Waste_t_MTD,MATCH(MIN(EOMONTH(DATE(cfg_Year,10,1),0),cfg_LastDataDate),cd_Date,0)),"")) | N25: =IF(DATE(cfg_Year,11,1)>cfg_LastDataDate,"",IFERROR(INDEX(cd_Waste_t_MTD,MATCH(MIN(EOMONTH(DATE(cfg_Year,11,1),0),cfg_LastDataDate),cd_Date,0)),"")) | O25: =IF(DATE(cfg_Year,12,1)>cfg_LastDataDate,"",IFERROR(INDEX(cd_Waste_t_MTD,MATCH(MIN(EOMONTH(DATE(cfg_Year,12,1),0),cfg_LastDataDate),cd_Date,0)),"")) | P25: =IFERROR(INDEX(cd_Waste_t_YTD,MATCH(MIN(cfg_YearEnd,cfg_LastDataDate),cd_Date,0)),"")
C26: Budget | D26: =IFERROR(INDEX(cd_Bud_Waste_t_Month,MATCH(DATE(cfg_Year,1,1),cd_Date,0)),"") | E26: =IFERROR(INDEX(cd_Bud_Waste_t_Month,MATCH(DATE(cfg_Year,2,1),cd_Date,0)),"") | F26: =IFERROR(INDEX(cd_Bud_Waste_t_Month,MATCH(DATE(cfg_Year,3,1),cd_Date,0)),"") | G26: =IFERROR(INDEX(cd_Bud_Waste_t_Month,MATCH(DATE(cfg_Year,4,1),cd_Date,0)),"") | H26: =IFERROR(INDEX(cd_Bud_Waste_t_Month,MATCH(DATE(cfg_Year,5,1),cd_Date,0)),"") | I26: =IFERROR(INDEX(cd_Bud_Waste_t_Month,MATCH(DATE(cfg_Year,6,1),cd_Date,0)),"") | J26: =IFERROR(INDEX(cd_Bud_Waste_t_Month,MATCH(DATE(cfg_Year,7,1),cd_Date,0)),"") | K26: =IFERROR(INDEX(cd_Bud_Waste_t_Month,MATCH(DATE(cfg_Year,8,1),cd_Date,0)),"") | L26: =IFERROR(INDEX(cd_Bud_Waste_t_Month,MATCH(DATE(cfg_Year,9,1),cd_Date,0)),"") | M26: =IFERROR(INDEX(cd_Bud_Waste_t_Month,MATCH(DATE(cfg_Year,10,1),cd_Date,0)),"") | N26: =IFERROR(INDEX(cd_Bud_Waste_t_Month,MATCH(DATE(cfg_Year,11,1),cd_Date,0)),"") | O26: =IFERROR(INDEX(cd_Bud_Waste_t_Month,MATCH(DATE(cfg_Year,12,1),cd_Date,0)),"") | P26: =IFERROR(INDEX(cd_Bud_Waste_t_YTD,MATCH(cfg_YearEnd,cd_Date,0)),"")
C27: Variance | D27: =IF(AND(ISNUMBER(D25),ISNUMBER(D26),D26<>0),D25/D26-1,"") | E27: =IF(AND(ISNUMBER(E25),ISNUMBER(E26),E26<>0),E25/E26-1,"") | F27: =IF(AND(ISNUMBER(F25),ISNUMBER(F26),F26<>0),F25/F26-1,"") | G27: =IF(AND(ISNUMBER(G25),ISNUMBER(G26),G26<>0),G25/G26-1,"") | H27: =IF(AND(ISNUMBER(H25),ISNUMBER(H26),H26<>0),H25/H26-1,"") | I27: =IF(AND(ISNUMBER(I25),ISNUMBER(I26),I26<>0),I25/I26-1,"") | J27: =IF(AND(ISNUMBER(J25),ISNUMBER(J26),J26<>0),J25/J26-1,"") | K27: =IF(AND(ISNUMBER(K25),ISNUMBER(K26),K26<>0),K25/K26-1,"") | ... P27: =IF(AND(ISNUMBER(P25),ISNUMBER(P26),P26<>0),P25/P26-1,"")
B29: Total material moved | C29: Actual | D29: =IF(DATE(cfg_Year,1,1)>cfg_LastDataDate,"",IFERROR(INDEX(cd_TMM_t_MTD,MATCH(MIN(EOMONTH(DATE(cfg_Year,1,1),0),cfg_LastDataDate),cd_Date,0)),"")) | E29: =IF(DATE(cfg_Year,2,1)>cfg_LastDataDate,"",IFERROR(INDEX(cd_TMM_t_MTD,MATCH(MIN(EOMONTH(DATE(cfg_Year,2,1),0),cfg_LastDataDate),cd_Date,0)),"")) | F29: =IF(DATE(cfg_Year,3,1)>cfg_LastDataDate,"",IFERROR(INDEX(cd_TMM_t_MTD,MATCH(MIN(EOMONTH(DATE(cfg_Year,3,1),0),cfg_LastDataDate),cd_Date,0)),"")) | G29: =IF(DATE(cfg_Year,4,1)>cfg_LastDataDate,"",IFERROR(INDEX(cd_TMM_t_MTD,MATCH(MIN(EOMONTH(DATE(cfg_Year,4,1),0),cfg_LastDataDate),cd_Date,0)),"")) | H29: =IF(DATE(cfg_Year,5,1)>cfg_LastDataDate,"",IFERROR(INDEX(cd_TMM_t_MTD,MATCH(MIN(EOMONTH(DATE(cfg_Year,5,1),0),cfg_LastDataDate),cd_Date,0)),"")) | I29: =IF(DATE(cfg_Year,6,1)>cfg_LastDataDate,"",IFERROR(INDEX(cd_TMM_t_MTD,MATCH(MIN(EOMONTH(DATE(cfg_Year,6,1),0),cfg_LastDataDate),cd_Date,0)),"")) | J29: =IF(DATE(cfg_Year,7,1)>cfg_LastDataDate,"",IFERROR(INDEX(cd_TMM_t_MTD,MATCH(MIN(EOMONTH(DATE(cfg_Year,7,1),0),cfg_LastDataDate),cd_Date,0)),"")) | K29: =IF(DATE(cfg_Year,8,1)>cfg_LastDataDate,"",IFERROR(INDEX(cd_TMM_t_MTD,MATCH(MIN(EOMONTH(DATE(cfg_Year,8,1),0),cfg_LastDataDate),cd_Date,0)),"")) | L29: =IF(DATE(cfg_Year,9,1)>cfg_LastDataDate,"",IFERROR(INDEX(cd_TMM_t_MTD,MATCH(MIN(EOMONTH(DATE(cfg_Year,9,1),0),cfg_LastDataDate),cd_Date,0)),"")) | M29: =IF(DATE(cfg_Year,10,1)>cfg_LastDataDate,"",IFERROR(INDEX(cd_TMM_t_MTD,MATCH(MIN(EOMONTH(DATE(cfg_Year,10,1),0),cfg_LastDataDate),cd_Date,0)),"")) | N29: =IF(DATE(cfg_Year,11,1)>cfg_LastDataDate,"",IFERROR(INDEX(cd_TMM_t_MTD,MATCH(MIN(EOMONTH(DATE(cfg_Year,11,1),0),cfg_LastDataDate),cd_Date,0)),"")) | O29: =IF(DATE(cfg_Year,12,1)>cfg_LastDataDate,"",IFERROR(INDEX(cd_TMM_t_MTD,MATCH(MIN(EOMONTH(DATE(cfg_Year,12,1),0),cfg_LastDataDate),cd_Date,0)),"")) | P29: =IFERROR(INDEX(cd_TMM_t_YTD,MATCH(MIN(cfg_YearEnd,cfg_LastDataDate),cd_Date,0)),"")
C30: Budget | D30: =IFERROR(INDEX(cd_Bud_TMM_t_Month,MATCH(DATE(cfg_Year,1,1),cd_Date,0)),"") | E30: =IFERROR(INDEX(cd_Bud_TMM_t_Month,MATCH(DATE(cfg_Year,2,1),cd_Date,0)),"") | F30: =IFERROR(INDEX(cd_Bud_TMM_t_Month,MATCH(DATE(cfg_Year,3,1),cd_Date,0)),"") | G30: =IFERROR(INDEX(cd_Bud_TMM_t_Month,MATCH(DATE(cfg_Year,4,1),cd_Date,0)),"") | H30: =IFERROR(INDEX(cd_Bud_TMM_t_Month,MATCH(DATE(cfg_Year,5,1),cd_Date,0)),"") | I30: =IFERROR(INDEX(cd_Bud_TMM_t_Month,MATCH(DATE(cfg_Year,6,1),cd_Date,0)),"") | J30: =IFERROR(INDEX(cd_Bud_TMM_t_Month,MATCH(DATE(cfg_Year,7,1),cd_Date,0)),"") | K30: =IFERROR(INDEX(cd_Bud_TMM_t_Month,MATCH(DATE(cfg_Year,8,1),cd_Date,0)),"") | L30: =IFERROR(INDEX(cd_Bud_TMM_t_Month,MATCH(DATE(cfg_Year,9,1),cd_Date,0)),"") | M30: =IFERROR(INDEX(cd_Bud_TMM_t_Month,MATCH(DATE(cfg_Year,10,1),cd_Date,0)),"") | N30: =IFERROR(INDEX(cd_Bud_TMM_t_Month,MATCH(DATE(cfg_Year,11,1),cd_Date,0)),"") | O30: =IFERROR(INDEX(cd_Bud_TMM_t_Month,MATCH(DATE(cfg_Year,12,1),cd_Date,0)),"") | P30: =IFERROR(INDEX(cd_Bud_TMM_t_YTD,MATCH(cfg_YearEnd,cd_Date,0)),"")
C31: Variance | D31: =IF(AND(ISNUMBER(D29),ISNUMBER(D30),D30<>0),D29/D30-1,"") | E31: =IF(AND(ISNUMBER(E29),ISNUMBER(E30),E30<>0),E29/E30-1,"") | F31: =IF(AND(ISNUMBER(F29),ISNUMBER(F30),F30<>0),F29/F30-1,"") | G31: =IF(AND(ISNUMBER(G29),ISNUMBER(G30),G30<>0),G29/G30-1,"") | H31: =IF(AND(ISNUMBER(H29),ISNUMBER(H30),H30<>0),H29/H30-1,"") | I31: =IF(AND(ISNUMBER(I29),ISNUMBER(I30),I30<>0),I29/I30-1,"") | J31: =IF(AND(ISNUMBER(J29),ISNUMBER(J30),J30<>0),J29/J30-1,"") | K31: =IF(AND(ISNUMBER(K29),ISNUMBER(K30),K30<>0),K29/K30-1,"") | ... P31: =IF(AND(ISNUMBER(P29),ISNUMBER(P30),P30<>0),P29/P30-1,"")
B33: Strip ratio (waste : ore) | C33: Actual | D33: =IF(DATE(cfg_Year,1,1)>cfg_LastDataDate,"",IFERROR(INDEX(cd_Strip_Ratio_MTD,MATCH(MIN(EOMONTH(DATE(cfg_Year,1,1),0),cfg_LastDataDate),cd_Date,0)),"")) | E33: =IF(DATE(cfg_Year,2,1)>cfg_LastDataDate,"",IFERROR(INDEX(cd_Strip_Ratio_MTD,MATCH(MIN(EOMONTH(DATE(cfg_Year,2,1),0),cfg_LastDataDate),cd_Date,0)),"")) | F33: =IF(DATE(cfg_Year,3,1)>cfg_LastDataDate,"",IFERROR(INDEX(cd_Strip_Ratio_MTD,MATCH(MIN(EOMONTH(DATE(cfg_Year,3,1),0),cfg_LastDataDate),cd_Date,0)),"")) | G33: =IF(DATE(cfg_Year,4,1)>cfg_LastDataDate,"",IFERROR(INDEX(cd_Strip_Ratio_MTD,MATCH(MIN(EOMONTH(DATE(cfg_Year,4,1),0),cfg_LastDataDate),cd_Date,0)),"")) | H33: =IF(DATE(cfg_Year,5,1)>cfg_LastDataDate,"",IFERROR(INDEX(cd_Strip_Ratio_MTD,MATCH(MIN(EOMONTH(DATE(cfg_Year,5,1),0),cfg_LastDataDate),cd_Date,0)),"")) | I33: =IF(DATE(cfg_Year,6,1)>cfg_LastDataDate,"",IFERROR(INDEX(cd_Strip_Ratio_MTD,MATCH(MIN(EOMONTH(DATE(cfg_Year,6,1),0),cfg_LastDataDate),cd_Date,0)),"")) | J33: =IF(DATE(cfg_Year,7,1)>cfg_LastDataDate,"",IFERROR(INDEX(cd_Strip_Ratio_MTD,MATCH(MIN(EOMONTH(DATE(cfg_Year,7,1),0),cfg_LastDataDate),cd_Date,0)),"")) | K33: =IF(DATE(cfg_Year,8,1)>cfg_LastDataDate,"",IFERROR(INDEX(cd_Strip_Ratio_MTD,MATCH(MIN(EOMONTH(DATE(cfg_Year,8,1),0),cfg_LastDataDate),cd_Date,0)),"")) | L33: =IF(DATE(cfg_Year,9,1)>cfg_LastDataDate,"",IFERROR(INDEX(cd_Strip_Ratio_MTD,MATCH(MIN(EOMONTH(DATE(cfg_Year,9,1),0),cfg_LastDataDate),cd_Date,0)),"")) | M33: =IF(DATE(cfg_Year,10,1)>cfg_LastDataDate,"",IFERROR(INDEX(cd_Strip_Ratio_MTD,MATCH(MIN(EOMONTH(DATE(cfg_Year,10,1),0),cfg_LastDataDate),cd_Date,0)),"")) | N33: =IF(DATE(cfg_Year,11,1)>cfg_LastDataDate,"",IFERROR(INDEX(cd_Strip_Ratio_MTD,MATCH(MIN(EOMONTH(DATE(cfg_Year,11,1),0),cfg_LastDataDate),cd_Date,0)),"")) | O33: =IF(DATE(cfg_Year,12,1)>cfg_LastDataDate,"",IFERROR(INDEX(cd_Strip_Ratio_MTD,MATCH(MIN(EOMONTH(DATE(cfg_Year,12,1),0),cfg_LastDataDate),cd_Date,0)),"")) | P33: =IFERROR(INDEX(cd_Strip_Ratio_YTD,MATCH(MIN(cfg_YearEnd,cfg_LastDataDate),cd_Date,0)),"")
C34: Budget | D34: =IFERROR(INDEX(cd_Bud_Strip_Ratio_Month,MATCH(DATE(cfg_Year,1,1),cd_Date,0)),"") | E34: =IFERROR(INDEX(cd_Bud_Strip_Ratio_Month,MATCH(DATE(cfg_Year,2,1),cd_Date,0)),"") | F34: =IFERROR(INDEX(cd_Bud_Strip_Ratio_Month,MATCH(DATE(cfg_Year,3,1),cd_Date,0)),"") | G34: =IFERROR(INDEX(cd_Bud_Strip_Ratio_Month,MATCH(DATE(cfg_Year,4,1),cd_Date,0)),"") | H34: =IFERROR(INDEX(cd_Bud_Strip_Ratio_Month,MATCH(DATE(cfg_Year,5,1),cd_Date,0)),"") | I34: =IFERROR(INDEX(cd_Bud_Strip_Ratio_Month,MATCH(DATE(cfg_Year,6,1),cd_Date,0)),"") | J34: =IFERROR(INDEX(cd_Bud_Strip_Ratio_Month,MATCH(DATE(cfg_Year,7,1),cd_Date,0)),"") | K34: =IFERROR(INDEX(cd_Bud_Strip_Ratio_Month,MATCH(DATE(cfg_Year,8,1),cd_Date,0)),"") | L34: =IFERROR(INDEX(cd_Bud_Strip_Ratio_Month,MATCH(DATE(cfg_Year,9,1),cd_Date,0)),"") | M34: =IFERROR(INDEX(cd_Bud_Strip_Ratio_Month,MATCH(DATE(cfg_Year,10,1),cd_Date,0)),"") | N34: =IFERROR(INDEX(cd_Bud_Strip_Ratio_Month,MATCH(DATE(cfg_Year,11,1),cd_Date,0)),"") | O34: =IFERROR(INDEX(cd_Bud_Strip_Ratio_Month,MATCH(DATE(cfg_Year,12,1),cd_Date,0)),"") | P34: =IFERROR(INDEX(cd_Bud_Strip_Ratio_YTD,MATCH(cfg_YearEnd,cd_Date,0)),"")
C35: Variance | D35: =IF(AND(ISNUMBER(D33),ISNUMBER(D34),D34<>0),D33/D34-1,"") | E35: =IF(AND(ISNUMBER(E33),ISNUMBER(E34),E34<>0),E33/E34-1,"") | F35: =IF(AND(ISNUMBER(F33),ISNUMBER(F34),F34<>0),F33/F34-1,"") | G35: =IF(AND(ISNUMBER(G33),ISNUMBER(G34),G34<>0),G33/G34-1,"") | H35: =IF(AND(ISNUMBER(H33),ISNUMBER(H34),H34<>0),H33/H34-1,"") | I35: =IF(AND(ISNUMBER(I33),ISNUMBER(I34),I34<>0),I33/I34-1,"") | J35: =IF(AND(ISNUMBER(J33),ISNUMBER(J34),J34<>0),J33/J34-1,"") | K35: =IF(AND(ISNUMBER(K33),ISNUMBER(K34),K34<>0),K33/K34-1,"") | ... P35: =IF(AND(ISNUMBER(P33),ISNUMBER(P34),P34<>0),P33/P34-1,"")
B37: Drilled | C37: Actual | D37: =IF(DATE(cfg_Year,1,1)>cfg_LastDataDate,"",IFERROR(INDEX(cd_Drill_m_MTD,MATCH(MIN(EOMONTH(DATE(cfg_Year,1,1),0),cfg_LastDataDate),cd_Date,0)),"")) | E37: =IF(DATE(cfg_Year,2,1)>cfg_LastDataDate,"",IFERROR(INDEX(cd_Drill_m_MTD,MATCH(MIN(EOMONTH(DATE(cfg_Year,2,1),0),cfg_LastDataDate),cd_Date,0)),"")) | F37: =IF(DATE(cfg_Year,3,1)>cfg_LastDataDate,"",IFERROR(INDEX(cd_Drill_m_MTD,MATCH(MIN(EOMONTH(DATE(cfg_Year,3,1),0),cfg_LastDataDate),cd_Date,0)),"")) | G37: =IF(DATE(cfg_Year,4,1)>cfg_LastDataDate,"",IFERROR(INDEX(cd_Drill_m_MTD,MATCH(MIN(EOMONTH(DATE(cfg_Year,4,1),0),cfg_LastDataDate),cd_Date,0)),"")) | H37: =IF(DATE(cfg_Year,5,1)>cfg_LastDataDate,"",IFERROR(INDEX(cd_Drill_m_MTD,MATCH(MIN(EOMONTH(DATE(cfg_Year,5,1),0),cfg_LastDataDate),cd_Date,0)),"")) | I37: =IF(DATE(cfg_Year,6,1)>cfg_LastDataDate,"",IFERROR(INDEX(cd_Drill_m_MTD,MATCH(MIN(EOMONTH(DATE(cfg_Year,6,1),0),cfg_LastDataDate),cd_Date,0)),"")) | J37: =IF(DATE(cfg_Year,7,1)>cfg_LastDataDate,"",IFERROR(INDEX(cd_Drill_m_MTD,MATCH(MIN(EOMONTH(DATE(cfg_Year,7,1),0),cfg_LastDataDate),cd_Date,0)),"")) | K37: =IF(DATE(cfg_Year,8,1)>cfg_LastDataDate,"",IFERROR(INDEX(cd_Drill_m_MTD,MATCH(MIN(EOMONTH(DATE(cfg_Year,8,1),0),cfg_LastDataDate),cd_Date,0)),"")) | L37: =IF(DATE(cfg_Year,9,1)>cfg_LastDataDate,"",IFERROR(INDEX(cd_Drill_m_MTD,MATCH(MIN(EOMONTH(DATE(cfg_Year,9,1),0),cfg_LastDataDate),cd_Date,0)),"")) | M37: =IF(DATE(cfg_Year,10,1)>cfg_LastDataDate,"",IFERROR(INDEX(cd_Drill_m_MTD,MATCH(MIN(EOMONTH(DATE(cfg_Year,10,1),0),cfg_LastDataDate),cd_Date,0)),"")) | N37: =IF(DATE(cfg_Year,11,1)>cfg_LastDataDate,"",IFERROR(INDEX(cd_Drill_m_MTD,MATCH(MIN(EOMONTH(DATE(cfg_Year,11,1),0),cfg_LastDataDate),cd_Date,0)),"")) | O37: =IF(DATE(cfg_Year,12,1)>cfg_LastDataDate,"",IFERROR(INDEX(cd_Drill_m_MTD,MATCH(MIN(EOMONTH(DATE(cfg_Year,12,1),0),cfg_LastDataDate),cd_Date,0)),"")) | P37: =IFERROR(INDEX(cd_Drill_m_YTD,MATCH(MIN(cfg_YearEnd,cfg_LastDataDate),cd_Date,0)),"")
C38: Budget | D38: =IFERROR(INDEX(cd_Bud_Drill_m_Month,MATCH(DATE(cfg_Year,1,1),cd_Date,0)),"") | E38: =IFERROR(INDEX(cd_Bud_Drill_m_Month,MATCH(DATE(cfg_Year,2,1),cd_Date,0)),"") | F38: =IFERROR(INDEX(cd_Bud_Drill_m_Month,MATCH(DATE(cfg_Year,3,1),cd_Date,0)),"") | G38: =IFERROR(INDEX(cd_Bud_Drill_m_Month,MATCH(DATE(cfg_Year,4,1),cd_Date,0)),"") | H38: =IFERROR(INDEX(cd_Bud_Drill_m_Month,MATCH(DATE(cfg_Year,5,1),cd_Date,0)),"") | I38: =IFERROR(INDEX(cd_Bud_Drill_m_Month,MATCH(DATE(cfg_Year,6,1),cd_Date,0)),"") | J38: =IFERROR(INDEX(cd_Bud_Drill_m_Month,MATCH(DATE(cfg_Year,7,1),cd_Date,0)),"") | K38: =IFERROR(INDEX(cd_Bud_Drill_m_Month,MATCH(DATE(cfg_Year,8,1),cd_Date,0)),"") | L38: =IFERROR(INDEX(cd_Bud_Drill_m_Month,MATCH(DATE(cfg_Year,9,1),cd_Date,0)),"") | M38: =IFERROR(INDEX(cd_Bud_Drill_m_Month,MATCH(DATE(cfg_Year,10,1),cd_Date,0)),"") | N38: =IFERROR(INDEX(cd_Bud_Drill_m_Month,MATCH(DATE(cfg_Year,11,1),cd_Date,0)),"") | O38: =IFERROR(INDEX(cd_Bud_Drill_m_Month,MATCH(DATE(cfg_Year,12,1),cd_Date,0)),"") | P38: =IFERROR(INDEX(cd_Bud_Drill_m_YTD,MATCH(cfg_YearEnd,cd_Date,0)),"")
C39: Variance | D39: =IF(AND(ISNUMBER(D37),ISNUMBER(D38),D38<>0),D37/D38-1,"") | E39: =IF(AND(ISNUMBER(E37),ISNUMBER(E38),E38<>0),E37/E38-1,"") | F39: =IF(AND(ISNUMBER(F37),ISNUMBER(F38),F38<>0),F37/F38-1,"") | G39: =IF(AND(ISNUMBER(G37),ISNUMBER(G38),G38<>0),G37/G38-1,"") | H39: =IF(AND(ISNUMBER(H37),ISNUMBER(H38),H38<>0),H37/H38-1,"") | I39: =IF(AND(ISNUMBER(I37),ISNUMBER(I38),I38<>0),I37/I38-1,"") | J39: =IF(AND(ISNUMBER(J37),ISNUMBER(J38),J38<>0),J37/J38-1,"") | K39: =IF(AND(ISNUMBER(K37),ISNUMBER(K38),K38<>0),K37/K38-1,"") | ... P39: =IF(AND(ISNUMBER(P37),ISNUMBER(P38),P38<>0),P37/P38-1,"")
B41: Milled | C41: Actual | D41: =IF(DATE(cfg_Year,1,1)>cfg_LastDataDate,"",IFERROR(INDEX(cd_Milled_t_MTD,MATCH(MIN(EOMONTH(DATE(cfg_Year,1,1),0),cfg_LastDataDate),cd_Date,0)),"")) | E41: =IF(DATE(cfg_Year,2,1)>cfg_LastDataDate,"",IFERROR(INDEX(cd_Milled_t_MTD,MATCH(MIN(EOMONTH(DATE(cfg_Year,2,1),0),cfg_LastDataDate),cd_Date,0)),"")) | F41: =IF(DATE(cfg_Year,3,1)>cfg_LastDataDate,"",IFERROR(INDEX(cd_Milled_t_MTD,MATCH(MIN(EOMONTH(DATE(cfg_Year,3,1),0),cfg_LastDataDate),cd_Date,0)),"")) | G41: =IF(DATE(cfg_Year,4,1)>cfg_LastDataDate,"",IFERROR(INDEX(cd_Milled_t_MTD,MATCH(MIN(EOMONTH(DATE(cfg_Year,4,1),0),cfg_LastDataDate),cd_Date,0)),"")) | H41: =IF(DATE(cfg_Year,5,1)>cfg_LastDataDate,"",IFERROR(INDEX(cd_Milled_t_MTD,MATCH(MIN(EOMONTH(DATE(cfg_Year,5,1),0),cfg_LastDataDate),cd_Date,0)),"")) | I41: =IF(DATE(cfg_Year,6,1)>cfg_LastDataDate,"",IFERROR(INDEX(cd_Milled_t_MTD,MATCH(MIN(EOMONTH(DATE(cfg_Year,6,1),0),cfg_LastDataDate),cd_Date,0)),"")) | J41: =IF(DATE(cfg_Year,7,1)>cfg_LastDataDate,"",IFERROR(INDEX(cd_Milled_t_MTD,MATCH(MIN(EOMONTH(DATE(cfg_Year,7,1),0),cfg_LastDataDate),cd_Date,0)),"")) | K41: =IF(DATE(cfg_Year,8,1)>cfg_LastDataDate,"",IFERROR(INDEX(cd_Milled_t_MTD,MATCH(MIN(EOMONTH(DATE(cfg_Year,8,1),0),cfg_LastDataDate),cd_Date,0)),"")) | L41: =IF(DATE(cfg_Year,9,1)>cfg_LastDataDate,"",IFERROR(INDEX(cd_Milled_t_MTD,MATCH(MIN(EOMONTH(DATE(cfg_Year,9,1),0),cfg_LastDataDate),cd_Date,0)),"")) | M41: =IF(DATE(cfg_Year,10,1)>cfg_LastDataDate,"",IFERROR(INDEX(cd_Milled_t_MTD,MATCH(MIN(EOMONTH(DATE(cfg_Year,10,1),0),cfg_LastDataDate),cd_Date,0)),"")) | N41: =IF(DATE(cfg_Year,11,1)>cfg_LastDataDate,"",IFERROR(INDEX(cd_Milled_t_MTD,MATCH(MIN(EOMONTH(DATE(cfg_Year,11,1),0),cfg_LastDataDate),cd_Date,0)),"")) | O41: =IF(DATE(cfg_Year,12,1)>cfg_LastDataDate,"",IFERROR(INDEX(cd_Milled_t_MTD,MATCH(MIN(EOMONTH(DATE(cfg_Year,12,1),0),cfg_LastDataDate),cd_Date,0)),"")) | P41: =IFERROR(INDEX(cd_Milled_t_YTD,MATCH(MIN(cfg_YearEnd,cfg_LastDataDate),cd_Date,0)),"")
C42: Budget | D42: =IFERROR(INDEX(cd_Bud_Milled_t_Month,MATCH(DATE(cfg_Year,1,1),cd_Date,0)),"") | E42: =IFERROR(INDEX(cd_Bud_Milled_t_Month,MATCH(DATE(cfg_Year,2,1),cd_Date,0)),"") | F42: =IFERROR(INDEX(cd_Bud_Milled_t_Month,MATCH(DATE(cfg_Year,3,1),cd_Date,0)),"") | G42: =IFERROR(INDEX(cd_Bud_Milled_t_Month,MATCH(DATE(cfg_Year,4,1),cd_Date,0)),"") | H42: =IFERROR(INDEX(cd_Bud_Milled_t_Month,MATCH(DATE(cfg_Year,5,1),cd_Date,0)),"") | I42: =IFERROR(INDEX(cd_Bud_Milled_t_Month,MATCH(DATE(cfg_Year,6,1),cd_Date,0)),"") | J42: =IFERROR(INDEX(cd_Bud_Milled_t_Month,MATCH(DATE(cfg_Year,7,1),cd_Date,0)),"") | K42: =IFERROR(INDEX(cd_Bud_Milled_t_Month,MATCH(DATE(cfg_Year,8,1),cd_Date,0)),"") | L42: =IFERROR(INDEX(cd_Bud_Milled_t_Month,MATCH(DATE(cfg_Year,9,1),cd_Date,0)),"") | M42: =IFERROR(INDEX(cd_Bud_Milled_t_Month,MATCH(DATE(cfg_Year,10,1),cd_Date,0)),"") | N42: =IFERROR(INDEX(cd_Bud_Milled_t_Month,MATCH(DATE(cfg_Year,11,1),cd_Date,0)),"") | O42: =IFERROR(INDEX(cd_Bud_Milled_t_Month,MATCH(DATE(cfg_Year,12,1),cd_Date,0)),"") | P42: =IFERROR(INDEX(cd_Bud_Milled_t_YTD,MATCH(cfg_YearEnd,cd_Date,0)),"")
C43: Variance | D43: =IF(AND(ISNUMBER(D41),ISNUMBER(D42),D42<>0),D41/D42-1,"") | E43: =IF(AND(ISNUMBER(E41),ISNUMBER(E42),E42<>0),E41/E42-1,"") | F43: =IF(AND(ISNUMBER(F41),ISNUMBER(F42),F42<>0),F41/F42-1,"") | G43: =IF(AND(ISNUMBER(G41),ISNUMBER(G42),G42<>0),G41/G42-1,"") | H43: =IF(AND(ISNUMBER(H41),ISNUMBER(H42),H42<>0),H41/H42-1,"") | I43: =IF(AND(ISNUMBER(I41),ISNUMBER(I42),I42<>0),I41/I42-1,"") | J43: =IF(AND(ISNUMBER(J41),ISNUMBER(J42),J42<>0),J41/J42-1,"") | K43: =IF(AND(ISNUMBER(K41),ISNUMBER(K42),K42<>0),K41/K42-1,"") | ... P43: =IF(AND(ISNUMBER(P41),ISNUMBER(P42),P42<>0),P41/P42-1,"")
B45: Head grade | C45: Actual | D45: =IF(DATE(cfg_Year,1,1)>cfg_LastDataDate,"",IFERROR(INDEX(cd_Head_Grade_gpt_MTD,MATCH(MIN(EOMONTH(DATE(cfg_Year,1,1),0),cfg_LastDataDate),cd_Date,0)),"")) | E45: =IF(DATE(cfg_Year,2,1)>cfg_LastDataDate,"",IFERROR(INDEX(cd_Head_Grade_gpt_MTD,MATCH(MIN(EOMONTH(DATE(cfg_Year,2,1),0),cfg_LastDataDate),cd_Date,0)),"")) | F45: =IF(DATE(cfg_Year,3,1)>cfg_LastDataDate,"",IFERROR(INDEX(cd_Head_Grade_gpt_MTD,MATCH(MIN(EOMONTH(DATE(cfg_Year,3,1),0),cfg_LastDataDate),cd_Date,0)),"")) | G45: =IF(DATE(cfg_Year,4,1)>cfg_LastDataDate,"",IFERROR(INDEX(cd_Head_Grade_gpt_MTD,MATCH(MIN(EOMONTH(DATE(cfg_Year,4,1),0),cfg_LastDataDate),cd_Date,0)),"")) | H45: =IF(DATE(cfg_Year,5,1)>cfg_LastDataDate,"",IFERROR(INDEX(cd_Head_Grade_gpt_MTD,MATCH(MIN(EOMONTH(DATE(cfg_Year,5,1),0),cfg_LastDataDate),cd_Date,0)),"")) | I45: =IF(DATE(cfg_Year,6,1)>cfg_LastDataDate,"",IFERROR(INDEX(cd_Head_Grade_gpt_MTD,MATCH(MIN(EOMONTH(DATE(cfg_Year,6,1),0),cfg_LastDataDate),cd_Date,0)),"")) | J45: =IF(DATE(cfg_Year,7,1)>cfg_LastDataDate,"",IFERROR(INDEX(cd_Head_Grade_gpt_MTD,MATCH(MIN(EOMONTH(DATE(cfg_Year,7,1),0),cfg_LastDataDate),cd_Date,0)),"")) | K45: =IF(DATE(cfg_Year,8,1)>cfg_LastDataDate,"",IFERROR(INDEX(cd_Head_Grade_gpt_MTD,MATCH(MIN(EOMONTH(DATE(cfg_Year,8,1),0),cfg_LastDataDate),cd_Date,0)),"")) | L45: =IF(DATE(cfg_Year,9,1)>cfg_LastDataDate,"",IFERROR(INDEX(cd_Head_Grade_gpt_MTD,MATCH(MIN(EOMONTH(DATE(cfg_Year,9,1),0),cfg_LastDataDate),cd_Date,0)),"")) | M45: =IF(DATE(cfg_Year,10,1)>cfg_LastDataDate,"",IFERROR(INDEX(cd_Head_Grade_gpt_MTD,MATCH(MIN(EOMONTH(DATE(cfg_Year,10,1),0),cfg_LastDataDate),cd_Date,0)),"")) | N45: =IF(DATE(cfg_Year,11,1)>cfg_LastDataDate,"",IFERROR(INDEX(cd_Head_Grade_gpt_MTD,MATCH(MIN(EOMONTH(DATE(cfg_Year,11,1),0),cfg_LastDataDate),cd_Date,0)),"")) | O45: =IF(DATE(cfg_Year,12,1)>cfg_LastDataDate,"",IFERROR(INDEX(cd_Head_Grade_gpt_MTD,MATCH(MIN(EOMONTH(DATE(cfg_Year,12,1),0),cfg_LastDataDate),cd_Date,0)),"")) | P45: =IFERROR(INDEX(cd_Head_Grade_gpt_YTD,MATCH(MIN(cfg_YearEnd,cfg_LastDataDate),cd_Date,0)),"")
C46: Budget | D46: =IFERROR(INDEX(cd_Bud_Head_Grade_gpt_Month,MATCH(DATE(cfg_Year,1,1),cd_Date,0)),"") | E46: =IFERROR(INDEX(cd_Bud_Head_Grade_gpt_Month,MATCH(DATE(cfg_Year,2,1),cd_Date,0)),"") | F46: =IFERROR(INDEX(cd_Bud_Head_Grade_gpt_Month,MATCH(DATE(cfg_Year,3,1),cd_Date,0)),"") | G46: =IFERROR(INDEX(cd_Bud_Head_Grade_gpt_Month,MATCH(DATE(cfg_Year,4,1),cd_Date,0)),"") | H46: =IFERROR(INDEX(cd_Bud_Head_Grade_gpt_Month,MATCH(DATE(cfg_Year,5,1),cd_Date,0)),"") | I46: =IFERROR(INDEX(cd_Bud_Head_Grade_gpt_Month,MATCH(DATE(cfg_Year,6,1),cd_Date,0)),"") | J46: =IFERROR(INDEX(cd_Bud_Head_Grade_gpt_Month,MATCH(DATE(cfg_Year,7,1),cd_Date,0)),"") | K46: =IFERROR(INDEX(cd_Bud_Head_Grade_gpt_Month,MATCH(DATE(cfg_Year,8,1),cd_Date,0)),"") | L46: =IFERROR(INDEX(cd_Bud_Head_Grade_gpt_Month,MATCH(DATE(cfg_Year,9,1),cd_Date,0)),"") | M46: =IFERROR(INDEX(cd_Bud_Head_Grade_gpt_Month,MATCH(DATE(cfg_Year,10,1),cd_Date,0)),"") | N46: =IFERROR(INDEX(cd_Bud_Head_Grade_gpt_Month,MATCH(DATE(cfg_Year,11,1),cd_Date,0)),"") | O46: =IFERROR(INDEX(cd_Bud_Head_Grade_gpt_Month,MATCH(DATE(cfg_Year,12,1),cd_Date,0)),"") | P46: =IFERROR(INDEX(cd_Bud_Head_Grade_gpt_YTD,MATCH(cfg_YearEnd,cd_Date,0)),"")
C47: Variance | D47: =IF(AND(ISNUMBER(D45),ISNUMBER(D46),D46<>0),D45/D46-1,"") | E47: =IF(AND(ISNUMBER(E45),ISNUMBER(E46),E46<>0),E45/E46-1,"") | F47: =IF(AND(ISNUMBER(F45),ISNUMBER(F46),F46<>0),F45/F46-1,"") | G47: =IF(AND(ISNUMBER(G45),ISNUMBER(G46),G46<>0),G45/G46-1,"") | H47: =IF(AND(ISNUMBER(H45),ISNUMBER(H46),H46<>0),H45/H46-1,"") | I47: =IF(AND(ISNUMBER(I45),ISNUMBER(I46),I46<>0),I45/I46-1,"") | J47: =IF(AND(ISNUMBER(J45),ISNUMBER(J46),J46<>0),J45/J46-1,"") | K47: =IF(AND(ISNUMBER(K45),ISNUMBER(K46),K46<>0),K45/K46-1,"") | ... P47: =IF(AND(ISNUMBER(P45),ISNUMBER(P46),P46<>0),P45/P46-1,"")
B49: Recovery | C49: Actual | D49: =IF(DATE(cfg_Year,1,1)>cfg_LastDataDate,"",IFERROR(INDEX(cd_Recovery_pct_MTD,MATCH(MIN(EOMONTH(DATE(cfg_Year,1,1),0),cfg_LastDataDate),cd_Date,0)),"")) | E49: =IF(DATE(cfg_Year,2,1)>cfg_LastDataDate,"",IFERROR(INDEX(cd_Recovery_pct_MTD,MATCH(MIN(EOMONTH(DATE(cfg_Year,2,1),0),cfg_LastDataDate),cd_Date,0)),"")) | F49: =IF(DATE(cfg_Year,3,1)>cfg_LastDataDate,"",IFERROR(INDEX(cd_Recovery_pct_MTD,MATCH(MIN(EOMONTH(DATE(cfg_Year,3,1),0),cfg_LastDataDate),cd_Date,0)),"")) | G49: =IF(DATE(cfg_Year,4,1)>cfg_LastDataDate,"",IFERROR(INDEX(cd_Recovery_pct_MTD,MATCH(MIN(EOMONTH(DATE(cfg_Year,4,1),0),cfg_LastDataDate),cd_Date,0)),"")) | H49: =IF(DATE(cfg_Year,5,1)>cfg_LastDataDate,"",IFERROR(INDEX(cd_Recovery_pct_MTD,MATCH(MIN(EOMONTH(DATE(cfg_Year,5,1),0),cfg_LastDataDate),cd_Date,0)),"")) | I49: =IF(DATE(cfg_Year,6,1)>cfg_LastDataDate,"",IFERROR(INDEX(cd_Recovery_pct_MTD,MATCH(MIN(EOMONTH(DATE(cfg_Year,6,1),0),cfg_LastDataDate),cd_Date,0)),"")) | J49: =IF(DATE(cfg_Year,7,1)>cfg_LastDataDate,"",IFERROR(INDEX(cd_Recovery_pct_MTD,MATCH(MIN(EOMONTH(DATE(cfg_Year,7,1),0),cfg_LastDataDate),cd_Date,0)),"")) | K49: =IF(DATE(cfg_Year,8,1)>cfg_LastDataDate,"",IFERROR(INDEX(cd_Recovery_pct_MTD,MATCH(MIN(EOMONTH(DATE(cfg_Year,8,1),0),cfg_LastDataDate),cd_Date,0)),"")) | L49: =IF(DATE(cfg_Year,9,1)>cfg_LastDataDate,"",IFERROR(INDEX(cd_Recovery_pct_MTD,MATCH(MIN(EOMONTH(DATE(cfg_Year,9,1),0),cfg_LastDataDate),cd_Date,0)),"")) | M49: =IF(DATE(cfg_Year,10,1)>cfg_LastDataDate,"",IFERROR(INDEX(cd_Recovery_pct_MTD,MATCH(MIN(EOMONTH(DATE(cfg_Year,10,1),0),cfg_LastDataDate),cd_Date,0)),"")) | N49: =IF(DATE(cfg_Year,11,1)>cfg_LastDataDate,"",IFERROR(INDEX(cd_Recovery_pct_MTD,MATCH(MIN(EOMONTH(DATE(cfg_Year,11,1),0),cfg_LastDataDate),cd_Date,0)),"")) | O49: =IF(DATE(cfg_Year,12,1)>cfg_LastDataDate,"",IFERROR(INDEX(cd_Recovery_pct_MTD,MATCH(MIN(EOMONTH(DATE(cfg_Year,12,1),0),cfg_LastDataDate),cd_Date,0)),"")) | P49: =IFERROR(INDEX(cd_Recovery_pct_YTD,MATCH(MIN(cfg_YearEnd,cfg_LastDataDate),cd_Date,0)),"")
C50: Budget | D50: =IFERROR(INDEX(cd_Bud_Recovery_pct_Month,MATCH(DATE(cfg_Year,1,1),cd_Date,0)),"") | E50: =IFERROR(INDEX(cd_Bud_Recovery_pct_Month,MATCH(DATE(cfg_Year,2,1),cd_Date,0)),"") | F50: =IFERROR(INDEX(cd_Bud_Recovery_pct_Month,MATCH(DATE(cfg_Year,3,1),cd_Date,0)),"") | G50: =IFERROR(INDEX(cd_Bud_Recovery_pct_Month,MATCH(DATE(cfg_Year,4,1),cd_Date,0)),"") | H50: =IFERROR(INDEX(cd_Bud_Recovery_pct_Month,MATCH(DATE(cfg_Year,5,1),cd_Date,0)),"") | I50: =IFERROR(INDEX(cd_Bud_Recovery_pct_Month,MATCH(DATE(cfg_Year,6,1),cd_Date,0)),"") | J50: =IFERROR(INDEX(cd_Bud_Recovery_pct_Month,MATCH(DATE(cfg_Year,7,1),cd_Date,0)),"") | K50: =IFERROR(INDEX(cd_Bud_Recovery_pct_Month,MATCH(DATE(cfg_Year,8,1),cd_Date,0)),"") | L50: =IFERROR(INDEX(cd_Bud_Recovery_pct_Month,MATCH(DATE(cfg_Year,9,1),cd_Date,0)),"") | M50: =IFERROR(INDEX(cd_Bud_Recovery_pct_Month,MATCH(DATE(cfg_Year,10,1),cd_Date,0)),"") | N50: =IFERROR(INDEX(cd_Bud_Recovery_pct_Month,MATCH(DATE(cfg_Year,11,1),cd_Date,0)),"") | O50: =IFERROR(INDEX(cd_Bud_Recovery_pct_Month,MATCH(DATE(cfg_Year,12,1),cd_Date,0)),"") | P50: =IFERROR(INDEX(cd_Bud_Recovery_pct_YTD,MATCH(cfg_YearEnd,cd_Date,0)),"")
C51: Variance | D51: =IF(AND(ISNUMBER(D49),ISNUMBER(D50),D50<>0),D49/D50-1,"") | E51: =IF(AND(ISNUMBER(E49),ISNUMBER(E50),E50<>0),E49/E50-1,"") | F51: =IF(AND(ISNUMBER(F49),ISNUMBER(F50),F50<>0),F49/F50-1,"") | G51: =IF(AND(ISNUMBER(G49),ISNUMBER(G50),G50<>0),G49/G50-1,"") | H51: =IF(AND(ISNUMBER(H49),ISNUMBER(H50),H50<>0),H49/H50-1,"") | I51: =IF(AND(ISNUMBER(I49),ISNUMBER(I50),I50<>0),I49/I50-1,"") | J51: =IF(AND(ISNUMBER(J49),ISNUMBER(J50),J50<>0),J49/J50-1,"") | K51: =IF(AND(ISNUMBER(K49),ISNUMBER(K50),K50<>0),K49/K50-1,"") | ... P51: =IF(AND(ISNUMBER(P49),ISNUMBER(P50),P50<>0),P49/P50-1,"")
B53: Gold recovered | C53: Actual | D53: =IF(DATE(cfg_Year,1,1)>cfg_LastDataDate,"",IFERROR(INDEX(cd_Recovered_oz_MTD,MATCH(MIN(EOMONTH(DATE(cfg_Year,1,1),0),cfg_LastDataDate),cd_Date,0)),"")) | E53: =IF(DATE(cfg_Year,2,1)>cfg_LastDataDate,"",IFERROR(INDEX(cd_Recovered_oz_MTD,MATCH(MIN(EOMONTH(DATE(cfg_Year,2,1),0),cfg_LastDataDate),cd_Date,0)),"")) | F53: =IF(DATE(cfg_Year,3,1)>cfg_LastDataDate,"",IFERROR(INDEX(cd_Recovered_oz_MTD,MATCH(MIN(EOMONTH(DATE(cfg_Year,3,1),0),cfg_LastDataDate),cd_Date,0)),"")) | G53: =IF(DATE(cfg_Year,4,1)>cfg_LastDataDate,"",IFERROR(INDEX(cd_Recovered_oz_MTD,MATCH(MIN(EOMONTH(DATE(cfg_Year,4,1),0),cfg_LastDataDate),cd_Date,0)),"")) | H53: =IF(DATE(cfg_Year,5,1)>cfg_LastDataDate,"",IFERROR(INDEX(cd_Recovered_oz_MTD,MATCH(MIN(EOMONTH(DATE(cfg_Year,5,1),0),cfg_LastDataDate),cd_Date,0)),"")) | I53: =IF(DATE(cfg_Year,6,1)>cfg_LastDataDate,"",IFERROR(INDEX(cd_Recovered_oz_MTD,MATCH(MIN(EOMONTH(DATE(cfg_Year,6,1),0),cfg_LastDataDate),cd_Date,0)),"")) | J53: =IF(DATE(cfg_Year,7,1)>cfg_LastDataDate,"",IFERROR(INDEX(cd_Recovered_oz_MTD,MATCH(MIN(EOMONTH(DATE(cfg_Year,7,1),0),cfg_LastDataDate),cd_Date,0)),"")) | K53: =IF(DATE(cfg_Year,8,1)>cfg_LastDataDate,"",IFERROR(INDEX(cd_Recovered_oz_MTD,MATCH(MIN(EOMONTH(DATE(cfg_Year,8,1),0),cfg_LastDataDate),cd_Date,0)),"")) | L53: =IF(DATE(cfg_Year,9,1)>cfg_LastDataDate,"",IFERROR(INDEX(cd_Recovered_oz_MTD,MATCH(MIN(EOMONTH(DATE(cfg_Year,9,1),0),cfg_LastDataDate),cd_Date,0)),"")) | M53: =IF(DATE(cfg_Year,10,1)>cfg_LastDataDate,"",IFERROR(INDEX(cd_Recovered_oz_MTD,MATCH(MIN(EOMONTH(DATE(cfg_Year,10,1),0),cfg_LastDataDate),cd_Date,0)),"")) | N53: =IF(DATE(cfg_Year,11,1)>cfg_LastDataDate,"",IFERROR(INDEX(cd_Recovered_oz_MTD,MATCH(MIN(EOMONTH(DATE(cfg_Year,11,1),0),cfg_LastDataDate),cd_Date,0)),"")) | O53: =IF(DATE(cfg_Year,12,1)>cfg_LastDataDate,"",IFERROR(INDEX(cd_Recovered_oz_MTD,MATCH(MIN(EOMONTH(DATE(cfg_Year,12,1),0),cfg_LastDataDate),cd_Date,0)),"")) | P53: =IFERROR(INDEX(cd_Recovered_oz_YTD,MATCH(MIN(cfg_YearEnd,cfg_LastDataDate),cd_Date,0)),"")
C54: Budget | D54: =IFERROR(INDEX(cd_Bud_Recovered_oz_Month,MATCH(DATE(cfg_Year,1,1),cd_Date,0)),"") | E54: =IFERROR(INDEX(cd_Bud_Recovered_oz_Month,MATCH(DATE(cfg_Year,2,1),cd_Date,0)),"") | F54: =IFERROR(INDEX(cd_Bud_Recovered_oz_Month,MATCH(DATE(cfg_Year,3,1),cd_Date,0)),"") | G54: =IFERROR(INDEX(cd_Bud_Recovered_oz_Month,MATCH(DATE(cfg_Year,4,1),cd_Date,0)),"") | H54: =IFERROR(INDEX(cd_Bud_Recovered_oz_Month,MATCH(DATE(cfg_Year,5,1),cd_Date,0)),"") | I54: =IFERROR(INDEX(cd_Bud_Recovered_oz_Month,MATCH(DATE(cfg_Year,6,1),cd_Date,0)),"") | J54: =IFERROR(INDEX(cd_Bud_Recovered_oz_Month,MATCH(DATE(cfg_Year,7,1),cd_Date,0)),"") | K54: =IFERROR(INDEX(cd_Bud_Recovered_oz_Month,MATCH(DATE(cfg_Year,8,1),cd_Date,0)),"") | L54: =IFERROR(INDEX(cd_Bud_Recovered_oz_Month,MATCH(DATE(cfg_Year,9,1),cd_Date,0)),"") | M54: =IFERROR(INDEX(cd_Bud_Recovered_oz_Month,MATCH(DATE(cfg_Year,10,1),cd_Date,0)),"") | N54: =IFERROR(INDEX(cd_Bud_Recovered_oz_Month,MATCH(DATE(cfg_Year,11,1),cd_Date,0)),"") | O54: =IFERROR(INDEX(cd_Bud_Recovered_oz_Month,MATCH(DATE(cfg_Year,12,1),cd_Date,0)),"") | P54: =IFERROR(INDEX(cd_Bud_Recovered_oz_YTD,MATCH(cfg_YearEnd,cd_Date,0)),"")
C55: Variance | D55: =IF(AND(ISNUMBER(D53),ISNUMBER(D54),D54<>0),D53/D54-1,"") | E55: =IF(AND(ISNUMBER(E53),ISNUMBER(E54),E54<>0),E53/E54-1,"") | F55: =IF(AND(ISNUMBER(F53),ISNUMBER(F54),F54<>0),F53/F54-1,"") | G55: =IF(AND(ISNUMBER(G53),ISNUMBER(G54),G54<>0),G53/G54-1,"") | H55: =IF(AND(ISNUMBER(H53),ISNUMBER(H54),H54<>0),H53/H54-1,"") | I55: =IF(AND(ISNUMBER(I53),ISNUMBER(I54),I54<>0),I53/I54-1,"") | J55: =IF(AND(ISNUMBER(J53),ISNUMBER(J54),J54<>0),J53/J54-1,"") | K55: =IF(AND(ISNUMBER(K53),ISNUMBER(K54),K54<>0),K53/K54-1,"") | ... P55: =IF(AND(ISNUMBER(P53),ISNUMBER(P54),P54<>0),P53/P54-1,"")
B57: Gold poured | C57: Actual | D57: =IF(DATE(cfg_Year,1,1)>cfg_LastDataDate,"",IFERROR(INDEX(cd_Gold_Poured_oz_MTD,MATCH(MIN(EOMONTH(DATE(cfg_Year,1,1),0),cfg_LastDataDate),cd_Date,0)),"")) | E57: =IF(DATE(cfg_Year,2,1)>cfg_LastDataDate,"",IFERROR(INDEX(cd_Gold_Poured_oz_MTD,MATCH(MIN(EOMONTH(DATE(cfg_Year,2,1),0),cfg_LastDataDate),cd_Date,0)),"")) | F57: =IF(DATE(cfg_Year,3,1)>cfg_LastDataDate,"",IFERROR(INDEX(cd_Gold_Poured_oz_MTD,MATCH(MIN(EOMONTH(DATE(cfg_Year,3,1),0),cfg_LastDataDate),cd_Date,0)),"")) | G57: =IF(DATE(cfg_Year,4,1)>cfg_LastDataDate,"",IFERROR(INDEX(cd_Gold_Poured_oz_MTD,MATCH(MIN(EOMONTH(DATE(cfg_Year,4,1),0),cfg_LastDataDate),cd_Date,0)),"")) | H57: =IF(DATE(cfg_Year,5,1)>cfg_LastDataDate,"",IFERROR(INDEX(cd_Gold_Poured_oz_MTD,MATCH(MIN(EOMONTH(DATE(cfg_Year,5,1),0),cfg_LastDataDate),cd_Date,0)),"")) | I57: =IF(DATE(cfg_Year,6,1)>cfg_LastDataDate,"",IFERROR(INDEX(cd_Gold_Poured_oz_MTD,MATCH(MIN(EOMONTH(DATE(cfg_Year,6,1),0),cfg_LastDataDate),cd_Date,0)),"")) | J57: =IF(DATE(cfg_Year,7,1)>cfg_LastDataDate,"",IFERROR(INDEX(cd_Gold_Poured_oz_MTD,MATCH(MIN(EOMONTH(DATE(cfg_Year,7,1),0),cfg_LastDataDate),cd_Date,0)),"")) | K57: =IF(DATE(cfg_Year,8,1)>cfg_LastDataDate,"",IFERROR(INDEX(cd_Gold_Poured_oz_MTD,MATCH(MIN(EOMONTH(DATE(cfg_Year,8,1),0),cfg_LastDataDate),cd_Date,0)),"")) | L57: =IF(DATE(cfg_Year,9,1)>cfg_LastDataDate,"",IFERROR(INDEX(cd_Gold_Poured_oz_MTD,MATCH(MIN(EOMONTH(DATE(cfg_Year,9,1),0),cfg_LastDataDate),cd_Date,0)),"")) | M57: =IF(DATE(cfg_Year,10,1)>cfg_LastDataDate,"",IFERROR(INDEX(cd_Gold_Poured_oz_MTD,MATCH(MIN(EOMONTH(DATE(cfg_Year,10,1),0),cfg_LastDataDate),cd_Date,0)),"")) | N57: =IF(DATE(cfg_Year,11,1)>cfg_LastDataDate,"",IFERROR(INDEX(cd_Gold_Poured_oz_MTD,MATCH(MIN(EOMONTH(DATE(cfg_Year,11,1),0),cfg_LastDataDate),cd_Date,0)),"")) | O57: =IF(DATE(cfg_Year,12,1)>cfg_LastDataDate,"",IFERROR(INDEX(cd_Gold_Poured_oz_MTD,MATCH(MIN(EOMONTH(DATE(cfg_Year,12,1),0),cfg_LastDataDate),cd_Date,0)),"")) | P57: =IFERROR(INDEX(cd_Gold_Poured_oz_YTD,MATCH(MIN(cfg_YearEnd,cfg_LastDataDate),cd_Date,0)),"")
C58: Budget | D58: =IFERROR(INDEX(cd_Bud_Gold_Poured_oz_Month,MATCH(DATE(cfg_Year,1,1),cd_Date,0)),"") | E58: =IFERROR(INDEX(cd_Bud_Gold_Poured_oz_Month,MATCH(DATE(cfg_Year,2,1),cd_Date,0)),"") | F58: =IFERROR(INDEX(cd_Bud_Gold_Poured_oz_Month,MATCH(DATE(cfg_Year,3,1),cd_Date,0)),"") | G58: =IFERROR(INDEX(cd_Bud_Gold_Poured_oz_Month,MATCH(DATE(cfg_Year,4,1),cd_Date,0)),"") | H58: =IFERROR(INDEX(cd_Bud_Gold_Poured_oz_Month,MATCH(DATE(cfg_Year,5,1),cd_Date,0)),"") | I58: =IFERROR(INDEX(cd_Bud_Gold_Poured_oz_Month,MATCH(DATE(cfg_Year,6,1),cd_Date,0)),"") | J58: =IFERROR(INDEX(cd_Bud_Gold_Poured_oz_Month,MATCH(DATE(cfg_Year,7,1),cd_Date,0)),"") | K58: =IFERROR(INDEX(cd_Bud_Gold_Poured_oz_Month,MATCH(DATE(cfg_Year,8,1),cd_Date,0)),"") | L58: =IFERROR(INDEX(cd_Bud_Gold_Poured_oz_Month,MATCH(DATE(cfg_Year,9,1),cd_Date,0)),"") | M58: =IFERROR(INDEX(cd_Bud_Gold_Poured_oz_Month,MATCH(DATE(cfg_Year,10,1),cd_Date,0)),"") | N58: =IFERROR(INDEX(cd_Bud_Gold_Poured_oz_Month,MATCH(DATE(cfg_Year,11,1),cd_Date,0)),"") | O58: =IFERROR(INDEX(cd_Bud_Gold_Poured_oz_Month,MATCH(DATE(cfg_Year,12,1),cd_Date,0)),"") | P58: =IFERROR(INDEX(cd_Bud_Gold_Poured_oz_YTD,MATCH(cfg_YearEnd,cd_Date,0)),"")
C59: Variance | D59: =IF(AND(ISNUMBER(D57),ISNUMBER(D58),D58<>0),D57/D58-1,"") | E59: =IF(AND(ISNUMBER(E57),ISNUMBER(E58),E58<>0),E57/E58-1,"") | F59: =IF(AND(ISNUMBER(F57),ISNUMBER(F58),F58<>0),F57/F58-1,"") | G59: =IF(AND(ISNUMBER(G57),ISNUMBER(G58),G58<>0),G57/G58-1,"") | H59: =IF(AND(ISNUMBER(H57),ISNUMBER(H58),H58<>0),H57/H58-1,"") | I59: =IF(AND(ISNUMBER(I57),ISNUMBER(I58),I58<>0),I57/I58-1,"") | J59: =IF(AND(ISNUMBER(J57),ISNUMBER(J58),J58<>0),J57/J58-1,"") | K59: =IF(AND(ISNUMBER(K57),ISNUMBER(K58),K58<>0),K57/K58-1,"") | ... P59: =IF(AND(ISNUMBER(P57),ISNUMBER(P58),P58<>0),P57/P58-1,"")
B61: Gold sold | C61: Actual | D61: =IF(DATE(cfg_Year,1,1)>cfg_LastDataDate,"",IFERROR(INDEX(cd_Gold_Sold_oz_MTD,MATCH(MIN(EOMONTH(DATE(cfg_Year,1,1),0),cfg_LastDataDate),cd_Date,0)),"")) | E61: =IF(DATE(cfg_Year,2,1)>cfg_LastDataDate,"",IFERROR(INDEX(cd_Gold_Sold_oz_MTD,MATCH(MIN(EOMONTH(DATE(cfg_Year,2,1),0),cfg_LastDataDate),cd_Date,0)),"")) | F61: =IF(DATE(cfg_Year,3,1)>cfg_LastDataDate,"",IFERROR(INDEX(cd_Gold_Sold_oz_MTD,MATCH(MIN(EOMONTH(DATE(cfg_Year,3,1),0),cfg_LastDataDate),cd_Date,0)),"")) | G61: =IF(DATE(cfg_Year,4,1)>cfg_LastDataDate,"",IFERROR(INDEX(cd_Gold_Sold_oz_MTD,MATCH(MIN(EOMONTH(DATE(cfg_Year,4,1),0),cfg_LastDataDate),cd_Date,0)),"")) | H61: =IF(DATE(cfg_Year,5,1)>cfg_LastDataDate,"",IFERROR(INDEX(cd_Gold_Sold_oz_MTD,MATCH(MIN(EOMONTH(DATE(cfg_Year,5,1),0),cfg_LastDataDate),cd_Date,0)),"")) | I61: =IF(DATE(cfg_Year,6,1)>cfg_LastDataDate,"",IFERROR(INDEX(cd_Gold_Sold_oz_MTD,MATCH(MIN(EOMONTH(DATE(cfg_Year,6,1),0),cfg_LastDataDate),cd_Date,0)),"")) | J61: =IF(DATE(cfg_Year,7,1)>cfg_LastDataDate,"",IFERROR(INDEX(cd_Gold_Sold_oz_MTD,MATCH(MIN(EOMONTH(DATE(cfg_Year,7,1),0),cfg_LastDataDate),cd_Date,0)),"")) | K61: =IF(DATE(cfg_Year,8,1)>cfg_LastDataDate,"",IFERROR(INDEX(cd_Gold_Sold_oz_MTD,MATCH(MIN(EOMONTH(DATE(cfg_Year,8,1),0),cfg_LastDataDate),cd_Date,0)),"")) | L61: =IF(DATE(cfg_Year,9,1)>cfg_LastDataDate,"",IFERROR(INDEX(cd_Gold_Sold_oz_MTD,MATCH(MIN(EOMONTH(DATE(cfg_Year,9,1),0),cfg_LastDataDate),cd_Date,0)),"")) | M61: =IF(DATE(cfg_Year,10,1)>cfg_LastDataDate,"",IFERROR(INDEX(cd_Gold_Sold_oz_MTD,MATCH(MIN(EOMONTH(DATE(cfg_Year,10,1),0),cfg_LastDataDate),cd_Date,0)),"")) | N61: =IF(DATE(cfg_Year,11,1)>cfg_LastDataDate,"",IFERROR(INDEX(cd_Gold_Sold_oz_MTD,MATCH(MIN(EOMONTH(DATE(cfg_Year,11,1),0),cfg_LastDataDate),cd_Date,0)),"")) | O61: =IF(DATE(cfg_Year,12,1)>cfg_LastDataDate,"",IFERROR(INDEX(cd_Gold_Sold_oz_MTD,MATCH(MIN(EOMONTH(DATE(cfg_Year,12,1),0),cfg_LastDataDate),cd_Date,0)),"")) | P61: =IFERROR(INDEX(cd_Gold_Sold_oz_YTD,MATCH(MIN(cfg_YearEnd,cfg_LastDataDate),cd_Date,0)),"")
B62: Mill throughput | C62: Actual | D62: =IF(DATE(cfg_Year,1,1)>cfg_LastDataDate,"",IFERROR(INDEX(cd_Throughput_tph_MTD,MATCH(MIN(EOMONTH(DATE(cfg_Year,1,1),0),cfg_LastDataDate),cd_Date,0)),"")) | E62: =IF(DATE(cfg_Year,2,1)>cfg_LastDataDate,"",IFERROR(INDEX(cd_Throughput_tph_MTD,MATCH(MIN(EOMONTH(DATE(cfg_Year,2,1),0),cfg_LastDataDate),cd_Date,0)),"")) | F62: =IF(DATE(cfg_Year,3,1)>cfg_LastDataDate,"",IFERROR(INDEX(cd_Throughput_tph_MTD,MATCH(MIN(EOMONTH(DATE(cfg_Year,3,1),0),cfg_LastDataDate),cd_Date,0)),"")) | G62: =IF(DATE(cfg_Year,4,1)>cfg_LastDataDate,"",IFERROR(INDEX(cd_Throughput_tph_MTD,MATCH(MIN(EOMONTH(DATE(cfg_Year,4,1),0),cfg_LastDataDate),cd_Date,0)),"")) | H62: =IF(DATE(cfg_Year,5,1)>cfg_LastDataDate,"",IFERROR(INDEX(cd_Throughput_tph_MTD,MATCH(MIN(EOMONTH(DATE(cfg_Year,5,1),0),cfg_LastDataDate),cd_Date,0)),"")) | I62: =IF(DATE(cfg_Year,6,1)>cfg_LastDataDate,"",IFERROR(INDEX(cd_Throughput_tph_MTD,MATCH(MIN(EOMONTH(DATE(cfg_Year,6,1),0),cfg_LastDataDate),cd_Date,0)),"")) | J62: =IF(DATE(cfg_Year,7,1)>cfg_LastDataDate,"",IFERROR(INDEX(cd_Throughput_tph_MTD,MATCH(MIN(EOMONTH(DATE(cfg_Year,7,1),0),cfg_LastDataDate),cd_Date,0)),"")) | K62: =IF(DATE(cfg_Year,8,1)>cfg_LastDataDate,"",IFERROR(INDEX(cd_Throughput_tph_MTD,MATCH(MIN(EOMONTH(DATE(cfg_Year,8,1),0),cfg_LastDataDate),cd_Date,0)),"")) | L62: =IF(DATE(cfg_Year,9,1)>cfg_LastDataDate,"",IFERROR(INDEX(cd_Throughput_tph_MTD,MATCH(MIN(EOMONTH(DATE(cfg_Year,9,1),0),cfg_LastDataDate),cd_Date,0)),"")) | M62: =IF(DATE(cfg_Year,10,1)>cfg_LastDataDate,"",IFERROR(INDEX(cd_Throughput_tph_MTD,MATCH(MIN(EOMONTH(DATE(cfg_Year,10,1),0),cfg_LastDataDate),cd_Date,0)),"")) | N62: =IF(DATE(cfg_Year,11,1)>cfg_LastDataDate,"",IFERROR(INDEX(cd_Throughput_tph_MTD,MATCH(MIN(EOMONTH(DATE(cfg_Year,11,1),0),cfg_LastDataDate),cd_Date,0)),"")) | O62: =IF(DATE(cfg_Year,12,1)>cfg_LastDataDate,"",IFERROR(INDEX(cd_Throughput_tph_MTD,MATCH(MIN(EOMONTH(DATE(cfg_Year,12,1),0),cfg_LastDataDate),cd_Date,0)),"")) | P62: =IFERROR(INDEX(cd_Throughput_tph_YTD,MATCH(MIN(cfg_YearEnd,cfg_LastDataDate),cd_Date,0)),"")
B63: Mill availability | C63: Actual | D63: =IF(DATE(cfg_Year,1,1)>cfg_LastDataDate,"",IFERROR(INDEX(cd_Mill_Availability_pct_MTD,MATCH(MIN(EOMONTH(DATE(cfg_Year,1,1),0),cfg_LastDataDate),cd_Date,0)),"")) | E63: =IF(DATE(cfg_Year,2,1)>cfg_LastDataDate,"",IFERROR(INDEX(cd_Mill_Availability_pct_MTD,MATCH(MIN(EOMONTH(DATE(cfg_Year,2,1),0),cfg_LastDataDate),cd_Date,0)),"")) | F63: =IF(DATE(cfg_Year,3,1)>cfg_LastDataDate,"",IFERROR(INDEX(cd_Mill_Availability_pct_MTD,MATCH(MIN(EOMONTH(DATE(cfg_Year,3,1),0),cfg_LastDataDate),cd_Date,0)),"")) | G63: =IF(DATE(cfg_Year,4,1)>cfg_LastDataDate,"",IFERROR(INDEX(cd_Mill_Availability_pct_MTD,MATCH(MIN(EOMONTH(DATE(cfg_Year,4,1),0),cfg_LastDataDate),cd_Date,0)),"")) | H63: =IF(DATE(cfg_Year,5,1)>cfg_LastDataDate,"",IFERROR(INDEX(cd_Mill_Availability_pct_MTD,MATCH(MIN(EOMONTH(DATE(cfg_Year,5,1),0),cfg_LastDataDate),cd_Date,0)),"")) | I63: =IF(DATE(cfg_Year,6,1)>cfg_LastDataDate,"",IFERROR(INDEX(cd_Mill_Availability_pct_MTD,MATCH(MIN(EOMONTH(DATE(cfg_Year,6,1),0),cfg_LastDataDate),cd_Date,0)),"")) | J63: =IF(DATE(cfg_Year,7,1)>cfg_LastDataDate,"",IFERROR(INDEX(cd_Mill_Availability_pct_MTD,MATCH(MIN(EOMONTH(DATE(cfg_Year,7,1),0),cfg_LastDataDate),cd_Date,0)),"")) | K63: =IF(DATE(cfg_Year,8,1)>cfg_LastDataDate,"",IFERROR(INDEX(cd_Mill_Availability_pct_MTD,MATCH(MIN(EOMONTH(DATE(cfg_Year,8,1),0),cfg_LastDataDate),cd_Date,0)),"")) | L63: =IF(DATE(cfg_Year,9,1)>cfg_LastDataDate,"",IFERROR(INDEX(cd_Mill_Availability_pct_MTD,MATCH(MIN(EOMONTH(DATE(cfg_Year,9,1),0),cfg_LastDataDate),cd_Date,0)),"")) | M63: =IF(DATE(cfg_Year,10,1)>cfg_LastDataDate,"",IFERROR(INDEX(cd_Mill_Availability_pct_MTD,MATCH(MIN(EOMONTH(DATE(cfg_Year,10,1),0),cfg_LastDataDate),cd_Date,0)),"")) | N63: =IF(DATE(cfg_Year,11,1)>cfg_LastDataDate,"",IFERROR(INDEX(cd_Mill_Availability_pct_MTD,MATCH(MIN(EOMONTH(DATE(cfg_Year,11,1),0),cfg_LastDataDate),cd_Date,0)),"")) | O63: =IF(DATE(cfg_Year,12,1)>cfg_LastDataDate,"",IFERROR(INDEX(cd_Mill_Availability_pct_MTD,MATCH(MIN(EOMONTH(DATE(cfg_Year,12,1),0),cfg_LastDataDate),cd_Date,0)),"")) | P63: =IFERROR(INDEX(cd_Mill_Availability_pct_YTD,MATCH(MIN(cfg_YearEnd,cfg_LastDataDate),cd_Date,0)),"")
B64: Mill utilisation | C64: Actual | D64: =IF(DATE(cfg_Year,1,1)>cfg_LastDataDate,"",IFERROR(INDEX(cd_Mill_Utilisation_pct_MTD,MATCH(MIN(EOMONTH(DATE(cfg_Year,1,1),0),cfg_LastDataDate),cd_Date,0)),"")) | E64: =IF(DATE(cfg_Year,2,1)>cfg_LastDataDate,"",IFERROR(INDEX(cd_Mill_Utilisation_pct_MTD,MATCH(MIN(EOMONTH(DATE(cfg_Year,2,1),0),cfg_LastDataDate),cd_Date,0)),"")) | F64: =IF(DATE(cfg_Year,3,1)>cfg_LastDataDate,"",IFERROR(INDEX(cd_Mill_Utilisation_pct_MTD,MATCH(MIN(EOMONTH(DATE(cfg_Year,3,1),0),cfg_LastDataDate),cd_Date,0)),"")) | G64: =IF(DATE(cfg_Year,4,1)>cfg_LastDataDate,"",IFERROR(INDEX(cd_Mill_Utilisation_pct_MTD,MATCH(MIN(EOMONTH(DATE(cfg_Year,4,1),0),cfg_LastDataDate),cd_Date,0)),"")) | H64: =IF(DATE(cfg_Year,5,1)>cfg_LastDataDate,"",IFERROR(INDEX(cd_Mill_Utilisation_pct_MTD,MATCH(MIN(EOMONTH(DATE(cfg_Year,5,1),0),cfg_LastDataDate),cd_Date,0)),"")) | I64: =IF(DATE(cfg_Year,6,1)>cfg_LastDataDate,"",IFERROR(INDEX(cd_Mill_Utilisation_pct_MTD,MATCH(MIN(EOMONTH(DATE(cfg_Year,6,1),0),cfg_LastDataDate),cd_Date,0)),"")) | J64: =IF(DATE(cfg_Year,7,1)>cfg_LastDataDate,"",IFERROR(INDEX(cd_Mill_Utilisation_pct_MTD,MATCH(MIN(EOMONTH(DATE(cfg_Year,7,1),0),cfg_LastDataDate),cd_Date,0)),"")) | K64: =IF(DATE(cfg_Year,8,1)>cfg_LastDataDate,"",IFERROR(INDEX(cd_Mill_Utilisation_pct_MTD,MATCH(MIN(EOMONTH(DATE(cfg_Year,8,1),0),cfg_LastDataDate),cd_Date,0)),"")) | L64: =IF(DATE(cfg_Year,9,1)>cfg_LastDataDate,"",IFERROR(INDEX(cd_Mill_Utilisation_pct_MTD,MATCH(MIN(EOMONTH(DATE(cfg_Year,9,1),0),cfg_LastDataDate),cd_Date,0)),"")) | M64: =IF(DATE(cfg_Year,10,1)>cfg_LastDataDate,"",IFERROR(INDEX(cd_Mill_Utilisation_pct_MTD,MATCH(MIN(EOMONTH(DATE(cfg_Year,10,1),0),cfg_LastDataDate),cd_Date,0)),"")) | N64: =IF(DATE(cfg_Year,11,1)>cfg_LastDataDate,"",IFERROR(INDEX(cd_Mill_Utilisation_pct_MTD,MATCH(MIN(EOMONTH(DATE(cfg_Year,11,1),0),cfg_LastDataDate),cd_Date,0)),"")) | O64: =IF(DATE(cfg_Year,12,1)>cfg_LastDataDate,"",IFERROR(INDEX(cd_Mill_Utilisation_pct_MTD,MATCH(MIN(EOMONTH(DATE(cfg_Year,12,1),0),cfg_LastDataDate),cd_Date,0)),"")) | P64: =IFERROR(INDEX(cd_Mill_Utilisation_pct_YTD,MATCH(MIN(cfg_YearEnd,cfg_LastDataDate),cd_Date,0)),"")
B65: Cyanide consumption | C65: Actual | D65: =IF(DATE(cfg_Year,1,1)>cfg_LastDataDate,"",IFERROR(INDEX(cd_Cyanide_kgpt_MTD,MATCH(MIN(EOMONTH(DATE(cfg_Year,1,1),0),cfg_LastDataDate),cd_Date,0)),"")) | E65: =IF(DATE(cfg_Year,2,1)>cfg_LastDataDate,"",IFERROR(INDEX(cd_Cyanide_kgpt_MTD,MATCH(MIN(EOMONTH(DATE(cfg_Year,2,1),0),cfg_LastDataDate),cd_Date,0)),"")) | F65: =IF(DATE(cfg_Year,3,1)>cfg_LastDataDate,"",IFERROR(INDEX(cd_Cyanide_kgpt_MTD,MATCH(MIN(EOMONTH(DATE(cfg_Year,3,1),0),cfg_LastDataDate),cd_Date,0)),"")) | G65: =IF(DATE(cfg_Year,4,1)>cfg_LastDataDate,"",IFERROR(INDEX(cd_Cyanide_kgpt_MTD,MATCH(MIN(EOMONTH(DATE(cfg_Year,4,1),0),cfg_LastDataDate),cd_Date,0)),"")) | H65: =IF(DATE(cfg_Year,5,1)>cfg_LastDataDate,"",IFERROR(INDEX(cd_Cyanide_kgpt_MTD,MATCH(MIN(EOMONTH(DATE(cfg_Year,5,1),0),cfg_LastDataDate),cd_Date,0)),"")) | I65: =IF(DATE(cfg_Year,6,1)>cfg_LastDataDate,"",IFERROR(INDEX(cd_Cyanide_kgpt_MTD,MATCH(MIN(EOMONTH(DATE(cfg_Year,6,1),0),cfg_LastDataDate),cd_Date,0)),"")) | J65: =IF(DATE(cfg_Year,7,1)>cfg_LastDataDate,"",IFERROR(INDEX(cd_Cyanide_kgpt_MTD,MATCH(MIN(EOMONTH(DATE(cfg_Year,7,1),0),cfg_LastDataDate),cd_Date,0)),"")) | K65: =IF(DATE(cfg_Year,8,1)>cfg_LastDataDate,"",IFERROR(INDEX(cd_Cyanide_kgpt_MTD,MATCH(MIN(EOMONTH(DATE(cfg_Year,8,1),0),cfg_LastDataDate),cd_Date,0)),"")) | L65: =IF(DATE(cfg_Year,9,1)>cfg_LastDataDate,"",IFERROR(INDEX(cd_Cyanide_kgpt_MTD,MATCH(MIN(EOMONTH(DATE(cfg_Year,9,1),0),cfg_LastDataDate),cd_Date,0)),"")) | M65: =IF(DATE(cfg_Year,10,1)>cfg_LastDataDate,"",IFERROR(INDEX(cd_Cyanide_kgpt_MTD,MATCH(MIN(EOMONTH(DATE(cfg_Year,10,1),0),cfg_LastDataDate),cd_Date,0)),"")) | N65: =IF(DATE(cfg_Year,11,1)>cfg_LastDataDate,"",IFERROR(INDEX(cd_Cyanide_kgpt_MTD,MATCH(MIN(EOMONTH(DATE(cfg_Year,11,1),0),cfg_LastDataDate),cd_Date,0)),"")) | O65: =IF(DATE(cfg_Year,12,1)>cfg_LastDataDate,"",IFERROR(INDEX(cd_Cyanide_kgpt_MTD,MATCH(MIN(EOMONTH(DATE(cfg_Year,12,1),0),cfg_LastDataDate),cd_Date,0)),"")) | P65: =IFERROR(INDEX(cd_Cyanide_kgpt_YTD,MATCH(MIN(cfg_YearEnd,cfg_LastDataDate),cd_Date,0)),"")
B66: Power consumption | C66: Actual | D66: =IF(DATE(cfg_Year,1,1)>cfg_LastDataDate,"",IFERROR(INDEX(cd_Power_kWhpt_MTD,MATCH(MIN(EOMONTH(DATE(cfg_Year,1,1),0),cfg_LastDataDate),cd_Date,0)),"")) | E66: =IF(DATE(cfg_Year,2,1)>cfg_LastDataDate,"",IFERROR(INDEX(cd_Power_kWhpt_MTD,MATCH(MIN(EOMONTH(DATE(cfg_Year,2,1),0),cfg_LastDataDate),cd_Date,0)),"")) | F66: =IF(DATE(cfg_Year,3,1)>cfg_LastDataDate,"",IFERROR(INDEX(cd_Power_kWhpt_MTD,MATCH(MIN(EOMONTH(DATE(cfg_Year,3,1),0),cfg_LastDataDate),cd_Date,0)),"")) | G66: =IF(DATE(cfg_Year,4,1)>cfg_LastDataDate,"",IFERROR(INDEX(cd_Power_kWhpt_MTD,MATCH(MIN(EOMONTH(DATE(cfg_Year,4,1),0),cfg_LastDataDate),cd_Date,0)),"")) | H66: =IF(DATE(cfg_Year,5,1)>cfg_LastDataDate,"",IFERROR(INDEX(cd_Power_kWhpt_MTD,MATCH(MIN(EOMONTH(DATE(cfg_Year,5,1),0),cfg_LastDataDate),cd_Date,0)),"")) | I66: =IF(DATE(cfg_Year,6,1)>cfg_LastDataDate,"",IFERROR(INDEX(cd_Power_kWhpt_MTD,MATCH(MIN(EOMONTH(DATE(cfg_Year,6,1),0),cfg_LastDataDate),cd_Date,0)),"")) | J66: =IF(DATE(cfg_Year,7,1)>cfg_LastDataDate,"",IFERROR(INDEX(cd_Power_kWhpt_MTD,MATCH(MIN(EOMONTH(DATE(cfg_Year,7,1),0),cfg_LastDataDate),cd_Date,0)),"")) | K66: =IF(DATE(cfg_Year,8,1)>cfg_LastDataDate,"",IFERROR(INDEX(cd_Power_kWhpt_MTD,MATCH(MIN(EOMONTH(DATE(cfg_Year,8,1),0),cfg_LastDataDate),cd_Date,0)),"")) | L66: =IF(DATE(cfg_Year,9,1)>cfg_LastDataDate,"",IFERROR(INDEX(cd_Power_kWhpt_MTD,MATCH(MIN(EOMONTH(DATE(cfg_Year,9,1),0),cfg_LastDataDate),cd_Date,0)),"")) | M66: =IF(DATE(cfg_Year,10,1)>cfg_LastDataDate,"",IFERROR(INDEX(cd_Power_kWhpt_MTD,MATCH(MIN(EOMONTH(DATE(cfg_Year,10,1),0),cfg_LastDataDate),cd_Date,0)),"")) | N66: =IF(DATE(cfg_Year,11,1)>cfg_LastDataDate,"",IFERROR(INDEX(cd_Power_kWhpt_MTD,MATCH(MIN(EOMONTH(DATE(cfg_Year,11,1),0),cfg_LastDataDate),cd_Date,0)),"")) | O66: =IF(DATE(cfg_Year,12,1)>cfg_LastDataDate,"",IFERROR(INDEX(cd_Power_kWhpt_MTD,MATCH(MIN(EOMONTH(DATE(cfg_Year,12,1),0),cfg_LastDataDate),cd_Date,0)),"")) | P66: =IFERROR(INDEX(cd_Power_kWhpt_YTD,MATCH(MIN(cfg_YearEnd,cfg_LastDataDate),cd_Date,0)),"")

Sheet Plant
A1: Processing plant, one row per day
A2: Owner: Processing (met accountant / shift supervisor). Yellow-free rule: type values only in the blue-headed columns; grey-headed columns are formulas.
A4: Date | B4: Crushed (t) | C4: Milled (t) | D4: Head grade (g/t) | E4: Tails grade (g/t) | F4: Gravity gold (oz) | G4: Gold poured (oz) | H4: Mill run hours (h) | I4: Planned maintenance (h) | J4: Unplanned downtime (h) | K4: Crusher run hours (h) | L4: Cyanide (kg) | M4: Lime (kg) | N4: Grinding media (kg) | O4: Power (kWh) | P4: Raw water (m3) | Q4: Gold in circuit (oz) | R4: Comments | S4: Contained gold in feed (oz) | T4: Gold lost to tails (oz) | U4: Gold recovered (oz) | V4: Recovery (%) | W4: Throughput (t/h) | X4: Mill availability (%) | Y4: Mill utilisation (%)
A5: Date | B5: Crushed_t | C5: Milled_t | D5: Head_Grade_gpt | E5: Tails_Grade_gpt | F5: Gravity_Gold_oz | G5: Gold_Poured_oz | H5: Mill_Run_h | I5: Mill_Planned_Maint_h | J5: Mill_Unplanned_Down_h | K5: Crusher_Run_h | L5: Cyanide_kg | M5: Lime_kg | N5: Grinding_Media_kg | O5: Power_kWh | P5: Raw_Water_m3 | Q5: GIC_oz | R5: Comments | S5: Feed_oz | T5: Tails_oz | U5: Recovered_oz | V5: Recovery_pct | W5: Throughput_tph | X5: Availability_pct | Y5: Utilisation_pct
A6: 46023 | S6: =IF(tblPlant[[#This Row],[Milled_t]]="","",tblPlant[[#This Row],[Milled_t]]*tblPlant[[#This Row],[Head_Grade_gpt]]/cfg_TroyOz) | T6: =IF(tblPlant[[#This Row],[Milled_t]]="","",tblPlant[[#This Row],[Milled_t]]*tblPlant[[#This Row],[Tails_Grade_gpt]]/cfg_TroyOz) | U6: =IF(tblPlant[[#This Row],[Milled_t]]="","",tblPlant[[#This Row],[Feed_oz]]-tblPlant[[#This Row],[Tails_oz]]) | V6: =IF(AND(tblPlant[[#This Row],[Milled_t]]<>"",tblPlant[[#This Row],[Feed_oz]]>0),tblPlant[[#This Row],[Recovered_oz]]/tblPlant[[#This Row],[Feed_oz]],"") | W6: =IF(AND(tblPlant[[#This Row],[Milled_t]]<>"",tblPlant[[#This Row],[Mill_Run_h]]>0),tblPlant[[#This Row],[Milled_t]]/tblPlant[[#This Row],[Mill_Run_h]],"") | X6: =IF(tblPlant[[#This Row],[Mill_Run_h]]="","",(24-tblPlant[[#This Row],[Mill_Planned_Maint_h]]-tblPlant[[#This Row],[Mill_Unplanned_Down_h]])/24) | Y6: =IF(AND(tblPlant[[#This Row],[Mill_Run_h]]<>"",(24-tblPlant[[#This Row],[Mill_Planned_Maint_h]]-tblPlant[[#This Row],[Mill_Unplanned_Down_h]])>0),tblPlant[[#This Row],[Mill_Run_h]]/(24-tblPlant[[#This Row],[Mill_Planned_Maint_h]]-tblPlant[[#This Row],[Mill_Unplanned_Down_h]]),"")
A7: 46024 | S7: =IF(tblPlant[[#This Row],[Milled_t]]="","",tblPlant[[#This Row],[Milled_t]]*tblPlant[[#This Row],[Head_Grade_gpt]]/cfg_TroyOz) | T7: =IF(tblPlant[[#This Row],[Milled_t]]="","",tblPlant[[#This Row],[Milled_t]]*tblPlant[[#This Row],[Tails_Grade_gpt]]/cfg_TroyOz) | U7: =IF(tblPlant[[#This Row],[Milled_t]]="","",tblPlant[[#This Row],[Feed_oz]]-tblPlant[[#This Row],[Tails_oz]]) | V7: =IF(AND(tblPlant[[#This Row],[Milled_t]]<>"",tblPlant[[#This Row],[Feed_oz]]>0),tblPlant[[#This Row],[Recovered_oz]]/tblPlant[[#This Row],[Feed_oz]],"") | W7: =IF(AND(tblPlant[[#This Row],[Milled_t]]<>"",tblPlant[[#This Row],[Mill_Run_h]]>0),tblPlant[[#This Row],[Milled_t]]/tblPlant[[#This Row],[Mill_Run_h]],"") | X7: =IF(tblPlant[[#This Row],[Mill_Run_h]]="","",(24-tblPlant[[#This Row],[Mill_Planned_Maint_h]]-tblPlant[[#This Row],[Mill_Unplanned_Down_h]])/24) | Y7: =IF(AND(tblPlant[[#This Row],[Mill_Run_h]]<>"",(24-tblPlant[[#This Row],[Mill_Planned_Maint_h]]-tblPlant[[#This Row],[Mill_Unplanned_Down_h]])>0),tblPlant[[#This Row],[Mill_Run_h]]/(24-tblPlant[[#This Row],[Mill_Planned_Maint_h]]-tblPlant[[#This Row],[Mill_Unplanned_Down_h]]),"")
A8: 46025 | S8: =IF(tblPlant[[#This Row],[Milled_t]]="","",tblPlant[[#This Row],[Milled_t]]*tblPlant[[#This Row],[Head_Grade_gpt]]/cfg_TroyOz) | T8: =IF(tblPlant[[#This Row],[Milled_t]]="","",tblPlant[[#This Row],[Milled_t]]*tblPlant[[#This Row],[Tails_Grade_gpt]]/cfg_TroyOz) | U8: =IF(tblPlant[[#This Row],[Milled_t]]="","",tblPlant[[#This Row],[Feed_oz]]-tblPlant[[#This Row],[Tails_oz]]) | V8: =IF(AND(tblPlant[[#This Row],[Milled_t]]<>"",tblPlant[[#This Row],[Feed_oz]]>0),tblPlant[[#This Row],[Recovered_oz]]/tblPlant[[#This Row],[Feed_oz]],"") | W8: =IF(AND(tblPlant[[#This Row],[Milled_t]]<>"",tblPlant[[#This Row],[Mill_Run_h]]>0),tblPlant[[#This Row],[Milled_t]]/tblPlant[[#This Row],[Mill_Run_h]],"") | X8: =IF(tblPlant[[#This Row],[Mill_Run_h]]="","",(24-tblPlant[[#This Row],[Mill_Planned_Maint_h]]-tblPlant[[#This Row],[Mill_Unplanned_Down_h]])/24) | Y8: =IF(AND(tblPlant[[#This Row],[Mill_Run_h]]<>"",(24-tblPlant[[#This Row],[Mill_Planned_Maint_h]]-tblPlant[[#This Row],[Mill_Unplanned_Down_h]])>0),tblPlant[[#This Row],[Mill_Run_h]]/(24-tblPlant[[#This Row],[Mill_Planned_Maint_h]]-tblPlant[[#This Row],[Mill_Unplanned_Down_h]]),"")
A9: 46026 | S9: =IF(tblPlant[[#This Row],[Milled_t]]="","",tblPlant[[#This Row],[Milled_t]]*tblPlant[[#This Row],[Head_Grade_gpt]]/cfg_TroyOz) | T9: =IF(tblPlant[[#This Row],[Milled_t]]="","",tblPlant[[#This Row],[Milled_t]]*tblPlant[[#This Row],[Tails_Grade_gpt]]/cfg_TroyOz) | U9: =IF(tblPlant[[#This Row],[Milled_t]]="","",tblPlant[[#This Row],[Feed_oz]]-tblPlant[[#This Row],[Tails_oz]]) | V9: =IF(AND(tblPlant[[#This Row],[Milled_t]]<>"",tblPlant[[#This Row],[Feed_oz]]>0),tblPlant[[#This Row],[Recovered_oz]]/tblPlant[[#This Row],[Feed_oz]],"") | W9: =IF(AND(tblPlant[[#This Row],[Milled_t]]<>"",tblPlant[[#This Row],[Mill_Run_h]]>0),tblPlant[[#This Row],[Milled_t]]/tblPlant[[#This Row],[Mill_Run_h]],"") | X9: =IF(tblPlant[[#This Row],[Mill_Run_h]]="","",(24-tblPlant[[#This Row],[Mill_Planned_Maint_h]]-tblPlant[[#This Row],[Mill_Unplanned_Down_h]])/24) | Y9: =IF(AND(tblPlant[[#This Row],[Mill_Run_h]]<>"",(24-tblPlant[[#This Row],[Mill_Planned_Maint_h]]-tblPlant[[#This Row],[Mill_Unplanned_Down_h]])>0),tblPlant[[#This Row],[Mill_Run_h]]/(24-tblPlant[[#This Row],[Mill_Planned_Maint_h]]-tblPlant[[#This Row],[Mill_Unplanned_Down_h]]),"")
A10: 46027 | S10: =IF(tblPlant[[#This Row],[Milled_t]]="","",tblPlant[[#This Row],[Milled_t]]*tblPlant[[#This Row],[Head_Grade_gpt]]/cfg_TroyOz) | T10: =IF(tblPlant[[#This Row],[Milled_t]]="","",tblPlant[[#This Row],[Milled_t]]*tblPlant[[#This Row],[Tails_Grade_gpt]]/cfg_TroyOz) | U10: =IF(tblPlant[[#This Row],[Milled_t]]="","",tblPlant[[#This Row],[Feed_oz]]-tblPlant[[#This Row],[Tails_oz]]) | V10: =IF(AND(tblPlant[[#This Row],[Milled_t]]<>"",tblPlant[[#This Row],[Feed_oz]]>0),tblPlant[[#This Row],[Recovered_oz]]/tblPlant[[#This Row],[Feed_oz]],"") | W10: =IF(AND(tblPlant[[#This Row],[Milled_t]]<>"",tblPlant[[#This Row],[Mill_Run_h]]>0),tblPlant[[#This Row],[Milled_t]]/tblPlant[[#This Row],[Mill_Run_h]],"") | X10: =IF(tblPlant[[#This Row],[Mill_Run_h]]="","",(24-tblPlant[[#This Row],[Mill_Planned_Maint_h]]-tblPlant[[#This Row],[Mill_Unplanned_Down_h]])/24) | Y10: =IF(AND(tblPlant[[#This Row],[Mill_Run_h]]<>"",(24-tblPlant[[#This Row],[Mill_Planned_Maint_h]]-tblPlant[[#This Row],[Mill_Unplanned_Down_h]])>0),tblPlant[[#This Row],[Mill_Run_h]]/(24-tblPlant[[#This Row],[Mill_Planned_Maint_h]]-tblPlant[[#This Row],[Mill_Unplanned_Down_h]]),"")
A11: 46028 | S11: =IF(tblPlant[[#This Row],[Milled_t]]="","",tblPlant[[#This Row],[Milled_t]]*tblPlant[[#This Row],[Head_Grade_gpt]]/cfg_TroyOz) | T11: =IF(tblPlant[[#This Row],[Milled_t]]="","",tblPlant[[#This Row],[Milled_t]]*tblPlant[[#This Row],[Tails_Grade_gpt]]/cfg_TroyOz) | U11: =IF(tblPlant[[#This Row],[Milled_t]]="","",tblPlant[[#This Row],[Feed_oz]]-tblPlant[[#This Row],[Tails_oz]]) | V11: =IF(AND(tblPlant[[#This Row],[Milled_t]]<>"",tblPlant[[#This Row],[Feed_oz]]>0),tblPlant[[#This Row],[Recovered_oz]]/tblPlant[[#This Row],[Feed_oz]],"") | W11: =IF(AND(tblPlant[[#This Row],[Milled_t]]<>"",tblPlant[[#This Row],[Mill_Run_h]]>0),tblPlant[[#This Row],[Milled_t]]/tblPlant[[#This Row],[Mill_Run_h]],"") | X11: =IF(tblPlant[[#This Row],[Mill_Run_h]]="","",(24-tblPlant[[#This Row],[Mill_Planned_Maint_h]]-tblPlant[[#This Row],[Mill_Unplanned_Down_h]])/24) | Y11: =IF(AND(tblPlant[[#This Row],[Mill_Run_h]]<>"",(24-tblPlant[[#This Row],[Mill_Planned_Maint_h]]-tblPlant[[#This Row],[Mill_Unplanned_Down_h]])>0),tblPlant[[#This Row],[Mill_Run_h]]/(24-tblPlant[[#This Row],[Mill_Planned_Maint_h]]-tblPlant[[#This Row],[Mill_Unplanned_Down_h]]),"")
A12: 46029 | S12: =IF(tblPlant[[#This Row],[Milled_t]]="","",tblPlant[[#This Row],[Milled_t]]*tblPlant[[#This Row],[Head_Grade_gpt]]/cfg_TroyOz) | T12: =IF(tblPlant[[#This Row],[Milled_t]]="","",tblPlant[[#This Row],[Milled_t]]*tblPlant[[#This Row],[Tails_Grade_gpt]]/cfg_TroyOz) | U12: =IF(tblPlant[[#This Row],[Milled_t]]="","",tblPlant[[#This Row],[Feed_oz]]-tblPlant[[#This Row],[Tails_oz]]) | V12: =IF(AND(tblPlant[[#This Row],[Milled_t]]<>"",tblPlant[[#This Row],[Feed_oz]]>0),tblPlant[[#This Row],[Recovered_oz]]/tblPlant[[#This Row],[Feed_oz]],"") | W12: =IF(AND(tblPlant[[#This Row],[Milled_t]]<>"",tblPlant[[#This Row],[Mill_Run_h]]>0),tblPlant[[#This Row],[Milled_t]]/tblPlant[[#This Row],[Mill_Run_h]],"") | X12: =IF(tblPlant[[#This Row],[Mill_Run_h]]="","",(24-tblPlant[[#This Row],[Mill_Planned_Maint_h]]-tblPlant[[#This Row],[Mill_Unplanned_Down_h]])/24) | Y12: =IF(AND(tblPlant[[#This Row],[Mill_Run_h]]<>"",(24-tblPlant[[#This Row],[Mill_Planned_Maint_h]]-tblPlant[[#This Row],[Mill_Unplanned_Down_h]])>0),tblPlant[[#This Row],[Mill_Run_h]]/(24-tblPlant[[#This Row],[Mill_Planned_Maint_h]]-tblPlant[[#This Row],[Mill_Unplanned_Down_h]]),"")
A13: 46030 | S13: =IF(tblPlant[[#This Row],[Milled_t]]="","",tblPlant[[#This Row],[Milled_t]]*tblPlant[[#This Row],[Head_Grade_gpt]]/cfg_TroyOz) | T13: =IF(tblPlant[[#This Row],[Milled_t]]="","",tblPlant[[#This Row],[Milled_t]]*tblPlant[[#This Row],[Tails_Grade_gpt]]/cfg_TroyOz) | U13: =IF(tblPlant[[#This Row],[Milled_t]]="","",tblPlant[[#This Row],[Feed_oz]]-tblPlant[[#This Row],[Tails_oz]]) | V13: =IF(AND(tblPlant[[#This Row],[Milled_t]]<>"",tblPlant[[#This Row],[Feed_oz]]>0),tblPlant[[#This Row],[Recovered_oz]]/tblPlant[[#This Row],[Feed_oz]],"") | W13: =IF(AND(tblPlant[[#This Row],[Milled_t]]<>"",tblPlant[[#This Row],[Mill_Run_h]]>0),tblPlant[[#This Row],[Milled_t]]/tblPlant[[#This Row],[Mill_Run_h]],"") | X13: =IF(tblPlant[[#This Row],[Mill_Run_h]]="","",(24-tblPlant[[#This Row],[Mill_Planned_Maint_h]]-tblPlant[[#This Row],[Mill_Unplanned_Down_h]])/24) | Y13: =IF(AND(tblPlant[[#This Row],[Mill_Run_h]]<>"",(24-tblPlant[[#This Row],[Mill_Planned_Maint_h]]-tblPlant[[#This Row],[Mill_Unplanned_Down_h]])>0),tblPlant[[#This Row],[Mill_Run_h]]/(24-tblPlant[[#This Row],[Mill_Planned_Maint_h]]-tblPlant[[#This Row],[Mill_Unplanned_Down_h]]),"")
A14: 46031 | S14: =IF(tblPlant[[#This Row],[Milled_t]]="","",tblPlant[[#This Row],[Milled_t]]*tblPlant[[#This Row],[Head_Grade_gpt]]/cfg_TroyOz) | T14: =IF(tblPlant[[#This Row],[Milled_t]]="","",tblPlant[[#This Row],[Milled_t]]*tblPlant[[#This Row],[Tails_Grade_gpt]]/cfg_TroyOz) | U14: =IF(tblPlant[[#This Row],[Milled_t]]="","",tblPlant[[#This Row],[Feed_oz]]-tblPlant[[#This Row],[Tails_oz]]) | V14: =IF(AND(tblPlant[[#This Row],[Milled_t]]<>"",tblPlant[[#This Row],[Feed_oz]]>0),tblPlant[[#This Row],[Recovered_oz]]/tblPlant[[#This Row],[Feed_oz]],"") | W14: =IF(AND(tblPlant[[#This Row],[Milled_t]]<>"",tblPlant[[#This Row],[Mill_Run_h]]>0),tblPlant[[#This Row],[Milled_t]]/tblPlant[[#This Row],[Mill_Run_h]],"") | X14: =IF(tblPlant[[#This Row],[Mill_Run_h]]="","",(24-tblPlant[[#This Row],[Mill_Planned_Maint_h]]-tblPlant[[#This Row],[Mill_Unplanned_Down_h]])/24) | Y14: =IF(AND(tblPlant[[#This Row],[Mill_Run_h]]<>"",(24-tblPlant[[#This Row],[Mill_Planned_Maint_h]]-tblPlant[[#This Row],[Mill_Unplanned_Down_h]])>0),tblPlant[[#This Row],[Mill_Run_h]]/(24-tblPlant[[#This Row],[Mill_Planned_Maint_h]]-tblPlant[[#This Row],[Mill_Unplanned_Down_h]]),"")
A15: 46032 | S15: =IF(tblPlant[[#This Row],[Milled_t]]="","",tblPlant[[#This Row],[Milled_t]]*tblPlant[[#This Row],[Head_Grade_gpt]]/cfg_TroyOz) | T15: =IF(tblPlant[[#This Row],[Milled_t]]="","",tblPlant[[#This Row],[Milled_t]]*tblPlant[[#This Row],[Tails_Grade_gpt]]/cfg_TroyOz) | U15: =IF(tblPlant[[#This Row],[Milled_t]]="","",tblPlant[[#This Row],[Feed_oz]]-tblPlant[[#This Row],[Tails_oz]]) | V15: =IF(AND(tblPlant[[#This Row],[Milled_t]]<>"",tblPlant[[#This Row],[Feed_oz]]>0),tblPlant[[#This Row],[Recovered_oz]]/tblPlant[[#This Row],[Feed_oz]],"") | W15: =IF(AND(tblPlant[[#This Row],[Milled_t]]<>"",tblPlant[[#This Row],[Mill_Run_h]]>0),tblPlant[[#This Row],[Milled_t]]/tblPlant[[#This Row],[Mill_Run_h]],"") | X15: =IF(tblPlant[[#This Row],[Mill_Run_h]]="","",(24-tblPlant[[#This Row],[Mill_Planned_Maint_h]]-tblPlant[[#This Row],[Mill_Unplanned_Down_h]])/24) | Y15: =IF(AND(tblPlant[[#This Row],[Mill_Run_h]]<>"",(24-tblPlant[[#This Row],[Mill_Planned_Maint_h]]-tblPlant[[#This Row],[Mill_Unplanned_Down_h]])>0),tblPlant[[#This Row],[Mill_Run_h]]/(24-tblPlant[[#This Row],[Mill_Planned_Maint_h]]-tblPlant[[#This Row],[Mill_Unplanned_Down_h]]),"")
A16: 46033 | S16: =IF(tblPlant[[#This Row],[Milled_t]]="","",tblPlant[[#This Row],[Milled_t]]*tblPlant[[#This Row],[Head_Grade_gpt]]/cfg_TroyOz) | T16: =IF(tblPlant[[#This Row],[Milled_t]]="","",tblPlant[[#This Row],[Milled_t]]*tblPlant[[#This Row],[Tails_Grade_gpt]]/cfg_TroyOz) | U16: =IF(tblPlant[[#This Row],[Milled_t]]="","",tblPlant[[#This Row],[Feed_oz]]-tblPlant[[#This Row],[Tails_oz]]) | V16: =IF(AND(tblPlant[[#This Row],[Milled_t]]<>"",tblPlant[[#This Row],[Feed_oz]]>0),tblPlant[[#This Row],[Recovered_oz]]/tblPlant[[#This Row],[Feed_oz]],"") | W16: =IF(AND(tblPlant[[#This Row],[Milled_t]]<>"",tblPlant[[#This Row],[Mill_Run_h]]>0),tblPlant[[#This Row],[Milled_t]]/tblPlant[[#This Row],[Mill_Run_h]],"") | X16: =IF(tblPlant[[#This Row],[Mill_Run_h]]="","",(24-tblPlant[[#This Row],[Mill_Planned_Maint_h]]-tblPlant[[#This Row],[Mill_Unplanned_Down_h]])/24) | Y16: =IF(AND(tblPlant[[#This Row],[Mill_Run_h]]<>"",(24-tblPlant[[#This Row],[Mill_Planned_Maint_h]]-tblPlant[[#This Row],[Mill_Unplanned_Down_h]])>0),tblPlant[[#This Row],[Mill_Run_h]]/(24-tblPlant[[#This Row],[Mill_Planned_Maint_h]]-tblPlant[[#This Row],[Mill_Unplanned_Down_h]]),"")
A17: 46034 | S17: =IF(tblPlant[[#This Row],[Milled_t]]="","",tblPlant[[#This Row],[Milled_t]]*tblPlant[[#This Row],[Head_Grade_gpt]]/cfg_TroyOz) | T17: =IF(tblPlant[[#This Row],[Milled_t]]="","",tblPlant[[#This Row],[Milled_t]]*tblPlant[[#This Row],[Tails_Grade_gpt]]/cfg_TroyOz) | U17: =IF(tblPlant[[#This Row],[Milled_t]]="","",tblPlant[[#This Row],[Feed_oz]]-tblPlant[[#This Row],[Tails_oz]]) | V17: =IF(AND(tblPlant[[#This Row],[Milled_t]]<>"",tblPlant[[#This Row],[Feed_oz]]>0),tblPlant[[#This Row],[Recovered_oz]]/tblPlant[[#This Row],[Feed_oz]],"") | W17: =IF(AND(tblPlant[[#This Row],[Milled_t]]<>"",tblPlant[[#This Row],[Mill_Run_h]]>0),tblPlant[[#This Row],[Milled_t]]/tblPlant[[#This Row],[Mill_Run_h]],"") | X17: =IF(tblPlant[[#This Row],[Mill_Run_h]]="","",(24-tblPlant[[#This Row],[Mill_Planned_Maint_h]]-tblPlant[[#This Row],[Mill_Unplanned_Down_h]])/24) | Y17: =IF(AND(tblPlant[[#This Row],[Mill_Run_h]]<>"",(24-tblPlant[[#This Row],[Mill_Planned_Maint_h]]-tblPlant[[#This Row],[Mill_Unplanned_Down_h]])>0),tblPlant[[#This Row],[Mill_Run_h]]/(24-tblPlant[[#This Row],[Mill_Planned_Maint_h]]-tblPlant[[#This Row],[Mill_Unplanned_Down_h]]),"")
... A370: 46387 | S370: =IF(tblPlant[[#This Row],[Milled_t]]="","",tblPlant[[#This Row],[Milled_t]]*tblPlant[[#This Row],[Head_Grade_gpt]]/cfg_TroyOz) | T370: =IF(tblPlant[[#This Row],[Milled_t]]="","",tblPlant[[#This Row],[Milled_t]]*tblPlant[[#This Row],[Tails_Grade_gpt]]/cfg_TroyOz) | U370: =IF(tblPlant[[#This Row],[Milled_t]]="","",tblPlant[[#This Row],[Feed_oz]]-tblPlant[[#This Row],[Tails_oz]]) | V370: =IF(AND(tblPlant[[#This Row],[Milled_t]]<>"",tblPlant[[#This Row],[Feed_oz]]>0),tblPlant[[#This Row],[Recovered_oz]]/tblPlant[[#This Row],[Feed_oz]],"") | W370: =IF(AND(tblPlant[[#This Row],[Milled_t]]<>"",tblPlant[[#This Row],[Mill_Run_h]]>0),tblPlant[[#This Row],[Milled_t]]/tblPlant[[#This Row],[Mill_Run_h]],"") | X370: =IF(tblPlant[[#This Row],[Mill_Run_h]]="","",(24-tblPlant[[#This Row],[Mill_Planned_Maint_h]]-tblPlant[[#This Row],[Mill_Unplanned_Down_h]])/24) | Y370: =IF(AND(tblPlant[[#This Row],[Mill_Run_h]]<>"",(24-tblPlant[[#This Row],[Mill_Planned_Maint_h]]-tblPlant[[#This Row],[Mill_Unplanned_Down_h]])>0),tblPlant[[#This Row],[Mill_Run_h]]/(24-tblPlant[[#This Row],[Mill_Planned_Maint_h]]-tblPlant[[#This Row],[Mill_Unplanned_Down_h]]),"")

Sheet Mining_Movements
A1: Material movements, one row per source, material and destination per day (or per shift)
A2: Owner: Mining (dispatch / production engineer). Yellow-free rule: type values only in the blue-headed columns; grey-headed columns are formulas.
A4: Date | B4: Shift | C4: Source | D4: Material | E4: Destination | F4: Tonnes (t) | G4: Grade (g/t) | H4: Volume (bcm) | I4: Truck loads | J4: Comments | K4: Source type | L4: Destination type | M4: Ore flag | N4: Contained gold (oz) | O4: Ore gold (oz)
A5: Date | B5: Shift | C5: Source | D5: Material | E5: Destination | F5: Tonnes_t | G5: Grade_gpt | H5: BCM | I5: Loads | J5: Comments | K5: Source_Type | L5: Dest_Type | M5: Is_Ore | N5: Contained_oz | O5: Ore_oz
K6: =IF(tblMovement[[#This Row],[Source]]="","",IFERROR(INDEX(tblSources[Type],MATCH(tblMovement[[#This Row],[Source]],tblSources[Source],0)),"?")) | L6: =IF(tblMovement[[#This Row],[Destination]]="","",IFERROR(INDEX(tblDestinations[Type],MATCH(tblMovement[[#This Row],[Destination]],tblDestinations[Destination],0)),"?")) | M6: =IF(tblMovement[[#This Row],[Material]]="","",IF(LEFT(tblMovement[[#This Row],[Material]],3)="Ore",1,0)) | N6: =IF(OR(tblMovement[[#This Row],[Tonnes_t]]="",tblMovement[[#This Row],[Grade_gpt]]=""),0,tblMovement[[#This Row],[Tonnes_t]]*tblMovement[[#This Row],[Grade_gpt]]/cfg_TroyOz) | O6: =IF(tblMovement[[#This Row],[Is_Ore]]=1,tblMovement[[#This Row],[Contained_oz]],0)
K7: =IF(tblMovement[[#This Row],[Source]]="","",IFERROR(INDEX(tblSources[Type],MATCH(tblMovement[[#This Row],[Source]],tblSources[Source],0)),"?")) | L7: =IF(tblMovement[[#This Row],[Destination]]="","",IFERROR(INDEX(tblDestinations[Type],MATCH(tblMovement[[#This Row],[Destination]],tblDestinations[Destination],0)),"?")) | M7: =IF(tblMovement[[#This Row],[Material]]="","",IF(LEFT(tblMovement[[#This Row],[Material]],3)="Ore",1,0)) | N7: =IF(OR(tblMovement[[#This Row],[Tonnes_t]]="",tblMovement[[#This Row],[Grade_gpt]]=""),0,tblMovement[[#This Row],[Tonnes_t]]*tblMovement[[#This Row],[Grade_gpt]]/cfg_TroyOz) | O7: =IF(tblMovement[[#This Row],[Is_Ore]]=1,tblMovement[[#This Row],[Contained_oz]],0)
K8: =IF(tblMovement[[#This Row],[Source]]="","",IFERROR(INDEX(tblSources[Type],MATCH(tblMovement[[#This Row],[Source]],tblSources[Source],0)),"?")) | L8: =IF(tblMovement[[#This Row],[Destination]]="","",IFERROR(INDEX(tblDestinations[Type],MATCH(tblMovement[[#This Row],[Destination]],tblDestinations[Destination],0)),"?")) | M8: =IF(tblMovement[[#This Row],[Material]]="","",IF(LEFT(tblMovement[[#This Row],[Material]],3)="Ore",1,0)) | N8: =IF(OR(tblMovement[[#This Row],[Tonnes_t]]="",tblMovement[[#This Row],[Grade_gpt]]=""),0,tblMovement[[#This Row],[Tonnes_t]]*tblMovement[[#This Row],[Grade_gpt]]/cfg_TroyOz) | O8: =IF(tblMovement[[#This Row],[Is_Ore]]=1,tblMovement[[#This Row],[Contained_oz]],0)
K9: =IF(tblMovement[[#This Row],[Source]]="","",IFERROR(INDEX(tblSources[Type],MATCH(tblMovement[[#This Row],[Source]],tblSources[Source],0)),"?")) | L9: =IF(tblMovement[[#This Row],[Destination]]="","",IFERROR(INDEX(tblDestinations[Type],MATCH(tblMovement[[#This Row],[Destination]],tblDestinations[Destination],0)),"?")) | M9: =IF(tblMovement[[#This Row],[Material]]="","",IF(LEFT(tblMovement[[#This Row],[Material]],3)="Ore",1,0)) | N9: =IF(OR(tblMovement[[#This Row],[Tonnes_t]]="",tblMovement[[#This Row],[Grade_gpt]]=""),0,tblMovement[[#This Row],[Tonnes_t]]*tblMovement[[#This Row],[Grade_gpt]]/cfg_TroyOz) | O9: =IF(tblMovement[[#This Row],[Is_Ore]]=1,tblMovement[[#This Row],[Contained_oz]],0)
K10: =IF(tblMovement[[#This Row],[Source]]="","",IFERROR(INDEX(tblSources[Type],MATCH(tblMovement[[#This Row],[Source]],tblSources[Source],0)),"?")) | L10: =IF(tblMovement[[#This Row],[Destination]]="","",IFERROR(INDEX(tblDestinations[Type],MATCH(tblMovement[[#This Row],[Destination]],tblDestinations[Destination],0)),"?")) | M10: =IF(tblMovement[[#This Row],[Material]]="","",IF(LEFT(tblMovement[[#This Row],[Material]],3)="Ore",1,0)) | N10: =IF(OR(tblMovement[[#This Row],[Tonnes_t]]="",tblMovement[[#This Row],[Grade_gpt]]=""),0,tblMovement[[#This Row],[Tonnes_t]]*tblMovement[[#This Row],[Grade_gpt]]/cfg_TroyOz) | O10: =IF(tblMovement[[#This Row],[Is_Ore]]=1,tblMovement[[#This Row],[Contained_oz]],0)
K11: =IF(tblMovement[[#This Row],[Source]]="","",IFERROR(INDEX(tblSources[Type],MATCH(tblMovement[[#This Row],[Source]],tblSources[Source],0)),"?")) | L11: =IF(tblMovement[[#This Row],[Destination]]="","",IFERROR(INDEX(tblDestinations[Type],MATCH(tblMovement[[#This Row],[Destination]],tblDestinations[Destination],0)),"?")) | M11: =IF(tblMovement[[#This Row],[Material]]="","",IF(LEFT(tblMovement[[#This Row],[Material]],3)="Ore",1,0)) | N11: =IF(OR(tblMovement[[#This Row],[Tonnes_t]]="",tblMovement[[#This Row],[Grade_gpt]]=""),0,tblMovement[[#This Row],[Tonnes_t]]*tblMovement[[#This Row],[Grade_gpt]]/cfg_TroyOz) | O11: =IF(tblMovement[[#This Row],[Is_Ore]]=1,tblMovement[[#This Row],[Contained_oz]],0)
K12: =IF(tblMovement[[#This Row],[Source]]="","",IFERROR(INDEX(tblSources[Type],MATCH(tblMovement[[#This Row],[Source]],tblSources[Source],0)),"?")) | L12: =IF(tblMovement[[#This Row],[Destination]]="","",IFERROR(INDEX(tblDestinations[Type],MATCH(tblMovement[[#This Row],[Destination]],tblDestinations[Destination],0)),"?")) | M12: =IF(tblMovement[[#This Row],[Material]]="","",IF(LEFT(tblMovement[[#This Row],[Material]],3)="Ore",1,0)) | N12: =IF(OR(tblMovement[[#This Row],[Tonnes_t]]="",tblMovement[[#This Row],[Grade_gpt]]=""),0,tblMovement[[#This Row],[Tonnes_t]]*tblMovement[[#This Row],[Grade_gpt]]/cfg_TroyOz) | O12: =IF(tblMovement[[#This Row],[Is_Ore]]=1,tblMovement[[#This Row],[Contained_oz]],0)
K13: =IF(tblMovement[[#This Row],[Source]]="","",IFERROR(INDEX(tblSources[Type],MATCH(tblMovement[[#This Row],[Source]],tblSources[Source],0)),"?")) | L13: =IF(tblMovement[[#This Row],[Destination]]="","",IFERROR(INDEX(tblDestinations[Type],MATCH(tblMovement[[#This Row],[Destination]],tblDestinations[Destination],0)),"?")) | M13: =IF(tblMovement[[#This Row],[Material]]="","",IF(LEFT(tblMovement[[#This Row],[Material]],3)="Ore",1,0)) | N13: =IF(OR(tblMovement[[#This Row],[Tonnes_t]]="",tblMovement[[#This Row],[Grade_gpt]]=""),0,tblMovement[[#This Row],[Tonnes_t]]*tblMovement[[#This Row],[Grade_gpt]]/cfg_TroyOz) | O13: =IF(tblMovement[[#This Row],[Is_Ore]]=1,tblMovement[[#This Row],[Contained_oz]],0)
K14: =IF(tblMovement[[#This Row],[Source]]="","",IFERROR(INDEX(tblSources[Type],MATCH(tblMovement[[#This Row],[Source]],tblSources[Source],0)),"?")) | L14: =IF(tblMovement[[#This Row],[Destination]]="","",IFERROR(INDEX(tblDestinations[Type],MATCH(tblMovement[[#This Row],[Destination]],tblDestinations[Destination],0)),"?")) | M14: =IF(tblMovement[[#This Row],[Material]]="","",IF(LEFT(tblMovement[[#This Row],[Material]],3)="Ore",1,0)) | N14: =IF(OR(tblMovement[[#This Row],[Tonnes_t]]="",tblMovement[[#This Row],[Grade_gpt]]=""),0,tblMovement[[#This Row],[Tonnes_t]]*tblMovement[[#This Row],[Grade_gpt]]/cfg_TroyOz) | O14: =IF(tblMovement[[#This Row],[Is_Ore]]=1,tblMovement[[#This Row],[Contained_oz]],0)
K15: =IF(tblMovement[[#This Row],[Source]]="","",IFERROR(INDEX(tblSources[Type],MATCH(tblMovement[[#This Row],[Source]],tblSources[Source],0)),"?")) | L15: =IF(tblMovement[[#This Row],[Destination]]="","",IFERROR(INDEX(tblDestinations[Type],MATCH(tblMovement[[#This Row],[Destination]],tblDestinations[Destination],0)),"?")) | M15: =IF(tblMovement[[#This Row],[Material]]="","",IF(LEFT(tblMovement[[#This Row],[Material]],3)="Ore",1,0)) | N15: =IF(OR(tblMovement[[#This Row],[Tonnes_t]]="",tblMovement[[#This Row],[Grade_gpt]]=""),0,tblMovement[[#This Row],[Tonnes_t]]*tblMovement[[#This Row],[Grade_gpt]]/cfg_TroyOz) | O15: =IF(tblMovement[[#This Row],[Is_Ore]]=1,tblMovement[[#This Row],[Contained_oz]],0)
K16: =IF(tblMovement[[#This Row],[Source]]="","",IFERROR(INDEX(tblSources[Type],MATCH(tblMovement[[#This Row],[Source]],tblSources[Source],0)),"?")) | L16: =IF(tblMovement[[#This Row],[Destination]]="","",IFERROR(INDEX(tblDestinations[Type],MATCH(tblMovement[[#This Row],[Destination]],tblDestinations[Destination],0)),"?")) | M16: =IF(tblMovement[[#This Row],[Material]]="","",IF(LEFT(tblMovement[[#This Row],[Material]],3)="Ore",1,0)) | N16: =IF(OR(tblMovement[[#This Row],[Tonnes_t]]="",tblMovement[[#This Row],[Grade_gpt]]=""),0,tblMovement[[#This Row],[Tonnes_t]]*tblMovement[[#This Row],[Grade_gpt]]/cfg_TroyOz) | O16: =IF(tblMovement[[#This Row],[Is_Ore]]=1,tblMovement[[#This Row],[Contained_oz]],0)
K17: =IF(tblMovement[[#This Row],[Source]]="","",IFERROR(INDEX(tblSources[Type],MATCH(tblMovement[[#This Row],[Source]],tblSources[Source],0)),"?")) | L17: =IF(tblMovement[[#This Row],[Destination]]="","",IFERROR(INDEX(tblDestinations[Type],MATCH(tblMovement[[#This Row],[Destination]],tblDestinations[Destination],0)),"?")) | M17: =IF(tblMovement[[#This Row],[Material]]="","",IF(LEFT(tblMovement[[#This Row],[Material]],3)="Ore",1,0)) | N17: =IF(OR(tblMovement[[#This Row],[Tonnes_t]]="",tblMovement[[#This Row],[Grade_gpt]]=""),0,tblMovement[[#This Row],[Tonnes_t]]*tblMovement[[#This Row],[Grade_gpt]]/cfg_TroyOz) | O17: =IF(tblMovement[[#This Row],[Is_Ore]]=1,tblMovement[[#This Row],[Contained_oz]],0)
... K5005: =IF(tblMovement[[#This Row],[Source]]="","",IFERROR(INDEX(tblSources[Type],MATCH(tblMovement[[#This Row],[Source]],tblSources[Source],0)),"?")) | L5005: =IF(tblMovement[[#This Row],[Destination]]="","",IFERROR(INDEX(tblDestinations[Type],MATCH(tblMovement[[#This Row],[Destination]],tblDestinations[Destination],0)),"?")) | M5005: =IF(tblMovement[[#This Row],[Material]]="","",IF(LEFT(tblMovement[[#This Row],[Material]],3)="Ore",1,0)) | N5005: =IF(OR(tblMovement[[#This Row],[Tonnes_t]]="",tblMovement[[#This Row],[Grade_gpt]]=""),0,tblMovement[[#This Row],[Tonnes_t]]*tblMovement[[#This Row],[Grade_gpt]]/cfg_TroyOz) | O5005: =IF(tblMovement[[#This Row],[Is_Ore]]=1,tblMovement[[#This Row],[Contained_oz]],0)

Sheet Mining_Daily
A1: Mining daily totals, one row per day
A2: Owner: Mining (production engineer). Yellow-free rule: type values only in the blue-headed columns; grey-headed columns are formulas.
A4: Date | B4: Drilled (m) | C4: Blasted (t) | D4: Explosives (kg) | E4: Diesel (L) | F4: Dewatering (m3) | G4: Comments | H4: Powder factor (kg/t)
A5: Date | B5: Drill_m | C5: Blast_t | D5: Explosives_kg | E5: Diesel_L | F5: Dewatering_m3 | G5: Comments | H5: Powder_Factor_kgpt
A6: 46023 | H6: =IF(AND(tblMiningDaily[[#This Row],[Blast_t]]<>"",tblMiningDaily[[#This Row],[Blast_t]]>0),tblMiningDaily[[#This Row],[Explosives_kg]]/tblMiningDaily[[#This Row],[Blast_t]],"")
A7: 46024 | H7: =IF(AND(tblMiningDaily[[#This Row],[Blast_t]]<>"",tblMiningDaily[[#This Row],[Blast_t]]>0),tblMiningDaily[[#This Row],[Explosives_kg]]/tblMiningDaily[[#This Row],[Blast_t]],"")
A8: 46025 | H8: =IF(AND(tblMiningDaily[[#This Row],[Blast_t]]<>"",tblMiningDaily[[#This Row],[Blast_t]]>0),tblMiningDaily[[#This Row],[Explosives_kg]]/tblMiningDaily[[#This Row],[Blast_t]],"")
A9: 46026 | H9: =IF(AND(tblMiningDaily[[#This Row],[Blast_t]]<>"",tblMiningDaily[[#This Row],[Blast_t]]>0),tblMiningDaily[[#This Row],[Explosives_kg]]/tblMiningDaily[[#This Row],[Blast_t]],"")
A10: 46027 | H10: =IF(AND(tblMiningDaily[[#This Row],[Blast_t]]<>"",tblMiningDaily[[#This Row],[Blast_t]]>0),tblMiningDaily[[#This Row],[Explosives_kg]]/tblMiningDaily[[#This Row],[Blast_t]],"")
A11: 46028 | H11: =IF(AND(tblMiningDaily[[#This Row],[Blast_t]]<>"",tblMiningDaily[[#This Row],[Blast_t]]>0),tblMiningDaily[[#This Row],[Explosives_kg]]/tblMiningDaily[[#This Row],[Blast_t]],"")
A12: 46029 | H12: =IF(AND(tblMiningDaily[[#This Row],[Blast_t]]<>"",tblMiningDaily[[#This Row],[Blast_t]]>0),tblMiningDaily[[#This Row],[Explosives_kg]]/tblMiningDaily[[#This Row],[Blast_t]],"")
A13: 46030 | H13: =IF(AND(tblMiningDaily[[#This Row],[Blast_t]]<>"",tblMiningDaily[[#This Row],[Blast_t]]>0),tblMiningDaily[[#This Row],[Explosives_kg]]/tblMiningDaily[[#This Row],[Blast_t]],"")
A14: 46031 | H14: =IF(AND(tblMiningDaily[[#This Row],[Blast_t]]<>"",tblMiningDaily[[#This Row],[Blast_t]]>0),tblMiningDaily[[#This Row],[Explosives_kg]]/tblMiningDaily[[#This Row],[Blast_t]],"")
A15: 46032 | H15: =IF(AND(tblMiningDaily[[#This Row],[Blast_t]]<>"",tblMiningDaily[[#This Row],[Blast_t]]>0),tblMiningDaily[[#This Row],[Explosives_kg]]/tblMiningDaily[[#This Row],[Blast_t]],"")
A16: 46033 | H16: =IF(AND(tblMiningDaily[[#This Row],[Blast_t]]<>"",tblMiningDaily[[#This Row],[Blast_t]]>0),tblMiningDaily[[#This Row],[Explosives_kg]]/tblMiningDaily[[#This Row],[Blast_t]],"")
A17: 46034 | H17: =IF(AND(tblMiningDaily[[#This Row],[Blast_t]]<>"",tblMiningDaily[[#This Row],[Blast_t]]>0),tblMiningDaily[[#This Row],[Explosives_kg]]/tblMiningDaily[[#This Row],[Blast_t]],"")
... A370: 46387 | H370: =IF(AND(tblMiningDaily[[#This Row],[Blast_t]]<>"",tblMiningDaily[[#This Row],[Blast_t]]>0),tblMiningDaily[[#This Row],[Explosives_kg]]/tblMiningDaily[[#This Row],[Blast_t]],"")

Sheet Fleet
A1: Mining fleet time model, one row per equipment class per day
A2: Owner: Mining (dispatch / maintenance planner). Yellow-free rule: type values only in the blue-headed columns; grey-headed columns are formulas.
A4: Date | B4: Equipment class | C4: Units in fleet | D4: Down hours (h) | E4: Operating hours (h) | F4: Comments | G4: Calendar hours (h) | H4: Available hours (h) | I4: Availability (%) | J4: Utilisation (%)
A5: Date | B5: Equipment_Class | C5: Units | D5: Down_h | E5: Operating_h | F5: Comments | G5: Calendar_h | H5: Available_h | I5: Availability_pct | J5: Utilisation_pct
G6: =IF(tblFleet[[#This Row],[Units]]="","",tblFleet[[#This Row],[Units]]*24) | H6: =IF(tblFleet[[#This Row],[Units]]="","",tblFleet[[#This Row],[Calendar_h]]-tblFleet[[#This Row],[Down_h]]) | I6: =IF(AND(tblFleet[[#This Row],[Units]]<>"",tblFleet[[#This Row],[Calendar_h]]>0),tblFleet[[#This Row],[Available_h]]/tblFleet[[#This Row],[Calendar_h]],"") | J6: =IF(AND(tblFleet[[#This Row],[Units]]<>"",tblFleet[[#This Row],[Available_h]]>0),tblFleet[[#This Row],[Operating_h]]/tblFleet[[#This Row],[Available_h]],"")
G7: =IF(tblFleet[[#This Row],[Units]]="","",tblFleet[[#This Row],[Units]]*24) | H7: =IF(tblFleet[[#This Row],[Units]]="","",tblFleet[[#This Row],[Calendar_h]]-tblFleet[[#This Row],[Down_h]]) | I7: =IF(AND(tblFleet[[#This Row],[Units]]<>"",tblFleet[[#This Row],[Calendar_h]]>0),tblFleet[[#This Row],[Available_h]]/tblFleet[[#This Row],[Calendar_h]],"") | J7: =IF(AND(tblFleet[[#This Row],[Units]]<>"",tblFleet[[#This Row],[Available_h]]>0),tblFleet[[#This Row],[Operating_h]]/tblFleet[[#This Row],[Available_h]],"")
G8: =IF(tblFleet[[#This Row],[Units]]="","",tblFleet[[#This Row],[Units]]*24) | H8: =IF(tblFleet[[#This Row],[Units]]="","",tblFleet[[#This Row],[Calendar_h]]-tblFleet[[#This Row],[Down_h]]) | I8: =IF(AND(tblFleet[[#This Row],[Units]]<>"",tblFleet[[#This Row],[Calendar_h]]>0),tblFleet[[#This Row],[Available_h]]/tblFleet[[#This Row],[Calendar_h]],"") | J8: =IF(AND(tblFleet[[#This Row],[Units]]<>"",tblFleet[[#This Row],[Available_h]]>0),tblFleet[[#This Row],[Operating_h]]/tblFleet[[#This Row],[Available_h]],"")
G9: =IF(tblFleet[[#This Row],[Units]]="","",tblFleet[[#This Row],[Units]]*24) | H9: =IF(tblFleet[[#This Row],[Units]]="","",tblFleet[[#This Row],[Calendar_h]]-tblFleet[[#This Row],[Down_h]]) | I9: =IF(AND(tblFleet[[#This Row],[Units]]<>"",tblFleet[[#This Row],[Calendar_h]]>0),tblFleet[[#This Row],[Available_h]]/tblFleet[[#This Row],[Calendar_h]],"") | J9: =IF(AND(tblFleet[[#This Row],[Units]]<>"",tblFleet[[#This Row],[Available_h]]>0),tblFleet[[#This Row],[Operating_h]]/tblFleet[[#This Row],[Available_h]],"")
G10: =IF(tblFleet[[#This Row],[Units]]="","",tblFleet[[#This Row],[Units]]*24) | H10: =IF(tblFleet[[#This Row],[Units]]="","",tblFleet[[#This Row],[Calendar_h]]-tblFleet[[#This Row],[Down_h]]) | I10: =IF(AND(tblFleet[[#This Row],[Units]]<>"",tblFleet[[#This Row],[Calendar_h]]>0),tblFleet[[#This Row],[Available_h]]/tblFleet[[#This Row],[Calendar_h]],"") | J10: =IF(AND(tblFleet[[#This Row],[Units]]<>"",tblFleet[[#This Row],[Available_h]]>0),tblFleet[[#This Row],[Operating_h]]/tblFleet[[#This Row],[Available_h]],"")
G11: =IF(tblFleet[[#This Row],[Units]]="","",tblFleet[[#This Row],[Units]]*24) | H11: =IF(tblFleet[[#This Row],[Units]]="","",tblFleet[[#This Row],[Calendar_h]]-tblFleet[[#This Row],[Down_h]]) | I11: =IF(AND(tblFleet[[#This Row],[Units]]<>"",tblFleet[[#This Row],[Calendar_h]]>0),tblFleet[[#This Row],[Available_h]]/tblFleet[[#This Row],[Calendar_h]],"") | J11: =IF(AND(tblFleet[[#This Row],[Units]]<>"",tblFleet[[#This Row],[Available_h]]>0),tblFleet[[#This Row],[Operating_h]]/tblFleet[[#This Row],[Available_h]],"")
G12: =IF(tblFleet[[#This Row],[Units]]="","",tblFleet[[#This Row],[Units]]*24) | H12: =IF(tblFleet[[#This Row],[Units]]="","",tblFleet[[#This Row],[Calendar_h]]-tblFleet[[#This Row],[Down_h]]) | I12: =IF(AND(tblFleet[[#This Row],[Units]]<>"",tblFleet[[#This Row],[Calendar_h]]>0),tblFleet[[#This Row],[Available_h]]/tblFleet[[#This Row],[Calendar_h]],"") | J12: =IF(AND(tblFleet[[#This Row],[Units]]<>"",tblFleet[[#This Row],[Available_h]]>0),tblFleet[[#This Row],[Operating_h]]/tblFleet[[#This Row],[Available_h]],"")
G13: =IF(tblFleet[[#This Row],[Units]]="","",tblFleet[[#This Row],[Units]]*24) | H13: =IF(tblFleet[[#This Row],[Units]]="","",tblFleet[[#This Row],[Calendar_h]]-tblFleet[[#This Row],[Down_h]]) | I13: =IF(AND(tblFleet[[#This Row],[Units]]<>"",tblFleet[[#This Row],[Calendar_h]]>0),tblFleet[[#This Row],[Available_h]]/tblFleet[[#This Row],[Calendar_h]],"") | J13: =IF(AND(tblFleet[[#This Row],[Units]]<>"",tblFleet[[#This Row],[Available_h]]>0),tblFleet[[#This Row],[Operating_h]]/tblFleet[[#This Row],[Available_h]],"")
G14: =IF(tblFleet[[#This Row],[Units]]="","",tblFleet[[#This Row],[Units]]*24) | H14: =IF(tblFleet[[#This Row],[Units]]="","",tblFleet[[#This Row],[Calendar_h]]-tblFleet[[#This Row],[Down_h]]) | I14: =IF(AND(tblFleet[[#This Row],[Units]]<>"",tblFleet[[#This Row],[Calendar_h]]>0),tblFleet[[#This Row],[Available_h]]/tblFleet[[#This Row],[Calendar_h]],"") | J14: =IF(AND(tblFleet[[#This Row],[Units]]<>"",tblFleet[[#This Row],[Available_h]]>0),tblFleet[[#This Row],[Operating_h]]/tblFleet[[#This Row],[Available_h]],"")
G15: =IF(tblFleet[[#This Row],[Units]]="","",tblFleet[[#This Row],[Units]]*24) | H15: =IF(tblFleet[[#This Row],[Units]]="","",tblFleet[[#This Row],[Calendar_h]]-tblFleet[[#This Row],[Down_h]]) | I15: =IF(AND(tblFleet[[#This Row],[Units]]<>"",tblFleet[[#This Row],[Calendar_h]]>0),tblFleet[[#This Row],[Available_h]]/tblFleet[[#This Row],[Calendar_h]],"") | J15: =IF(AND(tblFleet[[#This Row],[Units]]<>"",tblFleet[[#This Row],[Available_h]]>0),tblFleet[[#This Row],[Operating_h]]/tblFleet[[#This Row],[Available_h]],"")
G16: =IF(tblFleet[[#This Row],[Units]]="","",tblFleet[[#This Row],[Units]]*24) | H16: =IF(tblFleet[[#This Row],[Units]]="","",tblFleet[[#This Row],[Calendar_h]]-tblFleet[[#This Row],[Down_h]]) | I16: =IF(AND(tblFleet[[#This Row],[Units]]<>"",tblFleet[[#This Row],[Calendar_h]]>0),tblFleet[[#This Row],[Available_h]]/tblFleet[[#This Row],[Calendar_h]],"") | J16: =IF(AND(tblFleet[[#This Row],[Units]]<>"",tblFleet[[#This Row],[Available_h]]>0),tblFleet[[#This Row],[Operating_h]]/tblFleet[[#This Row],[Available_h]],"")
G17: =IF(tblFleet[[#This Row],[Units]]="","",tblFleet[[#This Row],[Units]]*24) | H17: =IF(tblFleet[[#This Row],[Units]]="","",tblFleet[[#This Row],[Calendar_h]]-tblFleet[[#This Row],[Down_h]]) | I17: =IF(AND(tblFleet[[#This Row],[Units]]<>"",tblFleet[[#This Row],[Calendar_h]]>0),tblFleet[[#This Row],[Available_h]]/tblFleet[[#This Row],[Calendar_h]],"") | J17: =IF(AND(tblFleet[[#This Row],[Units]]<>"",tblFleet[[#This Row],[Available_h]]>0),tblFleet[[#This Row],[Operating_h]]/tblFleet[[#This Row],[Available_h]],"")
... G3005: =IF(tblFleet[[#This Row],[Units]]="","",tblFleet[[#This Row],[Units]]*24) | H3005: =IF(tblFleet[[#This Row],[Units]]="","",tblFleet[[#This Row],[Calendar_h]]-tblFleet[[#This Row],[Down_h]]) | I3005: =IF(AND(tblFleet[[#This Row],[Units]]<>"",tblFleet[[#This Row],[Calendar_h]]>0),tblFleet[[#This Row],[Available_h]]/tblFleet[[#This Row],[Calendar_h]],"") | J3005: =IF(AND(tblFleet[[#This Row],[Units]]<>"",tblFleet[[#This Row],[Available_h]]>0),tblFleet[[#This Row],[Operating_h]]/tblFleet[[#This Row],[Available_h]],"")

Sheet Safety
A1: Safety, health, environment and community, one row per day
A2: Owner: HSE. Yellow-free rule: type values only in the blue-headed columns; grey-headed columns are formulas.
A4: Date | B4: Hours worked, employees (h) | C4: Hours worked, contractors (h) | D4: Fatalities | E4: Lost time injuries | F4: Restricted work injuries | G4: Medical treatment injuries | H4: First aid injuries | I4: Near misses | J4: Hazard reports | K4: High potential incidents | L4: Environmental incidents | M4: Community incidents or grievances | N4: Vehicle incidents | O4: Toolbox talks | P4: Inspections and audits | Q4: Comments | R4: Hours worked, total (h) | S4: Recordable injuries
A5: Date | B5: Hours_Employees | C5: Hours_Contractors | D5: Fatality | E5: LTI | F5: RWI | G5: MTI | H5: FAI | I5: Near_Miss | J5: Hazard_Reports | K5: HPI | L5: Env_Incidents | M5: Community_Incidents | N5: Vehicle_Incidents | O5: Toolbox_Talks | P5: Inspections | Q5: Comments | R5: Hours_Total | S5: Recordables
A6: 46023 | R6: =IF(AND(tblSafety[[#This Row],[Hours_Employees]]="",tblSafety[[#This Row],[Hours_Contractors]]=""),"",N(tblSafety[[#This Row],[Hours_Employees]])+N(tblSafety[[#This Row],[Hours_Contractors]])) | S6: =N(tblSafety[[#This Row],[Fatality]])+N(tblSafety[[#This Row],[LTI]])+N(tblSafety[[#This Row],[RWI]])+N(tblSafety[[#This Row],[MTI]])
A7: 46024 | R7: =IF(AND(tblSafety[[#This Row],[Hours_Employees]]="",tblSafety[[#This Row],[Hours_Contractors]]=""),"",N(tblSafety[[#This Row],[Hours_Employees]])+N(tblSafety[[#This Row],[Hours_Contractors]])) | S7: =N(tblSafety[[#This Row],[Fatality]])+N(tblSafety[[#This Row],[LTI]])+N(tblSafety[[#This Row],[RWI]])+N(tblSafety[[#This Row],[MTI]])
A8: 46025 | R8: =IF(AND(tblSafety[[#This Row],[Hours_Employees]]="",tblSafety[[#This Row],[Hours_Contractors]]=""),"",N(tblSafety[[#This Row],[Hours_Employees]])+N(tblSafety[[#This Row],[Hours_Contractors]])) | S8: =N(tblSafety[[#This Row],[Fatality]])+N(tblSafety[[#This Row],[LTI]])+N(tblSafety[[#This Row],[RWI]])+N(tblSafety[[#This Row],[MTI]])
A9: 46026 | R9: =IF(AND(tblSafety[[#This Row],[Hours_Employees]]="",tblSafety[[#This Row],[Hours_Contractors]]=""),"",N(tblSafety[[#This Row],[Hours_Employees]])+N(tblSafety[[#This Row],[Hours_Contractors]])) | S9: =N(tblSafety[[#This Row],[Fatality]])+N(tblSafety[[#This Row],[LTI]])+N(tblSafety[[#This Row],[RWI]])+N(tblSafety[[#This Row],[MTI]])
A10: 46027 | R10: =IF(AND(tblSafety[[#This Row],[Hours_Employees]]="",tblSafety[[#This Row],[Hours_Contractors]]=""),"",N(tblSafety[[#This Row],[Hours_Employees]])+N(tblSafety[[#This Row],[Hours_Contractors]])) | S10: =N(tblSafety[[#This Row],[Fatality]])+N(tblSafety[[#This Row],[LTI]])+N(tblSafety[[#This Row],[RWI]])+N(tblSafety[[#This Row],[MTI]])
A11: 46028 | R11: =IF(AND(tblSafety[[#This Row],[Hours_Employees]]="",tblSafety[[#This Row],[Hours_Contractors]]=""),"",N(tblSafety[[#This Row],[Hours_Employees]])+N(tblSafety[[#This Row],[Hours_Contractors]])) | S11: =N(tblSafety[[#This Row],[Fatality]])+N(tblSafety[[#This Row],[LTI]])+N(tblSafety[[#This Row],[RWI]])+N(tblSafety[[#This Row],[MTI]])
A12: 46029 | R12: =IF(AND(tblSafety[[#This Row],[Hours_Employees]]="",tblSafety[[#This Row],[Hours_Contractors]]=""),"",N(tblSafety[[#This Row],[Hours_Employees]])+N(tblSafety[[#This Row],[Hours_Contractors]])) | S12: =N(tblSafety[[#This Row],[Fatality]])+N(tblSafety[[#This Row],[LTI]])+N(tblSafety[[#This Row],[RWI]])+N(tblSafety[[#This Row],[MTI]])
A13: 46030 | R13: =IF(AND(tblSafety[[#This Row],[Hours_Employees]]="",tblSafety[[#This Row],[Hours_Contractors]]=""),"",N(tblSafety[[#This Row],[Hours_Employees]])+N(tblSafety[[#This Row],[Hours_Contractors]])) | S13: =N(tblSafety[[#This Row],[Fatality]])+N(tblSafety[[#This Row],[LTI]])+N(tblSafety[[#This Row],[RWI]])+N(tblSafety[[#This Row],[MTI]])
A14: 46031 | R14: =IF(AND(tblSafety[[#This Row],[Hours_Employees]]="",tblSafety[[#This Row],[Hours_Contractors]]=""),"",N(tblSafety[[#This Row],[Hours_Employees]])+N(tblSafety[[#This Row],[Hours_Contractors]])) | S14: =N(tblSafety[[#This Row],[Fatality]])+N(tblSafety[[#This Row],[LTI]])+N(tblSafety[[#This Row],[RWI]])+N(tblSafety[[#This Row],[MTI]])
A15: 46032 | R15: =IF(AND(tblSafety[[#This Row],[Hours_Employees]]="",tblSafety[[#This Row],[Hours_Contractors]]=""),"",N(tblSafety[[#This Row],[Hours_Employees]])+N(tblSafety[[#This Row],[Hours_Contractors]])) | S15: =N(tblSafety[[#This Row],[Fatality]])+N(tblSafety[[#This Row],[LTI]])+N(tblSafety[[#This Row],[RWI]])+N(tblSafety[[#This Row],[MTI]])
A16: 46033 | R16: =IF(AND(tblSafety[[#This Row],[Hours_Employees]]="",tblSafety[[#This Row],[Hours_Contractors]]=""),"",N(tblSafety[[#This Row],[Hours_Employees]])+N(tblSafety[[#This Row],[Hours_Contractors]])) | S16: =N(tblSafety[[#This Row],[Fatality]])+N(tblSafety[[#This Row],[LTI]])+N(tblSafety[[#This Row],[RWI]])+N(tblSafety[[#This Row],[MTI]])
A17: 46034 | R17: =IF(AND(tblSafety[[#This Row],[Hours_Employees]]="",tblSafety[[#This Row],[Hours_Contractors]]=""),"",N(tblSafety[[#This Row],[Hours_Employees]])+N(tblSafety[[#This Row],[Hours_Contractors]])) | S17: =N(tblSafety[[#This Row],[Fatality]])+N(tblSafety[[#This Row],[LTI]])+N(tblSafety[[#This Row],[RWI]])+N(tblSafety[[#This Row],[MTI]])
... A370: 46387 | R370: =IF(AND(tblSafety[[#This Row],[Hours_Employees]]="",tblSafety[[#This Row],[Hours_Contractors]]=""),"",N(tblSafety[[#This Row],[Hours_Employees]])+N(tblSafety[[#This Row],[Hours_Contractors]])) | S370: =N(tblSafety[[#This Row],[Fatality]])+N(tblSafety[[#This Row],[LTI]])+N(tblSafety[[#This Row],[RWI]])+N(tblSafety[[#This Row],[MTI]])

Sheet Gold
A1: Gold shipments and sales
A2: Owner: Finance / gold room. Yellow-free rule: type values only in the blue-headed columns; grey-headed columns are formulas.
A4: Date | B4: Type | C4: Dore weight (kg) | D4: Gold (oz) | E4: Silver (oz) | F4: Reference | G4: Comments
A5: Date | B5: Type | C5: Dore_kg | D5: Gold_oz | E5: Silver_oz | F5: Reference | G5: Comments

Sheet Budget
A1: Monthly budget (or latest forecast), one row per month
A2: Owner: Technical services / finance. Yellow-free rule: type values only in the blue-headed columns; grey-headed columns are formulas.
A4: Month | B4: Ore mined (t) | C4: Ore grade mined (g/t) | D4: Waste mined (t) | E4: Milled (t) | F4: Head grade (g/t) | G4: Recovery (%) | H4: Gold poured (oz) | I4: Hours worked (h) | J4: Drilled (m) | K4: Mining diesel (L) | L4: Days in month | M4: Ore gold mined (oz) | N4: Total material moved (t) | O4: Contained gold in feed (oz) | P4: Gold recovered (oz)
A5: Month | B5: Ore_Mined_t | C5: Ore_Grade_gpt | D5: Waste_t | E5: Milled_t | F5: Head_Grade_gpt | G5: Recovery_pct | H5: Gold_Poured_oz | I5: Hours_Worked | J5: Drill_m | K5: Diesel_L | L5: Days | M5: Ore_oz | N5: TMM_t | O5: Feed_oz | P5: Recovered_oz
A6: 46023 | L6: =DAY(EOMONTH(tblBudget[[#This Row],[Month]],0)) | M6: =N(tblBudget[[#This Row],[Ore_Mined_t]])*N(tblBudget[[#This Row],[Ore_Grade_gpt]])/cfg_TroyOz | N6: =N(tblBudget[[#This Row],[Ore_Mined_t]])+N(tblBudget[[#This Row],[Waste_t]]) | O6: =N(tblBudget[[#This Row],[Milled_t]])*N(tblBudget[[#This Row],[Head_Grade_gpt]])/cfg_TroyOz | P6: =tblBudget[[#This Row],[Feed_oz]]*N(tblBudget[[#This Row],[Recovery_pct]])
A7: 46054 | L7: =DAY(EOMONTH(tblBudget[[#This Row],[Month]],0)) | M7: =N(tblBudget[[#This Row],[Ore_Mined_t]])*N(tblBudget[[#This Row],[Ore_Grade_gpt]])/cfg_TroyOz | N7: =N(tblBudget[[#This Row],[Ore_Mined_t]])+N(tblBudget[[#This Row],[Waste_t]]) | O7: =N(tblBudget[[#This Row],[Milled_t]])*N(tblBudget[[#This Row],[Head_Grade_gpt]])/cfg_TroyOz | P7: =tblBudget[[#This Row],[Feed_oz]]*N(tblBudget[[#This Row],[Recovery_pct]])
A8: 46082 | L8: =DAY(EOMONTH(tblBudget[[#This Row],[Month]],0)) | M8: =N(tblBudget[[#This Row],[Ore_Mined_t]])*N(tblBudget[[#This Row],[Ore_Grade_gpt]])/cfg_TroyOz | N8: =N(tblBudget[[#This Row],[Ore_Mined_t]])+N(tblBudget[[#This Row],[Waste_t]]) | O8: =N(tblBudget[[#This Row],[Milled_t]])*N(tblBudget[[#This Row],[Head_Grade_gpt]])/cfg_TroyOz | P8: =tblBudget[[#This Row],[Feed_oz]]*N(tblBudget[[#This Row],[Recovery_pct]])
A9: 46113 | L9: =DAY(EOMONTH(tblBudget[[#This Row],[Month]],0)) | M9: =N(tblBudget[[#This Row],[Ore_Mined_t]])*N(tblBudget[[#This Row],[Ore_Grade_gpt]])/cfg_TroyOz | N9: =N(tblBudget[[#This Row],[Ore_Mined_t]])+N(tblBudget[[#This Row],[Waste_t]]) | O9: =N(tblBudget[[#This Row],[Milled_t]])*N(tblBudget[[#This Row],[Head_Grade_gpt]])/cfg_TroyOz | P9: =tblBudget[[#This Row],[Feed_oz]]*N(tblBudget[[#This Row],[Recovery_pct]])
A10: 46143 | L10: =DAY(EOMONTH(tblBudget[[#This Row],[Month]],0)) | M10: =N(tblBudget[[#This Row],[Ore_Mined_t]])*N(tblBudget[[#This Row],[Ore_Grade_gpt]])/cfg_TroyOz | N10: =N(tblBudget[[#This Row],[Ore_Mined_t]])+N(tblBudget[[#This Row],[Waste_t]]) | O10: =N(tblBudget[[#This Row],[Milled_t]])*N(tblBudget[[#This Row],[Head_Grade_gpt]])/cfg_TroyOz | P10: =tblBudget[[#This Row],[Feed_oz]]*N(tblBudget[[#This Row],[Recovery_pct]])
A11: 46174 | L11: =DAY(EOMONTH(tblBudget[[#This Row],[Month]],0)) | M11: =N(tblBudget[[#This Row],[Ore_Mined_t]])*N(tblBudget[[#This Row],[Ore_Grade_gpt]])/cfg_TroyOz | N11: =N(tblBudget[[#This Row],[Ore_Mined_t]])+N(tblBudget[[#This Row],[Waste_t]]) | O11: =N(tblBudget[[#This Row],[Milled_t]])*N(tblBudget[[#This Row],[Head_Grade_gpt]])/cfg_TroyOz | P11: =tblBudget[[#This Row],[Feed_oz]]*N(tblBudget[[#This Row],[Recovery_pct]])
A12: 46204 | L12: =DAY(EOMONTH(tblBudget[[#This Row],[Month]],0)) | M12: =N(tblBudget[[#This Row],[Ore_Mined_t]])*N(tblBudget[[#This Row],[Ore_Grade_gpt]])/cfg_TroyOz | N12: =N(tblBudget[[#This Row],[Ore_Mined_t]])+N(tblBudget[[#This Row],[Waste_t]]) | O12: =N(tblBudget[[#This Row],[Milled_t]])*N(tblBudget[[#This Row],[Head_Grade_gpt]])/cfg_TroyOz | P12: =tblBudget[[#This Row],[Feed_oz]]*N(tblBudget[[#This Row],[Recovery_pct]])
A13: 46235 | L13: =DAY(EOMONTH(tblBudget[[#This Row],[Month]],0)) | M13: =N(tblBudget[[#This Row],[Ore_Mined_t]])*N(tblBudget[[#This Row],[Ore_Grade_gpt]])/cfg_TroyOz | N13: =N(tblBudget[[#This Row],[Ore_Mined_t]])+N(tblBudget[[#This Row],[Waste_t]]) | O13: =N(tblBudget[[#This Row],[Milled_t]])*N(tblBudget[[#This Row],[Head_Grade_gpt]])/cfg_TroyOz | P13: =tblBudget[[#This Row],[Feed_oz]]*N(tblBudget[[#This Row],[Recovery_pct]])
A14: 46266 | L14: =DAY(EOMONTH(tblBudget[[#This Row],[Month]],0)) | M14: =N(tblBudget[[#This Row],[Ore_Mined_t]])*N(tblBudget[[#This Row],[Ore_Grade_gpt]])/cfg_TroyOz | N14: =N(tblBudget[[#This Row],[Ore_Mined_t]])+N(tblBudget[[#This Row],[Waste_t]]) | O14: =N(tblBudget[[#This Row],[Milled_t]])*N(tblBudget[[#This Row],[Head_Grade_gpt]])/cfg_TroyOz | P14: =tblBudget[[#This Row],[Feed_oz]]*N(tblBudget[[#This Row],[Recovery_pct]])
A15: 46296 | L15: =DAY(EOMONTH(tblBudget[[#This Row],[Month]],0)) | M15: =N(tblBudget[[#This Row],[Ore_Mined_t]])*N(tblBudget[[#This Row],[Ore_Grade_gpt]])/cfg_TroyOz | N15: =N(tblBudget[[#This Row],[Ore_Mined_t]])+N(tblBudget[[#This Row],[Waste_t]]) | O15: =N(tblBudget[[#This Row],[Milled_t]])*N(tblBudget[[#This Row],[Head_Grade_gpt]])/cfg_TroyOz | P15: =tblBudget[[#This Row],[Feed_oz]]*N(tblBudget[[#This Row],[Recovery_pct]])
A16: 46327 | L16: =DAY(EOMONTH(tblBudget[[#This Row],[Month]],0)) | M16: =N(tblBudget[[#This Row],[Ore_Mined_t]])*N(tblBudget[[#This Row],[Ore_Grade_gpt]])/cfg_TroyOz | N16: =N(tblBudget[[#This Row],[Ore_Mined_t]])+N(tblBudget[[#This Row],[Waste_t]]) | O16: =N(tblBudget[[#This Row],[Milled_t]])*N(tblBudget[[#This Row],[Head_Grade_gpt]])/cfg_TroyOz | P16: =tblBudget[[#This Row],[Feed_oz]]*N(tblBudget[[#This Row],[Recovery_pct]])
A17: 46357 | L17: =DAY(EOMONTH(tblBudget[[#This Row],[Month]],0)) | M17: =N(tblBudget[[#This Row],[Ore_Mined_t]])*N(tblBudget[[#This Row],[Ore_Grade_gpt]])/cfg_TroyOz | N17: =N(tblBudget[[#This Row],[Ore_Mined_t]])+N(tblBudget[[#This Row],[Waste_t]]) | O17: =N(tblBudget[[#This Row],[Milled_t]])*N(tblBudget[[#This Row],[Head_Grade_gpt]])/cfg_TroyOz | P17: =tblBudget[[#This Row],[Feed_oz]]*N(tblBudget[[#This Row],[Recovery_pct]])

Sheet Commentary
A1: Daily report narrative, one row per comment
A2: Owner: All departments; compiled by the production engineer. Yellow-free rule: type values only in the blue-headed columns; grey-headed columns are formulas.
A4: Date | B4: Area | C4: Comment | D4: Author | E4: Sequence in day | F4: Day key
A5: Date | B5: Area | C5: Comment | D5: Author | E5: Seq_Day | F5: Key_Day
E6: =IF(tblCommentary[[#This Row],[Date]]="","",COUNTIFS(INDEX(tblCommentary[Date],1):tblCommentary[[#This Row],[Date]],tblCommentary[[#This Row],[Date]])) | F6: =IF(tblCommentary[[#This Row],[Date]]="","",tblCommentary[[#This Row],[Date]]&"|"&tblCommentary[[#This Row],[Seq_Day]])
E7: =IF(tblCommentary[[#This Row],[Date]]="","",COUNTIFS(INDEX(tblCommentary[Date],1):tblCommentary[[#This Row],[Date]],tblCommentary[[#This Row],[Date]])) | F7: =IF(tblCommentary[[#This Row],[Date]]="","",tblCommentary[[#This Row],[Date]]&"|"&tblCommentary[[#This Row],[Seq_Day]])
E8: =IF(tblCommentary[[#This Row],[Date]]="","",COUNTIFS(INDEX(tblCommentary[Date],1):tblCommentary[[#This Row],[Date]],tblCommentary[[#This Row],[Date]])) | F8: =IF(tblCommentary[[#This Row],[Date]]="","",tblCommentary[[#This Row],[Date]]&"|"&tblCommentary[[#This Row],[Seq_Day]])
E9: =IF(tblCommentary[[#This Row],[Date]]="","",COUNTIFS(INDEX(tblCommentary[Date],1):tblCommentary[[#This Row],[Date]],tblCommentary[[#This Row],[Date]])) | F9: =IF(tblCommentary[[#This Row],[Date]]="","",tblCommentary[[#This Row],[Date]]&"|"&tblCommentary[[#This Row],[Seq_Day]])
E10: =IF(tblCommentary[[#This Row],[Date]]="","",COUNTIFS(INDEX(tblCommentary[Date],1):tblCommentary[[#This Row],[Date]],tblCommentary[[#This Row],[Date]])) | F10: =IF(tblCommentary[[#This Row],[Date]]="","",tblCommentary[[#This Row],[Date]]&"|"&tblCommentary[[#This Row],[Seq_Day]])
E11: =IF(tblCommentary[[#This Row],[Date]]="","",COUNTIFS(INDEX(tblCommentary[Date],1):tblCommentary[[#This Row],[Date]],tblCommentary[[#This Row],[Date]])) | F11: =IF(tblCommentary[[#This Row],[Date]]="","",tblCommentary[[#This Row],[Date]]&"|"&tblCommentary[[#This Row],[Seq_Day]])
E12: =IF(tblCommentary[[#This Row],[Date]]="","",COUNTIFS(INDEX(tblCommentary[Date],1):tblCommentary[[#This Row],[Date]],tblCommentary[[#This Row],[Date]])) | F12: =IF(tblCommentary[[#This Row],[Date]]="","",tblCommentary[[#This Row],[Date]]&"|"&tblCommentary[[#This Row],[Seq_Day]])
E13: =IF(tblCommentary[[#This Row],[Date]]="","",COUNTIFS(INDEX(tblCommentary[Date],1):tblCommentary[[#This Row],[Date]],tblCommentary[[#This Row],[Date]])) | F13: =IF(tblCommentary[[#This Row],[Date]]="","",tblCommentary[[#This Row],[Date]]&"|"&tblCommentary[[#This Row],[Seq_Day]])
E14: =IF(tblCommentary[[#This Row],[Date]]="","",COUNTIFS(INDEX(tblCommentary[Date],1):tblCommentary[[#This Row],[Date]],tblCommentary[[#This Row],[Date]])) | F14: =IF(tblCommentary[[#This Row],[Date]]="","",tblCommentary[[#This Row],[Date]]&"|"&tblCommentary[[#This Row],[Seq_Day]])
E15: =IF(tblCommentary[[#This Row],[Date]]="","",COUNTIFS(INDEX(tblCommentary[Date],1):tblCommentary[[#This Row],[Date]],tblCommentary[[#This Row],[Date]])) | F15: =IF(tblCommentary[[#This Row],[Date]]="","",tblCommentary[[#This Row],[Date]]&"|"&tblCommentary[[#This Row],[Seq_Day]])
E16: =IF(tblCommentary[[#This Row],[Date]]="","",COUNTIFS(INDEX(tblCommentary[Date],1):tblCommentary[[#This Row],[Date]],tblCommentary[[#This Row],[Date]])) | F16: =IF(tblCommentary[[#This Row],[Date]]="","",tblCommentary[[#This Row],[Date]]&"|"&tblCommentary[[#This Row],[Seq_Day]])
E17: =IF(tblCommentary[[#This Row],[Date]]="","",COUNTIFS(INDEX(tblCommentary[Date],1):tblCommentary[[#This Row],[Date]],tblCommentary[[#This Row],[Date]])) | F17: =IF(tblCommentary[[#This Row],[Date]]="","",tblCommentary[[#This Row],[Date]]&"|"&tblCommentary[[#This Row],[Seq_Day]])
... E3005: =IF(tblCommentary[[#This Row],[Date]]="","",COUNTIFS(INDEX(tblCommentary[Date],1):tblCommentary[[#This Row],[Date]],tblCommentary[[#This Row],[Date]])) | F3005: =IF(tblCommentary[[#This Row],[Date]]="","",tblCommentary[[#This Row],[Date]]&"|"&tblCommentary[[#This Row],[Seq_Day]])

Sheet Config
A1: Config
A2: Site settings and opening balances. Names in column C are used by the formulas.
E3: Stockpile opening balances (survey at start of year) | K3: Prior-year safety history by month, for rolling 12-month rates
A4: Setting | B4: Value | C4: Name | E4: Stockpile | F4: Opening_t (t) | G4: Opening_gpt (g/t) | H4: Plant_Feed | I4: Survey_Date | K4: Month | L4: Hours worked (h) | M4: Recordable injuries | N4: Lost time injuries
A5: Site | B5: Mako Gold Mine | C5: cfg_Site | E5: Stockpile | F5: Opening_t | G5: Opening_gpt | H5: Plant_Feed | I5: Survey_Date | K5: Month | L5: Hours_Total | M5: Recordables | N5: LTI
A6: Company | B6: Petowal Mining Company S.A. | C6: cfg_Company | E6: ROM Pad | F6: 0 | G6: 0 | H6: Y | K6: 45658
A7: Reporting year | B7: 2026 | C7: cfg_Year | E7: Stockpile HG | F7: 0 | G7: 0 | H7: N | K7: 45689
A8: Year start | B8: =DATE(cfg_Year,1,1) | C8: cfg_YearStart | E8: Stockpile MG | F8: 0 | G8: 0 | H8: N | K8: 45717
A9: Year end | B9: =DATE(cfg_Year,12,31) | C9: cfg_YearEnd | E9: Stockpile LG | F9: 0 | G9: 0 | H9: N | K9: 45748
A10: Troy ounce (g) | B10: 31.1035 | C10: cfg_TroyOz | E10: Mineralised Waste Dump | F10: 0 | G10: 0 | H10: N | K10: 45778
A11: Date of last LTI before this year | C11: cfg_PriorLTIDate | K11: 45809
A12: Last date with plant data (calculated) | B12: =SUMPRODUCT(MAX((tblPlant[Milled_t]<>"")*tblPlant[Date])) | C12: cfg_LastDataDate | K12: 45839
A13: Report title | B13: Mako Gold Mine daily production report | C13: cfg_ReportTitle | K13: 45870
K14: 45901
K15: 45931
K16: 45962
K17: 45992

Sheet Lists
A1: Lists
A2: Drop-down values. Add rows at the bottom of a list; do not rename headers. Every list is referenced by name (lst_...) in data validation.
A4: Shift | C4: Material | E4: Area | G4: Equipment Class | I4: Gold Movement Type | K4: Yes No | M4: Source Type | O4: Destination Type | R4: Source | S4: Type | U4: Destination | V4: Type
A5: Shift | C5: Material | E5: Area | G5: Equipment_Class | I5: Gold_Movement_Type | K5: Yes_No | M5: Source_Type | O5: Destination_Type | R5: Source | S5: Type | U5: Destination | V5: Type
A6: Day | C6: Ore HG | E6: Safety | G6: Excavator | I6: Shipment | K6: Y | M6: Pit | O6: Stockpile | R6: Petowal Pit | S6: Pit | U6: ROM Pad | V6: Stockpile
A7: Night | C7: Ore MG | E7: Mining | G7: Haul Truck | I7: Sale | K7: N | M7: Stockpile | O7: Plant | R7: Satellite Pit | S7: Pit | U7: Crusher Direct Tip | V7: Plant
C8: Ore LG | E8: Geology | G8: Drill | O8: Waste | R8: ROM Pad | S8: Stockpile | U8: Stockpile HG | V8: Stockpile
C9: Mineralised Waste | E9: Processing | G9: Dozer | R9: Stockpile HG | S9: Stockpile | U9: Stockpile MG | V9: Stockpile
C10: Waste | E10: Maintenance | G10: Grader | R10: Stockpile MG | S10: Stockpile | U10: Stockpile LG | V10: Stockpile
C11: Topsoil | E11: Environment | G11: Water Cart | R11: Stockpile LG | S11: Stockpile | U11: Mineralised Waste Dump | V11: Stockpile
E12: Community | G12: Wheel Loader | R12: Mineralised Waste Dump | S12: Stockpile | U12: Waste Dump | V12: Waste
E13: Supply | G13: Ancillary | U13: TSF Wall | V13: Waste
E14: People | U14: Topsoil Stockpile | V14: Waste
E15: Projects
E16: General

Sheet Calc_Daily
A1: Date | B1: Month | C1: Day | D1: Days_In_Month | E1: Month_Start | F1: Ore_Mined_t | G1: Ore_Mined_t_MTD | H1: Ore_Mined_t_YTD | I1: Ore_Mined_oz | J1: Ore_Mined_oz_MTD | K1: Ore_Mined_oz_YTD | L1: Ore_Grade_gpt | M1: Ore_Grade_gpt_MTD | N1: Ore_Grade_gpt_YTD | O1: Waste_t | P1: Waste_t_MTD | Q1: Waste_t_YTD | R1: TMM_t | S1: TMM_t_MTD | T1: TMM_t_YTD | U1: Strip_Ratio | V1: Strip_Ratio_MTD | W1: Strip_Ratio_YTD | X1: Rehandle_t | Y1: Rehandle_t_MTD | Z1: Rehandle_t_YTD | AA1: Drill_m | AB1: Drill_m_MTD | AC1: Drill_m_YTD | AD1: Blast_t | AE1: Blast_t_MTD | AF1: Blast_t_YTD | AG1: Explosives_kg | AH1: Explosives_kg_MTD | AI1: Explosives_kg_YTD | AJ1: Powder_Factor_kgpt | AK1: Powder_Factor_kgpt_MTD | AL1: Powder_Factor_kgpt_YTD | AM1: Diesel_Mining_L | AN1: Diesel_Mining_L_MTD | AO1: Diesel_Mining_L_YTD | AP1: Dewatering_m3 | AQ1: Dewatering_m3_MTD | AR1: Dewatering_m3_YTD | AS1: Exc_Calendar_h | AT1: Exc_Calendar_h_MTD | AU1: Exc_Calendar_h_YTD | AV1: Exc_Available_h | AW1: Exc_Available_h_MTD | AX1: Exc_Available_h_YTD | AY1: Exc_Operating_h | AZ1: Exc_Operating_h_MTD | BA1: Exc_Operating_h_YTD | BB1: Exc_Availability_pct | BC1: Exc_Availability_pct_MTD | BD1: Exc_Availability_pct_YTD | BE1: Exc_Utilisation_pct | BF1: Exc_Utilisation_pct_MTD | BG1: Exc_Utilisation_pct_YTD | BH1: Trk_Calendar_h | BI1: Trk_Calendar_h_MTD | BJ1: Trk_Calendar_h_YTD | BK1: Trk_Available_h | BL1: Trk_Available_h_MTD | BM1: Trk_Available_h_YTD | BN1: Trk_Operating_h | BO1: Trk_Operating_h_MTD | BP1: Trk_Operating_h_YTD | BQ1: Trk_Availability_pct | BR1: Trk_Availability_pct_MTD | BS1: Trk_Availability_pct_YTD | BT1: Trk_Utilisation_pct | BU1: Trk_Utilisation_pct_MTD | BV1: Trk_Utilisation_pct_YTD | BW1: Crushed_t | BX1: Crushed_t_MTD | BY1: Crushed_t_YTD | BZ1: Milled_t | CA1: Milled_t_MTD | CB1: Milled_t_YTD | CC1: Feed_oz | CD1: Feed_oz_MTD | CE1: Feed_oz_YTD | CF1: Tails_oz | CG1: Tails_oz_MTD | CH1: Tails_oz_YTD | CI1: Recovered_oz | CJ1: Recovered_oz_MTD | CK1: Recovered_oz_YTD | CL1: Head_Grade_gpt | CM1: Head_Grade_gpt_MTD | CN1: Head_Grade_gpt_YTD | CO1: Tails_Grade_gpt | CP1: Tails_Grade_gpt_MTD | CQ1: Tails_Grade_gpt_YTD | CR1: Recovery_pct | CS1: Recovery_pct_MTD | CT1: Recovery_pct_YTD | CU1: Gravity_Gold_oz | CV1: Gravity_Gold_oz_MTD | CW1: Gravity_Gold_oz_YTD | CX1: Gold_Poured_oz | CY1: Gold_Poured_oz_MTD | CZ1: Gold_Poured_oz_YTD | DA1: Mill_Run_h | DB1: Mill_Run_h_MTD | DC1: Mill_Run_h_YTD | DD1: Mill_Planned_Maint_h | DE1: Mill_Planned_Maint_h_MTD | DF1: Mill_Planned_Maint_h_YTD | DG1: Mill_Unplanned_Down_h | DH1: Mill_Unplanned_Down_h_MTD | DI1: Mill_Unplanned_Down_h_YTD | DJ1: Mill_Calendar_h | DK1: Mill_Calendar_h_MTD | DL1: Mill_Calendar_h_YTD | DM1: Crusher_Run_h | DN1: Crusher_Run_h_MTD | DO1: Crusher_Run_h_YTD | DP1: Throughput_tph | DQ1: Throughput_tph_MTD | DR1: Throughput_tph_YTD | DS1: Mill_Availability_pct | DT1: Mill_Availability_pct_MTD | DU1: Mill_Availability_pct_YTD | DV1: Mill_Utilisation_pct | DW1: Mill_Utilisation_pct_MTD | DX1: Mill_Utilisation_pct_YTD | DY1: Cyanide_kg | DZ1: Cyanide_kg_MTD | EA1: Cyanide_kg_YTD | EB1: Lime_kg | EC1: Lime_kg_MTD | ED1: Lime_kg_YTD | EE1: Grinding_Media_kg | EF1: Grinding_Media_kg_MTD | EG1: Grinding_Media_kg_YTD | EH1: Power_kWh | EI1: Power_kWh_MTD | EJ1: Power_kWh_YTD | EK1: Raw_Water_m3 | EL1: Raw_Water_m3_MTD | EM1: Raw_Water_m3_YTD | EN1: Cyanide_kgpt | EO1: Cyanide_kgpt_MTD | EP1: Cyanide_kgpt_YTD | EQ1: Lime_kgpt | ER1: Lime_kgpt_MTD | ES1: Lime_kgpt_YTD | ET1: Media_kgpt | EU1: Media_kgpt_MTD | EV1: Media_kgpt_YTD | EW1: Power_kWhpt | EX1: Power_kWhpt_MTD | EY1: Power_kWhpt_YTD | EZ1: Water_m3pt | FA1: Water_m3pt_MTD | FB1: Water_m3pt_YTD | FC1: GIC_oz | FD1: Gold_Shipped_oz | FE1: Gold_Shipped_oz_MTD | FF1: Gold_Shipped_oz_YTD | FG1: Gold_Sold_oz | FH1: Gold_Sold_oz_MTD | FI1: Gold_Sold_oz_YTD | FJ1: Dore_Shipped_kg | FK1: Dore_Shipped_kg_MTD | FL1: Dore_Shipped_kg_YTD | FM1: Hours_Worked | FN1: Hours_Worked_MTD | FO1: Hours_Worked_YTD | FP1: Fatality | FQ1: Fatality_MTD | FR1: Fatality_YTD | FS1: LTI | FT1: LTI_MTD | FU1: LTI_YTD | FV1: RWI | FW1: RWI_MTD | FX1: RWI_YTD | FY1: MTI | FZ1: MTI_MTD | GA1: MTI_YTD | GB1: FAI | GC1: FAI_MTD | GD1: FAI_YTD | GE1: Recordables | GF1: Recordables_MTD | GG1: Recordables_YTD | GH1: Near_Miss | GI1: Near_Miss_MTD | GJ1: Near_Miss_YTD | GK1: Hazard_Reports | GL1: Hazard_Reports_MTD | GM1: Hazard_Reports_YTD | GN1: HPI | GO1: HPI_MTD | GP1: HPI_YTD | GQ1: Env_Incidents | GR1: Env_Incidents_MTD | GS1: Env_Incidents_YTD | GT1: Community_Incidents | GU1: Community_Incidents_MTD | GV1: Community_Incidents_YTD | GW1: Vehicle_Incidents | GX1: Vehicle_Incidents_MTD | GY1: Vehicle_Incidents_YTD | GZ1: Toolbox_Talks | HA1: Toolbox_Talks_MTD | HB1: Toolbox_Talks_YTD | HC1: Inspections | HD1: Inspections_MTD | HE1: Inspections_YTD | HF1: TRIFR_12m | HG1: LTIFR_12m | HH1: Days_Since_LTI | HI1: Bud_Ore_Mined_t_Month | HJ1: Bud_Ore_Mined_t_MTD | HK1: Bud_Ore_Mined_t_YTD | HL1: Bud_Ore_Mined_oz_Month | HM1: Bud_Ore_Mined_oz_MTD | HN1: Bud_Ore_Mined_oz_YTD | HO1: Bud_Ore_Grade_gpt_Month | HP1: Bud_Ore_Grade_gpt_MTD | HQ1: Bud_Ore_Grade_gpt_YTD | HR1: Bud_Waste_t_Month | HS1: Bud_Waste_t_MTD | HT1: Bud_Waste_t_YTD | HU1: Bud_TMM_t_Month | HV1: Bud_TMM_t_MTD | HW1: Bud_TMM_t_YTD | HX1: Bud_Strip_Ratio_Month | HY1: Bud_Strip_Ratio_MTD | HZ1: Bud_Strip_Ratio_YTD | IA1: Bud_Drill_m_Month | IB1: Bud_Drill_m_MTD | IC1: Bud_Drill_m_YTD | ID1: Bud_Diesel_Mining_L_Month | IE1: Bud_Diesel_Mining_L_MTD | IF1: Bud_Diesel_Mining_L_YTD | IG1: Bud_Milled_t_Month | IH1: Bud_Milled_t_MTD | II1: Bud_Milled_t_YTD | IJ1: Bud_Feed_oz_Month | IK1: Bud_Feed_oz_MTD | IL1: Bud_Feed_oz_YTD | IM1: Bud_Recovered_oz_Month | IN1: Bud_Recovered_oz_MTD | IO1: Bud_Recovered_oz_YTD | IP1: Bud_Head_Grade_gpt_Month | IQ1: Bud_Head_Grade_gpt_MTD | IR1: Bud_Head_Grade_gpt_YTD | IS1: Bud_Recovery_pct_Month | IT1: Bud_Recovery_pct_MTD | IU1: Bud_Recovery_pct_YTD | IV1: Bud_Gold_Poured_oz_Month | IW1: Bud_Gold_Poured_oz_MTD | IX1: Bud_Gold_Poured_oz_YTD | IY1: Bud_Hours_Worked_Month | IZ1: Bud_Hours_Worked_MTD | JA1: Bud_Hours_Worked_YTD
A2: 46023 | B2: =MONTH($A2) | C2: =DAY($A2) | D2: =DAY(EOMONTH($A2,0)) | E2: =DATE(YEAR($A2),MONTH($A2),1) | F2: =SUMIFS(tblMovement[Tonnes_t],tblMovement[Date],$A2,tblMovement[Is_Ore],1,tblMovement[Source_Type],"Pit") | G2: =$F2 | H2: =$F2 | I2: =SUMIFS(tblMovement[Ore_oz],tblMovement[Date],$A2,tblMovement[Source_Type],"Pit") | J2: =$I2 | K2: =$I2 | L2: =IFERROR(IF(($F2)>0,($I2*cfg_TroyOz)/($F2),""),"") | M2: =IFERROR(IF(($G2)>0,($J2*cfg_TroyOz)/($G2),""),"") | N2: =IFERROR(IF(($H2)>0,($K2*cfg_TroyOz)/($H2),""),"") | O2: =SUMIFS(tblMovement[Tonnes_t],tblMovement[Date],$A2,tblMovement[Is_Ore],0,tblMovement[Source_Type],"Pit") | P2: =$O2 | Q2: =$O2 | R2: =$F2+$O2 | S2: =$R2 | T2: =$R2 | U2: =IFERROR(IF(($F2)>0,($O2)/($F2),""),"") | V2: =IFERROR(IF(($G2)>0,($P2)/($G2),""),"") | W2: =IFERROR(IF(($H2)>0,($Q2)/($H2),""),"") | X2: =SUMIFS(tblMovement[Tonnes_t],tblMovement[Date],$A2,tblMovement[Source_Type],"Stockpile") | Y2: =$X2 | Z2: =$X2 | AA2: =SUMIFS(tblMiningDaily[Drill_m],tblMiningDaily[Date],$A2) | AB2: =$AA2 | AC2: =$AA2 | AD2: =SUMIFS(tblMiningDaily[Blast_t],tblMiningDaily[Date],$A2) | AE2: =$AD2 | AF2: =$AD2 | AG2: =SUMIFS(tblMiningDaily[Explosives_kg],tblMiningDaily[Date],$A2) | AH2: =$AG2 | AI2: =$AG2 | AJ2: =IFERROR(IF(($AD2)>0,($AG2)/($AD2),""),"") | AK2: =IFERROR(IF(($AE2)>0,($AH2)/($AE2),""),"") | AL2: =IFERROR(IF(($AF2)>0,($AI2)/($AF2),""),"") | AM2: =SUMIFS(tblMiningDaily[Diesel_L],tblMiningDaily[Date],$A2) | AN2: =$AM2 | AO2: =$AM2 | AP2: =SUMIFS(tblMiningDaily[Dewatering_m3],tblMiningDaily[Date],$A2) | AQ2: =$AP2 | AR2: =$AP2 | AS2: =SUMIFS(tblFleet[Calendar_h],tblFleet[Date],$A2,tblFleet[Equipment_Class],"Excavator") | AT2: =$AS2 | AU2: =$AS2 | AV2: =SUMIFS(tblFleet[Available_h],tblFleet[Date],$A2,tblFleet[Equipment_Class],"Excavator") | AW2: =$AV2 | AX2: =$AV2 | AY2: =SUMIFS(tblFleet[Operating_h],tblFleet[Date],$A2,tblFleet[Equipment_Class],"Excavator") | AZ2: =$AY2 | BA2: =$AY2 | BB2: =IFERROR(IF(($AS2)>0,($AV2)/($AS2),""),"") | BC2: =IFERROR(IF(($AT2)>0,($AW2)/($AT2),""),"") | BD2: =IFERROR(IF(($AU2)>0,($AX2)/($AU2),""),"") | BE2: =IFERROR(IF(($AV2)>0,($AY2)/($AV2),""),"") | BF2: =IFERROR(IF(($AW2)>0,($AZ2)/($AW2),""),"") | BG2: =IFERROR(IF(($AX2)>0,($BA2)/($AX2),""),"") | BH2: =SUMIFS(tblFleet[Calendar_h],tblFleet[Date],$A2,tblFleet[Equipment_Class],"Haul Truck") | BI2: =$BH2 | BJ2: =$BH2 | BK2: =SUMIFS(tblFleet[Available_h],tblFleet[Date],$A2,tblFleet[Equipment_Class],"Haul Truck") | BL2: =$BK2 | BM2: =$BK2 | BN2: =SUMIFS(tblFleet[Operating_h],tblFleet[Date],$A2,tblFleet[Equipment_Class],"Haul Truck") | BO2: =$BN2 | BP2: =$BN2 | BQ2: =IFERROR(IF(($BH2)>0,($BK2)/($BH2),""),"") | BR2: =IFERROR(IF(($BI2)>0,($BL2)/($BI2),""),"") | BS2: =IFERROR(IF(($BJ2)>0,($BM2)/($BJ2),""),"") | BT2: =IFERROR(IF(($BK2)>0,($BN2)/($BK2),""),"") | BU2: =IFERROR(IF(($BL2)>0,($BO2)/($BL2),""),"") | BV2: =IFERROR(IF(($BM2)>0,($BP2)/($BM2),""),"") | BW2: =SUMIFS(tblPlant[Crushed_t],tblPlant[Date],$A2) | BX2: =$BW2 | BY2: =$BW2 | BZ2: =SUMIFS(tblPlant[Milled_t],tblPlant[Date],$A2) | CA2: =$BZ2 | CB2: =$BZ2 | CC2: =SUMIFS(tblPlant[Feed_oz],tblPlant[Date],$A2) | CD2: =$CC2 | CE2: =$CC2 | CF2: =SUMIFS(tblPlant[Tails_oz],tblPlant[Date],$A2) | CG2: =$CF2 | CH2: =$CF2 | CI2: =SUMIFS(tblPlant[Recovered_oz],tblPlant[Date],$A2) | CJ2: =$CI2 | CK2: =$CI2 | CL2: =IFERROR(IF(($BZ2)>0,($CC2*cfg_TroyOz)/($BZ2),""),"") | CM2: =IFERROR(IF(($CA2)>0,($CD2*cfg_TroyOz)/($CA2),""),"") | CN2: =IFERROR(IF(($CB2)>0,($CE2*cfg_TroyOz)/($CB2),""),"") | CO2: =IFERROR(IF(($BZ2)>0,($CF2*cfg_TroyOz)/($BZ2),""),"") | CP2: =IFERROR(IF(($CA2)>0,($CG2*cfg_TroyOz)/($CA2),""),"") | CQ2: =IFERROR(IF(($CB2)>0,($CH2*cfg_TroyOz)/($CB2),""),"") | CR2: =IFERROR(IF(($CC2)>0,($CI2)/($CC2),""),"") | CS2: =IFERROR(IF(($CD2)>0,($CJ2)/($CD2),""),"") | CT2: =IFERROR(IF(($CE2)>0,($CK2)/($CE2),""),"") | CU2: =SUMIFS(tblPlant[Gravity_Gold_oz],tblPlant[Date],$A2) | CV2: =$CU2 | CW2: =$CU2 | CX2: =SUMIFS(tblPlant[Gold_Poured_oz],tblPlant[Date],$A2) | CY2: =$CX2 | CZ2: =$CX2 | DA2: =SUMIFS(tblPlant[Mill_Run_h],tblPlant[Date],$A2) | DB2: =$DA2 | DC2: =$DA2 | DD2: =SUMIFS(tblPlant[Mill_Planned_Maint_h],tblPlant[Date],$A2) | DE2: =$DD2 | DF2: =$DD2 | DG2: =SUMIFS(tblPlant[Mill_Unplanned_Down_h],tblPlant[Date],$A2) | DH2: =$DG2 | DI2: =$DG2 | DJ2: =COUNTIFS(tblPlant[Date],$A2,tblPlant[Mill_Run_h],"<>")*24 | DK2: =$DJ2 | DL2: =$DJ2 | DM2: =SUMIFS(tblPlant[Crusher_Run_h],tblPlant[Date],$A2) | DN2: =$DM2 | DO2: =$DM2 | DP2: =IFERROR(IF(($DA2)>0,($BZ2)/($DA2),""),"") | DQ2: =IFERROR(IF(($DB2)>0,($CA2)/($DB2),""),"") | DR2: =IFERROR(IF(($DC2)>0,($CB2)/($DC2),""),"") | DS2: =IFERROR(IF(($DJ2)>0,($DJ2-$DD2-$DG2)/($DJ2),""),"") | DT2: =IFERROR(IF(($DK2)>0,($DK2-$DE2-$DH2)/($DK2),""),"") | DU2: =IFERROR(IF(($DL2)>0,($DL2-$DF2-$DI2)/($DL2),""),"") | DV2: =IFERROR(IF(($DJ2-$DD2-$DG2)>0,($DA2)/($DJ2-$DD2-$DG2),""),"") | DW2: =IFERROR(IF(($DK2-$DE2-$DH2)>0,($DB2)/($DK2-$DE2-$DH2),""),"") | DX2: =IFERROR(IF(($DL2-$DF2-$DI2)>0,($DC2)/($DL2-$DF2-$DI2),""),"") | DY2: =SUMIFS(tblPlant[Cyanide_kg],tblPlant[Date],$A2) | DZ2: =$DY2 | EA2: =$DY2 | EB2: =SUMIFS(tblPlant[Lime_kg],tblPlant[Date],$A2) | EC2: =$EB2 | ED2: =$EB2 | EE2: =SUMIFS(tblPlant[Grinding_Media_kg],tblPlant[Date],$A2) | EF2: =$EE2 | EG2: =$EE2 | EH2: =SUMIFS(tblPlant[Power_kWh],tblPlant[Date],$A2) | EI2: =$EH2 | EJ2: =$EH2 | EK2: =SUMIFS(tblPlant[Raw_Water_m3],tblPlant[Date],$A2) | EL2: =$EK2 | EM2: =$EK2 | EN2: =IFERROR(IF(($BZ2)>0,($DY2)/($BZ2),""),"") | EO2: =IFERROR(IF(($CA2)>0,($DZ2)/($CA2),""),"") | EP2: =IFERROR(IF(($CB2)>0,($EA2)/($CB2),""),"") | EQ2: =IFERROR(IF(($BZ2)>0,($EB2)/($BZ2),""),"") | ER2: =IFERROR(IF(($CA2)>0,($EC2)/($CA2),""),"") | ES2: =IFERROR(IF(($CB2)>0,($ED2)/($CB2),""),"") | ET2: =IFERROR(IF(($BZ2)>0,($EE2)/($BZ2),""),"") | EU2: =IFERROR(IF(($CA2)>0,($EF2)/($CA2),""),"") | EV2: =IFERROR(IF(($CB2)>0,($EG2)/($CB2),""),"") | EW2: =IFERROR(IF(($BZ2)>0,($EH2)/($BZ2),""),"") | EX2: =IFERROR(IF(($CA2)>0,($EI2)/($CA2),""),"") | EY2: =IFERROR(IF(($CB2)>0,($EJ2)/($CB2),""),"") | EZ2: =IFERROR(IF(($BZ2)>0,($EK2)/($BZ2),""),"") | FA2: =IFERROR(IF(($CA2)>0,($EL2)/($CA2),""),"") | FB2: =IFERROR(IF(($CB2)>0,($EM2)/($CB2),""),"") | FC2: =IF(SUMIFS(tblPlant[GIC_oz],tblPlant[Date],$A2)>0,SUMIFS(tblPlant[GIC_oz],tblPlant[Date],$A2),"") | FD2: =SUMIFS(tblGold[Gold_oz],tblGold[Date],$A2,tblGold[Type],"Shipment") | FE2: =$FD2 | FF2: =$FD2 | FG2: =SUMIFS(tblGold[Gold_oz],tblGold[Date],$A2,tblGold[Type],"Sale") | FH2: =$FG2 | FI2: =$FG2 | FJ2: =SUMIFS(tblGold[Dore_kg],tblGold[Date],$A2,tblGold[Type],"Shipment") | FK2: =$FJ2 | FL2: =$FJ2 | FM2: =SUMIFS(tblSafety[Hours_Total],tblSafety[Date],$A2) | FN2: =$FM2 | FO2: =$FM2 | FP2: =SUMIFS(tblSafety[Fatality],tblSafety[Date],$A2) | FQ2: =$FP2 | FR2: =$FP2 | FS2: =SUMIFS(tblSafety[LTI],tblSafety[Date],$A2) | FT2: =$FS2 | FU2: =$FS2 | FV2: =SUMIFS(tblSafety[RWI],tblSafety[Date],$A2) | FW2: =$FV2 | FX2: =$FV2 | FY2: =SUMIFS(tblSafety[MTI],tblSafety[Date],$A2) | FZ2: =$FY2 | GA2: =$FY2 | GB2: =SUMIFS(tblSafety[FAI],tblSafety[Date],$A2) | GC2: =$GB2 | GD2: =$GB2 | GE2: =SUMIFS(tblSafety[Recordables],tblSafety[Date],$A2) | GF2: =$GE2 | GG2: =$GE2 | GH2: =SUMIFS(tblSafety[Near_Miss],tblSafety[Date],$A2) | GI2: =$GH2 | GJ2: =$GH2 | GK2: =SUMIFS(tblSafety[Hazard_Reports],tblSafety[Date],$A2) | GL2: =$GK2 | GM2: =$GK2 | GN2: =SUMIFS(tblSafety[HPI],tblSafety[Date],$A2) | GO2: =$GN2 | GP2: =$GN2 | GQ2: =SUMIFS(tblSafety[Env_Incidents],tblSafety[Date],$A2) | GR2: =$GQ2 | GS2: =$GQ2 | GT2: =SUMIFS(tblSafety[Community_Incidents],tblSafety[Date],$A2) | GU2: =$GT2 | GV2: =$GT2 | GW2: =SUMIFS(tblSafety[Vehicle_Incidents],tblSafety[Date],$A2) | GX2: =$GW2 | GY2: =$GW2 | GZ2: =SUMIFS(tblSafety[Toolbox_Talks],tblSafety[Date],$A2) | HA2: =$GZ2 | HB2: =$GZ2 | HC2: =SUMIFS(tblSafety[Inspections],tblSafety[Date],$A2) | HD2: =$HC2 | HE2: =$HC2 | HF2: =IFERROR((SUMIFS(tblSafety[Recordables],tblSafety[Date],">="&EDATE($E2,-12),tblSafety[Date],"<="&$A2)+SUMIFS(tblSafetyHistory[Recordables],tblSafetyHistory[Month],">="&EDATE($E2,-12),tblSafetyHistory[Month],"<"&cfg_YearStart))/(SUMIFS(tblSafety[Hours_Total],tblSafety[Date],">="&EDATE($E2,-12),tblSafety[Date],"<="&$A2)+SUMIFS(tblSafetyHistory[Hours_Total],tblSafetyHistory[Month],">="&EDATE($E2,-12),tblSafetyHistory[Month],"<"&cfg_YearStart))*1000000,"") | HG2: =IFERROR((SUMIFS(tblSafety[LTI],tblSafety[Date],">="&EDATE($E2,-12),tblSafety[Date],"<="&$A2)+SUMIFS(tblSafetyHistory[LTI],tblSafetyHistory[Month],">="&EDATE($E2,-12),tblSafetyHistory[Month],"<"&cfg_YearStart))/(SUMIFS(tblSafety[Hours_Total],tblSafety[Date],">="&EDATE($E2,-12),tblSafety[Date],"<="&$A2)+SUMIFS(tblSafetyHistory[Hours_Total],tblSafetyHistory[Month],">="&EDATE($E2,-12),tblSafetyHistory[Month],"<"&cfg_YearStart))*1000000,"") | HH2: =IF(MAX(N(cfg_PriorLTIDate),_xlfn.MAXIFS(tblSafety[Date],tblSafety[LTI],">0",tblSafety[Date],"<="&$A2))=0,"",$A2-MAX(N(cfg_PriorLTIDate),_xlfn.MAXIFS(tblSafety[Date],tblSafety[LTI],">0",tblSafety[Date],"<="&$A2))) | HI2: =SUMIFS(tblBudget[Ore_Mined_t],tblBudget[Month],$E2) | HJ2: =$HI2*$C2/$D2 | HK2: =SUMIFS(tblBudget[Ore_Mined_t],tblBudget[Month],"<"&$E2)+$HJ2 | HL2: =SUMIFS(tblBudget[Ore_oz],tblBudget[Month],$E2) | HM2: =$HL2*$C2/$D2 | HN2: =SUMIFS(tblBudget[Ore_oz],tblBudget[Month],"<"&$E2)+$HM2 | HO2: =IFERROR(IF(($HI2)>0,($HL2*cfg_TroyOz)/($HI2),""),"") | HP2: =IFERROR(IF(($HJ2)>0,($HM2*cfg_TroyOz)/($HJ2),""),"") | HQ2: =IFERROR(IF(($HK2)>0,($HN2*cfg_TroyOz)/($HK2),""),"") | HR2: =SUMIFS(tblBudget[Waste_t],tblBudget[Month],$E2) | HS2: =$HR2*$C2/$D2 | HT2: =SUMIFS(tblBudget[Waste_t],tblBudget[Month],"<"&$E2)+$HS2 | HU2: =SUMIFS(tblBudget[TMM_t],tblBudget[Month],$E2) | HV2: =$HU2*$C2/$D2 | HW2: =SUMIFS(tblBudget[TMM_t],tblBudget[Month],"<"&$E2)+$HV2 | HX2: =IFERROR(IF(($HI2)>0,($HR2)/($HI2),""),"") | HY2: =IFERROR(IF(($HJ2)>0,($HS2)/($HJ2),""),"") | HZ2: =IFERROR(IF(($HK2)>0,($HT2)/($HK2),""),"") | IA2: =SUMIFS(tblBudget[Drill_m],tblBudget[Month],$E2) | IB2: =$IA2*$C2/$D2 | IC2: =SUMIFS(tblBudget[Drill_m],tblBudget[Month],"<"&$E2)+$IB2 | ID2: =SUMIFS(tblBudget[Diesel_L],tblBudget[Month],$E2) | IE2: =$ID2*$C2/$D2 | IF2: =SUMIFS(tblBudget[Diesel_L],tblBudget[Month],"<"&$E2)+$IE2 | IG2: =SUMIFS(tblBudget[Milled_t],tblBudget[Month],$E2) | IH2: =$IG2*$C2/$D2 | II2: =SUMIFS(tblBudget[Milled_t],tblBudget[Month],"<"&$E2)+$IH2 | IJ2: =SUMIFS(tblBudget[Feed_oz],tblBudget[Month],$E2) | IK2: =$IJ2*$C2/$D2 | IL2: =SUMIFS(tblBudget[Feed_oz],tblBudget[Month],"<"&$E2)+$IK2 | IM2: =SUMIFS(tblBudget[Recovered_oz],tblBudget[Month],$E2) | IN2: =$IM2*$C2/$D2 | IO2: =SUMIFS(tblBudget[Recovered_oz],tblBudget[Month],"<"&$E2)+$IN2 | IP2: =IFERROR(IF(($IG2)>0,($IJ2*cfg_TroyOz)/($IG2),""),"") | IQ2: =IFERROR(IF(($IH2)>0,($IK2*cfg_TroyOz)/($IH2),""),"") | IR2: =IFERROR(IF(($II2)>0,($IL2*cfg_TroyOz)/($II2),""),"") | IS2: =IFERROR(IF(($IJ2)>0,($IM2)/($IJ2),""),"") | IT2: =IFERROR(IF(($IK2)>0,($IN2)/($IK2),""),"") | IU2: =IFERROR(IF(($IL2)>0,($IO2)/($IL2),""),"") | IV2: =SUMIFS(tblBudget[Gold_Poured_oz],tblBudget[Month],$E2) | IW2: =$IV2*$C2/$D2 | IX2: =SUMIFS(tblBudget[Gold_Poured_oz],tblBudget[Month],"<"&$E2)+$IW2 | IY2: =SUMIFS(tblBudget[Hours_Worked],tblBudget[Month],$E2) | IZ2: =$IY2*$C2/$D2 | JA2: =SUMIFS(tblBudget[Hours_Worked],tblBudget[Month],"<"&$E2)+$IZ2
A3: 46024 | B3: =MONTH($A3) | C3: =DAY($A3) | D3: =DAY(EOMONTH($A3,0)) | E3: =DATE(YEAR($A3),MONTH($A3),1) | F3: =SUMIFS(tblMovement[Tonnes_t],tblMovement[Date],$A3,tblMovement[Is_Ore],1,tblMovement[Source_Type],"Pit") | G3: =IF($B3=$B2,$G2,0)+$F3 | H3: =$H2+$F3 | I3: =SUMIFS(tblMovement[Ore_oz],tblMovement[Date],$A3,tblMovement[Source_Type],"Pit") | J3: =IF($B3=$B2,$J2,0)+$I3 | K3: =$K2+$I3 | L3: =IFERROR(IF(($F3)>0,($I3*cfg_TroyOz)/($F3),""),"") | M3: =IFERROR(IF(($G3)>0,($J3*cfg_TroyOz)/($G3),""),"") | N3: =IFERROR(IF(($H3)>0,($K3*cfg_TroyOz)/($H3),""),"") | O3: =SUMIFS(tblMovement[Tonnes_t],tblMovement[Date],$A3,tblMovement[Is_Ore],0,tblMovement[Source_Type],"Pit") | P3: =IF($B3=$B2,$P2,0)+$O3 | Q3: =$Q2+$O3 | R3: =$F3+$O3 | S3: =IF($B3=$B2,$S2,0)+$R3 | T3: =$T2+$R3 | U3: =IFERROR(IF(($F3)>0,($O3)/($F3),""),"") | V3: =IFERROR(IF(($G3)>0,($P3)/($G3),""),"") | W3: =IFERROR(IF(($H3)>0,($Q3)/($H3),""),"") | X3: =SUMIFS(tblMovement[Tonnes_t],tblMovement[Date],$A3,tblMovement[Source_Type],"Stockpile") | Y3: =IF($B3=$B2,$Y2,0)+$X3 | Z3: =$Z2+$X3 | AA3: =SUMIFS(tblMiningDaily[Drill_m],tblMiningDaily[Date],$A3) | AB3: =IF($B3=$B2,$AB2,0)+$AA3 | AC3: =$AC2+$AA3 | AD3: =SUMIFS(tblMiningDaily[Blast_t],tblMiningDaily[Date],$A3) | AE3: =IF($B3=$B2,$AE2,0)+$AD3 | AF3: =$AF2+$AD3 | AG3: =SUMIFS(tblMiningDaily[Explosives_kg],tblMiningDaily[Date],$A3) | AH3: =IF($B3=$B2,$AH2,0)+$AG3 | AI3: =$AI2+$AG3 | AJ3: =IFERROR(IF(($AD3)>0,($AG3)/($AD3),""),"") | AK3: =IFERROR(IF(($AE3)>0,($AH3)/($AE3),""),"") | AL3: =IFERROR(IF(($AF3)>0,($AI3)/($AF3),""),"") | AM3: =SUMIFS(tblMiningDaily[Diesel_L],tblMiningDaily[Date],$A3) | AN3: =IF($B3=$B2,$AN2,0)+$AM3 | AO3: =$AO2+$AM3 | AP3: =SUMIFS(tblMiningDaily[Dewatering_m3],tblMiningDaily[Date],$A3) | AQ3: =IF($B3=$B2,$AQ2,0)+$AP3 | AR3: =$AR2+$AP3 | AS3: =SUMIFS(tblFleet[Calendar_h],tblFleet[Date],$A3,tblFleet[Equipment_Class],"Excavator") | AT3: =IF($B3=$B2,$AT2,0)+$AS3 | AU3: =$AU2+$AS3 | AV3: =SUMIFS(tblFleet[Available_h],tblFleet[Date],$A3,tblFleet[Equipment_Class],"Excavator") | AW3: =IF($B3=$B2,$AW2,0)+$AV3 | AX3: =$AX2+$AV3 | AY3: =SUMIFS(tblFleet[Operating_h],tblFleet[Date],$A3,tblFleet[Equipment_Class],"Excavator") | AZ3: =IF($B3=$B2,$AZ2,0)+$AY3 | BA3: =$BA2+$AY3 | BB3: =IFERROR(IF(($AS3)>0,($AV3)/($AS3),""),"") | BC3: =IFERROR(IF(($AT3)>0,($AW3)/($AT3),""),"") | BD3: =IFERROR(IF(($AU3)>0,($AX3)/($AU3),""),"") | BE3: =IFERROR(IF(($AV3)>0,($AY3)/($AV3),""),"") | BF3: =IFERROR(IF(($AW3)>0,($AZ3)/($AW3),""),"") | BG3: =IFERROR(IF(($AX3)>0,($BA3)/($AX3),""),"") | BH3: =SUMIFS(tblFleet[Calendar_h],tblFleet[Date],$A3,tblFleet[Equipment_Class],"Haul Truck") | BI3: =IF($B3=$B2,$BI2,0)+$BH3 | BJ3: =$BJ2+$BH3 | BK3: =SUMIFS(tblFleet[Available_h],tblFleet[Date],$A3,tblFleet[Equipment_Class],"Haul Truck") | BL3: =IF($B3=$B2,$BL2,0)+$BK3 | BM3: =$BM2+$BK3 | BN3: =SUMIFS(tblFleet[Operating_h],tblFleet[Date],$A3,tblFleet[Equipment_Class],"Haul Truck") | BO3: =IF($B3=$B2,$BO2,0)+$BN3 | BP3: =$BP2+$BN3 | BQ3: =IFERROR(IF(($BH3)>0,($BK3)/($BH3),""),"") | BR3: =IFERROR(IF(($BI3)>0,($BL3)/($BI3),""),"") | BS3: =IFERROR(IF(($BJ3)>0,($BM3)/($BJ3),""),"") | BT3: =IFERROR(IF(($BK3)>0,($BN3)/($BK3),""),"") | BU3: =IFERROR(IF(($BL3)>0,($BO3)/($BL3),""),"") | BV3: =IFERROR(IF(($BM3)>0,($BP3)/($BM3),""),"") | BW3: =SUMIFS(tblPlant[Crushed_t],tblPlant[Date],$A3) | BX3: =IF($B3=$B2,$BX2,0)+$BW3 | BY3: =$BY2+$BW3 | BZ3: =SUMIFS(tblPlant[Milled_t],tblPlant[Date],$A3) | CA3: =IF($B3=$B2,$CA2,0)+$BZ3 | CB3: =$CB2+$BZ3 | CC3: =SUMIFS(tblPlant[Feed_oz],tblPlant[Date],$A3) | CD3: =IF($B3=$B2,$CD2,0)+$CC3 | CE3: =$CE2+$CC3 | CF3: =SUMIFS(tblPlant[Tails_oz],tblPlant[Date],$A3) | CG3: =IF($B3=$B2,$CG2,0)+$CF3 | CH3: =$CH2+$CF3 | CI3: =SUMIFS(tblPlant[Recovered_oz],tblPlant[Date],$A3) | CJ3: =IF($B3=$B2,$CJ2,0)+$CI3 | CK3: =$CK2+$CI3 | CL3: =IFERROR(IF(($BZ3)>0,($CC3*cfg_TroyOz)/($BZ3),""),"") | CM3: =IFERROR(IF(($CA3)>0,($CD3*cfg_TroyOz)/($CA3),""),"") | CN3: =IFERROR(IF(($CB3)>0,($CE3*cfg_TroyOz)/($CB3),""),"") | CO3: =IFERROR(IF(($BZ3)>0,($CF3*cfg_TroyOz)/($BZ3),""),"") | CP3: =IFERROR(IF(($CA3)>0,($CG3*cfg_TroyOz)/($CA3),""),"") | CQ3: =IFERROR(IF(($CB3)>0,($CH3*cfg_TroyOz)/($CB3),""),"") | CR3: =IFERROR(IF(($CC3)>0,($CI3)/($CC3),""),"") | CS3: =IFERROR(IF(($CD3)>0,($CJ3)/($CD3),""),"") | CT3: =IFERROR(IF(($CE3)>0,($CK3)/($CE3),""),"") | CU3: =SUMIFS(tblPlant[Gravity_Gold_oz],tblPlant[Date],$A3) | CV3: =IF($B3=$B2,$CV2,0)+$CU3 | CW3: =$CW2+$CU3 | CX3: =SUMIFS(tblPlant[Gold_Poured_oz],tblPlant[Date],$A3) | CY3: =IF($B3=$B2,$CY2,0)+$CX3 | CZ3: =$CZ2+$CX3 | DA3: =SUMIFS(tblPlant[Mill_Run_h],tblPlant[Date],$A3) | DB3: =IF($B3=$B2,$DB2,0)+$DA3 | DC3: =$DC2+$DA3 | DD3: =SUMIFS(tblPlant[Mill_Planned_Maint_h],tblPlant[Date],$A3) | DE3: =IF($B3=$B2,$DE2,0)+$DD3 | DF3: =$DF2+$DD3 | DG3: =SUMIFS(tblPlant[Mill_Unplanned_Down_h],tblPlant[Date],$A3) | DH3: =IF($B3=$B2,$DH2,0)+$DG3 | DI3: =$DI2+$DG3 | DJ3: =COUNTIFS(tblPlant[Date],$A3,tblPlant[Mill_Run_h],"<>")*24 | DK3: =IF($B3=$B2,$DK2,0)+$DJ3 | DL3: =$DL2+$DJ3 | DM3: =SUMIFS(tblPlant[Crusher_Run_h],tblPlant[Date],$A3) | DN3: =IF($B3=$B2,$DN2,0)+$DM3 | DO3: =$DO2+$DM3 | DP3: =IFERROR(IF(($DA3)>0,($BZ3)/($DA3),""),"") | DQ3: =IFERROR(IF(($DB3)>0,($CA3)/($DB3),""),"") | DR3: =IFERROR(IF(($DC3)>0,($CB3)/($DC3),""),"") | DS3: =IFERROR(IF(($DJ3)>0,($DJ3-$DD3-$DG3)/($DJ3),""),"") | DT3: =IFERROR(IF(($DK3)>0,($DK3-$DE3-$DH3)/($DK3),""),"") | DU3: =IFERROR(IF(($DL3)>0,($DL3-$DF3-$DI3)/($DL3),""),"") | DV3: =IFERROR(IF(($DJ3-$DD3-$DG3)>0,($DA3)/($DJ3-$DD3-$DG3),""),"") | DW3: =IFERROR(IF(($DK3-$DE3-$DH3)>0,($DB3)/($DK3-$DE3-$DH3),""),"") | DX3: =IFERROR(IF(($DL3-$DF3-$DI3)>0,($DC3)/($DL3-$DF3-$DI3),""),"") | DY3: =SUMIFS(tblPlant[Cyanide_kg],tblPlant[Date],$A3) | DZ3: =IF($B3=$B2,$DZ2,0)+$DY3 | EA3: =$EA2+$DY3 | EB3: =SUMIFS(tblPlant[Lime_kg],tblPlant[Date],$A3) | EC3: =IF($B3=$B2,$EC2,0)+$EB3 | ED3: =$ED2+$EB3 | EE3: =SUMIFS(tblPlant[Grinding_Media_kg],tblPlant[Date],$A3) | EF3: =IF($B3=$B2,$EF2,0)+$EE3 | EG3: =$EG2+$EE3 | EH3: =SUMIFS(tblPlant[Power_kWh],tblPlant[Date],$A3) | EI3: =IF($B3=$B2,$EI2,0)+$EH3 | EJ3: =$EJ2+$EH3 | EK3: =SUMIFS(tblPlant[Raw_Water_m3],tblPlant[Date],$A3) | EL3: =IF($B3=$B2,$EL2,0)+$EK3 | EM3: =$EM2+$EK3 | EN3: =IFERROR(IF(($BZ3)>0,($DY3)/($BZ3),""),"") | EO3: =IFERROR(IF(($CA3)>0,($DZ3)/($CA3),""),"") | EP3: =IFERROR(IF(($CB3)>0,($EA3)/($CB3),""),"") | EQ3: =IFERROR(IF(($BZ3)>0,($EB3)/($BZ3),""),"") | ER3: =IFERROR(IF(($CA3)>0,($EC3)/($CA3),""),"") | ES3: =IFERROR(IF(($CB3)>0,($ED3)/($CB3),""),"") | ET3: =IFERROR(IF(($BZ3)>0,($EE3)/($BZ3),""),"") | EU3: =IFERROR(IF(($CA3)>0,($EF3)/($CA3),""),"") | EV3: =IFERROR(IF(($CB3)>0,($EG3)/($CB3),""),"") | EW3: =IFERROR(IF(($BZ3)>0,($EH3)/($BZ3),""),"") | EX3: =IFERROR(IF(($CA3)>0,($EI3)/($CA3),""),"") | EY3: =IFERROR(IF(($CB3)>0,($EJ3)/($CB3),""),"") | EZ3: =IFERROR(IF(($BZ3)>0,($EK3)/($BZ3),""),"") | FA3: =IFERROR(IF(($CA3)>0,($EL3)/($CA3),""),"") | FB3: =IFERROR(IF(($CB3)>0,($EM3)/($CB3),""),"") | FC3: =IF(SUMIFS(tblPlant[GIC_oz],tblPlant[Date],$A3)>0,SUMIFS(tblPlant[GIC_oz],tblPlant[Date],$A3),"") | FD3: =SUMIFS(tblGold[Gold_oz],tblGold[Date],$A3,tblGold[Type],"Shipment") | FE3: =IF($B3=$B2,$FE2,0)+$FD3 | FF3: =$FF2+$FD3 | FG3: =SUMIFS(tblGold[Gold_oz],tblGold[Date],$A3,tblGold[Type],"Sale") | FH3: =IF($B3=$B2,$FH2,0)+$FG3 | FI3: =$FI2+$FG3 | FJ3: =SUMIFS(tblGold[Dore_kg],tblGold[Date],$A3,tblGold[Type],"Shipment") | FK3: =IF($B3=$B2,$FK2,0)+$FJ3 | FL3: =$FL2+$FJ3 | FM3: =SUMIFS(tblSafety[Hours_Total],tblSafety[Date],$A3) | FN3: =IF($B3=$B2,$FN2,0)+$FM3 | FO3: =$FO2+$FM3 | FP3: =SUMIFS(tblSafety[Fatality],tblSafety[Date],$A3) | FQ3: =IF($B3=$B2,$FQ2,0)+$FP3 | FR3: =$FR2+$FP3 | FS3: =SUMIFS(tblSafety[LTI],tblSafety[Date],$A3) | FT3: =IF($B3=$B2,$FT2,0)+$FS3 | FU3: =$FU2+$FS3 | FV3: =SUMIFS(tblSafety[RWI],tblSafety[Date],$A3) | FW3: =IF($B3=$B2,$FW2,0)+$FV3 | FX3: =$FX2+$FV3 | FY3: =SUMIFS(tblSafety[MTI],tblSafety[Date],$A3) | FZ3: =IF($B3=$B2,$FZ2,0)+$FY3 | GA3: =$GA2+$FY3 | GB3: =SUMIFS(tblSafety[FAI],tblSafety[Date],$A3) | GC3: =IF($B3=$B2,$GC2,0)+$GB3 | GD3: =$GD2+$GB3 | GE3: =SUMIFS(tblSafety[Recordables],tblSafety[Date],$A3) | GF3: =IF($B3=$B2,$GF2,0)+$GE3 | GG3: =$GG2+$GE3 | GH3: =SUMIFS(tblSafety[Near_Miss],tblSafety[Date],$A3) | GI3: =IF($B3=$B2,$GI2,0)+$GH3 | GJ3: =$GJ2+$GH3 | GK3: =SUMIFS(tblSafety[Hazard_Reports],tblSafety[Date],$A3) | GL3: =IF($B3=$B2,$GL2,0)+$GK3 | GM3: =$GM2+$GK3 | GN3: =SUMIFS(tblSafety[HPI],tblSafety[Date],$A3) | GO3: =IF($B3=$B2,$GO2,0)+$GN3 | GP3: =$GP2+$GN3 | GQ3: =SUMIFS(tblSafety[Env_Incidents],tblSafety[Date],$A3) | GR3: =IF($B3=$B2,$GR2,0)+$GQ3 | GS3: =$GS2+$GQ3 | GT3: =SUMIFS(tblSafety[Community_Incidents],tblSafety[Date],$A3) | GU3: =IF($B3=$B2,$GU2,0)+$GT3 | GV3: =$GV2+$GT3 | GW3: =SUMIFS(tblSafety[Vehicle_Incidents],tblSafety[Date],$A3) | GX3: =IF($B3=$B2,$GX2,0)+$GW3 | GY3: =$GY2+$GW3 | GZ3: =SUMIFS(tblSafety[Toolbox_Talks],tblSafety[Date],$A3) | HA3: =IF($B3=$B2,$HA2,0)+$GZ3 | HB3: =$HB2+$GZ3 | HC3: =SUMIFS(tblSafety[Inspections],tblSafety[Date],$A3) | HD3: =IF($B3=$B2,$HD2,0)+$HC3 | HE3: =$HE2+$HC3 | HF3: =IFERROR((SUMIFS(tblSafety[Recordables],tblSafety[Date],">="&EDATE($E3,-12),tblSafety[Date],"<="&$A3)+SUMIFS(tblSafetyHistory[Recordables],tblSafetyHistory[Month],">="&EDATE($E3,-12),tblSafetyHistory[Month],"<"&cfg_YearStart))/(SUMIFS(tblSafety[Hours_Total],tblSafety[Date],">="&EDATE($E3,-12),tblSafety[Date],"<="&$A3)+SUMIFS(tblSafetyHistory[Hours_Total],tblSafetyHistory[Month],">="&EDATE($E3,-12),tblSafetyHistory[Month],"<"&cfg_YearStart))*1000000,"") | HG3: =IFERROR((SUMIFS(tblSafety[LTI],tblSafety[Date],">="&EDATE($E3,-12),tblSafety[Date],"<="&$A3)+SUMIFS(tblSafetyHistory[LTI],tblSafetyHistory[Month],">="&EDATE($E3,-12),tblSafetyHistory[Month],"<"&cfg_YearStart))/(SUMIFS(tblSafety[Hours_Total],tblSafety[Date],">="&EDATE($E3,-12),tblSafety[Date],"<="&$A3)+SUMIFS(tblSafetyHistory[Hours_Total],tblSafetyHistory[Month],">="&EDATE($E3,-12),tblSafetyHistory[Month],"<"&cfg_YearStart))*1000000,"") | HH3: =IF(MAX(N(cfg_PriorLTIDate),_xlfn.MAXIFS(tblSafety[Date],tblSafety[LTI],">0",tblSafety[Date],"<="&$A3))=0,"",$A3-MAX(N(cfg_PriorLTIDate),_xlfn.MAXIFS(tblSafety[Date],tblSafety[LTI],">0",tblSafety[Date],"<="&$A3))) | HI3: =SUMIFS(tblBudget[Ore_Mined_t],tblBudget[Month],$E3) | HJ3: =$HI3*$C3/$D3 | HK3: =SUMIFS(tblBudget[Ore_Mined_t],tblBudget[Month],"<"&$E3)+$HJ3 | HL3: =SUMIFS(tblBudget[Ore_oz],tblBudget[Month],$E3) | HM3: =$HL3*$C3/$D3 | HN3: =SUMIFS(tblBudget[Ore_oz],tblBudget[Month],"<"&$E3)+$HM3 | HO3: =IFERROR(IF(($HI3)>0,($HL3*cfg_TroyOz)/($HI3),""),"") | HP3: =IFERROR(IF(($HJ3)>0,($HM3*cfg_TroyOz)/($HJ3),""),"") | HQ3: =IFERROR(IF(($HK3)>0,($HN3*cfg_TroyOz)/($HK3),""),"") | HR3: =SUMIFS(tblBudget[Waste_t],tblBudget[Month],$E3) | HS3: =$HR3*$C3/$D3 | HT3: =SUMIFS(tblBudget[Waste_t],tblBudget[Month],"<"&$E3)+$HS3 | HU3: =SUMIFS(tblBudget[TMM_t],tblBudget[Month],$E3) | HV3: =$HU3*$C3/$D3 | HW3: =SUMIFS(tblBudget[TMM_t],tblBudget[Month],"<"&$E3)+$HV3 | HX3: =IFERROR(IF(($HI3)>0,($HR3)/($HI3),""),"") | HY3: =IFERROR(IF(($HJ3)>0,($HS3)/($HJ3),""),"") | HZ3: =IFERROR(IF(($HK3)>0,($HT3)/($HK3),""),"") | IA3: =SUMIFS(tblBudget[Drill_m],tblBudget[Month],$E3) | IB3: =$IA3*$C3/$D3 | IC3: =SUMIFS(tblBudget[Drill_m],tblBudget[Month],"<"&$E3)+$IB3 | ID3: =SUMIFS(tblBudget[Diesel_L],tblBudget[Month],$E3) | IE3: =$ID3*$C3/$D3 | IF3: =SUMIFS(tblBudget[Diesel_L],tblBudget[Month],"<"&$E3)+$IE3 | IG3: =SUMIFS(tblBudget[Milled_t],tblBudget[Month],$E3) | IH3: =$IG3*$C3/$D3 | II3: =SUMIFS(tblBudget[Milled_t],tblBudget[Month],"<"&$E3)+$IH3 | IJ3: =SUMIFS(tblBudget[Feed_oz],tblBudget[Month],$E3) | IK3: =$IJ3*$C3/$D3 | IL3: =SUMIFS(tblBudget[Feed_oz],tblBudget[Month],"<"&$E3)+$IK3 | IM3: =SUMIFS(tblBudget[Recovered_oz],tblBudget[Month],$E3) | IN3: =$IM3*$C3/$D3 | IO3: =SUMIFS(tblBudget[Recovered_oz],tblBudget[Month],"<"&$E3)+$IN3 | IP3: =IFERROR(IF(($IG3)>0,($IJ3*cfg_TroyOz)/($IG3),""),"") | IQ3: =IFERROR(IF(($IH3)>0,($IK3*cfg_TroyOz)/($IH3),""),"") | IR3: =IFERROR(IF(($II3)>0,($IL3*cfg_TroyOz)/($II3),""),"") | IS3: =IFERROR(IF(($IJ3)>0,($IM3)/($IJ3),""),"") | IT3: =IFERROR(IF(($IK3)>0,($IN3)/($IK3),""),"") | IU3: =IFERROR(IF(($IL3)>0,($IO3)/($IL3),""),"") | IV3: =SUMIFS(tblBudget[Gold_Poured_oz],tblBudget[Month],$E3) | IW3: =$IV3*$C3/$D3 | IX3: =SUMIFS(tblBudget[Gold_Poured_oz],tblBudget[Month],"<"&$E3)+$IW3 | IY3: =SUMIFS(tblBudget[Hours_Worked],tblBudget[Month],$E3) | IZ3: =$IY3*$C3/$D3 | JA3: =SUMIFS(tblBudget[Hours_Worked],tblBudget[Month],"<"&$E3)+$IZ3
A4: 46025 | B4: =MONTH($A4) | C4: =DAY($A4) | D4: =DAY(EOMONTH($A4,0)) | E4: =DATE(YEAR($A4),MONTH($A4),1) | F4: =SUMIFS(tblMovement[Tonnes_t],tblMovement[Date],$A4,tblMovement[Is_Ore],1,tblMovement[Source_Type],"Pit") | G4: =IF($B4=$B3,$G3,0)+$F4 | H4: =$H3+$F4 | I4: =SUMIFS(tblMovement[Ore_oz],tblMovement[Date],$A4,tblMovement[Source_Type],"Pit") | J4: =IF($B4=$B3,$J3,0)+$I4 | K4: =$K3+$I4 | L4: =IFERROR(IF(($F4)>0,($I4*cfg_TroyOz)/($F4),""),"") | M4: =IFERROR(IF(($G4)>0,($J4*cfg_TroyOz)/($G4),""),"") | N4: =IFERROR(IF(($H4)>0,($K4*cfg_TroyOz)/($H4),""),"") | O4: =SUMIFS(tblMovement[Tonnes_t],tblMovement[Date],$A4,tblMovement[Is_Ore],0,tblMovement[Source_Type],"Pit") | P4: =IF($B4=$B3,$P3,0)+$O4 | Q4: =$Q3+$O4 | R4: =$F4+$O4 | S4: =IF($B4=$B3,$S3,0)+$R4 | T4: =$T3+$R4 | U4: =IFERROR(IF(($F4)>0,($O4)/($F4),""),"") | V4: =IFERROR(IF(($G4)>0,($P4)/($G4),""),"") | W4: =IFERROR(IF(($H4)>0,($Q4)/($H4),""),"") | X4: =SUMIFS(tblMovement[Tonnes_t],tblMovement[Date],$A4,tblMovement[Source_Type],"Stockpile") | Y4: =IF($B4=$B3,$Y3,0)+$X4 | Z4: =$Z3+$X4 | AA4: =SUMIFS(tblMiningDaily[Drill_m],tblMiningDaily[Date],$A4) | AB4: =IF($B4=$B3,$AB3,0)+$AA4 | AC4: =$AC3+$AA4 | AD4: =SUMIFS(tblMiningDaily[Blast_t],tblMiningDaily[Date],$A4) | AE4: =IF($B4=$B3,$AE3,0)+$AD4 | AF4: =$AF3+$AD4 | AG4: =SUMIFS(tblMiningDaily[Explosives_kg],tblMiningDaily[Date],$A4) | AH4: =IF($B4=$B3,$AH3,0)+$AG4 | AI4: =$AI3+$AG4 | AJ4: =IFERROR(IF(($AD4)>0,($AG4)/($AD4),""),"") | AK4: =IFERROR(IF(($AE4)>0,($AH4)/($AE4),""),"") | AL4: =IFERROR(IF(($AF4)>0,($AI4)/($AF4),""),"") | AM4: =SUMIFS(tblMiningDaily[Diesel_L],tblMiningDaily[Date],$A4) | AN4: =IF($B4=$B3,$AN3,0)+$AM4 | AO4: =$AO3+$AM4 | AP4: =SUMIFS(tblMiningDaily[Dewatering_m3],tblMiningDaily[Date],$A4) | AQ4: =IF($B4=$B3,$AQ3,0)+$AP4 | AR4: =$AR3+$AP4 | AS4: =SUMIFS(tblFleet[Calendar_h],tblFleet[Date],$A4,tblFleet[Equipment_Class],"Excavator") | AT4: =IF($B4=$B3,$AT3,0)+$AS4 | AU4: =$AU3+$AS4 | AV4: =SUMIFS(tblFleet[Available_h],tblFleet[Date],$A4,tblFleet[Equipment_Class],"Excavator") | AW4: =IF($B4=$B3,$AW3,0)+$AV4 | AX4: =$AX3+$AV4 | AY4: =SUMIFS(tblFleet[Operating_h],tblFleet[Date],$A4,tblFleet[Equipment_Class],"Excavator") | AZ4: =IF($B4=$B3,$AZ3,0)+$AY4 | BA4: =$BA3+$AY4 | BB4: =IFERROR(IF(($AS4)>0,($AV4)/($AS4),""),"") | BC4: =IFERROR(IF(($AT4)>0,($AW4)/($AT4),""),"") | BD4: =IFERROR(IF(($AU4)>0,($AX4)/($AU4),""),"") | BE4: =IFERROR(IF(($AV4)>0,($AY4)/($AV4),""),"") | BF4: =IFERROR(IF(($AW4)>0,($AZ4)/($AW4),""),"") | BG4: =IFERROR(IF(($AX4)>0,($BA4)/($AX4),""),"") | BH4: =SUMIFS(tblFleet[Calendar_h],tblFleet[Date],$A4,tblFleet[Equipment_Class],"Haul Truck") | BI4: =IF($B4=$B3,$BI3,0)+$BH4 | BJ4: =$BJ3+$BH4 | BK4: =SUMIFS(tblFleet[Available_h],tblFleet[Date],$A4,tblFleet[Equipment_Class],"Haul Truck") | BL4: =IF($B4=$B3,$BL3,0)+$BK4 | BM4: =$BM3+$BK4 | BN4: =SUMIFS(tblFleet[Operating_h],tblFleet[Date],$A4,tblFleet[Equipment_Class],"Haul Truck") | BO4: =IF($B4=$B3,$BO3,0)+$BN4 | BP4: =$BP3+$BN4 | BQ4: =IFERROR(IF(($BH4)>0,($BK4)/($BH4),""),"") | BR4: =IFERROR(IF(($BI4)>0,($BL4)/($BI4),""),"") | BS4: =IFERROR(IF(($BJ4)>0,($BM4)/($BJ4),""),"") | BT4: =IFERROR(IF(($BK4)>0,($BN4)/($BK4),""),"") | BU4: =IFERROR(IF(($BL4)>0,($BO4)/($BL4),""),"") | BV4: =IFERROR(IF(($BM4)>0,($BP4)/($BM4),""),"") | BW4: =SUMIFS(tblPlant[Crushed_t],tblPlant[Date],$A4) | BX4: =IF($B4=$B3,$BX3,0)+$BW4 | BY4: =$BY3+$BW4 | BZ4: =SUMIFS(tblPlant[Milled_t],tblPlant[Date],$A4) | CA4: =IF($B4=$B3,$CA3,0)+$BZ4 | CB4: =$CB3+$BZ4 | CC4: =SUMIFS(tblPlant[Feed_oz],tblPlant[Date],$A4) | CD4: =IF($B4=$B3,$CD3,0)+$CC4 | CE4: =$CE3+$CC4 | CF4: =SUMIFS(tblPlant[Tails_oz],tblPlant[Date],$A4) | CG4: =IF($B4=$B3,$CG3,0)+$CF4 | CH4: =$CH3+$CF4 | CI4: =SUMIFS(tblPlant[Recovered_oz],tblPlant[Date],$A4) | CJ4: =IF($B4=$B3,$CJ3,0)+$CI4 | CK4: =$CK3+$CI4 | CL4: =IFERROR(IF(($BZ4)>0,($CC4*cfg_TroyOz)/($BZ4),""),"") | CM4: =IFERROR(IF(($CA4)>0,($CD4*cfg_TroyOz)/($CA4),""),"") | CN4: =IFERROR(IF(($CB4)>0,($CE4*cfg_TroyOz)/($CB4),""),"") | CO4: =IFERROR(IF(($BZ4)>0,($CF4*cfg_TroyOz)/($BZ4),""),"") | CP4: =IFERROR(IF(($CA4)>0,($CG4*cfg_TroyOz)/($CA4),""),"") | CQ4: =IFERROR(IF(($CB4)>0,($CH4*cfg_TroyOz)/($CB4),""),"") | CR4: =IFERROR(IF(($CC4)>0,($CI4)/($CC4),""),"") | CS4: =IFERROR(IF(($CD4)>0,($CJ4)/($CD4),""),"") | CT4: =IFERROR(IF(($CE4)>0,($CK4)/($CE4),""),"") | CU4: =SUMIFS(tblPlant[Gravity_Gold_oz],tblPlant[Date],$A4) | CV4: =IF($B4=$B3,$CV3,0)+$CU4 | CW4: =$CW3+$CU4 | CX4: =SUMIFS(tblPlant[Gold_Poured_oz],tblPlant[Date],$A4) | CY4: =IF($B4=$B3,$CY3,0)+$CX4 | CZ4: =$CZ3+$CX4 | DA4: =SUMIFS(tblPlant[Mill_Run_h],tblPlant[Date],$A4) | DB4: =IF($B4=$B3,$DB3,0)+$DA4 | DC4: =$DC3+$DA4 | DD4: =SUMIFS(tblPlant[Mill_Planned_Maint_h],tblPlant[Date],$A4) | DE4: =IF($B4=$B3,$DE3,0)+$DD4 | DF4: =$DF3+$DD4 | DG4: =SUMIFS(tblPlant[Mill_Unplanned_Down_h],tblPlant[Date],$A4) | DH4: =IF($B4=$B3,$DH3,0)+$DG4 | DI4: =$DI3+$DG4 | DJ4: =COUNTIFS(tblPlant[Date],$A4,tblPlant[Mill_Run_h],"<>")*24 | DK4: =IF($B4=$B3,$DK3,0)+$DJ4 | DL4: =$DL3+$DJ4 | DM4: =SUMIFS(tblPlant[Crusher_Run_h],tblPlant[Date],$A4) | DN4: =IF($B4=$B3,$DN3,0)+$DM4 | DO4: =$DO3+$DM4 | DP4: =IFERROR(IF(($DA4)>0,($BZ4)/($DA4),""),"") | DQ4: =IFERROR(IF(($DB4)>0,($CA4)/($DB4),""),"") | DR4: =IFERROR(IF(($DC4)>0,($CB4)/($DC4),""),"") | DS4: =IFERROR(IF(($DJ4)>0,($DJ4-$DD4-$DG4)/($DJ4),""),"") | DT4: =IFERROR(IF(($DK4)>0,($DK4-$DE4-$DH4)/($DK4),""),"") | DU4: =IFERROR(IF(($DL4)>0,($DL4-$DF4-$DI4)/($DL4),""),"") | DV4: =IFERROR(IF(($DJ4-$DD4-$DG4)>0,($DA4)/($DJ4-$DD4-$DG4),""),"") | DW4: =IFERROR(IF(($DK4-$DE4-$DH4)>0,($DB4)/($DK4-$DE4-$DH4),""),"") | DX4: =IFERROR(IF(($DL4-$DF4-$DI4)>0,($DC4)/($DL4-$DF4-$DI4),""),"") | DY4: =SUMIFS(tblPlant[Cyanide_kg],tblPlant[Date],$A4) | DZ4: =IF($B4=$B3,$DZ3,0)+$DY4 | EA4: =$EA3+$DY4 | EB4: =SUMIFS(tblPlant[Lime_kg],tblPlant[Date],$A4) | EC4: =IF($B4=$B3,$EC3,0)+$EB4 | ED4: =$ED3+$EB4 | EE4: =SUMIFS(tblPlant[Grinding_Media_kg],tblPlant[Date],$A4) | EF4: =IF($B4=$B3,$EF3,0)+$EE4 | EG4: =$EG3+$EE4 | EH4: =SUMIFS(tblPlant[Power_kWh],tblPlant[Date],$A4) | EI4: =IF($B4=$B3,$EI3,0)+$EH4 | EJ4: =$EJ3+$EH4 | EK4: =SUMIFS(tblPlant[Raw_Water_m3],tblPlant[Date],$A4) | EL4: =IF($B4=$B3,$EL3,0)+$EK4 | EM4: =$EM3+$EK4 | EN4: =IFERROR(IF(($BZ4)>0,($DY4)/($BZ4),""),"") | EO4: =IFERROR(IF(($CA4)>0,($DZ4)/($CA4),""),"") | EP4: =IFERROR(IF(($CB4)>0,($EA4)/($CB4),""),"") | EQ4: =IFERROR(IF(($BZ4)>0,($EB4)/($BZ4),""),"") | ER4: =IFERROR(IF(($CA4)>0,($EC4)/($CA4),""),"") | ES4: =IFERROR(IF(($CB4)>0,($ED4)/($CB4),""),"") | ET4: =IFERROR(IF(($BZ4)>0,($EE4)/($BZ4),""),"") | EU4: =IFERROR(IF(($CA4)>0,($EF4)/($CA4),""),"") | EV4: =IFERROR(IF(($CB4)>0,($EG4)/($CB4),""),"") | EW4: =IFERROR(IF(($BZ4)>0,($EH4)/($BZ4),""),"") | EX4: =IFERROR(IF(($CA4)>0,($EI4)/($CA4),""),"") | EY4: =IFERROR(IF(($CB4)>0,($EJ4)/($CB4),""),"") | EZ4: =IFERROR(IF(($BZ4)>0,($EK4)/($BZ4),""),"") | FA4: =IFERROR(IF(($CA4)>0,($EL4)/($CA4),""),"") | FB4: =IFERROR(IF(($CB4)>0,($EM4)/($CB4),""),"") | FC4: =IF(SUMIFS(tblPlant[GIC_oz],tblPlant[Date],$A4)>0,SUMIFS(tblPlant[GIC_oz],tblPlant[Date],$A4),"") | FD4: =SUMIFS(tblGold[Gold_oz],tblGold[Date],$A4,tblGold[Type],"Shipment") | FE4: =IF($B4=$B3,$FE3,0)+$FD4 | FF4: =$FF3+$FD4 | FG4: =SUMIFS(tblGold[Gold_oz],tblGold[Date],$A4,tblGold[Type],"Sale") | FH4: =IF($B4=$B3,$FH3,0)+$FG4 | FI4: =$FI3+$FG4 | FJ4: =SUMIFS(tblGold[Dore_kg],tblGold[Date],$A4,tblGold[Type],"Shipment") | FK4: =IF($B4=$B3,$FK3,0)+$FJ4 | FL4: =$FL3+$FJ4 | FM4: =SUMIFS(tblSafety[Hours_Total],tblSafety[Date],$A4) | FN4: =IF($B4=$B3,$FN3,0)+$FM4 | FO4: =$FO3+$FM4 | FP4: =SUMIFS(tblSafety[Fatality],tblSafety[Date],$A4) | FQ4: =IF($B4=$B3,$FQ3,0)+$FP4 | FR4: =$FR3+$FP4 | FS4: =SUMIFS(tblSafety[LTI],tblSafety[Date],$A4) | FT4: =IF($B4=$B3,$FT3,0)+$FS4 | FU4: =$FU3+$FS4 | FV4: =SUMIFS(tblSafety[RWI],tblSafety[Date],$A4) | FW4: =IF($B4=$B3,$FW3,0)+$FV4 | FX4: =$FX3+$FV4 | FY4: =SUMIFS(tblSafety[MTI],tblSafety[Date],$A4) | FZ4: =IF($B4=$B3,$FZ3,0)+$FY4 | GA4: =$GA3+$FY4 | GB4: =SUMIFS(tblSafety[FAI],tblSafety[Date],$A4) | GC4: =IF($B4=$B3,$GC3,0)+$GB4 | GD4: =$GD3+$GB4 | GE4: =SUMIFS(tblSafety[Recordables],tblSafety[Date],$A4) | GF4: =IF($B4=$B3,$GF3,0)+$GE4 | GG4: =$GG3+$GE4 | GH4: =SUMIFS(tblSafety[Near_Miss],tblSafety[Date],$A4) | GI4: =IF($B4=$B3,$GI3,0)+$GH4 | GJ4: =$GJ3+$GH4 | GK4: =SUMIFS(tblSafety[Hazard_Reports],tblSafety[Date],$A4) | GL4: =IF($B4=$B3,$GL3,0)+$GK4 | GM4: =$GM3+$GK4 | GN4: =SUMIFS(tblSafety[HPI],tblSafety[Date],$A4) | GO4: =IF($B4=$B3,$GO3,0)+$GN4 | GP4: =$GP3+$GN4 | GQ4: =SUMIFS(tblSafety[Env_Incidents],tblSafety[Date],$A4) | GR4: =IF($B4=$B3,$GR3,0)+$GQ4 | GS4: =$GS3+$GQ4 | GT4: =SUMIFS(tblSafety[Community_Incidents],tblSafety[Date],$A4) | GU4: =IF($B4=$B3,$GU3,0)+$GT4 | GV4: =$GV3+$GT4 | GW4: =SUMIFS(tblSafety[Vehicle_Incidents],tblSafety[Date],$A4) | GX4: =IF($B4=$B3,$GX3,0)+$GW4 | GY4: =$GY3+$GW4 | GZ4: =SUMIFS(tblSafety[Toolbox_Talks],tblSafety[Date],$A4) | HA4: =IF($B4=$B3,$HA3,0)+$GZ4 | HB4: =$HB3+$GZ4 | HC4: =SUMIFS(tblSafety[Inspections],tblSafety[Date],$A4) | HD4: =IF($B4=$B3,$HD3,0)+$HC4 | HE4: =$HE3+$HC4 | HF4: =IFERROR((SUMIFS(tblSafety[Recordables],tblSafety[Date],">="&EDATE($E4,-12),tblSafety[Date],"<="&$A4)+SUMIFS(tblSafetyHistory[Recordables],tblSafetyHistory[Month],">="&EDATE($E4,-12),tblSafetyHistory[Month],"<"&cfg_YearStart))/(SUMIFS(tblSafety[Hours_Total],tblSafety[Date],">="&EDATE($E4,-12),tblSafety[Date],"<="&$A4)+SUMIFS(tblSafetyHistory[Hours_Total],tblSafetyHistory[Month],">="&EDATE($E4,-12),tblSafetyHistory[Month],"<"&cfg_YearStart))*1000000,"") | HG4: =IFERROR((SUMIFS(tblSafety[LTI],tblSafety[Date],">="&EDATE($E4,-12),tblSafety[Date],"<="&$A4)+SUMIFS(tblSafetyHistory[LTI],tblSafetyHistory[Month],">="&EDATE($E4,-12),tblSafetyHistory[Month],"<"&cfg_YearStart))/(SUMIFS(tblSafety[Hours_Total],tblSafety[Date],">="&EDATE($E4,-12),tblSafety[Date],"<="&$A4)+SUMIFS(tblSafetyHistory[Hours_Total],tblSafetyHistory[Month],">="&EDATE($E4,-12),tblSafetyHistory[Month],"<"&cfg_YearStart))*1000000,"") | HH4: =IF(MAX(N(cfg_PriorLTIDate),_xlfn.MAXIFS(tblSafety[Date],tblSafety[LTI],">0",tblSafety[Date],"<="&$A4))=0,"",$A4-MAX(N(cfg_PriorLTIDate),_xlfn.MAXIFS(tblSafety[Date],tblSafety[LTI],">0",tblSafety[Date],"<="&$A4))) | HI4: =SUMIFS(tblBudget[Ore_Mined_t],tblBudget[Month],$E4) | HJ4: =$HI4*$C4/$D4 | HK4: =SUMIFS(tblBudget[Ore_Mined_t],tblBudget[Month],"<"&$E4)+$HJ4 | HL4: =SUMIFS(tblBudget[Ore_oz],tblBudget[Month],$E4) | HM4: =$HL4*$C4/$D4 | HN4: =SUMIFS(tblBudget[Ore_oz],tblBudget[Month],"<"&$E4)+$HM4 | HO4: =IFERROR(IF(($HI4)>0,($HL4*cfg_TroyOz)/($HI4),""),"") | HP4: =IFERROR(IF(($HJ4)>0,($HM4*cfg_TroyOz)/($HJ4),""),"") | HQ4: =IFERROR(IF(($HK4)>0,($HN4*cfg_TroyOz)/($HK4),""),"") | HR4: =SUMIFS(tblBudget[Waste_t],tblBudget[Month],$E4) | HS4: =$HR4*$C4/$D4 | HT4: =SUMIFS(tblBudget[Waste_t],tblBudget[Month],"<"&$E4)+$HS4 | HU4: =SUMIFS(tblBudget[TMM_t],tblBudget[Month],$E4) | HV4: =$HU4*$C4/$D4 | HW4: =SUMIFS(tblBudget[TMM_t],tblBudget[Month],"<"&$E4)+$HV4 | HX4: =IFERROR(IF(($HI4)>0,($HR4)/($HI4),""),"") | HY4: =IFERROR(IF(($HJ4)>0,($HS4)/($HJ4),""),"") | HZ4: =IFERROR(IF(($HK4)>0,($HT4)/($HK4),""),"") | IA4: =SUMIFS(tblBudget[Drill_m],tblBudget[Month],$E4) | IB4: =$IA4*$C4/$D4 | IC4: =SUMIFS(tblBudget[Drill_m],tblBudget[Month],"<"&$E4)+$IB4 | ID4: =SUMIFS(tblBudget[Diesel_L],tblBudget[Month],$E4) | IE4: =$ID4*$C4/$D4 | IF4: =SUMIFS(tblBudget[Diesel_L],tblBudget[Month],"<"&$E4)+$IE4 | IG4: =SUMIFS(tblBudget[Milled_t],tblBudget[Month],$E4) | IH4: =$IG4*$C4/$D4 | II4: =SUMIFS(tblBudget[Milled_t],tblBudget[Month],"<"&$E4)+$IH4 | IJ4: =SUMIFS(tblBudget[Feed_oz],tblBudget[Month],$E4) | IK4: =$IJ4*$C4/$D4 | IL4: =SUMIFS(tblBudget[Feed_oz],tblBudget[Month],"<"&$E4)+$IK4 | IM4: =SUMIFS(tblBudget[Recovered_oz],tblBudget[Month],$E4) | IN4: =$IM4*$C4/$D4 | IO4: =SUMIFS(tblBudget[Recovered_oz],tblBudget[Month],"<"&$E4)+$IN4 | IP4: =IFERROR(IF(($IG4)>0,($IJ4*cfg_TroyOz)/($IG4),""),"") | IQ4: =IFERROR(IF(($IH4)>0,($IK4*cfg_TroyOz)/($IH4),""),"") | IR4: =IFERROR(IF(($II4)>0,($IL4*cfg_TroyOz)/($II4),""),"") | IS4: =IFERROR(IF(($IJ4)>0,($IM4)/($IJ4),""),"") | IT4: =IFERROR(IF(($IK4)>0,($IN4)/($IK4),""),"") | IU4: =IFERROR(IF(($IL4)>0,($IO4)/($IL4),""),"") | IV4: =SUMIFS(tblBudget[Gold_Poured_oz],tblBudget[Month],$E4) | IW4: =$IV4*$C4/$D4 | IX4: =SUMIFS(tblBudget[Gold_Poured_oz],tblBudget[Month],"<"&$E4)+$IW4 | IY4: =SUMIFS(tblBudget[Hours_Worked],tblBudget[Month],$E4) | IZ4: =$IY4*$C4/$D4 | JA4: =SUMIFS(tblBudget[Hours_Worked],tblBudget[Month],"<"&$E4)+$IZ4
